Workbook

Sheet Risks
A1: ID | B1: Workstream | C1: Assigned To | D1: Profile | E1: Priority | F1: Title | G1: Trigger_Date | H1: Countdown | I1: Days Open | J1: Update Log | K1: PMO Check | L1: URL
A2: 21 | B2: IAM | C2: Ted Balfour | D2: 4) Managing Sponsor | E2: 9 | F2: Application Remediation | G2: 26-Nov-12 | H2: 5 | I2: 231 | J2: 14-Nov: Per Ted on fortnightly RAID call, this is tracking to the trigger date. 100K synced so far, no issues. Another 50K users to be moved from tonight. 15 Oct: Approval for ID Sync deployment approved by CLT. JD&A effort still under way and deployment plan willbe adjusted to reflect anticapated remediation schedule. This item will remin open until the roll out is complete. 3-Oct: Per Ted, approx 11K apps analyzed, 19 require remediation, of those 8 are complete, 6 more with identified deployment dates. Ted presents to CLT today requesting approval to move forward with ID Sync and accept the risk that some apps may break. Ted will update thereafter. 22-Aug (LM): On fortnightly call, Ted took action to move trigger date, as this will not be impact until mid-Oct. 8-Aug (LM): Per Prog. RAID call, Ted said date will move out 2 months. Ted to add update and amend Trigger Date. 25-Jul (LM): Per Ted, doing assessment to see if can pushout date to service ready and go-live. Looking at what will happen if sync with O365 with data in current state. 20-Jul (SJ) Following 2 day Messaging / Lync workshop held 17/18th July the following updates were made during a deep dive on this point. - Approx 4/5000 apps still need to be assessed - Now within the scope of the J&DA program run by James Hartley. -IAM & M&C Program piloting standard attributes which will be required for Lync / Exchange / Outllok. - Process for Application Remendiation required - Funding of remediation required - Potential risk on SRT will occur - Action David Bingham to setup meeting with C. Driver, R. Bouji, N Sahdev, A. Harper, J. Els, N, Wood, and T. Balfour to discuss JD&A scope and Plan with James Hartley - Better control on Process / rules for coupling programs together (dependency process) - Ted to construct alternate plan 16-May: (LM) Ted on call: 20% of the 6,000 critical apps require remediation.Doing more detailed analysis now, following many avenues to resolve. 9-May: Resource availability is the risk here; 6,000 critical apps to analyze which is dependent on resource availability. 29-Mar: Added by Laura per Ted 29-Mar.​ | L2: http://sp.ey.net/msibm/Lists/Program%20Risks%20%20TEST/DispForm.aspx?ID=&RootFolder=*
A3: 22 | B3: IAM | C3: Ted Balfour | D3: 3) Program Mgt Team | E3: 6 | F3: AD Remediation - Complete the attribute cleansing | G3: 11-Oct-12 | H3: -41 | I3: 222 | J3: 5-Nov: All countries have now been sync'd with MMSSPP as far as im aware, but the error reports are currently going into no-mans land due to an addressing issue. Marina from IAM Ops is also driving MMSSPP error reporting processes etc. We have a meeting scheduled today on this topic. 9-May: Tolerance level 1% and we are just over that. Some remediation is taking place now. Still critical in terms of timeline. 28-Mar: Ted sent to Laura for addition to the log. LM emd Ted for details.​ | L3: http://sp.ey.net/msibm/Lists/Program%20Risks%20%20TEST/DispForm.aspx?ID=&RootFolder=*
A4: 23 | B4: IAM | C4: Ted Balfour | D4: 3) Program Mgt Team | E4: 6 | F4: ID SYNC - AD Attribute population & Standardazation. | G4: 26-Nov-12 | H4: 5 | I4: 201 | J4: 15 Oct: Data Standardazation kicking off 18 Oct and continuing for 6 weeks. Will review and close at the end of the deployment period. 9-May: Linked to R141 - until apps are remediated, can't do attribute population and standardization. 28-Mar: Ted sent to Laura for addition to the log. LM emd Ted for details.​ | L4: http://sp.ey.net/msibm/Lists/Program%20Risks%20%20TEST/DispForm.aspx?ID=&RootFolder=*
A5: 206 | B5: LNDR | C5: Christian Driver | D5: 3) Program Mgt Team | E5: 2 | F5: Onshore Notes developers are not secured for the duration of the plan. | G5: 30-Nov-12 | H5: 9 | I5: 71 | J5: CD, 19-Jul-12: Risk created (downgraded from issue).​ | L5: http://sp.ey.net/msibm/Lists/Program%20Risks%20%20TEST/DispForm.aspx?ID=&RootFolder=*
A6: 301 | B6: LNDR | C6: Christian Driver | D6: 3) Program Mgt Team | E6: 4 | F6: Later than planned deployment of EYAA may reduce number of deactivations in FY13 | G6: 07-Dec-12 | H6: 16 | I6: 28 | J6: CD, 18-Oct-12: Initial risk triggers not realised. Good progress on mitigating actions. Next review date moved back in line with next critical milestone/risk trigger. CD, 20-Sep-12: Risk created.​ | L6: http://sp.ey.net/msibm/Lists/Program%20Risks%20%20TEST/DispForm.aspx?ID=&RootFolder=*
A7: 74 | B7: Lync | C7: Stephen McCartney | D7: 3) Program Mgt Team | E7: 0 | F7: Inter-operability of Lync and existing softphones | G7: 30-Nov-12 | H7: 9 | I7: 207 | J7: 31-Oct-12: SM - Waiting for final recommendation from the technical team as to which headsets are recommended. 26/10 - Sandra to present options to DA w/e 09-Nov-12 ref options on how to handle the co-existence. 14-Sep: SM - Have pushed back the trigger and project review date as the technical analysis is now almost complete, and will be going to the DA for review on the 27th Sep. Following that meeting this will need to be updated with the outcome. 3-aug: BvG - Struggling a little to see this as interoperability issue beyond the technical issue of multiple audio applications using audio devices especially on the XP platform. Beyond that this is a change management issue that will require training. Existing softphone is no different from exisitng physical phone other than contention issues with audio devices etc. surely. 29-Jun: SM - Discussed in the Secaucus workshop. Agreed that this decision will need to go to the business - but first Sandra to provide a write-up of the inter-operability investigation. Tests have shown there are some issues with inter-operability, awaiting final results. | L7: http://sp.ey.net/msibm/Lists/Program%20Risks%20%20TEST/DispForm.aspx?ID=&RootFolder=*
A8: 76 | B8: Lync | C8: Neil Sahdev | D8: 3) Program Mgt Team | E8: 6 | F8: Parallel phases and programs may cause resource issues | G8: 30-Nov-12 | H8: 9 | I8: 204 | J8: 14-Sep: SM - Associated issue has been closed - reopening this as it will continue to be a risk throughout the project. Based on Sandra's update, I've updated this risk to push out the date of review until after Sandra's document has been seen by the DA. 11-Jul: SM - A recent call with John Murray has highlighted that he does not have enough time to complete work being assigned to him by Lync and O/E - he is going to have to prioritise one at the expense of the other. Both sets ​of work are on the critical path. | L8: http://sp.ey.net/msibm/Lists/Program%20Risks%20%20TEST/DispForm.aspx?ID=&RootFolder=*
A9: 78 | B9: Lync | C9: Stephen McCartney | D9: 3) Program Mgt Team | E9: 3 | F9: Offices' bandwidths may not support all Lync functionality | G9: 01-Jan-13 | H9: 41 | I9: 175 | J9: 09-Nov-12: SM - John Murray has the action to finish collecting the local office data. He is going to talk to Shaun Bradley to get more resource to get it completed. 26/10 - Call setup with John Murray Fri 02-Nov-11 to understand network analysis performed to-date, next steps, 'buy-in' required from network ops etc. 11-Jun: Deep dive will be done w/e 15-Jun to go futher into the infrastructure to try and make the bandwidth calculator more accurate. | L9: http://sp.ey.net/msibm/Lists/Program%20Risks%20%20TEST/DispForm.aspx?ID=&RootFolder=*
A10: 181 | B10: Lync | C10: Stephen McCartney | D10: 5) Steering Committee | E10: 4 | F10: Lync Performance Testing Approach Unresolved | G10: 31-Dec-12 | H10: 40 | I10: 123 | J10: 09-Nov-12: SM - Awaiting Sascha to update his strategy in line with the program managers requests. 26-Oct-12: SM - Sascha Mcdonald has been brought in as the M&C Performance Test Manager. He is currently working through a proposal for Lync Performance Testing which will be discussed and agreed on. | L10: http://sp.ey.net/msibm/Lists/Program%20Risks%20%20TEST/DispForm.aspx?ID=&RootFolder=*
A11: 32 | B11: M&C Program | C11: David Bingham | D11: 5) Steering Committee | E11: 9 | F11: Mechanisms for creating, storing and reusing components and other assets do not exist | G11: 01-May-13 | H11: 161 | I11: 154 | J11: 11-Sep: Per David, Trigger Date is May 2013; next monthly exec meeting to review after is 6-October 10-Sept (David): This is covered at the Exec meeting monthly. Therefore can I suggest we keep it at M&C level and based on the Exec meeting update it accordingly - it will remain a risk until Sharepoint 1 is live at least ! LM> David for trigger date, next review. 10-Sept (Brett): Not to do with Enterprise Plan; Certainly it impacts our ability to execute an enterprise plan of interdependent programs using/building SharePoint but they key issue is that while we need to be able to share SharePoint components etc between programs there is currently nothing in place to actually allow/facilitate this beyond individual developers and delivery programs more broadly talking to each other, establishing what is being worked on and available etc. The issue therefore results in a situation where business cases are being approved for independent programs to proceed (SDET, GAAIT etc) on the basis that they will share components etc and where our leadership believes this is actually achievable at scale. It is not and would be entirely ad hoc causing either high overhead to achieve or causing it simply not to happen. 4-Sept (LM): LM > Ian for guidance; convo may be needed amongst Chris, David and Brett to align. Per Brett, "This does not address the issue. The things Brian has linked to have always been there. The issue here is that in a practical way there is no real ability for programs to share code/components in the way that is expected by our leadership when they approve parallel efforts such as M&C with GAAIT Replacement, SDET, Oceania Records Management etc. We don't have the internal disciplines or processes and the reality is that code is not shared or managed and is, on the ground, reinvented etc." Ian agreed, 6-Sept, LM > Brett/David to gauge interest in such a call. 29-Aug (LM): E-mailed Brett with details to confirm whether resolution is satisfied by the processes described in the documentation linked below. 23-Aug (LM): Susan Pietretti discussed with Brian Blinco who confirmed that there is a process (documented) around reusable assets/components. He offered to discuss with someone from M&C if needed. Laura > David and Ian with this update; if satisfactory for the need specified in this risk, close. Links here: http://connections.ey.net/wikis/home?lang=en#/wiki/Strategy%20%26%20Architecture%20Library/page/Standards%20%26%20Roadmaps%20-%20Platform%20Usage%20and%20Enablement http://quickr.ey.net/LotusQuickr/saea/PageLibrary852576A20065DF81.nsf/h_Toc/9816CEAF5A1BDD19852576A200661FB3/?OpenDocument&ts=1319201730153#%7Btype=1&unid=94C3A972E50260FDC12576DC007C5176%7D http://quickr.ey.net/LotusQuickr/saea/PageLibrary852576A20065DF81.nsf/h_Toc/9816CEAF5A1BDD19852576A200661FB3/?OpenDocument&ts=1319201730153#%7Btype=0&unid=97E8331E4EF2649D852578B5006CC452%7D 22-Aug (LM): Followed-up with Chris; Susan Pietretti will be in touch to discuss. 13-Aug (LM): Discussed with Ian and David and David suggested this would be more appropriately owned by Chris d'Arcy as it is really a risk broader than just M&C. Laura emailed Chris for his input/agreement and update. 18-July: Per Alan, reassigned to David Bingham. LM > David to alert him of reassignment. 23-May: Rewrote Risk extensively following Wall discussion and follow-up between Nick Coburn, Andy Ioannou and Brett van Gelder 16-May: This needs to be escalated to Alan > IT Services leadership. Brett, Nick, and Andy MacRae to talk off-line and take to Alan by next week. 27-Apr: Team determined this is really a risk, not an issue. 23-Apr Brett: This is something that falls mostly in Brian Blinco's Application Architecture function with some involvement from EA Standards Office (Andy Macrae). There is almost certainly need for commitment by IT Services CLT and possible implications from a Methodologies perspective. ​ | L11: http://sp.ey.net/msibm/Lists/Program%20Risks%20%20TEST/DispForm.aspx?ID=&RootFolder=*
A12: 208 | B12: M&C Program | C12: Geoff Thompson | D12: 3) Program Mgt Team | E12: 0 | F12: Test schedule does not allow for effective Integration Testing between O/E & Lync | G12: 07-Nov-12 | H12: -14 | I12: 91 | J12: 17-Oct: Geoff - move this out till after 7/11 when we have a program wide test planning workshop which will look at this and other integration issues. 16 Oct (SB): updated re Test appriach - Simon Barkley 12 Sep CB: reassigned to Geoff ​09 Aug CB: under review by Brian Ford, revising review date to end Sept. | L12: http://sp.ey.net/msibm/Lists/Program%20Risks%20%20TEST/DispForm.aspx?ID=&RootFolder=*
A13: 211 | B13: M&C Program | C13: Rachel Phillips | D13: 3) Program Mgt Team | E13: 2 | F13: Lack of a consolidated deployment strategy for Lync & OE | G13: 13-Dec-12 | H13: 22 | I13: 121 | J13: 26/10/12: RP: awaiting confirmation of final Lync dates and will work to ensure as much alignment as possible for the deployment of both tools. 28/08 (IW) - Meeting scheduled for 30th Aug to discuss alignment further, continued discussion with Lync team on detailed deployment plan and approach which should be ready during the next week. 14/08 (IW) - Regular meetings scheduled to discuss alignment between the teams and get clarity around the possible options. Next meeting 15th Aug. 31/07/12 - Updated details and changed status to active.​ | L13: http://sp.ey.net/msibm/Lists/Program%20Risks%20%20TEST/DispForm.aspx?ID=&RootFolder=*
... A19: 288 | B19: M&C Program | C19: Anthony Firmin | D19: 3) Program Mgt Team | E19: 9 | F19: It is not known how programs which are targeting FY13 release to users will be prioritised in deployment windows or how I&O are required to prioritise deployments given limited resources | G19: 30-Nov-12 | H19: 9 | I19: 69 | J19: 14-Nov: reviewed on fortnightly RAID call; a number of actions underway to look at how deployment schedules line up and the challenge around user experience.A follow-up meeting has been scheduled for next week. Reassigned to Anthony who has taken on the Ent. Planning role for M&C 12-Oct (LM): Combined risk 284 (related) into this. May need to split out based on effect (operational readiness / deployment schedules). Laura sent to Susan 12-Oct for input. 25-Sep (SP): There is a need for guidance from I&O and the Enterprise Planning function as regards the prioritization of deployments across IT Services to determine whether our deployment schedules need to be revised. ​ Escalated to C. D’Arcy 19-Sep (LM): Discussed on fortnightly RAID call; team suggested this be owned by Susan (in line with risk 284) as aren't sure if this is better driven by the Enterprise Planning team. Steve to inform Susan 19-Sep, Laura 20-Sep. 08/09/12: RB logged risk. RB to seek guidance via S Pietretti in Enterprise Planning team, B Pardoe will also raise via J Pritchard. RB also flagged to S Bradley for discussion.​ History of Risk 284 (combined into this): 3-Oct: Susan and Rewa meeting today to develop approach to reviewing deployment schedules. Moving fwd; date should be set for end of Oct. 19-Sep (LM): Discussed on fortnightly RAID call- Rewa scheduled a meeting (Monday) to increase understanding of overall enterprise plan and how will manage business impact of all planned change.The team suggested this should be owned by Susan Pietretti; Steve to inform Susan 19-Sep, Laura 20-Sep. 4-Sept (LM): Per Blaine, the current action on this is that he is working with Gil Levit to address the change impacts of the changes to the operating model, as they are defined​. Gil has surfaced with the leaders of I&O to get their input. | L19: http://sp.ey.net/msibm/Lists/Program%20Risks%20%20TEST/DispForm.aspx?ID=&RootFolder=*
A20: 356 | B20: M&C Program | C20: Paul Thomas | D20: 3) Program Mgt Team | E20: 6 | F20: No nominated one point of contact for Active directory for the programme | G20: 25-Nov-12 | H20: 4 | I20: 0 | L20: http://sp.ey.net/msibm/Lists/Program%20Risks%20%20TEST/DispForm.aspx?ID=&RootFolder=*
A21: 19 | B21: Outlook/Exchange | C21: Rachel Phillips | D21: 3) Program Mgt Team | E21: 9 | F21: Delays in confirming deployment velocity | G21: 16-Nov-12 | H21: -5 | I21: 238 | J21: 21-Nov (DB): Reassign to Rachel (inc. Rachel for awareness) 14-Nov: On fortnightly RAID call, action assigned to Laura to check in with Shaun - Shaun had taken an acction to set-up a task force to look at impact assessment. Neil suggested may either need a second related risk raised for Lync (and possibly Collaboration) or as an alternative make this a program-wide risk and assign to Shaun. 15-Nov: LM > Shaun for his input. 9-Nov IM - continuing to work with Gil through to network teams 1-Nov IM - Meeting arranged 8/Nov with I&O Gil Levit for update on I&O readiness and on Network Assessment validation. Updated trigger and review dates. 29-Oct IM - Related risks 306, 307 and issue 187. Working with I&O on support side for velocity through Shaun/Gil. Working with Network Operations to confirm network constraints before being able to confirm a true velocity that I&O would be required to support. 17-Oct: Reassigned to Ian McGeachie per Rewa on fortnightly RAID call. 3-Oct (MK): <><><><><><><><><><>with all the latest meetings we have had with Gil and the wider I&O groups, we now have a good understanding of the issues that they see can/will impact the plan. We have one more meeting tonight (that I need to prepare for) that will conclude the schedule of meetings...after that we will get a consolidated view of issues from Gil...however - so far we are committed to meet the deployment plan milestone (baseline) on October 15 04-Sep (IW): Service design sessions continuing, briefing by deployment held, explaining deployment approach and drivers. Expect output from sessions over the next couple of weeks which will then be used to drive any updates to the deployment schedule. 28-Aug (IW): Successful meeting held with I&O leadership, strongly supported by Shaun Bradley. Acceptance of need for high velocity understood and details into I&O/ST service design sessions, furthermore design sessions will be kicked off with deployment plan walkthrough presentation. 14-Aug (IW): Action plan in place with Service transition and I&O, aim to host meeting w/c 20th Aug with I&O leadership to ensure common understanding acceptance of planning criteria and constraints driving the plan to date. Taking output into I&O/ST design sessions. Changing next review to 24th August. Furthermore presentation of findings and latest plan will be made available to I&O workshop w/c 27th August, changing trigger date to following week from workshop. 8-Aug (LM): From Prog RAID call, Martin took action to update this item. Will review next week the impact of delaying confirmation of velocity. 19 June 12: Updated impact and effect to match the latest info around delays from I&O. They no longer expect to be able to meet the mid-august confirmation and don't have a new target date yet. We're meeting with Shaun and Nick to discuss on Monday 23rd. Moving the next review date accordingly to end of next week. 07 June 12 : Socialization of draft plan continues under the assumption that I&O will be able to support the velocity in the draft. Changed the review date and required resolution date as discussed with Martin Kremmer. 16 May 12: Working to get the relevant people to review. Currently, it is expected that the review of I&O team will take place on 30 May 12 ​30 Apr 12: Discussed with Martin kremmer: To be reviewed with Sophie.Required resolution date - TBD | L21: http://sp.ey.net/msibm/Lists/Program%20Risks%20%20TEST/DispForm.aspx?ID=&RootFolder=*
A22: 27 | B22: Outlook/Exchange | C22: Rachel Phillips | D22: 3) Program Mgt Team | E22: 6 | F22: There is a risk that end user experience will be impacted if Exchange deploys prior to, or at the same time as, Lync | G22: 23-Nov-12 | H22: 2 | I22: 190 | J22: 26/10/12: extended due date to when we have confirmed Lync timescales. Proposed management through comms and stakeholder engagement and will finalise this once the Lync timescales are confirmed. 08/09/12: RB: Latest update from Lync team is: Pre-pilot Test - April; Pilot - May; Deployment - June. OE Pilot is March, Deployment is April. Change team will manage communications and learning but until there is further clarity on Lync service, further detailed planning to mitigate this risk may be limited. 15/08: RB: Meeting rescheduled from 15/08 to 29/08 due to unavailability of participants. Review date deferred. 31/07: Meeting planned for 19/07was rescheduled as a result of Messaging Workshop and holiday. Meeting to be held 02/08. Trigger date moved back to end September when Lync plan will be more concrete and when we have a clearer view as to I&Os ability to support deployment schedules across Lync and Outlook. 11/07: Two meetings already held with Lync, Transition and Business deployment team. Further updates required when M Kremmer and M Laci return from holiday. Meeting to be scheduled by RB for 19/07 13/06: Lync scope will not be confirmed until the end of June, after which it will be possible to determine what the timeline for deployment is. There are currently suggestions that deployment is being targeted for February 2013 which will be right up against the planned Outlook Pilot. Confirm with Neil and Martin K how deployment plan will factor this in, confirm with Service Transition if Ops can support it, and confirm with Business change that they can plan for managing impact of each outcome on users. 23/05: Review again once Lync vendor in place and there is clarity on Lync delivery timescales​ 19/04/12: RB: Risk created out of decision to close D223 | L22: http://sp.ey.net/msibm/Lists/Program%20Risks%20%20TEST/DispForm.aspx?ID=&RootFolder=*
A23: 34 | B23: Outlook/Exchange | C23: Rachel Phillips | D23: 3) Program Mgt Team | E23: 6 | F23: There is a risk that we cannot determine the total duration of Outlook migrations or the impact on the FY13 budget and effort required from program and I&O resource, nor ability to confirm that we can complete the migrations to O365 in the required 34 wks | G23: 16-Nov-12 | H23: -5 | I23: 274 | J23: 21-Nov (DB): Reassign to Rachel (Rachel inc for her awareness) 9-Nov IM - continuing to work with Gil through to networks 1-Nov-2012 IM - Ownership taken. Working with I&O to determine capacity to handle volume, and to re-validate Network Assessment on velocity. meeting scheduled 8/Nov, next update 9/Nov. Trigger and review dates updated. 08/09/12: RB: Deployment schedule to be validated with Stakeholders by M Kremmer. Contract with MSFT now has 3-month on-prem migration window built into commercial structure, Microland contract will also embed this. Changes to contractually agreed timeline will incur additional cost, program must bear the risk of this. Decision 256 requested to be made by Business Sponsors. J Brown confirmed this should be for the EY executive, not M&C EDG. As contracts now progressed, need to inform executive of risk of changes to migration schedule both for on-prem and O365 and request executive support in ensuring countries agree to migrate per schedule. Next review end of October per milestone for confirmed Business Deployment Schedule. 07/08: RB: Meeting held 02/08 to agree next steps. Nick Coburn to escalate via Service Transition on current I&O plans to manage deployment velocity, Martin to continue to validate migration schedule with business. Follow up meeting to be held 16/08. Network bandwidth assessment outcomes still pending. 20/07: RB: Wording of risk updated. Date moved back as further discussions need to be held with I&O and Business deployment to resolve. Date revised to end of August. 25/06/12: RB: Draft deployment schedule being circulated by Business Deployment team, ongoing discussions regarding what velocity operations can support. Meeting held 22/06 resulted in action for M Laci to secure from I&O an indication of maximum velocity they could support to feed into plan. M Kremmer to provide feedback from business re deployment plan/schedule. Follow up meeting scheduled for 29/06 30 May 12: Martin: Still awaiting confirmation from operations on their ability to support the velocity in the draft deployment plan 18-Apr: Can now start to work with operations to determine what migration velocity will be. Target to have deployment plan baslined at end of May. Updated due date from 20-Apr to 30-May. 02/04/12: RB: Draft pack developed by MK and RB with MK, needs to be presented for approval, already highlighted request for exception to black out periods. 09/03/12: RB: Meeting scheduled for 21/03/12 to agree migration strategy and velocity, and determine how these will be agreed with Microsoft, Ops, and Business 27/02/12: RB: Wording amended. Further discussion needed with Business Deployment, Transition Management, TF and MSFT to agree how to resolve these 22-Feb: Brett clarified: Msft does offer weekend migrations; the open question is that they have never had a client do only weekend migrations. EY had an assumption of weekend migrations in large part because we assumed we could do roll backs, which Msft has now told us with O365 they don't do rollbacks. EY needs to rethink assumptions on migration, thinking through the reasoning, Msft experience, etc. Rewa took an action to update the syntax of this item to reflect Brett's comments above. 21/02/12: RB: Added as output from Assumptions log. Assumption cannot be revalidated​ | L23: http://sp.ey.net/msibm/Lists/Program%20Risks%20%20TEST/DispForm.aspx?ID=&RootFolder=*
A24: 36 | B24: Outlook/Exchange | C24: Alexa Briggs | D24: 3) Program Mgt Team | E24: 3 | F24: Unconfirmed how 3-way lookup will work across O365, on-prem and LN. | G24: 28-Dec-12 | H24: 37 | I24: 230 | J24: 8-Oct - SOW in place, confidence will not be increased until we start testing in December (earliest) 17-Sept - hardware now available and SOW approaching agreement. Risk will be closed once SOW is signed and microsoft is on the hook to deliver a working solution into test 08/08 (PN) - Migration & coex signed off and agreed. Coex VMs ordered and implementation proceeding. Migration & Coex SOW WIP to put Migration on the hook for making 3 way work. Nxt review when have hardware, SOW etc. 22/06 (PN) - Migration & Coexistence document still to be signed off expected final review 28/06 07/06 (PN) - Migration & Coexistence document revisd and under review which will detail the design for the three way coexistence - need to resolve and prove the design before Service Ready for Exchange 13 Nov. 16/05 (RB): Migration & Coexistence document under review, aim is to complete in 3 review cycles rather than 5. With DA for review completion w/e 25/05 ​01/05: - Migration & Coexistence document expected 03_May, will include 3 way design from LN to Exch On_prem & Cloud 15/03/12: RB: CR026 with CCB for approval. Risk downgraded to minor but not to be closed until design is delivered. 12/03/12: RB: CR has been raised by TF Exchange to Microsoft to produce the design for 3-way coexistence. This has not been done before by Microsoft 27/02/12: RB: Update received from PN: "The change request to introduce the work to define the 3-way coexistence into the exchange On-Prem SOW, is still being drafted by Microsoft. We expect it to be delivered to us this week. We do know BinaryTree have a established POC of the threeway in their lab." 22-Feb: Paul and TF in conversations with Msft. Awaiting response from Msft. 21/02/12: RB: Added as output from Assumptions log. Assumption cannot be revalidated (Legacy A72) | L24: http://sp.ey.net/msibm/Lists/Program%20Risks%20%20TEST/DispForm.aspx?ID=&RootFolder=*
A25: 144 | B25: Outlook/Exchange | C25: Charles Sclater | D25: 3) Program Mgt Team | E25: 6 | F25: Dependency on JD&A for application readiness in preparation for rollout/deployment to Pilot countries | G25: 30-Nov-12 | H25: 9 | I25: 147 | J25: 19 Nov - CS working with Deployment to re-plan ZA and DE To Be ExMIA Application Landscape. ZA replanned to sign off 23 Nov,DE signed off 30 Dec. 05/11/12 - CS working with JD&A and SD to finalise/agree DE & ZA As Is and To Be AppLandscapes. scheduled for 16/11/12 12/10/12 - Lock down on pilot countries South Africa, Germany and Ireland. Working with pilot ocuntries to work out remediation. Charlie Sclater 1 Oct South Africa and Germany have been identified as the two Pilot countries for Cloud and On Perm respectively Charlie Sclater 25 Sep: Working with Deployment and JD&A to idetify and prioritise remediation activities. Developed high level stage plan to manage/deliver rememediation for Pilot. 19-Sep (LM): Per Rewa on fortnightly RAID call, working through this with JD&A team; have provided a high level plan and working with James H. to confirm can meet timelines. Trigger date moved out to close of next week. 5-Sept (LM): Rewa will raise for wall call tomorrow. 01-Aug: Steps being taken to resolve challenges surrounding D&A to ensure that impact assessment is completed and applications start getting remediated through the Service Delivery 'channels' to allow impact applications to be reconfigured, enhanced and tested before the migration of users. 25-Jul: ​Martin provided update on RAID call; plan in place which will bring to mid-Sept before will know impact on the on apps. Socialize mid-October. Martin will update further. | L25: http://sp.ey.net/msibm/Lists/Program%20Risks%20%20TEST/DispForm.aspx?ID=&RootFolder=*
A26: 213 | B26: Outlook/Exchange | C26: Rewa Bouji | D26: 3) Program Mgt Team | E26: 4 | F26: Commitment for O365 and On-premises services to be consistent gives rise to cost impact for upgrading on-premises infrastructure and undertaking further on-premises migrations when O365 moves to Exchange 2013. This is not budgeted for in FY13. | G26: 30-Nov-12 | H26: 9 | I26: 103 | J26: 04/11: RB: Microsoft have confirmed that Exchange 2013 is not an in-place upgrade and will require parallel infrastructure to be installed in all on-premises locations. No detail as yet around likely extent of infrastructure that can be re-used. Highlighted to Exec Sponsor Meeting on 06/11 as a watch item. RB working with BvG and DB to agree next steps. 12/10/12 - RB - Further clartiy required date pushed. 07/08: RB: Meeting held with Peter Li from Microsoft to explain scope of change and likely impact on infrastructure budget. Total value of investment required not yet known. Meeting to be held in two months to determine what financial planning needs to be undertaken. It is expected that at this point there will be further clarity on Microsoft's release dates for Exchange 13, for confirmation of the FY13 budget and also on the on-premises deployment timeline which may influence investment decisions. 24/07: RB: Risk logged. Meeting to be held 01/08/12 with Peter Li to understand scope of impact as a result of upgrade. EY team to then discuss next steps and develop resolution/mitigation plan.​ | L26: http://sp.ey.net/msibm/Lists/Program%20Risks%20%20TEST/DispForm.aspx?ID=&RootFolder=*
A27: 222 | B27: Outlook/Exchange | C27: Rewa Bouji | D27: 3) Program Mgt Team | E27: 6 | F27: Risk the build of On-Prem countries in scope of DCC will slip (china and austraila) | G27: 31-Oct-12 | H27: -21 | I27: 79 | J27: 16/10/12: RB: RB, A Briggs & D Bingham met with Gareth Thomas in the DCC program 15/10. DCC are working on responding to our request for confirmation of the DCC schedule per our requirements, and also on the cost of each on-prem site build so that we can raise a CR for the costs (logged under R258). The estimate Gareth gave was that they would have a response in the next 2-3 weeks, but we did not have any firm date for delivery. 8-Oct - no response from DCC issue escalated to Rewa being managed in weekly calls with DCC and escalations | L27: http://sp.ey.net/msibm/Lists/Program%20Risks%20%20TEST/DispForm.aspx?ID=&RootFolder=*
A28: 259 | B28: Outlook/Exchange | C28: David Bingham | D28: 3) Program Mgt Team | E28: 2 | F28: Outlook/Exchange Delivery will proceed without the 8 "TBC" countries being included in scope | G28: 07-Dec-12 | H28: 16 | I28: 90 | J28: 21-Nov (DB): meeting to arrange with Tim / Mo / Alan - to work through the options and the impact of the delay in decision making - likely to be first week in December 16/10/12 RB - Risk ownership reassigned to David Bingham from C Burnside. Ian McGeachie leading activity to confirm country status, working with Q&RM. D Bingham has also escalated​ to J Murphy. Target is for resolution by mid November so that on-prem hardware orders can be submitted by 1 December 03-Sep-12 CB: risk accepted and explained to Q&RM and EYGS Account Lead for EMEAI Richard Sheldon. 12-Sep-12 CB: reduced Prob from Med to Low and Impact from High to Med. Also set next review to end of the year as possible that decisions for these 8 countries will take to end of year so risk remains until that time. | L28: http://sp.ey.net/msibm/Lists/Program%20Risks%20%20TEST/DispForm.aspx?ID=&RootFolder=*
A29: 279 | B29: Outlook/Exchange | C29: Shaun Bradley | D29: 3) Program Mgt Team | E29: 0 | F29: MSP Vendor Business case could be eroded if further on prem countries cannot be supported offshore | G29: 16-Nov-12 | H29: -5 | I29: 45 | L29: http://sp.ey.net/msibm/Lists/Program%20Risks%20%20TEST/DispForm.aspx?ID=&RootFolder=*
A30: 286 | B30: Outlook/Exchange | C30: Charles Sclater | D30: 3) Program Mgt Team | E30: 6 | F30: Approval/Budget for all Cross Org Application Remediation | G30: 30-Nov-12 | H30: 9 | I30: 74 | J30: 19 Nov CS: ZA and DE To BE ExMIA Landscape Singoff delayed to 23 & 30 Nov respectively. Milestone will drive ExMIA Remediation scope, resource requirements and budgets 5 Nov CS: working with JD&A and ZA&DE to approve To Be App Landscape due 16 Nov, which will then drive ExMIA's App Remediation scope 12/10/12 - reviewed by CS at RAID call. Charlie Sclater 1 Oct: JD&A has some budget to remediate priority applications, currently working with Deployment to prioritise EMIA applications. Current plan is to have assessment completed by 15 Oct Jon Els Focus is align and prioritise app remediation to support Deployment Schedule, thus remedation of Pilot Country's apps will be highest priority | L30: http://sp.ey.net/msibm/Lists/Program%20Risks%20%20TEST/DispForm.aspx?ID=&RootFolder=*
A31: 287 | B31: Outlook/Exchange | C31: Rewa Bouji | D31: 3) Program Mgt Team | E31: 0 | F31: There is a risk that program delivery milestones will be impacted by resource availability constraints over the Christmas period | G31: 23-Nov-12 | H31: 2 | I31: 68 | J31: 04/11: RB: OE plans under review to determine if any slippage will be caused by resource absence. 15/10/12 - RB - No comms from Cross Org or I&O. Resource gaps need to be identified in workstream plans as orginal timelines need to be adhered to. RB to continue to escalte with Alan/David. 28/08/12 RB: Logged. RB raised with DB and IB. DB agreed to discuss with AG and SB as requires coordinated response across Cross Org, I&O and other IT teams.​ | L31: http://sp.ey.net/msibm/Lists/Program%20Risks%20%20TEST/DispForm.aspx?ID=&RootFolder=*
A32: 311 | B32: Outlook/Exchange | C32: David Bingham | D32: 3) Program Mgt Team | E32: 4 | F32: Risk hardware ordered for on prem countries prior to country buy-in and design being proved will be incorrect and further duplicate spend needed for implementation | G32: 01-Dec-12 | H32: 10 | I32: 32 | J32: 2-Nov: Per David, no orders will be placed until BOM is defined and agreed - and country is cleared to be on prem - move out to December 1 for check point ​ | L32: http://sp.ey.net/msibm/Lists/Program%20Risks%20%20TEST/DispForm.aspx?ID=&RootFolder=*
A33: 329 | B33: Outlook/Exchange | C33: David Bingham | D33: 3) Program Mgt Team | E33: 6 | F33: Countries not aware of the financial or operational impact of going On-Prem, so risk they won’t order required hardware on time | G33: 16-Nov-12 | H33: -5 | I33: 30 | J33: 21-Nov (DB): Meeting held with Paula Bowie - to build the cross charge framework - need to take the message and use the area relationship managers, Sherry Martin and Paula Bowie, to cascade the approach. Remains overdue. 21-Nov (DB): Assign to David. 9-Nov IM - On Prem deadline escalated to Mo/Tim. Continues to be in focus. 22-Oct - risk raised and managed by the ongoing work of Ian McGeachie.​ | L33: http://sp.ey.net/msibm/Lists/Program%20Risks%20%20TEST/DispForm.aspx?ID=&RootFolder=*
A34: 139 | B34: SharePoint | C34: Dave Fraser | D34: 3) Program Mgt Team | E34: 6 | F34: SP15 Key Delivery Dates | G34: 15-Feb-13 | H34: 86 | I34: 138 | J34: 15 Oct - DF - MS has annouced RTM for SP 2013 and Office 2013 so the Dec data has been mitigated. Our remaining risk is RTM for 2013 on O365. This is scheduled for 1 April 2013 and EY has been identified to be included in the first wave of customers to upgrade. There will be a pilot upgrade with another customer in February so that will be our next checkpoint on this risk. See the bullets below that were provided by O365: Key point are as follows: - There was not a commitment by Dave or Bob E&Y would be upgraded by 4/1/12 - There are NO confirmed / committed upgrade dates yet. - The first wave is TARGETED to start in the April / May timeframe - The duration of the wave and upgrading are unknown at this point - E&Y is included in the first wave - The first pilot upgrade is targeted for February - After the first pilot is complete, a schedule will be determined 19 July (AI): Have adjusted required date and review date to align with RTM announcement. 19-July (LM): Per Andy, keep status active to track mitigations as related to RTM and SR in O365. Andy will adjust due date to be closer to RTM date. 18-July: Dave said he considers this closed but left for EY agreement. LM > Brett, Andy and David to confirm closure. Brett confirmed as the risk has been acknowleged and team is activly mitigating. 10th July : See updates in Risk Triggers above for latest on the dates. Participation in the TAP program which has started will give the team insight into the product quality throughout the pre-release cycle. 3rd July : (NC)​ Dave to update to reflect the latest known dates. Please ensure you include the fundamental change in understanding of Beta 1/2 | L34: http://sp.ey.net/msibm/Lists/Program%20Risks%20%20TEST/DispForm.aspx?ID=&RootFolder=*
A35: 242 | B35: SharePoint | C35: Sherry Martin | D35: 3) Program Mgt Team | E35: 6 | F35: Risk that will not deliver extranet capability in SP in time per business need | G35: 30-Nov-12 | H35: 9 | I35: 85 | J35: 5-Nov (SM) This is definitely not in scope for R1. As prioritization efforts for R2 are not likely to be concluded until end of November or mid December, this item will be re-evaluated to determine if the risk still exists. It is planned that extranet would be included in R2 scope; however, there are no agreements on how data would be kept secure, how users would collaborate (inside or outside of extranet) - essentially, requirements have not been fully gathered. 20-Sept (NC) Expectation is the Release 2 planning and scope prioritisatio will have been defined by 15th October. If the prioritised scope requires the extranet however the extranet itself is not part of the R2 scope mitigation will need to be considered. 17-Sep: David provided desc update, prob. and impact info, trigger date. Trigger date will be scope for R2 sign-off. 18-Sep: Lauren>Nicola for date. Laura to update once receive response. 27-Aug (AI): without completing roadmap planning for future Collaboration releases - planned Oct 2012 - M&C cannot commit to introducing extranet capability by Dec 2013. 14-Aug: Added by Laura per call with David and Ian. Laura > David for additional details.​ | K35: 6-Nov: LM > Sherry - new trigger date? | L35: http://sp.ey.net/msibm/Lists/Program%20Risks%20%20TEST/DispForm.aspx?ID=&RootFolder=*
A36: 336 | B36: SharePoint | C36: Andy Ioannou | D36: 3) Program Mgt Team | E36: 6 | F36: Beta Pilot Deploment Schedule at Risk, concern regarding risks to "happy path" deployment schedule | G36: 25-Nov-12 | H36: 4 | I36: 25 | J36: 19-Nov(LS): Merged Risk 346 "Concern regarding risks to "happy path" deployment schedule" assigned to Cynthia into this risk. 16-Nov (AI): black-out period from 17/12 - 04/01 being upheld by O365 team. HAve therefore had to rethink deployment approach and plan. Decision taken to split deployment into 2 batches: Batch 1 (core functionality): plan to start deployment following CVS completion (27/11 - 28/11) and complete by Fri 14th Dec. Solution would then, technically, be live and available for user operation, although this is only expected from the New Year. Batch 2: (non-core functionality comprising profile sync of custom attributes and deployment of search crawl to update indexes): plan to execute 4/1 - 30/1. Impact on users operating Beta Pilot during Jan is inability to search for content or people using custom attributes. Risk deemed acceptable, however, decision to go live in this state will be governed by 'Go / No Go' process. 29-Oct (AI): ​Awaiting repsonse from Howard as per contingency plan. | L36: http://sp.ey.net/msibm/Lists/Program%20Risks%20%20TEST/DispForm.aspx?ID=&RootFolder=*
A37: 47 | B37: Transition | C37: Nick Coburn | D37: 3) Program Mgt Team | E37: 6 | F37: Complex deployment of Outlook and SharePoint | G37: 30-Nov-12 | H37: 9 | I37: 249 | J37: 04/04: Remain at high. Further information on impact following Service Design. 7-Mar: Nick provided additional detail for this item. R107 closed as it is accounted for in this item.​ 31/07 - Still open as a risk. We need to agree the deployment approach to determine what the impact will be. Sessions are planned with Martin Kremmer. 18/09 - Nick Coburn - Still open - deployment schedule is still to be determined though I/O are working closely with deployment on this. 19/10 - Remain open until deployment plan finalised. Likely to become an issue as overall cost will increase. | L37: http://sp.ey.net/msibm/Lists/Program%20Risks%20%20TEST/DispForm.aspx?ID=&RootFolder=*
A38: 109 | B38: Transition | C38: Nick Coburn | D38: 3) Program Mgt Team | E38: 6 | F38: Cross programme release management | G38: 30-Nov-12 | H38: 9 | I38: 145 | J38: Nick Coburn 31/07 Still an open risk - working through with program and I/O but overall deployment and release strategy both within MC and across all programs is not clear. NC 18/09 - Still open and decisions remain re GCL5, and deployment and of Lync and OE. | L38: http://sp.ey.net/msibm/Lists/Program%20Risks%20%20TEST/DispForm.aspx?ID=&RootFolder=*
A39: 142 | B39: Transition | C39: Nick Coburn | D39: 3) Program Mgt Team | E39: 6 | F39: The current I&O Change Management process does not support the planed rollout velocity for Lync and Outlook. | G39: 30-Nov-12 | H39: 9 | I39: 123 | J39: ​Nick Coburn 31/07 - Engaged with Business Deployment team to ensure that I/O input is included in the deployment approach and schedule. Nick Coburn 18/09 - Still open and being worked with delivery team, deployment and I/O. Neext meeting w/c 17/09. | L39: http://sp.ey.net/msibm/Lists/Program%20Risks%20%20TEST/DispForm.aspx?ID=&RootFolder=*
A40: 318 | B40: Transition | C40: Nick Coburn | D40: 3) Program Mgt Team | E40: 6 | F40: I/O may not sign off deployment plan without IT Services as early adopters | G40: 16-Nov-12 | H40: -5 | I40: 18 | L40: http://sp.ey.net/msibm/Lists/Program%20Risks%20%20TEST/DispForm.aspx?ID=&RootFolder=*

Sheet Issues
A1: ID | B1: Workstream | C1: Assigned to | D1: Profile | E1: Impact | F1: Title | G1: Required_Resolution | H1: Countdown | I1: Days Open | J1: Update Log | K1: PMO Check | L1: URL
A2: 18 | B2: IAM | C2: Ted Balfour | D2: 3) Program Mgt Team | E2: 3) High | F2: No policies or procedures have been provided by M&C for Group Management | G2: 11-Dec-12 | H2: 20 | I2: 206 | J2: 19-Nov: Ted sent note that req res date should be moved to 11-Dec-12. 14-Nov: Per update from Rewa and Ted on fortnightly call, they discussed off-line and need a new date; Rewa will follow-up with Charlie and Matt for a confirmed closure date. 17-Oct: Action taken on fortnightly call for Rewa and Ted to discuss off-line; currently need to determine new date. 3-Oct: Per Rewa, this is progressing; Sunil and Charlie are driving this, business manager for group management confirmed. Workshops scheduled for next couple of weeks. 19-Sept (LM): Per Rewa on fortnightly call, IAM still waiting on OE for policies and procedures. Workshop is being scheduled to gain an understanding of the gaps and who the business/IT owners are of the app; this is to be held within 2 weeks. 17-Sept (DW). We are deploying the infrastrucutre into EYUA from the 18 Oct. As we currnetly have no areement with respect to these Policies etc, the Service will not be available (although ALL Functional Capabilities will be available but not "Switched On"), until M&C advise/confirm. FYI, IAM had a draft available, and will be socialising hese with M&C by COP Tuesday 18th Sept. 14-Sept (Ted): I have passed this on to all parties involved to provide proper updates, including a resolution date by the next RAID meeting. 5-Sept (LM): Per Ted on fortnightly call, he will follow-up with Rewa and Nikolay. 29-Aug: LM > Daren again per Ted for date. 23-Aug: Charlie, Daren and Ted discussed and agree this should remain open. Laura > Daren, Ted for true RRD. 22-Aug (LM): Per fortnightly call, looking to roll out Group Management in October, but won't be effective without policies and procedures. Charlie was in a workshop with Ant Harper, Nick Wood and Daren Wicks to discuss, and believes this is resolved. Ted to circle back with Daren for his input. Charlie also to assess in terms of milestones and whether there are any issues around the delivery date. 15 Aug - Strategic discussions around EY Group Management are being led betwen the IAM DA, M&C EA and GLMS Team. Decisions are due w/e 17th Aug, that are very likely to impact what Group ID will deploy, and thus the associated Policies, procedures etc. A Draft version of this has now been provded by the GLMS Team, however, the review has been postponed until next week, when more direction wil be made available post this weeks Strategic conversations as mentioned above. This will also feed into the discussions and information required from M&C. Theses discussion will also impact the required by date. As mentioned in the description field above, IAM are NOT responsible for these policies, and thus we may end up in a situation where we deploy the Product and associated capabilities, and M&C will work with a viaraety of teams to Manage and deliver the associated Policies etc. Clearly we (IAM) are trying as much as possile to help, but we cannot delay the deployment into Production, as there are also competing Programs looking to utilise this service. DCC being but one example. 8 Aug - Provided feebdack to M&C Team. Awaiting feedback on next steps. 25-Jul (LM): Per Ted, Rewa's team working to provide this; updated date pending. Ted will update. 30-May (LM): Rewa - a BA is helping out on this and the output will go to governance group. This will remain open until there is a solid approach on groups. 9-May: Paul will follow-up with Rewa for an update and due date. 27-Apr: per Daren, R126 now an issue. 14-April - Requirements discussions are now taking place betwen M&C and IAM. This is now also an issue, and thus shoulod be moved to the issues log.​ | L2: http://sp.ey.net/msibm/Lists/RAID%20%20Issues%20TEST/DispForm.aspx?ID=&RootFolder=*
A3: 98 | B3: LNDR | C3: Christian Driver | D3: 3) Program Mgt Team | E3: 2) Medium | F3: No decom/archive capability within I&O | G3: 23-Nov-12 | H3: 2 | I3: 141 | J3: CD, 15-Nov-12: Update provided in Planned Resolution. Next review date updated to reflect anticipated resolution date. CD, 02-Nov-12: Update provided in Planned Resolution. Next review date updated to reflect anticipated resolution date. CD, 18-Oct-12: Update provided in Planned Resolution. Next review date updated to reflect anticipated resolution date. CD, 20-Sep-12: Work started to plan out deactivation capability with I&O. Plans updated to reflect this (CR100). Issue left open to ensure continued focus on finding a timely resolution. CD, 02-Aug-12: Updated issue to reflect conversations with I&O that indicate they will not able to support deactivation work until at least November 2012.​ | L3: http://sp.ey.net/msibm/Lists/RAID%20%20Issues%20TEST/DispForm.aspx?ID=&RootFolder=*
A4: 190 | B4: Lync | C4: Neil Sahdev | D4: 3) Program Mgt Team | E4: 3) High | F4: ATT Plan does not support FY13 'go-live' for Lync | G4: 31-Aug-12 | H4: -82 | I4: 137 | J4: 14-Nov: Per Neil on fortnightly RAID call, working with AT&T, expecting an update after 4pm today. Neil to update thereafter. 2-Nov: LM > Neil for Planned Resolution/Affected detail.​ 26-Oct: NS > Neil raised to supercede Issue 20. 09/11 - NS - Escalation call scheduled Fri 09/11/12 | L4: http://sp.ey.net/msibm/Lists/RAID%20%20Issues%20TEST/DispForm.aspx?ID=&RootFolder=*
A5: 26 | B5: M&C Program | C5: Steven Jelf | D5: 3) Program Mgt Team | E5: 3) High | F5: Limited traction being made on reducing the outstanding dependencies. | G5: 19-Dec-12 | H5: 28 | I5: 301 | J5: 2nd Nov - This is an ongoing issue. Alignment now reduced to 31%over the last month. Many mis-alignments due to PMs not speaking and agreeing dates / updating plans. Working with EP team on Interdependencies between programs, especially regarding better alignment processes between M&C and IAM programs. Additional work now being undertaken regarding internal dependency management within the Outlook / Exchange team. Date being pushed back by one month to monitor progress. This issue will be ongoing. 2nd Oct SJ) - Deep Dive session highlighted additional concerns so depdendency alignment was not the focus. Overall we continue to be aligned around 55%. Further deep dive session to be held, once plans are re-baselined for Exchange / Outlook, AT&T have a plan that EY buy into for Lync and it is understood how we can best align dependencies between to / from SharePoint given that the Infrastructure element of Collobaration is not longer aligns with EY Planning standards. The situation is being monitored, but pushing date out to end of Oct. 19-Sep (LM) - Per Steve on fortnightly call, traction being made, almost to 60% alignment. Areas of concern include lack of DCC schedule. Drains up review scheduled for 26-Sept. 4th Sept Traction being made on IAM dependencies - session held with Bharat (IAM dependency contact). Currently IAM use a separate spreadsheet to update depedencies, however there is no linkage to dependencies stored on IAM plans which is the central source for the EP team to take and produce metrics each week. Agered with Bharat that a separate follow up will occur weekly to ensure alignment is known and missing dependencies are entered on relevant plans. 20th Aug - Further internal dependencies coded regarding Outlook / Exchange. SP dependencies reviewed and work stream is standardising descriptions. PMO process documented and in place. Dependency aligment has risen above 50% for the first time in several months, Further work required to align dependencies internally to the work streams which will still take a number of weeks to code / correlate, but positive movement is being made. 1st Aug - Further internal dependencies have now been coded. Full analysis of dependency alignment report has occured. MEssaging fortnightly external program dependency meetings recommenced 1st Aug. Alignment now creeping up and will be over 40% this week. Further session organised with Enterprise Planning team on the internal dependency coding efforts required. 11th July - Date moving out - Planning standards enhancements being embedded into the plans and internal dependencies are now being fed into the plans allowing the complete picture to be tracked. This will be a gradual process. 13th June - Due to Program changes (ADM, SharePOint etc), Level 3 plans need again to be updated. Once this occurs, dependencies can then be removed / adjusted. Lync dependencies still not clear at this point, Majority of the Exchange / Outlook dependencies have been coded. - Further work required on alignment especially with the DCC Program. 09th May - EP team still coding of new dependencies. Starting to re-align dependencies and holding bi-weekly meetings with all teams. This will be a gradual process that will still take a number of weeks to resolve. 16th April Level 3 detailed plans starting to be reconstructed and dependencies at least on the core dependent programs (IAM) starting to be agreed. Dependencies between ADM and SharePoint now also starting to be aligned and dependency meetings now set up for all core programs. Further work is required on the revised org structure / remaining dependencies as previous dependencies now need to be validated. This will be a slow process to amend and fix, but the process has now started 4th April - Work continues on replanning. Level 0 and 1 plans are now in place for all work streams. However, detailed MPP's need to be rebaselined. Dependency management meetings will occur after Easter every 2 weeks. Working with EP team to code new dependencies when plans are re-baselined. 17th March - As expected, dependencies have reduced in alingment due to new plans being submitted. Resolution will be (a) Ensure Org restructure is known to determine if dependencies still exist. Secondly fortnightly meetings occuring on aligning dependencies throughout the M&C program 7th March - Dependencies are still likely to reduce over the next weeks whilst plans are now being refined based on potential org structure changes. 29th Feb - Dependency Alignment will dip further over the next 2 / 3 weeks as new plans replace the originals. Dependency alignment meeting with key external programs booked every 2 weeks from 15th March 15th Feb - Dependency alignment reduced to 51% - SharePoint and TF Lync plans are effectively shelved and a new plan is being constructed. Dependencies will be mis-aligned at least until 1st March, 31st Jan - Dependency alignment 58%. 2 plans will be dropped (Lync and SharePoint) as a complete replanning exercise is required. Therefore dependency alignment is projected to drop further. 23rd Jan - Dependency alignment 53%. There are a number of dependencies that could be aligned , but due to significant replaninng tasks being undertaken, current plans are effectively shelfed at this point. 17th Jan - Dependency alignment 49%. This will continue to drop as plans need validation. 11-Jan: Steve thinks got up to 60% this week, but this will probably reduce as replan on account of BPOS. As for a req. resolution date, this is dependent on re-planning of the SP and Exchange streams. For now, TBD; review again end of February. 06th - Jan. Dependency management meetings held with M&C Program Managers and external programs every 2 weeks, but in certain work streams sufficient priority isn't given to resolving this. ​ | L5: http://sp.ey.net/msibm/Lists/RAID%20%20Issues%20TEST/DispForm.aspx?ID=&RootFolder=*
A6: 116 | B6: M&C Program | C6: Laura Murphy | D6: 3) Program Mgt Team | E6: 3) High | F6: Exceeded item threshold limit for M&C Program library in SP | G6: 12-Dec-12 | H6: 21 | I6: 118 | J6: 13-Nov (LM): Continuing efforts to reduce documentation stored in site. Laura working with Scott around the possibility of increasing storage capacity. 2-Oct: Call with Ian and Brett. Workstream/library split to being with PMO mid-week, other workstreams to follow. Laura to submit newsletter article for this and next with what is coming and best practices moving forward. Upon moving will further restrict version history. Found Web Analytics and will use this to monitor Storage issue. Will encourage indiv to clean out documentation, reorg to use less folders, etc. Follow-up call scheduled 9-Nov to review progress. 14-Sep (LM): Flipped setting to save drafts for 10 major versions; no effect on item count. Meeting scheduled with Ian and Brett to discuss further on 28-Sept. Will then run a sanity check of plan by Norm or Mike N. Also thinking about this in terms of being able to provide guidance to future instances of SP. 12-Sep (LM): Discussing with Ian on 13-Sep; suggest implement setting of save draft versions for 10 mjr versions (likely will not have an impact) Thereafter sched meeting with Ian and Brett to discuss options for refining the setting. 5-Sept (LM): Plan to test setting on separate folder/library; see how works so can best determine # major versions to keep minor versions for. PMO continues to take re-org of SP site forward. 29-Aug (LM): Setting works differently than anticipated; working with Brett to determine # of versions (maintains minor versions for X number of major versions, as opposed to say, 10 minor versions). 14-Aug (LM): Second comm announcing the impending version limit settings (10 minor, unlimited major) distributed 13-Aug with implementation date of 28-August. Review at that point. 25-July (LM): Discussed on program RAID call; agreement by those on call to request clean-up actions be taken by streams to clean-up. First comm pending approval by David prior to send. 19-July: Added to RAID log by Laura. Action plan established and agreed with Ian/Steve. Initial comm to inspire awareness and behavior change drafted and sent to Steve/David for their review. Brett working with Msft team to determine areas where there are a large number of versions saved that will help us to determine 1. areas where we may lose versions upon implementing a limit, and 2. an appropriate limit to set such that we maintain a beneficial history of changes, but not so many that we cross the threshold.​ | L6: http://sp.ey.net/msibm/Lists/RAID%20%20Issues%20TEST/DispForm.aspx?ID=&RootFolder=*
A7: 150 | B7: M&C Program | C7: David Bingham | D7: 3) Program Mgt Team | E7: 3) High | F7: Current plans (L0,L1&L3) are outdated without the extent of slippages being known. | G7: 30-Nov-12 | H7: 9 | I7: 77 | J7: 21-Nov (DB): CR raised and approved for the re baseline of the outlook / exchange plan. Work is on going with ATT to agree a baseline plan - expectation is by end of November plans will be agreed and appropriate CR raised. Move date to end Nov. 10-Nov - CR has now been approved for Exchange / Outllook. L3 plans to be updated accordingly and baselined. There is still no traction being made with regard to Lync. Awaiting AT&T to review and commit to dates that are then accepted by EY. - Expectation is this will occur around the end of Nov now. 14-Nov: Reviewed on fortnightly RAID call; for the O/E piece of this, the CR was submitted this week, hoping for approval 15-Nov. For Lync, looking to go the CR route once issues are resolved (contingent upon resolution of I190. 2-Nov: Per David, 2 updates, for O/E CR to be raised and sent to CCB 8th November for review. For Lync - escalation raised to ATT through Mo to allow plan to baseline - checkpoint 9th November 17-Oct: sessions scheduled with Lync and Outlook this week to determine whether need CR. David reiterated on fortnightly RAID call that this is a huge issue presently. 10-Oct: Updated Assigned to to David (per Craig). Craig included David on the request for his awareness. 3-Oct: Per Steve, have had 2 deep dive sessions and have an agreement to review with David prior to raising CR. This meeting scheduled for early next week and by end of next week should have confirmation of way forward. 19-Sep-12 LM: Update from fortnightly RAID call - David to review with Neil (Lync) and Rewa (O/E) prior to either raising a CR. 05-Sep-12 CB: both OE & Lync programs will rebaseline within next 2-3 weeks. Expecting to close this before beginning of Oct Exec Steering Committee. Next issue review on 19th is timed nicely on basis that OE is expecting to have rebaseline plan via CR on 14th Sept and Lync should have agreed SOW for Technical Preview and be able to at least indicate for remaining 2/3s of DC build out what the timeline is and have estimated start date based on commercial position of that SOW at that time. Steve Jelf: Would suggest this needs to be resolved in time for the next Exec Steering Comittee Meeting and to share revised dates with Exec Sponsors.,​ | L7: http://sp.ey.net/msibm/Lists/RAID%20%20Issues%20TEST/DispForm.aspx?ID=&RootFolder=*
A8: 33 | B8: Outlook/Exchange | C8: David Bingham | D8: 5) Steering Committee | E8: 3) High | F8: Countries which will have email hosting on-premise are unclear | G8: 30-Nov-12 | H8: 9 | I8: 443 | J8: 14-Nov: Reviewed on fortnightly call. Per Rewa, summary pack delivered. This has the highest visibility possible (with John Murphy for resolution). It looks like 30Nov won't be met; will schedule countries as get confirmation of status. 08/11/12: RB Summary pack produced for escalation to IT Services Leadership to request support in closing out this issue. Deadline set of 30/11 as on-prem hardware orders must be placed by 1 December to meet on-prem deployment schedule and contracts agreed with Microsoft and Microland. 05-Sep CB: Susan advises she and Karin will be able to inform on timeline once they have met together this week. I anticipate it will be several weeks before the communications to clients occur and we have a clear outcome on whether any countries will be added to the on-premise list. 03-Sep CB: Karin Lutz and Susan Chakarian developing a decision tree to provide guidance for clients who raise concern about EY moving their in-country email to cloud. CB requested timescales for this on 3rd Sept. CB reminded the group that we are proceeding on basis that these countries will not be on-premise, so risk is that there may be one-off migration costs as a result of not being able to migrate within the provisional 3 month on-premise migration window of Aug-Oct 2013. Reiterated that this cannot be open-ended as delivery scope includes migration of these countries. Changed Required Resolution date to end of year with monthly reviews. Issue remains open until either these countries remain as going to cloud or if by when clarity is achieved then they become a CR back into the program to put them on-premise. 09-Aug CB: asked Mira & Susan for update on when Tim & John would be advised of Q&RM commercial assessment output. I am informed that it will be a further 2 weeks, due to leave, before this will be communicated and only then will the communication with the countries be commenced. Revising due date to end of September 2012. This update does not change direction to proceed on-premise delivery plan as per current baseline plan for the 12 countries detailed in the 10th July presentation which have not changed their status. For 8 countries remaining, their provisional status is to move to cloud so they should be treated as CRs if and when they become on-premise countries. 2-Aug: LM - Updated due date as per Craig's update below. 27-Jul CB: update received from Mira Tugnait who is leading Q&RM commercial review and risk assessment with local firms on whether local commercial arrangements require email to be stored within country - report findings making 'very good progress' but will be a further 2 weeks (so by 10th August) before report conclusions will be advised to Tim Eddy. Tim will then take that output to the country firms, via SAMPs, to drive the decision. Note this is relevant predominantly to the remaining 8 countries where there are 'market drivers' however DCC report output and ITS recommendation are that they move to the cloud. For 12 countries which have been identified to stay on-premise (full list is 12 out of 21 originally, no more are expected to be added but there is risk that in advising a country firm where their email will be stored, following earlier risk assessments, that the email hosting plan will not be accepted). Revising due date to 31st August on basis of 2 weeks after 10th Aug - this date consistent with what is being communicated to Exec sponsors (inc Tim) on 30th Jul update meeting. Also revised issue title to be more clear. 25-Jul (LM): On RAID call - reconfirming countries going on-prem. Action taken to discuss off-line. 16-Jul - Tim Eddy now pushed date out to 20th July, this is now critical path and delaying the exchange on-prem project day-on-day 27/06: RB: Required date has now moved to 15 July per agreement with Tim Eddy who is now engaging with the country leads to confirm their on-prem status. 21-Jun - re opened as this item is still causing project issues to the on-prem delivery 7-June (LM): Closed per Craig with planning assumptions. D20 should remain open for now until formal decision. LM > Craig to provide CR # so can include with decision at that point. 30-May (CB): Armenia, Azerbaijan, Belarus, Georgia, Kazakhstan, Ukraine, Uzbekistan, India (inc Americas & EYGS) will all go to O365. Planning assumption that Korea, Dominican Republic, Guatemala will also move to O365. AG advises agreed with JC that a further week is given to determine if UK, Australia & Germany stay on-prem (no hybrid). Fortnightly call - (CB) - if no decision reached by end of the week, will use planning assumptions (listed above). 22-May: (LM) On Get to Green call, Alan took action to have resolution by 29-May. 21-May: Alan sent update that he expects confirmation this week. 16-May: No update; still with Alan. ​9-May: Escalated to Alan to push for a decision. Added to management pack as top critical issue. 1-May-12 - re-opened issue as ongoing delays in the on-prem location decision (D92) is now causing delays for the On-Prem delivery (MSP contract, hanrdware ordering) and O365 delivery (purchase of licences for outlook in the cloud) 6-Mar: Closed this issue; will track from the decision on the same topic, D92. 15-Feb: Work in progress (working with Siggi and John); open in decisions, as well. will be 1-1.5 months before we understand this. Review 1 month. 11-Jan: Brett said we have the Q&RM report that says with exception of India, others in the red box will be on-premises. Al took an action to provide Adrian a list of countries building in or not building in (this will prob. come from Bob Reiner). Review beg. February. 04-Jan: Review next week; this is mostly resolved but we need Adrian's update (might be just about 8 remaining countries now) 23/11 - Adrian suggested we push review out 2 weeks as more clarity is sought around this. The next round of discussed are scheduled for this Thursday. 26/10 - Adrian said this is complex and at this point sits in hands of Q&RM and Brett. Next review date mid November. 19/10 - Adrian has questions around this. Laura to schedule meeting for Adrian and Brett to discuss. 05/10 - Brett provided updated description/impact. Assign to Mark/Paul to take it forward. Action created to engage with Q&RM for Lync, Outlook and SharePoint to determine exactly which data are restricted from the Secaucus data centre. 22/09 - There is an assumption that Secaucus in the data centre for the Americas. There are 16-28 countries that will now require data to be maintained in-country. EA, Strategy and Q&RM are working through the implications to clarify what planning is needed to move forward. 14/09 - Brett sent updated description to Adrian. Action for Adrian to update accordingly. Brett has a colleague who is chairing activities to clarify with Q&RM a far more detailed approach. We won't know the impact until following these activities. 07/09 - A number of discussions going on in Enterprise Architecture to determine what the implications are. Follow-up next week to see if we've determined anything further (Brett). 31/08 - Opened by Juan. | L8: http://sp.ey.net/msibm/Lists/RAID%20%20Issues%20TEST/DispForm.aspx?ID=&RootFolder=*
A9: 75 | B9: Outlook/Exchange | C9: Rewa Bouji | D9: 4) Managing Sponsor | E9: 3) High | F9: Lack of a confirmed DCC schedule is impacting planning for On-prem build and deployment | G9: 31-Oct-12 | H9: -21 | I9: 171 | J9: 14-Nov: Per Rewa on fortnightly call, this has been esc to David; still awaiting confirmation of date. 16/10/12: RB: Meeting held with D Bingham, A Briggs and G Thomas from DCC program. Still awaiting confirmation of schedule. 17-Oct RB on fortnightly RAID call: Gareth is taking this forward; until gain confirmation on known countries, this will remain open. 3-Oct: Rewa escalated to John Lawler yesterday; will raise on Messaging wall call 4-Oct. 02/10/12 - assigned to David Bingham from Craig Burnside 19-Sep (LM): Reopened/edited by Rewa/Alexa. 25th August - DCC confirmed they will carry out the On prem server builds to O/S Level but schedule is still outstanding. 7-June: Per Craig (LM), this is considered resolved. Added planning assumptions, these are being communicated to DCC. Formal decision still pending as D20, but Alan has confirmed these planning assumptions. 30/05: see planning assumptions added to I33 29/05: RB created issue from Risk 35. Assigned to Craig Burnside​ | L9: http://sp.ey.net/msibm/Lists/RAID%20%20Issues%20TEST/DispForm.aspx?ID=&RootFolder=*
A10: 84 | B10: Outlook/Exchange | C10: Nick Coburn | D10: 3) Program Mgt Team | E10: 2) Medium | F10: BAU service model and operation remit for Microland not yet defined | G10: 30-Nov-12 | H10: 9 | I10: 145 | J10: NC 05/11 - Keep open until Microland DD completed 15 - Oct - Clearly, there is work to be done to define the roles and responsibilities but, as agreed when Microland were with us recently, we will do this via due diligence and this will then be formalised in the contract. As agreed with Ana, we are actively progressing to finalise the specifics of the contract, rather than the contract not progressing. 8-Oct - Alexa re-opened as this has still not been confirmed or moved forwards. 16-Jul - Nick C confirmed date for this work is 22nd August. This has therefore delayed the microland onboarding as original target date has not been met​ 31/07 - Work progressing to engage Microland in Service Design workshop planned for end of August. UC team has completed their requirements for the scope of service from Microland though this requires validation ahead of the workshop. Agreement from Procurement to proceed with Microland based on their attendance at the workshop as their own 'cost of sale'. Work continues to develop a skinny MSA to allow several strands of work to continue prior to contract signature. Therefore, the lack of the service model is not holding up progress with Microland and this issue should be closed. | L10: http://sp.ey.net/msibm/Lists/RAID%20%20Issues%20TEST/DispForm.aspx?ID=&RootFolder=*
A11: 96 | B11: Outlook/Exchange | C11: Charles Sclater | D11: 3) Program Mgt Team | E11: 0) Under review | F11: Outlook Installations currently existing on user machines | G11: 30-Nov-12 | H11: 9 | I11: 132 | J11: 5 Nov CS- Global Service Desk has approved concept of manually unistalling Outlook 2003/07. now developing process and comms. Agree deployment process is to removed users with know Outlook 2010 issues from target list in order to complete deployment. There is a risk 5000 users will not have Outlook 2010 installed by 30 Nov, looking to prioritise pilot country users 12/10/12 - CS - Discussing with service desk and product owner the best way of upgrading users. 24-Sep (CS) - Of 5k users identified with Outlook already installed 3k responded to survey. Aprrox 50% of respondents have permitted the removal of Outlook. Will need to agree approach to upgrade users impacted by replacing Outlook with a dormant version. 19-Sept (LM): Per Rewa on fortnightly call, still collating survey responses; will have more info following review of surveys. 7th September- 12: Lynn Agoye: Outlook Survey responses are being collated, deadline for completion is today. Results will be analysed and next steps will be concluded. 15-AUG-12: Lynn Agoye: Survey to existing outlook users has been updated. and is ready to go, GLMS list is pending creation due to a backlog of requests Martin May is currently on leave but upon his return will be issued with a test plan and environment to further test the technical implications of removing mail profiles and PST as there are concerns that the initial test was not thorough enough. 6th August 2012: Survey to existing Outlook user base, is being prepped to be sent out for week of 6th July. However a GLMS list will potentially need to be created as the number exceeds 5,000. There are also discrepencies about the accuracy of the inventory report. These queries are to be discussed in a meeting with the communication, business change and service management team (scheduled for 6th August). A decision will be made following this. 30-July (LA): Tests are currently being conducted on the impact the removal of Outlook will have on outlook 2007 usres. Draft survey is awaiting sign-off before being sent to the users to understand how they are using Outlook 2007. 25-July (LM): Yvonne took action to get update from Lynn. Martin stressed that clear direction on how migrating the different paths is needed; Brett said may need Jeremy and Bob's help. Lynn to update further. 13th June- A meeting was held with Rachel Phillps and Iain Willets to discuss the end user impact and agree next steps, the agreement was that Lazzaro De Gennaro would send the updated Outlook Inventory for us to see the current amount of users today. Rachel will then work to get an email sent out to the end users requesting feedback on their use of Outlook. This would then help the team plan technically what to do with the remaining active users. 19th June- Lynn Agoye - Feedback from Transition Manager is that the tool that generates the report is down, Lynn Agoye to chase up on progress 20th July- Lynn Agoye - A decision has been passed to do some pre-deployment testing with some members of IT who already have Outlook installed on their machines, the purpose of the testing will be to see how the installer behaves and if the SCCM reports users with Outlook as being "failures" or if it just ignores them. The results of the tests will help detirmine how we move forward on this issue and will shape the comminications going out ​ | L11: http://sp.ey.net/msibm/Lists/RAID%20%20Issues%20TEST/DispForm.aspx?ID=&RootFolder=*
A12: 118 | B12: Outlook/Exchange | C12: Rachel Phillips | D12: 3) Program Mgt Team | E12: 2) Medium | F12: No identified country based business approval defined for MIA | G12: 16-Nov-12 | H12: -5 | I12: 100 | J12: 26/10/12: Charlie/ Jon have defined a process which will be used with South Africa and Germany as pilot countries. Pushing date to 15 November in order to monitor and assess this approach. 3-Oct (MK): I'm comfortable with the process made by Charlie, Jon and James Hartley...we now have agreement on a process where we will consult the countries with the apps that need clarification. I know Ian McG is also happy with this approach and the status of it. I will let him decide with Charlie if we can close the issue 22 Aug (IW): Details on deployment governance and process of working with the business to get agreement on EMIAs will be reviewed with Jon and feedback gained. Clear process to be put in place for this. August 10 (MK): The Deployment team is awaiting an JD&A milestone in mid-September that will provide more clarity of the scale of this potential issue. ​Reassigning to Jonathan Els - and updating dates - for further clarification on how this issue can/will materialise when the analysis is completed. | L12: http://sp.ey.net/msibm/Lists/RAID%20%20Issues%20TEST/DispForm.aspx?ID=&RootFolder=*
A13: 154 | B13: Outlook/Exchange | C13: Rewa Bouji | D13: 3) Program Mgt Team | E13: 3) High | F13: Policies and processes for re-imbursement of countries purchasing assets for M&C are not in place and are leading to delays in the ordering of hardware, risking O365 and On-prem timelines | G13: 30-Nov-12 | H13: 9 | I13: 126 | J13: 14-Nov: Reviewed on fortnightly call; still working with David and Paula to pull together, meetings occurring presently. On track for 30-Nov resolution. 03/10 RB: Ben Waterston has produced guidelines, are under review with D Bingham and P Bowie before publication, due 05/10 RB: Issue linked to I107 (country orders of network hardware to support O365 delivery). D Bingham and R Bouji agreed with P Bowie and R Sheldon that they would progress agreement and communication of process for purchase and reimbursement of in-country assets to support M&C delivery. M Kremmer collating expected costs on a country-by-country basis so these can be socialised alongside guidance. Must have this process in place and communicated by end November so as not to delay On-prem hardware orders in affected countries which will need to be placed at the end of December. | L13: http://sp.ey.net/msibm/Lists/RAID%20%20Issues%20TEST/DispForm.aspx?ID=&RootFolder=*
A14: 182 | B14: Outlook/Exchange | C14: Rewa Bouji | D14: 3) Program Mgt Team | E14: 2) Medium | F14: Unclear roles and responsibilities between engineering and architecture and lack of an overall technical "lead" for all technology areas impacting O/E | G14: 31-Oct-12 | H14: -21 | I14: 0 | L14: http://sp.ey.net/msibm/Lists/RAID%20%20Issues%20TEST/DispForm.aspx?ID=&RootFolder=*
A15: 187 | B15: Outlook/Exchange | C15: Yvonne McGrory | D15: 3) Program Mgt Team | E15: 0) Under review | F15: Network Assessment impact on deployment schedule | G15: 16-Nov-12 | H15: -5 | I15: 26 | J15: 9-Nov IM - continuing to work through Gil with Network Ops 2-Nov: Meeting on the 8th; date will move to 9-Nov and perhaps will be the next week. Being actively worked at present. 29-Oct IM - Gil working with Russ for network resources. Project to find resource to support & answer Networks questions ​- raised with Rewa for resource in Yvonne's absence. | L15: http://sp.ey.net/msibm/Lists/RAID%20%20Issues%20TEST/DispForm.aspx?ID=&RootFolder=*
A16: 193 | B16: Outlook/Exchange | C16: Rewa Bouji | D16: 3) Program Mgt Team | E16: 3) High | F16: Infrastructure Engineering resources are constrained, resulting in delays to activities across all workstreams | G16: 30-Nov-12 | H16: 9 | I16: 8 | J16: 14-Nov: Per Rewa on fortnightly RAID call, close to being able to address, plans in place to fill 2 positions. On track for 30-Nov resolution. 08/11/12: RB: Issue raised to consolidate I175, I176, I124​ | L16: http://sp.ey.net/msibm/Lists/RAID%20%20Issues%20TEST/DispForm.aspx?ID=&RootFolder=*
A17: 194 | B17: Outlook/Exchange | C17: David Bingham | D17: 3) Program Mgt Team | E17: 3) High | F17: Document management following move to Outlook | G17: 07-Dec-12 | H17: 16 | I17: 0 | L17: http://sp.ey.net/msibm/Lists/RAID%20%20Issues%20TEST/DispForm.aspx?ID=&RootFolder=*
A18: 199 | B18: Outlook/Exchange | C18: Simon Rutherford | D18: 3) Program Mgt Team | E18: 2) Medium | F18: Rogue AD Organization | G18: 23-Nov-12 | H18: 2 | I18: 8 | L18: http://sp.ey.net/msibm/Lists/RAID%20%20Issues%20TEST/DispForm.aspx?ID=&RootFolder=*
A19: 37 | B19: SharePoint | C19: Nick Coburn | D19: 3) Program Mgt Team | E19: 1) Low | F19: Need for new governance responsible for communications (maintenance, outages) | G19: 07-Dec-12 | H19: 16 | I19: 317 | J19: 02-Oct - N.Coburn - This is a central part of the service design and TOM for Collaboration. Need to determine who should be involved in discussing this given O365 will be with MS. 10-Sep - NC picked up and is investigating the requirement 06-Sep (LS): Emailed Nick to let him know item is overdue 27-Jun:Reassigned to Nick Coburn 19-Jun: With Service Design Team. Working with Transition Team to understand business needs. 01-Jun: Updated issue criticality to "Low" from medium based on current state of Sharepoint workstream. Also set the review date to 31 July and Reqired resulution to 31 August based on Service Design planning dates. 04/04: To be addressed through TOM model. 29-Feb: To be discussed at the M&C Transition Planning mtg in Secaucus. 31-Jan: Added to list of decisions needed by the newTarget Operate Model 25-Jan: Mike has meeting tomorrow with Binu and Mark around infrastructure 17-Jan: In process of integrating with operating model plan. 11-Jan: no owner of Tier 4 long term activities. Mike has put in charge to run this down for Alan overall. Focused on application side of SP. Review when Mike on call next week. 04-Jan: Michelle said this is still open due to external influences. The team said it should be assigned to Mike Laci instead of Guy. Mike not on these calls so maintained Guy's name, as well. Review next week. 19/12/11 - Guy took an action on the dec and assumptions review call to e-mail Chris d'Arcy, copying Alan and John. (LM emd reminder) 12/12 - Opened at the infrastructure meeting​ Migration note: Updated Profile to Program Mgt Team to maintain at Program level. | L19: http://sp.ey.net/msibm/Lists/RAID%20%20Issues%20TEST/DispForm.aspx?ID=&RootFolder=*
A20: 202 | B20: SharePoint | C20: Nicola Cooper | D20: 3) Program Mgt Team | E20: 2) Medium | F20: Test AD Accounts: There is a lack of a formalised or agreed process for creation of Test AD Accounts. | G20: 13-Dec-12 | H20: 22 | I20: 1 | J20: ​20th Nov (NC) This was an issue faced by both Messaging and Collaboration | L20: http://sp.ey.net/msibm/Lists/RAID%20%20Issues%20TEST/DispForm.aspx?ID=&RootFolder=*
A21: 24 | B21: Transition | C21: Nick Coburn | D21: 3) Program Mgt Team | E21: 1) Low | F21: Realignment of IT Transition group and Transition Managers | G21: 31-Jan-13 | H21: 71 | I21: 269 | J21: NC 05/11 Still open and to be considered as part of individual TOM for enterprise apps / platforms 10-May Migration Note: Changed workstream from M&C Program to Transition. 04/04: Still in progress. Formalizing through TOM work. 02/03: ACTION - N. Coburn to have a first draft view by 16th March.​ 15 JUN: NC progressing this. Meeting to be held with Mike to review all transition requirements. Nick to follow up with Alan on overall TM strategy in Cross-Org 31/07 - Still work in progress as we continue with the overall approach to TOM. | L21: http://sp.ey.net/msibm/Lists/RAID%20%20Issues%20TEST/DispForm.aspx?ID=&RootFolder=*
A22: 71 | B22: Transition | C22: Nick Coburn | D22: 3) Program Mgt Team | E22: 3) High | F22: Tier 3 level support is not defined for virtual desktops | G22: 30-Nov-12 | H22: 9 | I22: 163 | J22: NC 05/11 - NC working the open VM issue with Gil 15 Oct: (MM) Discussed the issue of defining the support model with Nick Coburn and Cynthia. Passed the environment details to Nick. Nick will discuss this with his team mates and will have meeting soon. On an another note, the blocks for realizing the VM environment associated with this issue # have been resolved and the VM is available now. Only the support model issue persists now.This is the current status 17-Oct: Per Alexa, assigned to Nick Coburn and Transition stream as opposed to Outlook. 3-Oct: Rewa will take action to Mike to update. 23-Sep - assigned to environment management team by Alexa 19-Sep (LM)- Per Rewa on fortnightly call, this has moved to the testing team; will look for update from testing team. 14-Aug (MM)- Created GCL4 & 5 Templates, transferred to Frankfurt GDC, and being test deployed there. 07-Aug (MM)- Trying to modify GCL5 VM templates. 18-Jul (MM)-Brett van Gelder referred the matter to Brain Booth. Brain B is now consulting his teams for any usable templates. 17-Jul: (MM) Plan B could not be pursued because of the Domain connectivity issue. GCL5 VDi Environment @ Secaucus does not connect to EY.net domain. 16-Jul: (MM) Checking the feasibility of Plan B: Hosting virtual test machines in GCL5 VDi Environment @ Secaucus. 11-Jul - PN meetings in place to review production of Virtual client server iVM mages and determine how we support these machines which fall outside the current BAU processes 10 July : (NC) After disucssion with Manesh at the weekly team meeting I have updated the description and visibility of this Issue. 5 July : (NC) After discussion with Paul Neave he is progressing this item and therefore we have agreed the best place for this to be owned is with him right now. 3 July : (NC) Reassigning all Collaboration RAID items related to transition to Nick Coburn 19-Jun: ​Mike to follow up with Nick. | L22: http://sp.ey.net/msibm/Lists/RAID%20%20Issues%20TEST/DispForm.aspx?ID=&RootFolder=*

Sheet Assumptions
A1: ID | B1: Workstream | C1: Assigned to | D1: Profile | E1: Status | F1: Title | G1: Validated by | H1: Validation_Due | I1: Countdown | J1: Days Open | K1: Update Log | L1: PMO Check | M1: URL
A2: 218 | B2: A&DM | C2: Alan Guthrie | D2: 3) Program Mgt Team | E2: 3) Validated | F2: A&DM Program budget assumes the use of India-based resources | G2: Alan Guthrie | H2: 09-Apr-12 | I2: 0 | J2: 0 | K2: 10-Aug: Christian confirmed still relevant. 2-Jul: LM > Christian. 22-Jun: LM > Christian 9-Apr: Alan provided updated syntax for this assumption and validated. Read previously: "The ADM program budget assumes the use of Hexaware as the offshore delivery team for the Portfolio teams." This assumption is partially correct. We may also look to use IT Services India and or Microsoft Global Delivery. ​ | M2: http://sp.ey.net/msibm/Lists/RAID%20%20Assumptions%20TEST/DispForm.aspx?ID=&RootFolder=*
A3: 219 | B3: A&DM | C3: Alan Guthrie | D3: 3) Program Mgt Team | E3: 3) Validated | F3: Industry standard ratios for Lotus Notes Migrations | G3: Alan Guthrie | H3: 09-Apr-12 | I3: 0 | J3: 0 | K3: 10-Aug: Christian confirmed this is still relevant. 2-Jul: LM > Christian. 22-Jun: LM > Christian. 9-Apr: Validated by Alan. ​ | M3: http://sp.ey.net/msibm/Lists/RAID%20%20Assumptions%20TEST/DispForm.aspx?ID=&RootFolder=*
A4: 93 | B4: Business Change | C4: Sophie Boiron | D4: 3) Program Mgt Team | E4: 3) Validated | F4: The change network is ready on time. | G4: Sophie Boiron | H4: 10-Apr-12 | I4: 0 | J4: 0 | M4: http://sp.ey.net/msibm/Lists/RAID%20%20Assumptions%20TEST/DispForm.aspx?ID=&RootFolder=*
A5: 94 | B5: Business Change | C5: Sophie Boiron | D5: 3) Program Mgt Team | E5: 3) Validated | F5: Learning materials will only be provided in English | G5: Sophie Boiron | H5: 10-Apr-12 | I5: 0 | J5: 0 | M5: http://sp.ey.net/msibm/Lists/RAID%20%20Assumptions%20TEST/DispForm.aspx?ID=&RootFolder=*
A6: 95 | B6: Business Change | C6: Sophie Boiron | D6: 3) Program Mgt Team | E6: 3) Validated | F6: Senior Leadership will support implementation/behavioural changes | G6: Sophie Boiron | H6: 10-Apr-12 | I6: 0 | J6: 0 | K6: Needs to be checked regularly and there is probabiliy that this could become a risk​ | L6: Note included by Sophie that needs to be checked regularly | M6: http://sp.ey.net/msibm/Lists/RAID%20%20Assumptions%20TEST/DispForm.aspx?ID=&RootFolder=*
A7: 96 | B7: Business Change | C7: Sophie Boiron | D7: 3) Program Mgt Team | E7: 3) Validated | F7: No end user learning in budget other than base learning resource | G7: Sophie Boiron | H7: 02-May-12 | I7: 0 | J7: 0 | M7: http://sp.ey.net/msibm/Lists/RAID%20%20Assumptions%20TEST/DispForm.aspx?ID=&RootFolder=*
A8: 21 | B8: LNDR | C8: Christian Driver | D8: 3) Program Mgt Team | E8: 2) Active Risk/Issue | F8: Development resource available from IT SD teams to support D&ME toolset development | G8: tbd | H8: 01-Nov-12 | I8: -20 | J8: 141 | K8: CD, 27 Jun 12: Updated to reflect latest status. Workstream and assigned to updated to reflect new D&ME workstream.​ CD, 19 Jul 12: Assumption trigger was realised. Risk raised to reflect latest position. | M8: http://sp.ey.net/msibm/Lists/RAID%20%20Assumptions%20TEST/DispForm.aspx?ID=&RootFolder=*
A9: 22 | B9: LNDR | C9: Christian Driver | D9: 3) Program Mgt Team | E9: 2) Active Risk/Issue | F9: I&O will support rollout of D&ME toolset and decom inactive/migrated applications​ | G9: tbd | H9: 01-Nov-12 | I9: -20 | J9: 141 | K9: CD, 27 Jun 12: Updated to reflect latest status. Updated workstream and owner to reflect new D&ME workstream.​ CD, 19 Jul 12: This assumption is still valid. However assumption updated to reflect that I&O currently cannot support this work until November 2012 and therefore a new issue has been raised to cover this. | M9: http://sp.ey.net/msibm/Lists/RAID%20%20Assumptions%20TEST/DispForm.aspx?ID=&RootFolder=*
A10: 23 | B10: LNDR | C10: Christian Driver | D10: 3) Program Mgt Team | E10: 3) Validated | F10: DCC Program will perform the archiving of the agreed applications | G10: tbd | H10: 09-Jun-12 | I10: 0 | J10: 0 | K10: CD, 27 Jun 12: Updated to reflect latest status. Workstream and ownership updated to reflect new D&ME workstream.​ CD, 19 Jul 12: Updated to reflect this has now been validated and moved to a decision. | M10: http://sp.ey.net/msibm/Lists/RAID%20%20Assumptions%20TEST/DispForm.aspx?ID=&RootFolder=*
A11: 10 | B11: Lync | C11: Stephen McCartney | D11: 3) Program Mgt Team | E11: 3) Validated | F11: For Lync go-live, business started transition to GCL5 | G11: GCL5 Program | H11: 16-Jul-12 | I11: 0 | J11: 0 | K11: SM: 20-Jul-12 We have confirmed that at least some users will be transitioning across to GCL5, so there will be some testing that we need to do on that platform. Therefore this assumption is validated. 13-Jun: SM - I have re-contacted the GCL5 team to confirm their deployment plan, but have had no response. I will keep chasing. 28-May: SM - I have contacted the GCL5 team and this is looking likely, however, they requested that I get back to them in a few weeks when their plans will be firmer. Will update this again then. 30-Apr: From LR101, Stephen requested this be managed as an assumption. Provided syntax and: I am 90% sure this will be the case, but I have contacted the GCL5 team to confirm their roll out plans. LM replied for due date, NRD, and who will validate.​ | M11: http://sp.ey.net/msibm/Lists/RAID%20%20Assumptions%20TEST/DispForm.aspx?ID=&RootFolder=*
A12: 182 | B12: Lync | C12: Paul Neave | D12: 3) Program Mgt Team | E12: 3) Validated | F12: Assumption that the required permanent network links to MS data centre's for O365 / SharePoint can be configured and delivered by the GNP Program in line with the revised delivery dates | G12: Steve Yeomans, Paul Neave | H12: 01-Jul-12 | I12: 0 | J12: 0 | K12: 2-Jul Migration Note: Note: This item was previously assigned to Brendan Millard. 10-Apr Paul: If Steve is committing to the dates agreed in the workshop then we can consider this validated. Note this is referring to the Permanent VPN which has date of 16/10/12 due to the procurement lead time. 4-Apr: Steve - I believe this has been validated but if the M&C team want to re-validate this then that's Ok with me. LM emd Al for confirmation. 4-Apr Steve sent updated wording (in desc column). Wording formerly read: The networks requirements for M&C program can be delivered to meet the time scales for M&C program. Network requirements will be delivered as part of the GWAN program, which is yet to be kicked off. 27-Mar: Laura em'd Steve for wording. 22-Mar Brett: This is an assumption and it does have serious impact but things have moved on and GWAN program is kicked off now. I think more critically we should assess whether delivery of dependency items for network should be managed as part of a GWAN program (which has a different charter and scope) or simply delivered by the network team. Either way this should be stated more specifically or be closed. 16-Mar: Steve confirmed he will send updated wording for this assumption. 6-Mar: This needs to be challenged with Brendan Millard; Laura em'd him the item for his awareness. John Murray's work will due to finish in June; would like to review mid-June with due beg-July.​ | M12: http://sp.ey.net/msibm/Lists/RAID%20%20Assumptions%20TEST/DispForm.aspx?ID=&RootFolder=*
A13: 183 | B13: Lync | C13: James Harrup-Brook | D13: 3) Program Mgt Team | E13: 3) Validated | F13: The vendor will start work on a LOI and start work before the MSA has been signed | G13: ? unknown | H13: 28-Mar-12 | I13: 0 | J13: 0 | K13: Both vendors have said they will start work on a n initial SOW 28-Mar-2012​ | L13: LM em'd James to update. | M13: http://sp.ey.net/msibm/Lists/RAID%20%20Assumptions%20TEST/DispForm.aspx?ID=&RootFolder=*
A14: 187 | B14: Lync | C14: James Harrup-Brook | D14: 3) Program Mgt Team | E14: 3) Validated | F14: No data conversion is required to turn on Lync | G14: Adrian Mickleson | H14: 04-Jan-12 | I14: 0 | J14: 0 | K14: 04-Jan: Adrian confirmed this has been validated, for all countries including Japan. Revalidated following O365 decision: James Harrup-Brook, 28/02/12​ | M14: http://sp.ey.net/msibm/Lists/RAID%20%20Assumptions%20TEST/DispForm.aspx?ID=&RootFolder=*
A15: 189 | B15: Lync | C15: James Harrup-Brook | D15: 3) Program Mgt Team | E15: 3) Validated | F15: Users will be able to operate Lync and Sametime simultaneously, | G15: 04-Jan RAID call attendees | H15: 04-Jan-12 | I15: 0 | J15: 0 | K15: 04-Jan: Al and Adrian confirmed that this has been validated. 04-Oct-11: Added by RB Revalidated following O365 decision: James Harrup-Brook, 28/02/12​ | M15: http://sp.ey.net/msibm/Lists/RAID%20%20Assumptions%20TEST/DispForm.aspx?ID=&RootFolder=*
A16: 97 | B16: M&C Program | C16: John Lawler | D16: 3) Program Mgt Team | E16: 3) Validated | F16: Sufficient capacity in global data centers | G16: Adrian, Al, Mark, others | H16: 06-Mar-12 | I16: 0 | J16: 0 | K16: ​6-Mar: It has been confirmed that Frankfurt will be the only data center (decision D210); assumption valid - there is sufficient capacity. | M16: http://sp.ey.net/msibm/Lists/RAID%20%20Assumptions%20TEST/DispForm.aspx?ID=&RootFolder=*
A17: 98 | B17: M&C Program | C17: Alan Guthrie | D17: 4) Executive Decision Group | E17: 3) Validated | F17: The scope of this effort will include all knowledge of the firm | G17: Alan Guthrie, Guy Morgan, team on 19-Dec. review call | H17: 19-Dec-11 | I17: 0 | J17: 0 | K17: Revalidated following O365 decision: Alan, 4-Apr-2012 (sent e-mail confirming this is still valid)​ 3-Apr: Laura emd Alan last week, Brett 3-Apr for revalidation. Validated by Alan on review call 19-Dec; agreed by team. Norm looking for sizing of this; will talk to Michelle about it. | M17: http://sp.ey.net/msibm/Lists/RAID%20%20Assumptions%20TEST/DispForm.aspx?ID=&RootFolder=*
A18: 6 | B18: Outlook/Exchange | C18: Rewa Bouji | D18: 3) Program Mgt Team | E18: 3) Validated | F18: Both Lync and Outlook will have a Business Pilot Phase | G18: Martin Kremmer | H18: 20-Apr-12 | I18: 0 | J18: 0 | K18: 30/04: RB: Draft Business Deployment strategy confirms Pilot. 24/03/12: (RB) Assumption cannot yet be validated as Deployment Strategy not yet published; further, pressure to bring forward the deployment timeline is giving rise to discussions about potentially reducing the Pilot scope and duration significantly. assumption to be revisited once baselined plan and deployment strategy published 15/03/12: RB: Pilot for Lync and Outlook agreed in principle, however volumes and duration still subject to agreement with Business Deployment and Operations (who will need to be ready to support Pilot volumes). Deployment/migration schedule and volumes to be discussed in meeting on 21/03/12 14/02/12: RB: Awaiting deployment strategy from Martin Kremmer 18/01/12: RB - To be confirmed with Martin Kremmer following development of business deployment plan 04-Oct-11: Added by RB​ | M18: http://sp.ey.net/msibm/Lists/RAID%20%20Assumptions%20TEST/DispForm.aspx?ID=6&RootFolder=*
A19: 16 | B19: Outlook/Exchange | C19: Yvonne McGrory | D19: 3) Program Mgt Team | E19: 2) Active Risk/Issue | F19: The email conversion process can convert 15K boxes per week. | G19: 04-Jan RAID call attendees | H19: 09-Jun-12 | I19: -165 | J19: 162 | K19: 21/02/12: RB: Network bandwith challenges may impact number of users able to be migrated. See LR91 (SPID34) 04-Jan: reworded from 5K boxes per night to 15K per week; then Adrian and Al confirmed it can be marked valid.​ | M19: http://sp.ey.net/msibm/Lists/RAID%20%20Assumptions%20TEST/DispForm.aspx?ID=&RootFolder=*
A20: 17 | B20: Outlook/Exchange | C20: Yvonne McGrory | D20: 3) Program Mgt Team | E20: 2) Active Risk/Issue | F20: Window for migration is 15 hours per weekend | G20: 04-Jan RAID call attendees | H20: 09-Jun-12 | I20: -165 | J20: 141 | K20: 21/02/12: RB: Output to R97 05-Jan: Al and Adrian confirmed this is valid. 04-Oct-11: Added by RB ​ | M20: http://sp.ey.net/msibm/Lists/RAID%20%20Assumptions%20TEST/DispForm.aspx?ID=17&RootFolder=*
A21: 18 | B21: Outlook/Exchange | C21: Yvonne McGrory | D21: 3) Program Mgt Team | E21: 2) Active Risk/Issue | F21: Email conversions only on Weekdays and the plan follows the sun | G21: O365 team, Transition management | H21: 28-Feb-12 | I21: -267 | J21: 141 | K21: 21/02/12: RB: Output to R97 14/02/12: RB: Needs to be confirmed with MSFT what the maximum number of migrations can be per window for O365, and to confirm with Transition Management what the maximum number of migrations can be for On-prem 18/01/12 - RB Needs to be confirmed with TF and Transition Management to determine what network impact will be if weekday vs weekend​ | M21: http://sp.ey.net/msibm/Lists/RAID%20%20Assumptions%20TEST/DispForm.aspx?ID=&RootFolder=*
A22: 19 | B22: Outlook/Exchange | C22: Yvonne McGrory | D22: 3) Program Mgt Team | E22: 2) Active Risk/Issue | F22: Migrating from Lotus Notes to Microsoft Outlook | G22: O365 team | H22: 21-Dec-12 | I22: 30 | J22: 152 | K22: 09/10/12_YM: To be validated as part of testing within CVS. To be re-visited post-CVS. ​ | M22: http://sp.ey.net/msibm/Lists/RAID%20%20Assumptions%20TEST/DispForm.aspx?ID=&RootFolder=*
A23: 20 | B23: Outlook/Exchange | C23: Paul Neave | D23: 3) Program Mgt Team | E23: 3) Validated | F23: GOOD are upgrading their product to support EWS by Q2 2012 | G23: Nicholas Wood | H23: 30-Aug-12 | I23: 0 | J23: 0 | K23: 5-Sept (LM): Per Rewa on fortnightly RAID call, this has been validated. Laura marked as such and sent to Rewa to complete the details. 01-Aug - advance code recieved - working with GOOD & MS on next version expected later this month. See Issue 32 25-Jul (LM): Update expected next wk. 07/06 - Still woriking to this assumption, expecting GOOD to have EWS on general relaese by end of July 3-Apr: This was in decisions log as D208, but Paul clarified that this is an assumption, not a decision. Marked that obsolete and opened here to be validated. Followed up for who will validate and due date.​ | L23: 5-Sept: LM > Rewa for Validated By info and other details. | M23: http://sp.ey.net/msibm/Lists/RAID%20%20Assumptions%20TEST/DispForm.aspx?ID=&RootFolder=*
A24: 89 | B24: Outlook/Exchange | C24: Charles Sclater | D24: 3) Program Mgt Team | E24: 3) Validated | F24: Supported languages in Outlook | G24: Matt Cross | H24: 19-Jul-12 | I24: 0 | J24: 0 | K24: 5 Sept (MC) - all languages that LN supports are available as language packs in Office 2010 (as well as many others). So no gap between what LN currently offers and what Outlook will provide. 24 Aug: Assumption is MS supports all languages EY conducts business in. Matt Cross to carry out a gap analysis 22-Aug (LM): Charlie and Craig unsure about this assumption, as this info should be picked up out of requirements and make it into a design document. Charlie will dig as to why this was opened and update or withdraw if necessary.​ | M24: http://sp.ey.net/msibm/Lists/RAID%20%20Assumptions%20TEST/DispForm.aspx?ID=&RootFolder=*
A25: 185 | B25: Outlook/Exchange | C25: Rewa Bouji | D25: 3) Program Mgt Team | E25: 3) Validated | F25: Countries where a DR site exists will have a DR solution for messaging, and countries which do not currently have a DR site will not have one implemented by the DCC or M&C Programs. | G25: Siggi Hauer, Alan Guthrie | H25: 19-Apr-12 | I25: 0 | J25: 0 | K25: 19/04/12: RB: Logged as output from decision D93. Ongoing assumption, no target validation date​ | M25: http://sp.ey.net/msibm/Lists/RAID%20%20Assumptions%20TEST/DispForm.aspx?ID=&RootFolder=*
A26: 188 | B26: Outlook/Exchange | C26: Paul Neave | D26: 3) Program Mgt Team | E26: 3) Validated | F26: Blackberry and iPhone users will be re-provisioned as part of the move to Exchange | G26: 04-Jan RAID call attendees | H26: 04-Jan-12 | I26: 0 | J26: 0 | K26: 04-Jan: Al and Adrian confirmed that this has been validated. Revalidated following O365 decision: Paul Neave, 27/02/12​ | M26: http://sp.ey.net/msibm/Lists/RAID%20%20Assumptions%20TEST/DispForm.aspx?ID=&RootFolder=*
A27: 190 | B27: Outlook/Exchange | C27: Rewa Bouji | D27: 3) Program Mgt Team | E27: 3) Validated | F27: CRM integration with Outlook is not expected to be delivered in Phase 1. | G27: Jeremy Brown | H27: 27-Jan-12 | I27: 0 | J27: 0 | K27: 06/02/12: RB - confirmed via email from Martin Kremmer that CRM not in scope for Day 1 18/01/12: RB - Martin Kremmer seeking clarification from Bob Reiner by Jan 27th 28-Oct-11: Added by RB. N Wood confirmed that CRM integration is not built into current design/planning.​ | M27: http://sp.ey.net/msibm/Lists/RAID%20%20Assumptions%20TEST/DispForm.aspx?ID=&RootFolder=*
A28: 191 | B28: Outlook/Exchange | C28: Paul Neave | D28: 3) Program Mgt Team | E28: 3) Validated | F28: Outlook packages can be deployed before hand and left inactive and be activated on desktops at the time of Migration | G28: 04-Jan RAID call attendees | H28: 04-Jan-12 | I28: 0 | J28: 0 | K28: 21/02/12: RB: Awaiting response from Paul Neave on revalidation 04-Jan: Adrian confirmed that this is valid. Revalidated following O365 decision: Paul Neave, 221/02/12​ | M28: http://sp.ey.net/msibm/Lists/RAID%20%20Assumptions%20TEST/DispForm.aspx?ID=&RootFolder=*
A29: 15 | B29: SharePoint | C29: Brett van Gelder | D29: 3) Program Mgt Team | E29: 3) Validated | F29: No SharePoint integration with Imanami GroupID | G29: Oleksiy Volkov | H29: 20-Jul-12 | I29: 0 | J29: 0 | K29: 18-July (LM): Brett confirmed this is validated (Oleksiy on holiday). (CC'd Oleksiy for his awareness) 2 July : Updated by BvG to be accurate. 29 Jun : Assigned to Brett van Gelder to confirm this was agreed. 28 Jun: NC Meeting setup with the Collaboration Architect Norm Lambert who wrote a white paper on this topic, to confirm this was agreed with Brett Van Gelder. 12-Jun (LM) Per Michelle, updated Assigned to to Nicola Cooper. 3-Apr - Logged ​ | M29: http://sp.ey.net/msibm/Lists/RAID%20%20Assumptions%20TEST/DispForm.aspx?ID=&RootFolder=*
A30: 99 | B30: SharePoint | C30: Michelle Edmonds | D30: 3) Program Mgt Team | E30: 3) Validated | F30: This SP POC effort does not include document management | G30: 04-Jan RAID call attendees | H30: 04-Jan-12 | I30: 0 | J30: 0 | K30: Revalidated following O365 decision: Michelle, 28-Mar-2012, December 20120 meeting with MS ​04-Jan: Michelle said this hs been validated; was from a meeting in December 2010. All docs have been updated accordingly. | M30: http://sp.ey.net/msibm/Lists/RAID%20%20Assumptions%20TEST/DispForm.aspx?ID=&RootFolder=*
A31: 100 | B31: SharePoint | C31: Michelle Edmonds | D31: 3) Program Mgt Team | E31: 3) Validated | F31: SP POC effort does not need to document collaboration requirements | G31: 04-Jan RAID call attendees | H31: 04-Jan-12 | I31: 0 | J31: 0 | K31: Revalidated following O365 decision: Michelle, 28-Mar-2012, December 20120 meeting with MS​ 04-Jan: Michelle said this hs been validated; was from a meeting in December 2010. All docs have been updated accordingly. | M31: http://sp.ey.net/msibm/Lists/RAID%20%20Assumptions%20TEST/DispForm.aspx?ID=&RootFolder=*
A32: 101 | B32: SharePoint | C32: Michelle Edmonds | D32: 3) Program Mgt Team | E32: 3) Validated | F32: The functionality of this SP POC effort will be dependent upon 2010 | G32: 04-Jan RAID call attendees | H32: 04-Jan-12 | I32: 0 | J32: 0 | K32: ​04-Jan: Michelle said this hs been validated; was from a meeting in December 2010. All docs have been updated accordingly. Revalidated following O365 decision: Michelle, 28-Mar-2012, December 20120 meeting with MS | M32: http://sp.ey.net/msibm/Lists/RAID%20%20Assumptions%20TEST/DispForm.aspx?ID=&RootFolder=*
A33: 102 | B33: SharePoint | C33: Michelle Edmonds | D33: 3) Program Mgt Team | E33: 3) Validated | F33: Decisions from the Design Authority will be received in 1 week | G33: 04-Jan RAID call attendees | H33: 04-Jan-12 | I33: 0 | J33: 0 | K33: ​1/4/2012 - Michelle stated on call that this is true. Has been validated. Revalidated following O365 decision: Michelle, 28-Mar-2012, replanned | M33: http://sp.ey.net/msibm/Lists/RAID%20%20Assumptions%20TEST/DispForm.aspx?ID=&RootFolder=*
A34: 103 | B34: SharePoint | C34: Michelle Edmonds | D34: 3) Program Mgt Team | E34: 3) Validated | F34: Code must be able to be used by other SP solutions, where applicable | G34: 04-Jan RAID call attendees | H34: 04-Jan-12 | I34: 0 | J34: 0 | K34: ​04-Jan: Michelle confirmed that this is true. List as validated/close. Revalidated following O365 decision: Michelle, 29-Mar-2012, revalidated | M34: http://sp.ey.net/msibm/Lists/RAID%20%20Assumptions%20TEST/DispForm.aspx?ID=&RootFolder=*
A35: 104 | B35: SharePoint | C35: Michelle Edmonds | D35: 3) Program Mgt Team | E35: 3) Validated | F35: Phase 1 Delivery - the project team is responsible for developing development, architecture and design standards for the SP platform | G35: 04-Jan RAID call attendees | H35: 04-Jan-12 | I35: 0 | J35: 0 | K35: 04-Jan: Michelle said this is true and has been validated. Plans have been updated accordingly. 07-Oct-2011: BvG: Development of standards etc. under the direction of Enterprise Architecture Revalidated following O365 decision: Michelle, 29-Mar-2012, revalidated.​ | M35: http://sp.ey.net/msibm/Lists/RAID%20%20Assumptions%20TEST/DispForm.aspx?ID=&RootFolder=*
... A98: 195 | B98: SharePoint | C98: Nicola Cooper | D98: 3) Program Mgt Team | E98: 3) Validated | F98: GAAIT replacement work has not yet been added to the plan | G98: Michelle Edmonds | H98: 20-Mar-12 | I98: 0 | J98: 0 | K98: 3-Jul: Per Nicola, still valid, migrate to new log. 2-Jul: LM > Michelle, Nicola - status update? Working to determine which GAAIT work to add 20-Mar-2012​ | M98: http://sp.ey.net/msibm/Lists/RAID%20%20Assumptions%20TEST/DispForm.aspx?ID=&RootFolder=*

Sheet Decisions
A1: ID | B1: Workstream | C1: Assigned To | D1: Status | E1: Title | F1: Decision Forum | G1: Required_By | H1: Countdown | I1: Days Open | J1: Update Log | K1: PMO Check | L1: URL
A2: 63 | B2: Business Change | C2: Sophie Boiron | D2: 4) Validated | E2: Generic Knowledge renamed to User Experience | F2: Functional Stakeholder Group | G2: 28-Sep-11 | H2: 0 | I2: 0 | J2: 13-Feb: This is not affected by O365 decision; consider revalidated.​ Decision makers: Participants in September 2011 FSG meeting in Washington DC | L2: http://sp.ey.net/msibm/Lists/RAID%20%20Decisions%20TEST/DispForm.aspx?ID=63&RootFolder=*
A3: 117 | B3: Business Deployment | C3: Martin Kremmer | D3: 4) Validated | E3: Business engagement via the ITSD teams for Mail-Integrated Applications | F3: IT Sponsor | G3: 30-Mar-12 | H3: 0 | I3: 0 | J3: ​IM 3 Aug: Forumed changed to IT Sponsor after EDG review | L3: http://sp.ey.net/msibm/Lists/RAID%20%20Decisions%20TEST/DispForm.aspx?ID=&RootFolder=*
A4: 256 | B4: Business Deployment | C4: Ian.McGeachie | D4: 4) Validated | E4: On-premises countries will be migrated to Outlook Exchange in a 3 month window between August and October 2013 | F4: Business Sponsor | G4: 31-Aug-12 | H4: 0 | I4: 0 | J4: 17-Oct: Per Rewa on fortnightly RAID call, it was decided in a review meeting with Bob and David on 12 September that we would move forward on the basis of moving in this 3 month window, with this tracked as a validated decision. Suggested reassign to Ian McGeachie. LM > Ian to inform him of assignment and validation.​ | L4: http://sp.ey.net/msibm/Lists/RAID%20%20Decisions%20TEST/DispForm.aspx?ID=&RootFolder=*
A5: 13 | B5: LNDR | C5: Christian Driver | D5: 4) Validated | E5: A&DM to build EYAA | F5: Program Mgt Team | G5: 09-May-12 | H5: 0 | I5: 0 | J5: 30-May (LM): Neil said on fortnightly call that this has been validated; took action to mark accordingly. 9-May: Neil trying to determine who can declare final confirmation on this decision. Ian suggested DA; Neil will follow-up. ​ CD, 27 Jun 12: Migrated ownership from Neil to Christian and changed workstream to D&ME. CD, 19 Jul 12: Updated to reflect this decision was actually made. | L5: http://sp.ey.net/msibm/Lists/RAID%20%20Decisions%20TEST/DispForm.aspx?ID=&RootFolder=*
A6: 196 | B6: LNDR | C6: Christian Driver | D6: 4) Validated | E6: A&DM renamed Decommission and Migration Enablement, to reflect revised scope for FY13. | F6: CLT | G6: 01-Jun-12 | H6: 0 | I6: 0 | J6: 21-June: LM added per Christian Driver.​ Decision Makers = CLT | L6: http://sp.ey.net/msibm/Lists/RAID%20%20Decisions%20TEST/DispForm.aspx?ID=&RootFolder=*
A7: 15 | B7: Lync | C7: Steven Jelf | D7: 4) Validated | E7: Voicemail retention period for auto deletion set to 30, 45 or 60days | F7: Executive Decision Group | G7: 25-Jul-12 | H7: 0 | I7: 0 | J7: 1st Aug -Decision now made by EDG- see above. 30Jul - recommendation was: After significant debate Q&RM have agreed that Voicemail Forwarding should be enabled (knowning the fact that once forwarded, voicemails can no longer be deleted automatically after a certain time period). The agreement is that by default non forwarded voicemails will be deleted (regardless of if they have been listened to or not) after a period of 30 days. In addition, it is agreed that assuming a sucessful series of further functional tests are conducted on the Speech to text translation feature, this should be enabled also, however it should be noted that Q&RM had an action to ensure tha the US GCO were informed of potential quality issues surrounding this functionality. 18-July (LM): Per Steve, this is not yet on the critical path for Outlook/Exchange. Steve will provide further update (Updated required by per 11-July update, EDG meeting 25-July, no material impact at this point.) 11th July - This decision needs to go to the Executive Decision Group. Iain Matheson aware, and documentation / slide available. Next EDG will be 25th July 19-June Q&RM update: Single frame sent to S Chakerian for further debate and guidance as to if this should be raised to the Executive Decision Group . Info to be provided by Tuesday 26th June. 13th June - Further discussions held on this topic with Ent Architecture and Inf Eng. Awaiting confirmation from Nick Wood on if there is ability to restrict listening to a voicemail that is over a certain time period. Single frame being produced for Q&RM (15th June) to then review and decide if this should be taken up to the Exec Decision Group. 21-May: Wait until June to review again; this decision from Q&RM still about a month out. 14-May​: Reviewed on Lync call; target updated to 12-June rather than 2-June since decision is still about a month out. 09 May - This is still ongoing. Escalation received about America's concerns. Working this through currently with the DA and SMEs 26-Apr Al: Steve should have answer next Wed, 2-May. (prior date - 12 Nov 2012) 16th April SJ to chase Susan Chakerian for formal response on if Lync functionality described sohuld be diabled for the Americas. 4th April - After detailed investigations, there is no practical technical solution to cater for automatically deleting forwarded / converted voicemails. Therefore an outstanding decision remains for the Americas - Disable forwarding and "Speech to text" functionality completely or accept the risk - Awaiting feedback - SC to advise on revised timings. 6th March - Accepted that no technical solution exists. Outstanding decision required by Americas area as to if voicemail forrwarding and speech translation to text should be disabled. All other areas have accepted the risk. 22nd Feb - It is confirmed that no technical solution exists out of the box or via RMS 3rd party tools to meet the business requirement. Further request made to confirm if a product does exist on the market to cater for our "auto delete" requirements. Q&RM have been asked to make a decision assuming no further tools are available to meet the requirement. Further info expected 9th March. (SJ) to set up a further meeting with IIT Services engineering architects to review what exact configurations can be made, reporting back to SC on this., The aim will then be to confirm a configuration for the enabling of legal disclaimers for external related chats. 1-Feb: Nick, Juan and Klara working on a deck around this. Need Nick to tell us whether Msft can meet the need or what 3rd party tools are available. Adrian will chase this as a first step and come back to Steve. 9-Feb James H.-Unable to clarify the scope with vendor (if cloud is chosen) until decision is made. 10-Feb SJ - Either the technology will support the requirements, or not. Awaiting technical validation, prior to cycling back to Q&RM. (Don’t believe this will be a business decision at this point). | L7: http://sp.ey.net/msibm/Lists/RAID%20%20Decisions%20TEST/DispForm.aspx?ID=&RootFolder=*
A8: 55 | B8: Lync | C8: Stephen McCartney | D8: 4) Validated | E8: Dialling emergency service numbers with Lync | F8: Messaging Design Authority | G8: 08-Jul-12 | H8: 0 | I8: 0 | L8: http://sp.ey.net/msibm/Lists/RAID%20%20Decisions%20TEST/DispForm.aspx?ID=55&RootFolder=*
A9: 59 | B9: Lync | C9: James Harrup-Brook | D9: 4) Validated | E9: Lync device spend in FY13 | F9: I&O | G9: 30-May-12 | H9: 0 | I9: 0 | J9: IM 3 Aug: Changed to I&O after EDG review​ | L9: http://sp.ey.net/msibm/Lists/RAID%20%20Decisions%20TEST/DispForm.aspx?ID=&RootFolder=*
A10: 64 | B10: Lync | C10: James Harrup-Brook | D10: 4) Validated | E10: Provisional agreement on Lync phases | F10: Program Mgt Team | G10: 28-Mar-11 | H10: 0 | I10: 0 | J10: No decision forum included in legacy data. ​ | K10: Need new link to document. | L10: http://sp.ey.net/msibm/Lists/RAID%20%20Decisions%20TEST/DispForm.aspx?ID=&RootFolder=*
A11: 65 | B11: Lync | C11: Martin Versteeg NL010015178 | D11: 4) Validated | E11: Deployment of latest Msft Updates for Lync and Outlook Dormant Client Packages | F11: Program Mgt Team | G11: 03-Apr-12 | H11: 0 | I11: 0 | J11: Migration note: Decision makers legacy data: Brett, Exchange and Lync PMs​ Project: Lync & Exchange From A83B. 3-Apr this item came up on daily calls as overdue for validation; Brett sent the following comment: A83B should be recorded as a decision and the Exchange and Lync PMs should be aware of that responsibility. I don't see any need for this to persist as an Assumption as it means it is not being acted on. Laura sent email to Ted and Daren with this update info. | L11: http://sp.ey.net/msibm/Lists/RAID%20%20Decisions%20TEST/DispForm.aspx?ID=65&RootFolder=*
A12: 66 | B12: Lync | C12: James Harrup-Brook | D12: 4) Validated | E12: Sametime groups will not be moved as part of the Lync go live. | F12: Functional Stakeholder Group | G12: 04-Oct-11 | H12: 0 | I12: 0 | J12: Migration note: Legacy decision makers: Participants in September 2011 FSG meeting in Wash. DC​ 4-Apr: Al > James, James: This is valid, we will not be migrating buddy list into Lync. 3-Apr-2012: Rewa believes this is valid, but needs to be confirmed by Al as relates to Lync and may change per the new vendor. Laura followed up with Al. Also, Rewa provided an update - there will NOT be an xml/widget to transfer existing buddy lists. Laura removed this line from the Decision desc. "There will be an xml applet/widget that users can choose to run once Lync is activated that will migrate their Sametime groups across to Lync" 04-Oct-11: Added by R Bouji | L12: http://sp.ey.net/msibm/Lists/RAID%20%20Decisions%20TEST/DispForm.aspx?ID=66&RootFolder=*
A13: 68 | B13: Lync | C13: James Harrup-Brook | D13: 4) Validated | E13: Sametime client will be hidden from use once Lync activated | F13: Program Mgt Team | G13: 04-Oct-11 | H13: 0 | I13: 0 | J13: 4-Apr Al > James: James - This is valid - the ST client will be hidden from use 3-Apr-2012: Rewa believes this is valid, but needs to be confirmed by Al as relates to Lync and may change per the new vendor. Laura followed up with Al. ​ | L13: http://sp.ey.net/msibm/Lists/RAID%20%20Decisions%20TEST/DispForm.aspx?ID=68&RootFolder=*
A14: 118 | B14: Lync | C14: Neil Sahdev | D14: 1) Pending | E14: Lync Performance Testing | F14: Program Mgt Team | G14: 23-Nov-12 | H14: 2 | I14: 159 | J14: 14-Nov: Discussed on fortnightly call; discussion planned around this topic tomorrow. Date set out end of next wk; Neil will update and open corresponding risk/issue if necessary. 17-Oct: Per Neil on fortnightly call, this is being looked at across the whole program. Date can push out to end of month. Sascha is looking at revise proposal/alternate solution, once articulate risks and associated costs, decision can be made. 3-Oct Ally: Sacha M is producing a plan for performance testing which should be ready by 5th Oct. Decision will be reviewed after lan produced. 19-Sept (LM): Per Neil on fortnightly call, asked by Geoff T to assess requirements and come up with a solution as to how much testing required. Meeting tomorrow that should provide more info. On track for end of month (at least as a check point). 5-Sept (LM): Per Neil on fortnightly call, date should be moved to end of Sept (no impact, this is not on critical path). Call scheduled for today to agree actions. 22-Aug (AW): Meetings with the performance team have taken place. Decision still required. meeting planned for w/c27 Aug to decide the way forwards. Required by Date left for now. 25-July (LM): Per Stephen, meeting being held today. Will update thereafter. 27-Jun (LM): Per Neil on fortnightly RAID call, this will be another month out. Neil will update.​ | L14: http://sp.ey.net/msibm/Lists/RAID%20%20Decisions%20TEST/DispForm.aspx?ID=&RootFolder=*
A15: 206 | B15: Lync | C15: Steven Jelf | D15: 1) Pending | E15: Wording of Legal Disclaimers (Lync) | F15: Quality & Risk Mgt Group | G15: 06-Dec-12 | H15: 15 | I15: 237 | J15: 2nd Nov - Steve to speak with Neil Sahdev regarding escalating the wording of the disclaimer from Microsoft. This is not a critical path activity. - It will be required for Lync Phase II. Given this situation, the date is being moved out.17-Oct: Steve said not on critical path; Neil and Steve to discuss off-line. May decrease the profile. 3-Oct: Still waiting on wording; this is not immediate for Phase 1. Ally will chase (once POC work is out of the way); date should move ot the end of this month; no affect. 19-Sep (LM): Update per fortnightly call that the team is waiting on the disclaimer wording; Msft to send. Q&RM has resource in place to review what Msft provides. Will have to look at next steps in the case that it is not acceptable. This is not yet impacting the critical path but does need to be validated within the next month. Neil will chase wording; Juan to do the same. 20th Aug - Date has been pushed back as this is a not a Phase 1 requirement. Further details are required in terms of setting out exactly what functionality is available, what hard coded messages are in place etc and provide Q&RM a solid view of what can be customised or not. 19th June S Jelf to confirm (a) the timeframe for wording on this and (b) if there is only 1 disclaimer available in Lync Update 9th May Wording needs to still be confirmed on Lync external disclaimer. Awaiting guidance from Q&RM on this. | L15: http://sp.ey.net/msibm/Lists/RAID%20%20Decisions%20TEST/DispForm.aspx?ID=&RootFolder=*
A16: 210 | B16: Lync | C16: Steven Jelf | D16: 4) Validated | E16: Enabling / disabling viewing of calendar information (Presence) within Lync | F16: Quality & Risk Mgt Group | G16: 01-Feb-12 | H16: 0 | I16: 0 | L16: http://sp.ey.net/msibm/Lists/RAID%20%20Decisions%20TEST/DispForm.aspx?ID=&RootFolder=*
A17: 211 | B17: Lync | C17: Steven Jelf | D17: 4) Validated | E17: Enabling the saving of Lync Chat Transcripts | F17: Quality & Risk Mgt Group | G17: 01-Mar-12 | H17: 0 | I17: 0 | L17: http://sp.ey.net/msibm/Lists/RAID%20%20Decisions%20TEST/DispForm.aspx?ID=&RootFolder=*
A18: 216 | B18: Lync | C18: Neil Sahdev | D18: 1) Pending | E18: Who should pay for in-office SBAs | F18: Program Mgt Team | G18: 23-Nov-12 | H18: 2 | I18: 132 | J18: 23-Nov: Per Neil on fortnightly call, a call is scheduled for Friday with David and Paula to discuss. Date set out 23-Nov; will raise issue if needed. 17-Oct: Neil provided update on fortnightly call that this cannot be closed until has all country agreements. Will review in 2 wks.​ | L18: http://sp.ey.net/msibm/Lists/RAID%20%20Decisions%20TEST/DispForm.aspx?ID=&RootFolder=*
A19: 217 | B19: Lync | C19: Neil Sahdev | D19: 4) Validated | E19: Confirmation required around who will pay for SBAs, which are required to enable Lync to be used for inbound / outbound dialling | F19: Executive Decision Group | G19: 13-Jul-12 | H19: 0 | I19: 0 | J19: 25-Jul (LM): This goes to the EDG today. Update pending.​ | L19: http://sp.ey.net/msibm/Lists/RAID%20%20Decisions%20TEST/DispForm.aspx?ID=&RootFolder=*
A20: 220 | B20: Lync | C20: Neil Sahdev | D20: 1) Pending | E20: Disablement of Lync softphone functionality for users already with existing softphone clients | F20: Program Mgt Team | G20: 30-Dec-12 | H20: 39 | I20: 131 | J20: 14-Nov: Per Neil on fortnightly call, this is not on the critical path. Date moved out to end of year, no impact. 17-Oct: Neil provided update on fortnightly RAID call that this is on track as part of change assessment; the date should move to the end of November, no impact. 19-Sept (LM): Neil holding voice workshop and this will be discussed therein. Required date set to 26-October; no impact. 22-Aug (AW): impact of having both phones still being investigated. Voice workshop planned for early September to decide voice issues and SOW II will decide deployment policies. Required by Date moved to encompass these decisions 9-Aug (NS): Required by date updated in-line with activity to define Lync Deployment Approach 08-Aug (LM): The date on this will push out, but wont yet impact the program. Neil to update. 07-Aug(SM): Updated with more detail on the options and their impacts 25-Jul (LM): Stephen to update.​ | L20: http://sp.ey.net/msibm/Lists/RAID%20%20Decisions%20TEST/DispForm.aspx?ID=&RootFolder=*
A21: 258 | B21: Lync | C21: Stephen McCartney | D21: 4) Validated | E21: Domain Controllers for use by Lync | F21: Enterprise and Information Architecture | G21: 17-Oct-12 | H21: 0 | I21: 0 | L21: http://sp.ey.net/msibm/Lists/RAID%20%20Decisions%20TEST/DispForm.aspx?ID=&RootFolder=*
A22: 16 | B22: M&C Program | C22: Ian Bourne | D22: 4) Validated | E22: Single/Central RAID Logs for entire Program | F22: Program Mgt Team | G22: 14-May-12 | H22: 0 | I22: 0 | J22: 9-May: Updated due date from 4-May due to back-up of migration. New process to be established and communicated by 14-May. 20-Apr Laura: Process changing; Moving to one log (SP list format) for entirety of program. Pilot to start 20-Apr, go live scheduled for w/e 4-May. Updated due date as plan to have all process documentation aligned with new process in place at that point. 14-Mar: changing - planning to move doc to different format. Other changes may occur out of 30 day plan. 27-Feb-2012: Ian and Laura confirming process for workstream RAID management. 21-Apr-2010 decision had been: We will have one RAID for the entire Program / each workstream may need a supplemental RAID​ | L22: http://sp.ey.net/msibm/Lists/RAID%20%20Decisions%20TEST/DispForm.aspx?ID=16&RootFolder=*
A23: 18 | B23: M&C Program | C23: Gregory Van Valkenburgh | D23: 4) Validated | E23: ​Do not populate Manager Attributes in AD at this time | F23: CBS | G23: 21-May-12 | H23: 0 | I23: 0 | J23: [Update from Q&RM log: 19-June:Recomendation from Q&RM is that this field is not displayed] 18-May: Reconfirmed decision to NOT populate one last time with Sandra Dillonn, Greg Nemeth, Jayee Nadkarni, Joan Kerrigan 11-May: Met again with representatives from People team and confirmed decision to NOT populate -- Sandra Dillon, Greg Nemeth, Jayee Nadkarni, Joan E. Kerrigan, Tony Crossley. Confirmed that they do not want this data populated in the short term. If and when it were populated with counselor data, the team felt it important that the term "Counselor" should be used in the UI instead of "Manager". (This would require customization(s) that would need to be analyzed -- e.g., for feasibilty) 9-May: Ted will follow-up with Ant and Daren. 4-May: Nick W. provided 3 areas for Outlook -- Organization tab on the contacts card, Outlook Properties, Ability to create team calendars based on this information 1-May: Initial Lync & Outlook analysis on the implication of NOT populating the Manager field in AD is that the organization information will not show on the contact card. Nick W. targeting review/analysis this week (e.g., on any potential further implications) 23-Apr: Impacts to SharePoint environment if the AD Manager field is not populated include: 1. Org chart will not have any data (& org chart features in Outlook and Lync will be similarly affected), 2. Auto population of colleagues is driven off of the Manager field and therefore won't work, 3. Privacy settings in the Profile have items like My Team, My Manager, etc. These options will still be present but will have no effect without the Manager field populated. 4. Audience targeting can be based on a "Reports Under" value (based upon Manager field), 5. SharePoint Designer workflows can out of the box make use of the Manager field, 6. If the MySite cleanup job in Office 365 is enabled in the future, it uses the Manager field for the re-assignment of the MySite to the Manager by default (this is currently disabled in Office 365). Microsoft's advice is that this does not "break" anything. It seems clear if we do not want the Manager data exposed within the application(s), it should also not be used for other purposes, and therefore Manager field should not be populated in AD. GJV 23-Apr 13-Apr: People Team needs to communicate impacts to BPO. Architects for Lync and Outlook also need to confirm. 3 - April: Pending Decision Logged, pending Brett van G and ID Sync Project confirmation​ | L23: http://sp.ey.net/msibm/Lists/RAID%20%20Decisions%20TEST/DispForm.aspx?ID=&RootFolder=*
A24: 69 | B24: M&C Program | C24: Steven Jelf | D24: 4) Validated | E24: Each workstream will have its own project plan. | F24: Program Mgt Team | G24: 21-Apr-11 | H24: 0 | I24: 0 | J24: 21-May: Legacy lacked Owner; Steve Jelf agreed assignment. Legacy decision makers: Adrian Mickleson, Michelle Edmonds 10-Apr: Michelle provided impact and rationale Confirmed as revalidated by Ian Bourne, 27-Feb.​ | L24: http://sp.ey.net/msibm/Lists/RAID%20%20Decisions%20TEST/DispForm.aspx?ID=69&RootFolder=*
A25: 70 | B25: M&C Program | C25: Steven Jelf | D25: 4) Validated | E25: There will be one Charter document for the entire program | F25: Program Mgt Team | G25: 21-Apr-11 | H25: 0 | I25: 0 | J25: 21-May: Legacy -- No Owner/assigned to. Steve Jelf agreed assignment. Legacy decision makers: Adrian Mickleson, Michelle Edmonds 26-Apr: Brett questioned this - business case is not a charter. Per Ian, updated the statement to specify one charter as opposed to business case. 3-April Ian: Still valid, once we have the PMP's we will create a program charter. 12-Mar Ian: In progress. 27-Feb: investigation required prior to revalidation (Ian B. took action)​ | L25: http://sp.ey.net/msibm/Lists/RAID%20%20Decisions%20TEST/DispForm.aspx?ID=70&RootFolder=*
A26: 71 | B26: M&C Program | C26: Alan Guthrie | D26: 4) Validated | E26: FSG face-to-face meeting schedule | F26: Functional Stakeholder Group | G26: 28-Sep-11 | H26: 0 | I26: 0 | J26: 21-May Migration Note: No legacy Owner; added Alan as Assigned to. Legacy decision makers: Participants in Sept 2011 FSG meeting in Wash DC 27-Feb-2012: Laura and Ian adjusted item from, "Next face to face meeting for functional stakeholders: 15-16 Nov LONDON. Jan (US TBD)" 27-Feb: revalidated.​ | L26: http://sp.ey.net/msibm/Lists/RAID%20%20Decisions%20TEST/DispForm.aspx?ID=71&RootFolder=*
A27: 72 | B27: M&C Program | C27: Alan Guthrie | D27: 4) Validated | E27: Regular FSG meeting schedule | F27: Functional Stakeholder Group | G27: 28-Sep-11 | H27: 0 | I27: 0 | J27: 21-May Migration Note: Legacy decision makers: Participants in Sept 2011 FSG meeting in Wash DC; No legacy assigned to. 27-Feb-2012: confirmed as revalidated by Ian Bourne.​ | L27: http://sp.ey.net/msibm/Lists/RAID%20%20Decisions%20TEST/DispForm.aspx?ID=72&RootFolder=*
A28: 73 | B28: M&C Program | C28: Irfan Rashid | D28: 4) Validated | E28: Change Control Process | F28: Program Mgt Team | G28: 27-Feb-12 | H28: 0 | I28: 0 | J28: 21-May Migration note: Legacy decision maker = Ian Bourne​ 11-Apr: Steve added rationale. 27-Feb: This item was opened as a result of D14 being marked obsolete (described an outdated change control process). 27-Feb: revalidated. | L28: http://sp.ey.net/msibm/Lists/RAID%20%20Decisions%20TEST/DispForm.aspx?ID=73&RootFolder=*
A29: 88 | B29: M&C Program | C29: Nick Coburn | D29: 4) Validated | E29: Cost of transition managers | F29: Program Mgt Team | G29: 04-Apr-12 | H29: 0 | I29: 0 | J29: Migration note: Legacy decision maker = Attendees of Get to Green Daily Standup Calls From LI144, discussed on daily stand-up call, and determined this is a decision rather than an issue. The team on that call agreed that the cost of transition managers will be in individual workstream budgets. ​ | L29: http://sp.ey.net/msibm/Lists/RAID%20%20Decisions%20TEST/DispForm.aspx?ID=88&RootFolder=*
A30: 189 | B30: M&C Program | C30: Ian Bourne | D30: 4) Validated | E30: Each workstream will have its own charge code | F30: Program Mgt Team | G30: 21-Apr-10 | H30: 0 | I30: 0 | J30: Migration note: Legacy decision makers = Michelle Edmonds/Adrian Mickleson​ 21-May: LM > Ian - inquiry 10-Apr: Michelle provided impact and rationale. 27-Feb-2012: Ian Bourne confirmed; added PMO to the list as it too has its own charge code. Revalidated. | L30: http://sp.ey.net/msibm/Lists/RAID%20%20Decisions%20TEST/DispForm.aspx?ID=189&RootFolder=*
A31: 190 | B31: M&C Program | C31: Ian Bourne | D31: 4) Validated | E31: Each workstream, in conjunction with the PMO, will validate hours and expenses | F31: Program Mgt Team | G31: 07-Mar-12 | H31: 0 | I31: 0 | J31: Migration note: Legacy decision maker = Ian Bourne​ 12-Mar Ian: This process is in place; consider revalidated. 27-Feb: Opened this decision as a result of D13 being marked obsolete. | L31: http://sp.ey.net/msibm/Lists/RAID%20%20Decisions%20TEST/DispForm.aspx?ID=190&RootFolder=*
A32: 14 | B32: Outlook/Exchange | C32: Punit Shah | D32: 4) Validated | E32: Email Deprovisioning | F32: Program Mgt Team | G32: 22-Jun-12 | H32: 0 | I32: 0 | J32: 16 Aug - Rohit Varshney is working on a to-be model for mailbox deprovisioning only, following discussing with Klara Neginsky. 11th July - Confirmed that there are 3 different streams here. (1) Generic process of email deprovisioning which the - recomendation is 30 days (2) The Litigation / Legal hold process (D207) , which is being moved forward by Paul Neave / Brett Van Gelder Q&RM and Microsoft as a separate entry. (3) The final piece of this relates to a concern Klara had surrounding the deprovision of "Hostile" leavers - where staff are asked to leave the firm immediately. Agreement made with Rewa Bouji that this process will be wrapped into Messaging BA work being driven by Punit Shah under reference D208. Hence this one is now being closed. 20th June - Klara expressed concerns in terms of a further process needing to be thought through further. - There are 3 scenario's to cater for - generic process for deprovisioning of email - standard leaver - recomendation is 30 days. The second scenario is surrouding a "legal" hold process - which Paul Neave, Brett Van Gelder and Susan Chakerian are reviewing with Microsoft and the 3rd process surrounds "hostile" leavers - where staff are asked to leave immediately - what should occur with the data. - Agreement made with Rewa Bouji that this process will be reviewed by the Exchange / Outlook BA Lead - Punit Shah. 13th June - Further info required from Klara on concerns. Meeting setup for Weds 20th June to explore this further with Klara / Susan Q&RM. 30-May (LM) - Steve provided update on fortnightly call that Q&RM has given guidance, but Klara has concerns. 09th May - SJ to re-chase Q&RM - No answer expected for 2 / 3 weeks. due to vacation of S. Chakerian. Steve and Klara to catch-up off-line. Due date revisedfrom 23-Mar to end of May. 26-Apr Al: Rewa/Steve to update. 16th April - SJ to chase Q&RM for formal response. 4th APril =-30 day period generally accepted. Just awaiting formal confirmation 8th March- General acceptance provided on this (30 day period) . It is thought that this setting could be changed based on a justified / approved Change Request -awaiting on confirmation from Nick Wood. (email sent 8th March) c20th Feb - Discussed with SC 21st Feb. Email being sent to members of the LEC to confirm a standard 30 day policy is likely to exist across all countries. Awaiting feedback from SC on this. 10-Feb: SJ - Q&RM direction required (escalated again 9th Feb). Paul Neave should confirm how critical a decision is, however it is believed that this needs to be fed into the “scope lock” phase- due to finalise early March. PIN – the opposite is also true - there are countries who also expect to retain mailboxes for leavers 10-Feb: Steve to go back to Susan (Q&RM): Our default position is 30 days, but we can move it to 5 if we need to. Our recommendation is not to leave it any longer than 30 days because of the cost implications.​ | L32: http://sp.ey.net/msibm/Lists/RAID%20%20Decisions%20TEST/DispForm.aspx?ID=&RootFolder=*
A33: 19 | B33: Outlook/Exchange | C33: Craig Burnside | D33: 4) Validated | E33: On-Prem and O365 migration strategy | F33: Steering Committee | G33: 17-Aug-12 | H33: 0 | I33: 0 | J33: 5-Sept (LM): Action to Rewa to review and update off-line. 22-Aug (LM): Action to Craig on fortnightly call to update; confirm with Rewa whether anything additional is needed here. If not, update the decision and Validate. 10 Aug CB: confirmed with RB that options to defer have been assessed and presented to DB. Direction is to proceed with on-premise delivery plan and not defer although no immediate spend will occur on 10 of the 12 in-country on-premise deliveries as separate issue relates to confirm where resp and budget lies for these as does not appear to be in DCC program scope since DCC scope is for GDCs. Messaging finance review with AG and team planned for Tues 14th Aug so expect further clarity from that meeting 09 Aug CB: CB had requested impact assessment of draft CR to defer all on-premise delivery (driven by need to manage budget forecast down). This was expected from O/E team by 27th Jul. CB to review with RB 10th Aug as no update provided on or since 27th Jul (CB also on leave 28th Jul to 7th Aug) 8-Aug (LM): Craig took action on program raid call to update offline. 25-Jul (LM): Fornightly call action: Martin and Craig to discuss off-line and provide an update. 27-Jun (LM): Rewa will discuss with Craig off-line. 13-Jun (LM): Per Craig, we will progress next steps with Tim Eddy who agreed to take the aciton to help resolve. This is still overdue, but set required date to end-June because won't go red again until that point. 28/05: RB: Still awaiting CO. Position of the program is that this is to be challenged. Assigned to changed to C Burnside. 20/05: RB: MSFT are now raising a Change Order for the number of weeks that the migration is expected to exceed the 9 month migration window. This is at a cost of $5,000 for every week over the 9 month 36 week period) contractually agreed. Decision to be escalated to EDG to determine whether On-prem activity should be delayed to enable all resources to focus on O365 and avert increasing financial penalties 20/04: RB presented suggestion to A Guthrie that on-prem activity be put on hold to allow efforts to focus on O365. However suggested by B van Gelder that delay to on-prem could mean extended time required to ramp on-prem up again 28/03/12: RB: Being addressed by R97 | L33: http://sp.ey.net/msibm/Lists/RAID%20%20Decisions%20TEST/DispForm.aspx?ID=&RootFolder=*
... A64: 203 | B64: Outlook/Exchange | C64: Rewa Bouji | D64: 4) Validated | E64: Decision required on whether to undertake IT SD Testing as part of the Outlook Dormant Deployment | F64: CLT | G64: 31-Jul-12 | H64: 0 | I64: 0 | J64: ​IM 3 Aug: added CLT as forum to better assign the decision (rather than EDG). | L64: http://sp.ey.net/msibm/Lists/RAID%20%20Decisions%20TEST/DispForm.aspx?ID=&RootFolder=*
A65: 212 | B65: Outlook/Exchange | C65: Steven Jelf | D65: 4) Validated | E65: Email Recall Request | F65: Quality & Risk Mgt Group | G65: 19-Jun-12 | H65: 0 | I65: 0 | L65: http://sp.ey.net/msibm/Lists/RAID%20%20Decisions%20TEST/DispForm.aspx?ID=&RootFolder=*
A66: 213 | B66: Outlook/Exchange | C66: Steven Jelf | D66: 4) Validated | E66: Social Connector functionality | F66: Quality & Risk Mgt Group | G66: 21-Jun-12 | H66: 0 | I66: 0 | J66: Update 21st June Screen shots received. Q&RM have reviewed and concluded that " on the basis that this feature appears to make it much easier to inadvertently reveal client confidential information onto an EY employee's external social media account/site, we recommend that EY should not enable this functionality." Update 19th June - Screen shot requested. Awaiting feedback from the BA team - originally rejected, but after further investigation, no concerns raised. Final debate occurring - update expected by c.o.b Friday 22nd June 14th June S. Jelf chased S Chakerian for update. Further info / direction requested by 15th June. Guidance being requested from Q&RM Independence on these topics. 29th May Recall and publishing of calendar information is still being discussed - Expected update 16th June ​ | L66: http://sp.ey.net/msibm/Lists/RAID%20%20Decisions%20TEST/DispForm.aspx?ID=&RootFolder=*
A67: 214 | B67: Outlook/Exchange | C67: Steven Jelf | D67: 4) Validated | E67: Publishing of Calendar info online (Microsoft.com) | F67: Quality & Risk Mgt Group | G67: 21-Jun-12 | H67: 0 | I67: 0 | L67: http://sp.ey.net/msibm/Lists/RAID%20%20Decisions%20TEST/DispForm.aspx?ID=&RootFolder=*
A68: 223 | B68: Outlook/Exchange | C68: Craig Burnside | D68: 4) Validated | E68: Switzerland On-Prem Decision | F68: CIO | G68: 20-Jul-12 | H68: 0 | I68: 0 | J68: 23-Aug: Craig sent list of countries confirmed by Tim Eddy to be either definitely On-Prem or definitely O365. ​ | L68: http://sp.ey.net/msibm/Lists/RAID%20%20Decisions%20TEST/DispForm.aspx?ID=&RootFolder=*
A69: 224 | B69: Outlook/Exchange | C69: Craig Burnside | D69: 4) Validated | E69: Luxembourg On Prem Decision | F69: CIO | G69: 20-Jul-12 | H69: 0 | I69: 0 | J69: 23-Aug: Per CB, Tim Eddy confirmed Luxembourg will definitely be on-prem.​ | L69: http://sp.ey.net/msibm/Lists/RAID%20%20Decisions%20TEST/DispForm.aspx?ID=&RootFolder=*
A70: 226 | B70: Outlook/Exchange | C70: Craig Burnside | D70: 4) Validated | E70: Japan On Prem Decision | F70: CIO | G70: 20-Jul-12 | H70: 0 | I70: 0 | J70: 23-Aug: Reconfirmed by CB per Tim Eddy.​ | L70: http://sp.ey.net/msibm/Lists/RAID%20%20Decisions%20TEST/DispForm.aspx?ID=&RootFolder=*
A71: 227 | B71: Outlook/Exchange | C71: Craig Burnside | D71: 4) Validated | E71: Russia On Prem decision | F71: CIO | G71: 20-Jul-12 | H71: 0 | I71: 0 | J71: ​10-Aug: Craig marked validated and added decision to log. 23-Aug: Per Craig, Tim Eddy confirmed this decision. | L71: http://sp.ey.net/msibm/Lists/RAID%20%20Decisions%20TEST/DispForm.aspx?ID=&RootFolder=*
A72: 228 | B72: Outlook/Exchange | C72: Craig Burnside | D72: 4) Validated | E72: On Prem decision for UK | F72: CIO | G72: 20-Jul-12 | H72: 0 | I72: 0 | J72: ​23-Aug: Craig sent list of countries confirmed by Tim Eddy to be either definitely On-Prem or definitely O365. | L72: http://sp.ey.net/msibm/Lists/RAID%20%20Decisions%20TEST/DispForm.aspx?ID=&RootFolder=*
A73: 229 | B73: Outlook/Exchange | C73: Craig Burnside | D73: 4) Validated | E73: Indonesia On Prem decision | F73: CIO | G73: 20-Jul-12 | H73: 0 | I73: 0 | J73: 23-Aug: Craig sent list of countries confirmed by Tim Eddy to be either definitely On-Prem or definitely O365.​ | L73: http://sp.ey.net/msibm/Lists/RAID%20%20Decisions%20TEST/DispForm.aspx?ID=&RootFolder=*
A74: 230 | B74: Outlook/Exchange | C74: Craig Burnside | D74: 4) Validated | E74: China on prem decision | F74: CIO | G74: 20-Jul-12 | H74: 0 | I74: 0 | J74: ​23-Aug: Craig sent list of countries confirmed by Tim Eddy to be either definitely On-Prem or definitely O365. | L74: http://sp.ey.net/msibm/Lists/RAID%20%20Decisions%20TEST/DispForm.aspx?ID=&RootFolder=*
A75: 231 | B75: Outlook/Exchange | C75: Craig Burnside | D75: 4) Validated | E75: Australia On Prem Decision | F75: CIO | G75: 20-Jul-12 | H75: 0 | I75: 0 | J75: 23-Aug: Craig sent list of countries confirmed by Tim Eddy to be either definitely On-Prem or definitely O365.​ | L75: http://sp.ey.net/msibm/Lists/RAID%20%20Decisions%20TEST/DispForm.aspx?ID=&RootFolder=*
A76: 232 | B76: Outlook/Exchange | C76: Craig Burnside | D76: 4) Validated | E76: Canada On Prem Decision | F76: CIO | G76: 20-Jul-12 | H76: 0 | I76: 0 | J76: 23-Aug: Craig sent list of countries confirmed by Tim Eddy to be either definitely On-Prem or definitely O365.​ | L76: http://sp.ey.net/msibm/Lists/RAID%20%20Decisions%20TEST/DispForm.aspx?ID=&RootFolder=*
A77: 233 | B77: Outlook/Exchange | C77: Craig Burnside | D77: 4) Validated | E77: Columbia on prem decision | F77: CIO | G77: 20-Jul-12 | H77: 0 | I77: 0 | J77: 23-Aug: Craig sent list of countries confirmed by Tim Eddy to be either definitely On-Prem or definitely O365.​ | L77: http://sp.ey.net/msibm/Lists/RAID%20%20Decisions%20TEST/DispForm.aspx?ID=&RootFolder=*
A78: 234 | B78: Outlook/Exchange | C78: Craig Burnside | D78: 4) Validated | E78: Peru On Prem Decision | F78: CIO | G78: 20-Jul-12 | H78: 0 | I78: 0 | J78: 23-Aug: Craig sent list of countries confirmed by Tim Eddy to be either definitely On-Prem or definitely O365.​ | L78: http://sp.ey.net/msibm/Lists/RAID%20%20Decisions%20TEST/DispForm.aspx?ID=&RootFolder=*
A79: 235 | B79: Outlook/Exchange | C79: Craig Burnside | D79: 4) Validated | E79: Armenia On prem decision | F79: CIO | G79: 20-Jul-12 | H79: 0 | I79: 0 | J79: 23-Aug: Craig sent list of countries confirmed by Tim Eddy to be either definitely On-Prem or definitely O365.​ | L79: http://sp.ey.net/msibm/Lists/RAID%20%20Decisions%20TEST/DispForm.aspx?ID=&RootFolder=*
... A96: 252 | B96: Outlook/Exchange | C96: Craig Burnside | D96: 1) Pending | E96: Philippines on prem decision | F96: CIO | G96: 31-Dec-12 | H96: 40 | I96: 67 | J96: 13-Sept (CB): due date changed to end of year in line with related issue being tracked (33) as do not expect this to be resolved until then. 23-Aug: Per Craig and Alexa, currently with Tim Eddy to push O365 but not yet confirmed.​ | L96: http://sp.ey.net/msibm/Lists/RAID%20%20Decisions%20TEST/DispForm.aspx?ID=&RootFolder=*
A97: 254 | B97: Outlook/Exchange | C97: Yvonne McGrory | D97: 4) Validated | E97: Local based mail should be deployed to countries where there is no local backup solution in place so long as there is a server copy. | F97: I&O | G97: 23-Jul-12 | H97: 0 | I97: 0 | L97: http://sp.ey.net/msibm/Lists/RAID%20%20Decisions%20TEST/DispForm.aspx?ID=&RootFolder=*
A98: 255 | B98: Outlook/Exchange | C98: Rewa Bouji | D98: 4) Validated | E98: Decision required to determine how encrypted mail migration will be managed when users are migrated to Outlook | F98: Quality & Risk Mgt Group | G98: 12-Sep-12 | H98: 0 | I98: 0 | J98: 19/09: RB. Confirmation received from Q&RM that Option 2 will be pursued. This has been presented to L&O Governance Group on 12/09/12, and R Phillips confirmed no challenge raised. Decision marked validated. 07/09/12: RB: Request made of S Jelf for confirmation of next QRM Meeting to escalate decision.​ | L98: http://sp.ey.net/msibm/Lists/RAID%20%20Decisions%20TEST/DispForm.aspx?ID=&RootFolder=*
A99: 259 | B99: Outlook/Exchange | C99: Yvonne McGrory | D99: 1) Pending | E99: Mobile migrations require device to be wiped, decision on if it should be automatically wiped or an end user has control to wipe. | F99: Lync and Outlook Governance | G99: 14-Dec-12 | H99: 23 | I99: 55 | J99: 14-Nov (LM): Reviewed on fortnightly RAID call; Rachel updated assignment, req. date and forum to reflect recent activity. This was intended for the governance group 14-Nov but more info and support from I&O are needed. 16-Oct (RP): waiting on more detailed information from Rohit (the business analyst working on this) in order to take this point to the L&O Governance Group. It's an agenda item for 14 November. The main impact (ok'd with Rohit and Yvonne) is on myself from a change perspective. This is an impact we can manage provided we have confirmation on this by mid-November. (Date moved to 16-Nov. ) 3-Oct: Per Rachel, had been hoping to take to the Lync/Outlook Governance group next week. Now will be proposing a way forward and will then discuss that proposal (with clear implications) at the meeting next month. This won't impact the time schedules.​ | L99: http://sp.ey.net/msibm/Lists/RAID%20%20Decisions%20TEST/DispForm.aspx?ID=&RootFolder=*
A100: 261 | B100: Outlook/Exchange | C100: David Bingham | D100: 4) Validated | E100: On-Prem in country kit to be ordered in advance of design being proved through testing | F100: IT Program Mgr | G100: 01-Oct-12 | H100: 0 | I100: 0 | L100: http://sp.ey.net/msibm/Lists/RAID%20%20Decisions%20TEST/DispForm.aspx?ID=&RootFolder=*
A101: 262 | B101: Outlook/Exchange | C101: David Bingham | D101: 1) Pending | E101: Poland hosting status confirmation | F101: Executive Decision Group | G101: 14-Dec-12 | H101: 23 | I101: 0 | J101: 03/10 RB logged and assigned to DB as agreed. Action now escalated to John Murphy who has agreed to finalise hosting status of all countries still under question by mid-December in time for on-prem hardware orders to be placed in January​. | L101: http://sp.ey.net/msibm/Lists/RAID%20%20Decisions%20TEST/DispForm.aspx?ID=&RootFolder=*
A102: 141 | B102: PMO | C102: Steven Jelf | D102: 4) Validated | E102: SharePoint - User Profile, Social and My site data decomissioning | F102: Quality & Risk Mgt Group | G102: 09-Aug-12 | H102: 0 | I102: 0 | J102: 3rd Aug - Further information received from G. Henbest (Global Data Privacy Director) - "If the information is kept for 30 days then it must be searchable, a requirement of data privacy law is that an individual should be allowed access to or a copy of all their data, so if this information is still available when a request is received we need to be able to provide a copy..." Marked (re)validated. 1st Aug - Key outstanding question is if data should remain visibile for 30 days. Q&RM to provide further clarification. Unclear of when this information is required by. 31 Jul (BvG): Setting to revalidation. Lots of missing information in the Decision log fields and outstanding responses from Q&RM still noted without resolution. | L102: http://sp.ey.net/msibm/Lists/RAID%20%20Decisions%20TEST/DispForm.aspx?ID=&RootFolder=*
A103: 17 | B103: SharePoint | C103: Andy Ioannou | D103: 4) Validated | E103: GAAIT replacement program now falls under FAS&T | F103: Steering Committee | G103: 08-Jul-12 | H103: 0 | I103: 0 | J103: 7-Sep: Jo Anne Offill sent the following correction to this decision: The GAAIT Replacement program is moving under the umbrella of the FAS&T program, not EYD. Decision previously read that GAAIT replacement will be managed by EYD. 03-Aug: Reassigned to Andy 09-Jul: Decision will reflect disposition of Issue #81 12-June (LM): Per Michelle, this decision should be made/complete July 9, updated. 22-Feb: on RAID call discussed I110, hoping to get more info at FSG meeting next week.​ | L103: http://sp.ey.net/msibm/Lists/RAID%20%20Decisions%20TEST/DispForm.aspx?ID=&RootFolder=*
A104: 28 | B104: SharePoint | C104: Norman Beard | D104: 4) Validated | E104: Extranet strategy for external authentication and content mgt | F104: Program Mgt Team | G104: 19-Aug-12 | H104: 0 | I104: 0 | J104: 16-July: Norm marked "Validated." 9-July: SharePoint Extranet Deployment and Access Model (authored by Gerd Hanussek) submitted to Design Authority 10-May IM: prior to migration, forum set to Decision Makers set to "Ant / Afzaal / Klara" so translated to "Workstream Lead" - to be confirmed. 26-Apr: Per Al, reassign to Norm, IAM/InfoSec 9-May: this activity is part of Release 2 design work​ | L104: http://sp.ey.net/msibm/Lists/RAID%20%20Decisions%20TEST/DispForm.aspx?ID=&RootFolder=*
A105: 29 | B105: SharePoint | C105: Michelle Edmonds | D105: 4) Validated | E105: EY SharePoint Governance body | F105: Program Mgt Team | G105: 20-Apr-12 | H105: 0 | I105: 0 | J105: 22-May: Marked Validated by Michelle Edmonds. 30-Apr: Al unsure, SP item. LM to Norm/Michelle. 26-Apr Al: Governing body has been established. LM > Al - need date, decision statement, impact and rationale. Program 7-Mar: Al and Mark had a conversation around this item; will be part of blueprints. Decision will need to come first from Fareed Naeem and then Jeremy Brown. ​ No assigned to; Forum set to Program Mgt team as opposed to Workstream Lead to keep at Program level. | L105: http://sp.ey.net/msibm/Lists/RAID%20%20Decisions%20TEST/DispForm.aspx?ID=&RootFolder=*
A106: 30 | B106: SharePoint | C106: Jeremy Brown | D106: 4) Validated | E106: Scope and business requirements for client collaboration (ECMA) | F106: Program Mgt Team | G106: 07-Aug-12 | H106: 0 | I106: 0 | J106: 08 - Aug (JB) Service Delivery for Assurance is part of the FAS&T program and not in scope for M&C. All service delivery processs in scope for M&C are proposed to be delivered via the EYD infrastructure. 03-Jul: Required date moved as Andy and Jeremy will discuss in Cleveland next week. 25-July (LM): workshops are planned for first 2 wks of August. Andy and Jeremy to discuss off-line and provide update. 18-July (LM): Per Jeremy, The working proposal is that ECMA will be delivered via EY/D. A series of workshops are planned to define and design the process and technical requirements so that all service lines can leverage EY/D from a service delivery perspective. This workstream is under the sponsorship of John Murphy. 27-Jun (LM): Nicola took an action to take to Andy to follow-up with Jeremy. 26-Apr: Per Al, reassign to Norm/Michelle. SharePoint enablement (requirements)​ | L106: http://sp.ey.net/msibm/Lists/RAID%20%20Decisions%20TEST/DispForm.aspx?ID=&RootFolder=*
A107: 34 | B107: SharePoint | C107: Nicola Cooper | D107: 4) Validated | E107: Conversion of existing SP sites | F107: Program Mgt Team | G107: 22-Sep-11 | H107: 0 | I107: 0 | J107: 2nd August : (NC Solution Delivery Lead ​Collaboratoin) Confirm decision that Collaboration EAX and Release 1 scope does not include the conversion of or data migration of any existing SP site already in the E&Y landscape. (Marked (re)validated) 16-Jul: Reassigned to Nicola 27-Feb: Reviewed - Decision in the past - Need to confirm at Replan; May be impacted | L107: http://sp.ey.net/msibm/Lists/RAID%20%20Decisions%20TEST/DispForm.aspx?ID=&RootFolder=*
A108: 36 | B108: SharePoint | C108: Michelle Edmonds | D108: 4) Validated | E108: Only new applications will be required to use the new taxonomy | F108: Program Mgt Team | G108: 23-Sep-11 | H108: 0 | I108: 0 | J108: 27-Feb: Reviewed - Decision in the past - Need to confirm at Replan; May be impacted​ | L108: http://sp.ey.net/msibm/Lists/RAID%20%20Decisions%20TEST/DispForm.aspx?ID=36&RootFolder=*
A109: 37 | B109: SharePoint | C109: Michelle Edmonds | D109: 4) Validated | E109: Tier-A only specific archiving solution for //content and //communities only | F109: Program Mgt Team | G109: 08-Nov-11 | H109: 0 | I109: 0 | J109: ​'11_11_08.1.15 - "Tier A: We will build a Tier-A only specific archiving solution for //content and //communities only" O365 Hosted if aplicable for workloads, therefore need to revalidate Travis 9-Mar: Need to re-validate what "archiving" means to EY. Although "Content" has a large user-base, it should still be considered an Application-Specific workload (i.e. vertical). Assuming verticals do not live in O365, it will require an on-premises archiving solution which is not considered in the "to-be" architecture. Assuming all community types live in O365, EY can take advantage of the O365 "Records Center" site collection which can grow to 400GB (at this threshold, this is a maximum of 300 based on latest service description). Need to re-visit the requirement for archiving and determine if the constraints still meet the requirement. Arch imp: YES Legacy decision makers: Participants in the November TF Meeting in Secaucus (selected Program Mgt Team) | L109: http://sp.ey.net/msibm/Lists/RAID%20%20Decisions%20TEST/DispForm.aspx?ID=&RootFolder=*
A110: 39 | B110: SharePoint | C110: Joshua Jackson | D110: 1) Pending | E110: Would like Service Applications to fit into Tier A | F110: Program Mgt Team | G110: 30-Nov-12 | H110: 9 | I110: 373 | J110: 9th Nov (NC) : Updated from BvG This assumption was documented and required for SP infrastructure architecture but information came from (and needs to come from) SP solutions level (previously Fusion). It also needs to come from other candidate programs but they have not had requirements at this level. Josh please review with Len to validate or revise this assumption as stated. 31-Oct (LS): Reassigned to Nicola Legacy decision makers: Participants in the November TF Meeting in Secaucus | L110: http://sp.ey.net/msibm/Lists/RAID%20%20Decisions%20TEST/DispForm.aspx?ID=&RootFolder=*
A111: 40 | B111: SharePoint | C111: Joshua Jackson | D111: 1) Pending | E111: Tier A: plan for 50 TBs and may scale to 300 TBs in next couple yrs. | F111: Program Mgt Team | G111: 30-Nov-12 | H111: 9 | I111: 368 | J111: 9th Nov (NC) : Updated from BvG This assumption was documented and required for SP infrastructure architecture but information came from (and needs to come from) SP solutions level (previously Fusion). It also needs to come from other candidate programs but they have not had requirements at this level. Josh please review with Len to validate or revise this assumption as stated. 31-Oct (LS): Reassigned to Nicola Legacy decision makers: Participants in the November TF Meeting in Secaucus​ | L111: http://sp.ey.net/msibm/Lists/RAID%20%20Decisions%20TEST/DispForm.aspx?ID=&RootFolder=*
A112: 41 | B112: SharePoint | C112: Michelle Edmonds | D112: 4) Validated | E112: CKRs (Community Knowledge Repository) will be migrated and searchable. | F112: Program Mgt Team | G112: 08-Nov-11 | H112: 0 | I112: 0 | J112: ​Confirmed with scope from Vel and Cheryl. Question about which release they are in Legacy decision makers:Participants in the November TF Meeting in Secaucus | L112: http://sp.ey.net/msibm/Lists/RAID%20%20Decisions%20TEST/DispForm.aspx?ID=&RootFolder=*
... A144: 140 | B144: SharePoint | C144: Michelle Edmonds | D144: 4) Validated | E144: 3 products will be purchased from Concept Searching | F144: Functional Stakeholder Group | G144: 30-Mar-12 | H144: 0 | I144: 0 | J144: Migration note: legacy decision maker = Cindy Hope ​3 - April - Decision Logged | L144: http://sp.ey.net/msibm/Lists/RAID%20%20Decisions%20TEST/DispForm.aspx?ID=140&RootFolder=*
A145: 142 | B145: SharePoint | C145: Michelle Edmonds | D145: 4) Validated | E145: SP solutions need to be designed to work on multiple devices | F145: Functional Stakeholder Group | G145: 28-Feb-12 | H145: 0 | I145: 0 | L145: http://sp.ey.net/msibm/Lists/RAID%20%20Decisions%20TEST/DispForm.aspx?ID=142&RootFolder=*
A146: 143 | B146: SharePoint | C146: Michelle Edmonds | D146: 4) Validated | E146: Adoption of Microsoft O365 cloud | F146: Steering Committee | G146: 09-Jan-12 | H146: 0 | I146: 0 | J146: Migration note: Legacy decision makers: Executive Sponsors​ Added in retrospect - to provide a reference 6-Mar: revalidated. | L146: http://sp.ey.net/msibm/Lists/RAID%20%20Decisions%20TEST/DispForm.aspx?ID=143&RootFolder=*
A147: 144 | B147: SharePoint | C147: Michelle Edmonds | D147: 4) Validated | E147: Tier A definition | F147: Program Mgt Team | G147: 08-Nov-11 | H147: 0 | I147: 0 | J147: Migration note: Legacy decision makers = Participants in the Novemebr TF Meeting in Secaucus​ 23-Apr: People & Communities will move to cloud; Communities provisioning to be on-prem given expected amount of customization. Revalidated. 9-Mar Travis: Need to re-work Tier A definition based on Office365 decision. Some services and capabilities may shift out of Tier A based on O365 constraints, policies and procedures and technical limitations of on-premises integration points. Arch imp: YES | L147: http://sp.ey.net/msibm/Lists/RAID%20%20Decisions%20TEST/DispForm.aspx?ID=144&RootFolder=*
A148: 145 | B148: SharePoint | C148: Michelle Edmonds | D148: 4) Validated | E148: User Experience will be a Farm WSP. | F148: Program Mgt Team | G148: 07-Nov-11 | H148: 0 | I148: 0 | J148: Migration note: Legacy decision makers = Participants in the Nov TF meeting in Secaucus ​3-Apr: Michelle reviewed for decisions comm - complete. 9-Mar Travis: Confirmed (revalidated). The design for UX is being delivered by Frog, but not sure who is doing the implementation to a WSP. This is guidance to the implementers. | L148: http://sp.ey.net/msibm/Lists/RAID%20%20Decisions%20TEST/DispForm.aspx?ID=145&RootFolder=*
A149: 146 | B149: SharePoint | C149: Michelle Edmonds | D149: 4) Validated | E149: Criteria for falling outside of Tier A | F149: Program Mgt Team | G149: 07-Nov-11 | H149: 0 | I149: 0 | J149: Migration note: Legacy decision makers = Participants in Nov TF Meeting in Secaucus ​10-Apr: michelle provided impact and rationale. 3-Apr: Michelle reviewed for decisions comm - complete. 9-Mar Travis: Confirmed. | L149: http://sp.ey.net/msibm/Lists/RAID%20%20Decisions%20TEST/DispForm.aspx?ID=146&RootFolder=*
A150: 147 | B150: SharePoint | C150: Michelle Edmonds | D150: 4) Validated | E150: BCS will only be used for User Profiles in Tier A for the GHRDB connection | F150: Program Mgt Team | G150: 07-Nov-11 | H150: 0 | I150: 0 | J150: Migration note: Legacy decision makers = Participants in the November TF Meeting in Secaucus.​ 3-Apr: Michelle reviewed for decisions comm - complete. 9-Mar Travis: Confirmed. BCS may not even be used for supplemental profile import depending on approach, but is supported by Office365 either way. | L150: http://sp.ey.net/msibm/Lists/RAID%20%20Decisions%20TEST/DispForm.aspx?ID=147&RootFolder=*
A151: 148 | B151: SharePoint | C151: Michelle Edmonds | D151: 4) Validated | E151: Use Web Trends for Web Analytics | F151: Program Mgt Team | G151: 07-Nov-11 | H151: 0 | I151: 0 | J151: Migration note: Legacy decision makers = Participants in the November TF Meeting in Secaucus​ 10-Apr: Michelle provided impact and rationale. 3-Apr: Michelle reviewed for decisions comm - complete. 9-Mar Travis: Confirmed. Web Trends is supported in Office365. | L151: http://sp.ey.net/msibm/Lists/RAID%20%20Decisions%20TEST/DispForm.aspx?ID=148&RootFolder=*
A152: 149 | B152: SharePoint | C152: Michelle Edmonds | D152: 4) Validated | E152: House cross-farm services in Frankfurt | F152: Program Mgt Team | G152: 07-Nov-11 | H152: 0 | I152: 0 | J152: Migration note: Legacy decision makers = Participants in the Nov. TF Meeting in Secaucus​ 9-Mar Travis: Revalidate based on Office365 decision. Since cross-farm services design were originally intended to be part tier A, we need to confirm that the O365 environment can still host these as cross-farm services. Arch imp: YES; 23-Apr: intention is to still house cross-farm services in the Frankfurt GDC | L152: http://sp.ey.net/msibm/Lists/RAID%20%20Decisions%20TEST/DispForm.aspx?ID=149&RootFolder=*
A153: 150 | B153: SharePoint | C153: Michelle Edmonds | D153: 4) Validated | E153: All farms will need to consume a single, global MMSA | F153: Program Mgt Team | G153: 07-Nov-11 | H153: 0 | I153: 0 | J153: Migration note: Legacy decision makers = Participants in the Nov TF Meeting in Secaucus​ Travis 9-Mar: Conceptually this decision holds, but technically there are hurdles with the integration scenarios with Office365. If this is the vision, we need to wrap a maturity model around this capability/feature. This is has been impacted by Office365. Arch imp: YES | L153: http://sp.ey.net/msibm/Lists/RAID%20%20Decisions%20TEST/DispForm.aspx?ID=150&RootFolder=*
A154: 151 | B154: SharePoint | C154: Michelle Edmonds | D154: 4) Validated | E154: User Profile sync will occur in Office365; GHRDB data will be populated in AD | F154: Program Mgt Team | G154: 07-Nov-11 | H154: 0 | I154: 0 | J154: Migration note: Legacy decision makers = participants in the November TF Meeting in Secaucus. ​ 10-Apr: Michelle provided impact. 3-Apr: Michelle reviewed for decisions comm - complete. 9-Mar Travis: Invalid decision. Based on Office365, User Profile sync will occur in Office365. GHRDB data will be populated in AD via a process outside of user profile sync (IDSync). Initially read: User Profiles and BCS: User profiles sync will live in Secaucus with GHRDB and BCS. UPRE will leverage that to replicate to the other two global data centers (Frankfurt and Singapore). | L154: http://sp.ey.net/msibm/Lists/RAID%20%20Decisions%20TEST/DispForm.aspx?ID=151&RootFolder=*
A155: 152 | B155: SharePoint | C155: Michelle Edmonds | D155: 4) Validated | E155: MySites will only live in Office 365. | F155: Program Mgt Team | G155: 07-Nov-11 | H155: 0 | I155: 0 | J155: Migration note: Legacy decision makers = Participants in the Nov. TF meeting in Secaucus​ 10-Apr: Michelle provided impact and rationale data. 3-Apr: Michelle reviewed for decisions comm - complete. 9-Mar Travis: Confirmed. MySites will only live in Office 365. | L155: http://sp.ey.net/msibm/Lists/RAID%20%20Decisions%20TEST/DispForm.aspx?ID=152&RootFolder=*
A156: 153 | B156: SharePoint | C156: Michelle Edmonds | D156: 4) Validated | E156: We will not use Power Pivot in the initial rollout | F156: Program Mgt Team | G156: 07-Nov-11 | H156: 0 | I156: 0 | J156: Migration note: Legacy decision makers = Participants in the November TF meeting in Secaucus ​3-Apr: Michelle reviewed for decisions comm - complete. Provided impact. 9-Mar Travis: Confirmed. This is not supported in Office365 in the current service description. | L156: http://sp.ey.net/msibm/Lists/RAID%20%20Decisions%20TEST/DispForm.aspx?ID=153&RootFolder=*
A157: 154 | B157: SharePoint | C157: Michelle Edmonds | D157: 4) Validated | E157: We will not include file shares in migration of business content | F157: Program Mgt Team | G157: 08-Nov-11 | H157: 0 | I157: 0 | J157: Migration note: Legacy decision makers = Participants in the Nov. TF Meeting in Secaucus​ 10-Apr: Michelle provided impact. 3-Apr: Michelle reviewed for decisions comm - complete. 9-Mar Travis: Confirmed. Long-term file shares may be migrated, but not in scope for initial phases/releases. | L157: http://sp.ey.net/msibm/Lists/RAID%20%20Decisions%20TEST/DispForm.aspx?ID=154&RootFolder=*
... A197: 184 | B197: Transition | C197: Blaine Pardoe | D197: 4) Validated | E197: IT Services will be early-adopter of SharePoint | F197: Program Mgt Team | G197: 18-Jun-12 | H197: 0 | I197: 0 | J197: 15 June (BP): Met with Brett. We are aligned on making IT Services an arly adopter to be able to better enable support. 1-June (LM): Per Blaine - Blaine has a meeting with Brett to discuss in two weeks. Required resolution updated as such. 02/03: Action - B. Pardoe to raise on the Program Level RAID Log.​ | L197: http://sp.ey.net/msibm/Lists/RAID%20%20Decisions%20TEST/DispForm.aspx?ID=184&RootFolder=*

Sheet RAID Summary
C1: 40898 | D1: 40912 | E1: 40919 | F1: 40926 | G1: 40933 | H1: 40940 | I1: 40947 | J1: 40954 | K1: 40961 | L1: 40968 | M1: 40974 | N1: 40975 | O1: 40976 | P1: 40977 | Q1: 40980 | R1: 40981 | S1: 40982 | T1: 40983 | U1: 40984 | V1: 40987 | W1: 40988 | X1: 40991 | Y1: 40994 | Z1: 40995 | AA1: 40996 | AB1: 40997 | AC1: 40998 | AD1: 41001 | AE1: 41002 | AF1: 41003 | AG1: 41005 | AH1: 41010 | AI1: 41015 | AJ1: 41017 | AK1: 41019 | AL1: 41025 | AM1: 41026 | AN1: 41032 | AO1: 41038 | AP1: 41046 | AQ1: 41053 | AR1: 41060 | AS1: 41061 | AT1: 41068 | AU1: 41075 | AV1: 41081 | AW1: 41088 | AX1: 41096 | AY1: 41103 | AZ1: 41110 | BA1: 41117 | BB1: 41124 | BC1: 41131 | BD1: 41138 | BE1: 41145 | BF1: 41152 | BG1: 41159 | BH1: 41166 | BI1: 41173 | BJ1: 41180 | BK1: 41187 | BL1: 41194 | BM1: 41201 | BN1: 41208 | BO1: 41215 | BP1: 41222 | BQ1: 41229 | BR1: 41236 | BS1: current
A2: Risks | B2: Open | C2: 40 | D2: 34 | E2: 33 | F2: 30 | G2: 32 | H2: 32 | I2: 30 | J2: 30 | K2: 32 | L2: 39 | M2: 45 | N2: 38 | O2: 37 | P2: 32 | Q2: 30 | R2: 29 | S2: 32 | T2: 32 | U2: 32 | V2: 35 | W2: 35 | X2: 35 | Y2: 35 | Z2: 34 | AA2: 38 | AB2: 35 | AC2: 35 | AD2: 36 | AE2: 34 | AF2: 35 | AG2: 35 | AH2: 37 | AI2: 36 | AJ2: 36 | AK2: 37 | AL2: 41 | AM2: 39 | AN2: 37 | AO2: 36 | AP2: 34 | AQ2: 34 | AR2: 33 | AS2: 32 | AT2: 34 | AU2: 34 | AV2: 34 | AW2: 35 | AX2: 34 | AY2: 36 | AZ2: 36 | BA2: 45 | BB2: 39 | BC2: 39 | BD2: 39 | BE2: 44 | BF2: 43 | BG2: 41 | BH2: 44 | BI2: 44 | BJ2: 45 | BK2: 46 | BL2: 48 | BM2: 43 | BN2: 46 | BO2: 44 | BP2: 41 | BQ2: 39 | BR2: 39 | BS2: =COUNT(Risks!A:A) -> 39
A3: Risks | B3: Critical | C3: 15 | D3: 10 | E3: 13 | F3: 13 | G3: 14 | H3: 14 | I3: 16 | J3: 16 | K3: 21 | L3: 28 | M3: 25 | N3: 19 | O3: 17 | P3: 14 | Q3: 14 | R3: 14 | S3: 17 | T3: 16 | U3: 16 | V3: 15 | W3: 15 | X3: 15 | Y3: 15 | Z3: 14 | AA3: 14 | AB3: 17 | AC3: 17 | AD3: 19 | AE3: 18 | AF3: 17 | AG3: 20 | AH3: 20 | AI3: 19 | AJ3: 19 | AK3: 19 | AL3: 22 | AM3: 21 | AN3: 21 | AO3: 20 | AP3: 11 | AQ3: 11 | AR3: 11 | AS3: 11 | AT3: 11 | AU3: 11 | AV3: 11 | AW3: 11 | AX3: 10 | AY3: 11 | AZ3: 11 | BA3: 12 | BB3: 11 | BC3: 12 | BD3: 12 | BE3: 12 | BF3: 12 | BG3: 10 | BH3: 12 | BI3: 11 | BJ3: 10 | BK3: 10 | BL3: 9 | BM3: 7 | BN3: 7 | BO3: 6 | BP3: 5 | BQ3: 5 | BR3: 4 | BS3: =COUNTIF(Risks!E:E,"9") -> 4
A4: Risks | B4: Missed Trigger Date | E4: 2 | F4: 3 | G4: 5 | H4: 7 | I4: 8 | J4: 10 | K4: 9 | L4: 13 | M4: 9 | N4: 2 | O4: 2 | P4: 1 | Q4: 1 | R4: 0 | S4: 1 | T4: 1 | U4: 0 | V4: 0 | W4: 0 | X4: 0 | Y4: 0 | Z4: 0 | AA4: 0 | AB4: 0 | AC4: 0 | AD4: 10 | AE4: 7 | AF4: 7 | AG4: 7 | AH4: 8 | AI4: 9 | AJ4: 6 | AK4: 5 | AL4: 7 | AM4: 4 | AN4: 6 | AO4: 9 | AP4: 8 | AQ4: 5 | AR4: 7 | AS4: 5 | AT4: 7 | AU4: 5 | AV4: 5 | AW4: 3 | AX4: 10 | AY4: 10 | AZ4: 7 | BA4: 7 | BB4: 8 | BC4: 5 | BD4: 6 | BE4: 4 | BF4: 2 | BG4: 9 | BH4: 5 | BI4: 2 | BJ4: 5 | BK4: 11 | BL4: 15 | BM4: 13 | BN4: 5 | BO4: 8 | BP4: 3 | BQ4: 3 | BR4: 9 | BS4: =COUNTIF(Risks!H:H,"<0") -> 9
A5: Risks | B5: Open | C5: =C2-C3 -> 25 | D5: =D2-D3 -> 24 | E5: =E2-E3 -> 20 | F5: =F2-F3 -> 17 | G5: =G2-G3 -> 18 | H5: =H2-H3 -> 18 | I5: =I2-I3 -> 14 | J5: =J2-J3 -> 14 | ... BO5: =BO2-BO3 -> 38 | BP5: 36 | BQ5: 34 | BR5: 35 | BS5: =BS2-BS3 -> 35
A6: Issues | B6: Open | C6: 37 | D6: 37 | E6: 42 | F6: 42 | G6: 45 | H6: 48 | I6: 52 | J6: 43 | K6: 49 | L6: 51 | M6: 55 | N6: 51 | O6: 53 | P6: 46 | Q6: 47 | R6: 44 | S6: 44 | T6: 42 | U6: 41 | V6: 37 | W6: 37 | X6: 37 | Y6: 37 | Z6: 37 | AA6: 36 | AB6: 32 | AC6: 31 | AD6: 29 | AE6: 29 | AF6: 29 | AG6: 30 | AH6: 30 | AI6: 31 | AJ6: 24 | AK6: 24 | AL6: 27 | AM6: 31 | AN6: 34 | AO6: 37 | AP6: 35 | AQ6: 33 | AR6: 32 | AS6: 31 | AT6: 26 | AU6: 28 | AV6: 27 | AW6: 33 | AX6: 32 | AY6: 31 | AZ6: 30 | BA6: 32 | BB6: 29 | BC6: 30 | BD6: 28 | BE6: 26 | BF6: 26 | BG6: 25 | BH6: 23 | BI6: 22 | BJ6: 23 | BK6: 18 | BL6: 20 | BM6: 20 | BN6: 22 | BO6: 20 | BP6: 20 | BQ6: 21 | BR6: 21 | BS6: =COUNT(Issues!A:A) -> 21
A7: Issues | B7: High Impact | E7: 25 | F7: 25 | G7: 28 | H7: 33 | I7: 39 | J7: 31 | K7: 37 | L7: 40 | M7: 45 | N7: 42 | O7: 45 | P7: 37 | Q7: 37 | R7: 36 | S7: 36 | T7: 34 | U7: 33 | V7: 29 | W7: 29 | X7: 29 | Y7: 29 | Z7: 29 | AA7: 28 | AB7: 26 | AC7: 25 | AD7: 23 | AE7: 23 | AF7: 24 | AG7: 24 | AH7: 24 | AI7: 25 | AJ7: 17 | AK7: 17 | AL7: 18 | AM7: 22 | AN7: 24 | AO7: 26 | AP7: 25 | AQ7: 22 | AR7: 21 | AS7: 21 | AT7: 17 | AU7: 15 | AV7: 16 | AW7: 18 | AX7: 17 | AY7: 15 | AZ7: 15 | BA7: 13 | BB7: 13 | BC7: 16 | BD7: 15 | BE7: 15 | BF7: 15 | BG7: 13 | BH7: 14 | BI7: 14 | BJ7: 14 | BK7: 9 | BL7: 11 | BM7: 11 | BN7: 12 | BO7: 12 | BP7: 12 | BQ7: 11 | BR7: 11 | BS7: =COUNTIF(Issues!E:E,"3) High") -> 11
A8: Issues | B8: Past Due | E8: 13 | F8: 12 | G8: 7 | H8: 13 | I8: 16 | J8: 14 | K8: 12 | L8: 22 | M8: 20 | N8: 14 | O8: 16 | P8: 13 | Q8: 8 | R8: 6 | S8: 4 | T8: 7 | U8: 6 | V8: 3 | W8: 10 | X8: 10 | Y8: 10 | Z8: 10 | AA8: 10 | AB8: 9 | AC8: 7 | AD8: 12 | AE8: 12 | AF8: 10 | AG8: 11 | AH8: 13 | AI8: 11 | AJ8: 4 | AK8: 4 | AL8: 6 | AM8: 4 | AN8: 9 | AO8: 6 | AP8: 11 | AQ8: 5 | AR8: 12 | AS8: 11 | AT8: 10 | AU8: 10 | AV8: 6 | AW8: 4 | AX8: 6 | AY8: 9 | AZ8: 8 | BA8: 12 | BB8: 16 | BC8: 12 | BD8: 8 | BE8: 9 | BF8: 9 | BG8: 11 | BH8: 7 | BI8: 6 | BJ8: 9 | BK8: 7 | BL8: 7 | BM8: 5 | BN8: 4 | BO8: 9 | BP8: 4 | BQ8: 5 | BR8: 5 | BS8: =COUNTIF(Issues!H:H,"<0") -> 5
A9: Issues | B9: Open | L9: =L6-L7 -> 11 | M9: =M6-M7 -> 10 | N9: =N6-N7 -> 9 | O9: =O6-O7 -> 8 | P9: =P6-P7 -> 9 | Q9: =Q6-Q7 -> 10 | R9: =R6-R7 -> 8 | S9: =S6-S7 -> 8 | ... BO9: =BO6-BO7 -> 8 | BP9: 8 | BQ9: 10 | BR9: 10 | BS9: =BS6-BS7 -> 10
A10: Decisions | B10: Validated | C10: 153 | D10: 153 | E10: 154 | F10: 154 | G10: 161 | H10: 182 | I10: 183 | J10: 179 | K10: 179 | L10: 179 | M10: 181 | N10: 194 | O10: 192 | P10: 191 | Q10: 192 | R10: 193 | S10: 193 | T10: 191 | U10: 191 | V10: 191 | W10: 191 | X10: 176 | Y10: 176 | Z10: 177 | AA10: 178 | AB10: 178 | AC10: 178 | AD10: 178 | AE10: 182 | AF10: 179 | AG10: 178 | AH10: 178 | AI10: 179 | AJ10: 180 | AK10: 178 | AL10: 177 | AM10: 172 | AN10: 172 | AO10: 172 | AP10: 135 | AQ10: 145 | AR10: 149 | AS10: 149 | AT10: =86+57 -> 143 | AU10: 144 | AV10: 137 | AW10: 134 | AX10: 140 | AY10: 142 | AZ10: 143 | BA10: 147 | BB10: 149 | BC10: 153 | BD10: 154 | BE10: 154 | BF10: 154 | BG10: 172 | BH10: 174 | BI10: 175 | BJ10: 175 | BK10: 176 | BL10: 176 | BM10: 177 | BN10: 177 | BO10: 177 | BP10: 177 | BQ10: 177 | BR10: 177 | BS10: =COUNTIF(Decisions!D:D,"4) Validated") -> 177
A11: Decisions | B11: Pending | C11: 24 | D11: 24 | E11: 25 | F11: 24 | G11: 30 | H11: 39 | I11: 40 | J11: 29 | K11: 28 | L11: 27 | M11: 22 | N11: 33 | O11: 28 | P11: 26 | Q11: 26 | R11: 26 | S11: 26 | T11: 23 | U11: 22 | V11: 21 | W11: 21 | X11: 21 | Y11: 21 | Z11: 22 | AA11: 22 | AB11: 22 | AC11: 22 | AD11: 22 | AE11: 23 | AF11: 23 | AG11: 23 | AH11: 23 | AI11: 22 | AJ11: 23 | AK11: 21 | AL11: 19 | AM11: 19 | AN11: 19 | AO11: 20 | AP11: 23 | AQ11: 23 | AR11: 19 | AS11: 19 | AT11: 16 | AU11: 12 | AV11: 12 | AW11: 12 | AX11: 16 | AY11: 19 | AZ11: 19 | BA11: 25 | BB11: 23 | BC11: 19 | BD11: 19 | BE11: 16 | BF11: 16 | BG11: 17 | BH11: 17 | BI11: 17 | BJ11: 17 | BK11: 18 | BL11: 18 | BM11: 15 | BN11: 15 | BO11: 19 | BP11: 19 | BQ11: 19 | BR11: 19 | BS11: =COUNTIF(Decisions!D:D,"1) Pending") -> 19
A12: Decisions | B12: Past Due | O12: 11 | P12: 9 | Q12: 9 | R12: 9 | S12: 8 | T12: 5 | U12: 2 | V12: 1 | W12: 3 | X12: 3 | Y12: 6 | Z12: 6 | AA12: 6 | AB12: 6 | AC12: 6 | AD12: 8 | AE12: 10 | AF12: 8 | AG12: 8 | AH12: 9 | AI12: 9 | AJ12: 8 | AK12: 7 | AL12: 9 | AM12: 9 | AN12: 9 | AO12: 9 | AP12: 13 | AQ12: 10 | AR12: 8 | AS12: 14 | AT12: 12 | AU12: 4 | AV12: 3 | AW12: 1 | AX12: 3 | AY12: 11 | AZ12: 7 | BA12: 17 | BB12: 16 | BC12: 9 | BD12: 10 | BE12: 9 | BF12: 9 | BG12: 10 | BH12: 2 | BI12: 1 | BJ12: 1 | BK12: 2 | BL12: 2 | BM12: 0 | BN12: 0 | BO12: 6 | BP12: 6 | BQ12: 0 | BR12: 0 | BS12: =COUNTIFS(Decisions!D:D,"1) Pending",Decisions!H:H,"<0") -> 0
A13: Assumptions | B13: Validated | C13: 78 | D13: 70 | E13: 67 | F13: 67 | G13: 68 | H13: 69 | I13: 69 | J13: 69 | K13: 63 | L13: 63 | M13: 63 | N13: 63 | O13: 63 | P13: 63 | Q13: 62 | R13: 62 | S13: 62 | T13: 62 | U13: 62 | V13: 62 | W13: 62 | X13: 54 | Y13: 54 | Z13: 53 | AA13: 53 | AB13: 54 | AC13: 55 | AD13: 55 | AE13: 100 | AF13: 99 | AG13: 99 | AH13: 102 | AI13: 102 | AJ13: 102 | AK13: 103 | AL13: 103 | AM13: 103 | AN13: 100 | AO13: 103 | AP13: 92 | AQ13: 92 | AR13: 93 | AS13: 93 | AT13: 93 | AU13: 93 | AV13: 93 | AW13: =78+15 -> 93 | AX13: 83 | AY13: 83 | AZ13: 86 | BA13: 86 | BB13: 86 | BC13: 86 | BD13: 88 | BE13: 88 | BF13: 88 | BG13: 90 | BH13: 90 | BI13: 90 | BJ13: 90 | BK13: 90 | BL13: 90 | BM13: 90 | BN13: 90 | BO13: 90 | BP13: 90 | BQ13: 90 | BR13: 90 | BS13: =COUNTIF(Assumptions!E:E,"3) Validated") -> 90
A14: Assumptions | B14: Pending | S14: 43 | T14: 43 | U14: 43 | V14: 43 | W14: 43 | X14: 12 | Y14: 12 | Z14: 11 | AA14: 10 | AB14: 11 | AC14: 7 | AD14: 7 | AE14: 25 | AF14: 24 | AG14: 24 | AH14: 22 | AI14: 22 | AJ14: 22 | AK14: 22 | AL14: 22 | AM14: 22 | AN14: 8 | AO14: 11 | AP14: 11 | AQ14: 11 | AR14: 10 | AS14: 10 | AT14: 10 | AU14: 10 | AV14: 12 | AW14: 6 | AX14: 7 | AY14: 6 | AZ14: 3 | BA14: 2 | BB14: 2 | BC14: 2 | BD14: 3 | BE14: 3 | BF14: 3 | BG14: 1 | BH14: 1 | BI14: 1 | BJ14: 1 | BK14: 1 | BL14: 1 | BM14: 1 | BN14: 1 | BO14: 1 | BP14: 1 | BQ14: 1 | BR14: 1 | BS14: =COUNTIF(Assumptions!E:E,"1) Not yet validated") -> 1
A15: Assumptions | B15: Past Due | O15: 41 | P15: 41 | Q15: 40 | R15: 39 | S15: 39 | T15: 38 | U15: 38 | V15: 37 | W15: 37 | X15: 6 | Y15: 6 | Z15: 6 | AA15: 5 | AB15: 7 | AC15: 3 | AD15: 5 | AE15: 5 | AF15: 4 | AG15: 6 | AH15: 4 | AI15: 8 | AJ15: 8 | AK15: 8 | AL15: 8 | AM15: 4 | AN15: 1 | AO15: 1 | AP15: 3 | AQ15: 1 | AR15: 1 | AS15: 1 | AT15: 1 | AU15: 7 | AV15: 9 | AW15: 3 | AX15: 3 | AY15: 2 | AZ15: 1 | BA15: 0 | BB15: 0 | BC15: 0 | BD15: 1 | BE15: 1 | BF15: 1 | BG15: 0 | BH15: 0 | BI15: 0 | BJ15: 0 | BK15: 0 | BL15: 0 | BM15: 0 | BN15: 0 | BO15: 1 | BP15: 1 | BQ15: 1 | BR15: 1 | BS15: =COUNTIFS(Assumptions!E:E,"1) Not yet validated",Assumptions!I:I,"<0") -> 1

Sheet Cross-Org
B1: Wk 31-Oct | C1: 40933 | D1: 40942 | E1: 40949 | F1: 40956 | G1: 40963 | H1: 40970 | I1: 40977 | J1: 40984 | K1: 40991 | L1: 40998 | M1: 41005 | N1: 41012 | O1: 41019 | P1: 41026 | Q1: 41033 | R1: 41040 | S1: 41047 | T1: 41054 | U1: 41061 | V1: 41068 | W1: 41075 | X1: 41082 | Y1: 41089 | Z1: 41096 | AA1: 41103 | AB1: 41110 | AC1: 41117 | AD1: 41124 | AE1: 41131 | AF1: 41138 | AG1: 41145 | AH1: 41152 | AI1: 41159 | AJ1: 41166 | AK1: 41173 | AL1: 41180 | AM1: 41187 | AN1: 41194 | AO1: 41201 | AP1: 41208 | AQ1: 41215 | AR1: 41222 | AS1: 41229 | AT1: 41236 | AU1: current
A2: Decisions | B2: 14 | C2: 161 | D2: 182 | E2: 183 | F2: 174 | G2: 179 | H2: 179 | I2: 194 | J2: 191 | K2: 176 | L2: 178 | M2: 178 | N2: 179 | O2: 178 | P2: 177 | Q2: 172 | R2: 172 | S2: 135 | T2: 145 | U2: 149 | V2: 143 | W2: 144 | X2: 137 | Y2: 134 | Z2: 140 | AA2: 142 | AB2: 143 | AC2: 146 | AD2: 149 | AE2: 152 | AF2: 154 | AG2: 154 | AH2: 154 | AI2: 172 | AJ2: 173 | AK2: 175 | AL2: 175 | AM2: 176 | AN2: 176 | AO2: 177 | AP2: 177 | AQ2: 177 | AR2: 177 | AS2: 177 | AT2: 177 | AU2: =COUNTIF(Decisions!D:D,"4) Validated") -> 177
A3: Critical Assumptions | B3: 0 | C3: 0 | D3: 0 | E3: 0 | F3: 0 | G3: 0 | H3: 0 | I3: 0 | J3: 0 | K3: 0 | L3: 0 | M3: 0 | N3: 0 | O3: 0 | P3: 0 | Q3: 0 | R3: 0 | S3: 0 | T3: 0 | U3: 0 | V3: 0 | W3: 0 | X3: 0 | Y3: 0 | Z3: 0 | AA3: 0 | AB3: 0 | AC3: 0 | AD3: 0 | AE3: 0 | AF3: 0 | AG3: 0 | AH3: 0 | AI3: 0 | AJ3: 0 | AK3: 0 | AL3: 0 | AM3: 0 | AN3: 0 | AO3: 0 | AP3: 0 | AQ3: 0 | AR3: 0 | AS3: 0 | AT3: 0 | AU3: 0
A4: Critical Risks | B4: 15 | C4: 14 | D4: 14 | E4: 16 | F4: 16 | G4: 21 | H4: 28 | I4: 16 | J4: 16 | K4: 15 | L4: 17 | M4: 20 | N4: 20 | O4: 19 | P4: 22 | Q4: 21 | R4: 20 | S4: 11 | T4: 11 | U4: 11 | V4: 11 | W4: 11 | X4: 11 | Y4: 11 | Z4: 10 | AA4: 11 | AB4: 11 | AC4: 11 | AD4: 12 | AE4: 11 | AF4: 12 | AG4: 12 | AH4: 12 | AI4: 10 | AJ4: 11 | AK4: 11 | AL4: 10 | AM4: 10 | AN4: 9 | AO4: 7 | AP4: 7 | AQ4: 6 | AR4: 5 | AS4: 5 | AT4: 4 | AU4: =COUNTIF(Risks!E:E,"9") -> 4
A5: Assumptions (Total) | B5: 71 | C5: 68 | D5: 69 | E5: 69 | F5: 69 | G5: 63 | H5: 63 | I5: 63 | J5: 62 | K5: 54 | L5: 54 | M5: 99 | N5: 102 | O5: 103 | P5: 103 | Q5: 100 | R5: 103 | S5: 92 | T5: 92 | U5: 93 | V5: 93 | W5: 93 | X5: 93 | Y5: 93 | Z5: 83 | AA5: 83 | AB5: 85 | AC5: 86 | AD5: 86 | AE5: 86 | AF5: 88 | AG5: 88 | AH5: 88 | AI5: 90 | AJ5: 90 | AK5: 90 | AL5: 90 | AM5: 90 | AN5: 90 | AO5: 90 | AP5: 90 | AQ5: 90 | AR5: 90 | AS5: 90 | AT5: 90 | AU5: =COUNTIF(Assumptions!E:E,"3) Validated") -> 90
A6: Issues (Total) | B6: 30 | C6: 45 | D6: 48 | E6: 52 | F6: 43 | G6: 49 | H6: 51 | I6: 53 | J6: 42 | K6: 37 | L6: 33 | M6: 30 | N6: 30 | O6: 24 | P6: 27 | Q6: 35 | R6: 37 | S6: 35 | T6: 33 | U6: 32 | V6: 26 | W6: 28 | X6: 27 | Y6: 33 | Z6: 32 | AA6: 31 | AB6: 29 | AC6: 33 | AD6: 29 | AE6: 31 | AF6: 28 | AG6: 26 | AH6: 26 | AI6: 25 | AJ6: 23 | AK6: 22 | AL6: 23 | AM6: 18 | AN6: 20 | AO6: 20 | AP6: 22 | AQ6: 20 | AR6: 20 | AS6: 22 | AT6: 21 | AU6: =COUNT(Issues!A:A) -> 21
A7: Risks (Total) | B7: 36 | C7: 32 | D7: 32 | E7: 30 | F7: 30 | G7: 32 | H7: 39 | I7: 37 | J7: 32 | K7: 35 | L7: 35 | M7: 35 | N7: 37 | O7: 37 | P7: 41 | Q7: 37 | R7: 36 | S7: 34 | T7: 34 | U7: 33 | V7: 34 | W7: 36 | X7: 34 | Y7: 35 | Z7: 34 | AA7: 36 | AB7: 36 | AC7: 44 | AD7: 40 | AE7: 38 | AF7: 39 | AG7: 43 | AH7: 43 | AI7: 41 | AJ7: 42 | AK7: 44 | AL7: 44 | AM7: 46 | AN7: 48 | AO7: 43 | AP7: 46 | AQ7: 44 | AR7: 41 | AS7: 39 | AT7: 39 | AU7: =COUNT(Risks!A:A) -> 39

Sheet Risk Pivot
A1: Overdue Risks
A2: Countdown | B2: (Multiple Items)
A3: Priority | B3: (All)
A5: ID | B5: Title | C5: Workstream | D5: Assigned To | E5: URL
A6: 19 | B6: Delays in confirming deployment velocity | C6: Outlook/Exchange | D6: Rachel Phillips | E6: http://sp.ey.net/msibm/Lists/Program%20Risks%20%20TEST/DispForm.aspx?ID=&RootFolder=*
A8: 22 | B8: AD Remediation - Complete the attribute cleansing | C8: IAM | D8: Ted Balfour | E8: http://sp.ey.net/msibm/Lists/Program%20Risks%20%20TEST/DispForm.aspx?ID=&RootFolder=*
A10: 34 | B10: There is a risk that we cannot determine the total duration of Outlook migrations or the impact on the FY13 budget and effort required from program and I&O resource, nor ability to confirm that we can complete the migrations to O365 in the required 34 wks | C10: Outlook/Exchange | D10: Rachel Phillips | E10: http://sp.ey.net/msibm/Lists/Program%20Risks%20%20TEST/DispForm.aspx?ID=&RootFolder=*
A12: 208 | B12: Test schedule does not allow for effective Integration Testing between O/E & Lync | C12: M&C Program | D12: Geoff Thompson | E12: http://sp.ey.net/msibm/Lists/Program%20Risks%20%20TEST/DispForm.aspx?ID=&RootFolder=*
A14: 251 | B14: Business Case - M&C Support Organization resources | C14: M&C Program | D14: Gavin Bell | E14: http://sp.ey.net/msibm/Lists/Program%20Risks%20%20TEST/DispForm.aspx?ID=&RootFolder=*
A16: 279 | B16: MSP Vendor Business case could be eroded if further on prem countries cannot be supported offshore | C16: Outlook/Exchange | D16: Shaun Bradley | E16: http://sp.ey.net/msibm/Lists/Program%20Risks%20%20TEST/DispForm.aspx?ID=&RootFolder=*
A18: 222 | B18: Risk the build of On-Prem countries in scope of DCC will slip (china and austraila) | C18: Outlook/Exchange | D18: Rewa Bouji | E18: http://sp.ey.net/msibm/Lists/Program%20Risks%20%20TEST/DispForm.aspx?ID=&RootFolder=*
A20: 318 | B20: I/O may not sign off deployment plan without IT Services as early adopters | C20: Transition | D20: Nick Coburn | E20: http://sp.ey.net/msibm/Lists/Program%20Risks%20%20TEST/DispForm.aspx?ID=&RootFolder=*
A22: 329 | B22: Countries not aware of the financial or operational impact of going On-Prem, so risk they won’t order required hardware on time | C22: Outlook/Exchange | D22: David Bingham | E22: http://sp.ey.net/msibm/Lists/Program%20Risks%20%20TEST/DispForm.aspx?ID=&RootFolder=*

Sheet Issue Pivot
A1: Overdue Issues
A2: Countdown | B2: (Multiple Items)
A3: Impact | B3: (All)
A5: ID | B5: Title | C5: Workstream | D5: Assigned to | E5: URL
A6: 118 | B6: No identified country based business approval defined for MIA | C6: Outlook/Exchange | D6: Rachel Phillips | E6: http://sp.ey.net/msibm/Lists/RAID%20%20Issues%20TEST/DispForm.aspx?ID=&RootFolder=*
A8: 75 | B8: Lack of a confirmed DCC schedule is impacting planning for On-prem build and deployment | C8: Outlook/Exchange | D8: Rewa Bouji | E8: http://sp.ey.net/msibm/Lists/RAID%20%20Issues%20TEST/DispForm.aspx?ID=&RootFolder=*
A10: 182 | B10: Unclear roles and responsibilities between engineering and architecture and lack of an overall technical "lead" for all technology areas impacting O/E | C10: Outlook/Exchange | D10: Rewa Bouji | E10: http://sp.ey.net/msibm/Lists/RAID%20%20Issues%20TEST/DispForm.aspx?ID=&RootFolder=*
A12: 187 | B12: Network Assessment impact on deployment schedule | C12: Outlook/Exchange | D12: Yvonne McGrory | E12: http://sp.ey.net/msibm/Lists/RAID%20%20Issues%20TEST/DispForm.aspx?ID=&RootFolder=*
A14: 190 | B14: ATT Plan does not support FY13 'go-live' for Lync | C14: Lync | D14: Neil Sahdev | E14: http://sp.ey.net/msibm/Lists/RAID%20%20Issues%20TEST/DispForm.aspx?ID=&RootFolder=*

Sheet Assumption Pivot
A1: Status | B1: 1) Not yet validated
A2: Countdown | B2: (Multiple Items)
A3: Assumptions
A4: ID | B4: Title | C4: Workstream | D4: Assigned to | E4: URL
A5: 194 | B5: Holiday impact on availability | C5: SharePoint | D5: Nicola Cooper | E5: http://sp.ey.net/msibm/Lists/RAID%20%20Assumptions%20TEST/DispForm.aspx?ID=&RootFolder=*
A7: Grand Total

Sheet Decision Pivot
A1: Status | B1: 1) Pending
A2: Countdown | B2: 0
A3: Decisions
A4: ID | B4: Title | C4: Workstream | D4: Assigned To | E4: URL
A5: Grand Total
