Workbook

Sheet Instructions
A1: Worksheet name | B1: How to use
A2: General | B2: 1. For each worksheet, enter the project name and last updated date in the header 2. Project leads and managers will raise items from their individual project RAIDs to the program level RAID if it cannot be resolved within the project and/or if it has an impact at the overall program level (scope, quality, cost and schedule). 3. The person identifying and raising the item to the log must follow the instructions outlined below to properly define the item. It is critical for this person to: a. Clearly describe the item, including its potential effect or impact on the program b. Assess each impact category (quality, scope, cost and schedule) with your workstream lead c, Talk to potential item owner or assigned party and agree ownership. If nobody is identified, assign to item identifier. 4. The person assigned to the item is responsible to: a. Manage until action plan completed. b. Create an action plan. c. Manage changes and tasks d. Keep workstream lead informed e. Update working notes, review notes and other fields as described below.
A3: Risks
A4: Risk Log | B4: 1. Enter a unique # for the Risk; this number serves as the item reference number. Proceed in numerical order such that first risk added to the log has # R1, the second R2, etc. 2. Enter the Date Captured. The Date Captured is the date on which the risk is discovered. 3. Enter the name of the person who raised the risk to the log in the Identified by column. 4. Select the Status from the dropdown list. The risk can be 01. Open, 02. Open & Assigned, 03. Action/Mitigation Plan Defined, 04. Action Plan Complete, 05. Risk Closed, 06. Deferred, 07. Risk has become an Issue, 08. Blank 5. Enter information in the Cause column. A Cause describes what may have created the risk and may be a requirement, assumption, constraint or condition that creates the possibility of negative or positive outcomes. 6. Enter description in the Risk column. A Risk is a threat (bad event) or an opportunity (good event) that may positively or negatively impact a project. Risks may be unknown factors. 7. Enter information in the Effect column. Describe to what the risk could/would/may lead. 8. Select the Workstream/Project/Program which owns the risk. It can be App and Data Migration, Change Management, IAM, M&C Program, SharePoint, Technology Foundation or Unified Communications. 9. Enter the name of the person who is the Risk Owner. The risk owner is someone from within the current program assigned to monitor the risk. 10. Enter the person Assigned to manage the risk. 11. Select the Priority from the dropdown list. It can be Critical, High, Moderate, Minor or Negligible. See chart in Ratings tab. 12. Select the Proximity. Proximity is, from a time perspective, how close the risk is to occurring Can be Impact < 4 weeks, Impact > 4 weeks, Impact > 3 months. 13. Select the Risk probability from the dropdown list. It is the likelihood that the risk will occur. It can be 01. Unsure, 02. Slight, 03. Doubtful, 04. Possible, 05. Probable, or 06. Certain. See the Probability chart in Ratings tab for further definition. 14. Select the impact factor this risk will have on the project Scope from the dropdown list. It is the effect on the project's scope if the risk occurs. See Impact table in Ratings tab for further clarification. 15. Select the impact factor this risk will have on the project Quality from the dropdown list. It is the effect on the project's quality if the risk occurs. See Impact table in Ratings tab for further clarification.
B5: 16. Select the impact factor this risk will have on the project Schedule from the dropdown list. It is the effect on the project's schedule if the risk occurs. See Impact table in Ratings tab for further clarification. 17. Select the impact factor this risk will have on the project Cost from the dropdown list. It is the effect on the project's cost if the risk occurs. See Impact table in Ratings tab for further clarification. 18. Enter the Trigger description for the identified risk. It is the risk symptoms or warning signs that a potential risk might happen 19. Select the Risk response. It describes how the project team is going to respond to the risk event. Choose a value from the dropdown list. It can be: Undecided, Acceptance, Avoidance , Mitigation. a. Risk Acceptance - A risk response planning technique that indicates that the project team has decided not to change the PMP to deal with a risk or is unable to identify any other suitable response strategy. b. Risk Avoidance - A risk response planning technique for a threat that creates changes to the project management plan that are meant to either eliminate the risk or to protect the project management objectives from its impact. c. Risk Mitigation - A risk response planning technique associated with threats that seeks to reduce the probability of occurrence or impact of a risk. 20. Enter description of the Contingency plan. It is the fallback plan should the risk occur. 21. Enter the description of the Mitigation plan. It is the plan to mitigate the risk. 22. Enter the date and updates, changes and actions taken/planned in the Update Log (Progress). Be sure to include justification for any alterations made to the Required Risk Resolution Date. 23. Enter the Next Review Date, the date of the next meeting during which the risk should be reviewed. 24. Choose the Escalation level from a dropdown list. It can be Project Manager, Program Manager, Program Director, Managing Sponsor, Executive Sponsor, or Other. 25. Enter the Risk resolution description. 26. Enter the Required Risk Resolution Date. This is the date by which actions need to be taken to be able to close the risk. Any changes to this field must be documented and justified in the Update Log (Progress) column. 27. Enter the Actual Risk Resolution Date. This is the date that the risk is closed. 28. If the risk becomes an Issue or Change Request, document the reference number of the new item in Output Reference.
A6: Issues
A7: Issue Definition | B7: 1. Enter a unique # for the issue; this number serves as the item reference number. Proceed in numerical order such that first issue added to the log has # I1, the second I2, etc. 2. Enter the date the issue was discovered in the Date captured field. 3. Enter the name of the person who identified the issue in the Identified by field. 4. Select the Status for the issue in the Issue definition section as Active or Closed. 5. Enter the Input Reference # from the Risk log. When a risk is realized / occurs, it becomes an issue and should be tracked in the Issues log. This field will help to maintain an audit trail of the lifecycle of a risk to an issue. 6. Enter a description of the issue in the Issue description field. Include brief definition of the issue, along with details of the impact to the project/program. 7. Select the impact factor this issue will have on the project Scope from the dropdown list. Can be Undecided, Low, Medium, High, Critical. See Impact table in Ratings tab for further clarification. 8. Select the impact factor this issue will have on the project Quality from the dropdown list. Can be Undecided, Low, Medium, High, Critical. See Impact table in Ratings tab for further clarification. 9. Select the impact factor this issue will have on the project Schedule from the dropdown list. Can be Undecided, Low, Medium, High, Critical. See Impact table in Ratings tab for further clarification. 10. Select the impact factor this issue will have on the project Cost from the dropdown list. Can be Undecided, Low, Medium, High, Critical. See Impact table in Ratings tab for further clarification. 11. Select the Priority from a dropdown list. It can be Critical, High, Moderate, Minor or Negligible. This value will reflect the highest impact value from the impact-related columns.Therefore, by definition, if any of the Impacts are rated High or Critical, the Priority must rated High or Critical, as well.
A8: Issue Assignment | B8: 1. Enter the name of the person who is the Issue Owner. The Issue Owner is a person within the current program assigned to monitor the Issue. 2. Enter the person the issue is Assigned to. This is the person assigned to manage the issue. 3. Select the Workstream/Project/Program which owns the issue. It can be App & Data Migration, Change Management, IAM, M&C Program, SharePoint, Technology Foundation or Unified Communications.
A9: Issue Resolution | B9: 1. Enter the planned resolution option for the issue in the Planned Resolution field. 2. Enter the Next review date. This is the date of the next meeting on which the item should be reviewed. 3. Provide the Required Resolution Date for complete resolution of the issue. This is the due date. 4. Enter the date and updates, changes and actions taken/planned in the Update Log. Be sure to include justification for any alterations made to the Required Resolution Date. 5. Select the Escalation level from a dropdown list. It can be Project Manager, Program Manager, Program Director, Managing Sponsor, Executive Sponsor, or Other. 6. Enter the Actual resolution details available for this issue. 7. Enter the Actual Resolution date for the issue. 8. If the output is a Change Request, please enter the Output Reference #.
A10: Assumptions
A11: Assumptions Log | B11: 1. Enter a unique # for the assumption; this number serves as the item reference number. Proceed in numerical order such that first assumption added to the log has # A1, the second A2, etc. 2. Enter the name of the person who raised the Assumption to the log in the Identified by column. 3. Select the Workstream/Project/Program which owns the assumption. It can be App & Data Migration, Change Management, M&C Program, SharePoint, Technology Foundation or Unified Communications. 4. Enter an Assumption, with a brief description. 5. Enter the Potential impact if assumption proves to be false. 6. Enter the Forum/Individual that will be responsible for validating the assumption. 7. Enter details of the person who validated the assumption in the Validated by column. 8. Enter the date the assumption was last reviewed on in the Last review date column. 9. Enter the date for the next review of the assumption in the Next review date column. 10. Enter the date by which the Assumption must be validated in the Due Date column. 11. Select the Status of the item. It can be Validated, Not yet validated, Output to Risk/Issue or Obsolete. 12. Enter the Risk or Issue # as the Output Reference # if the Assumption has become one of these. 13. Enter any Comments you may have on the assumption.
A12: Decisions
A13: Decisions Log | B13: 1. Enter a unique # for the decision; this number serves as the item reference number. Proceed in numerical order such that first decision added to the log has # D1, the second D2, etc. 2. Enter the name of the person who raised the Assumption to the log in the Identified by column. 3. Select the Workstream/Project/Program which owns the assumption. It can be App & Data Migration, Change Management, M&C Program, SharePoint, Technology Foundation or Unified Communications. 4. Select the Status of the Decision. It can be Pending, Closed, Obsolete. 5. Enter the Target Date for the decision; that is, the date by which the decision must be made. 6. Enter the Decision date when this decision was made. When this date is entered, the Status of the item should be changed from Pending to Closed. 7. Enter the details of all Decision makers involved in making the decision. 8. Enter Decision Description and Impact of the decision. 9. Enter any Comments you may have about the Decision.

Sheet Ratings
A1: Impact: Risks and Issues
A2: Area | B2: 00. Undecided | C2: 01. Low | D2: 02. Medium | E2: 03. High | F2: 04. Critical
A3: Time | B3: Priority to be determine | C3: Impact on Critical Path is less than 5% | D3: Impact on Critical Path is between 5% and 25% | E3: Impact on Critical path is between 25% and 50% | F3: Impact on Critical Path is greater than 50%
A4: Cost | B4: Priority to be determine | C4: Impact on cost baseline is less than 5% | D4: Impact on cost baseline is between 5% and 25% | E4: Impact on cost baseline is between 25% and 50% | F4: Impact on cost baseline is greater than 50%
A5: Scope | B5: Priority to be determine | C5: Scope change which impacts Time or Cost greater than 5% | D5: Scope change which impacts Time or Cost between 5% and 25% | E5: Scope change which impacts Time or Cost between 25% and 50% | F5: Scope change which impacts Time or Cost between more than 50%
A6: Quality | B6: Priority to be determine | C6: Minimal quality deliverable issues | D6: Small amount of quality deliverable issues which require remediation | E6: Large amount of quality deliverable issues which require remediation at program level | F6: Large amount of quality deliverable issues which impact Time and Cost and which require remediation at senior level
A9: Risk Priority Definitions:
A10: Critical | B10: If the risk event occurs, the program/project will fail. Minimum acceptable requirements will not be met.
A11: High | B11: If the risk event occurs, the program/project will encounter major cost/schedule increases. Minimum acceptable requirements will be met. Secondary requirements may not be met.
A12: Moderate | B12: If the risk event occurs, the program/project will encounter moderate cost/schedule increases. Minimum acceptable requirements will be met; some secondary requirements may not be met.
A13: Minor | B13: If the risk event occurs, the program/project will encounter small cost/schedule increases. Minimum acceptable requirements will be met. Most secondary requirements will be met.
A14: Negligible | B14: If the risk event occurs, it will have no effect on the program/project. All requirements will be met.
A17: Issue Priority Definitions:
A18: Critical | B18: The issue will cause the program/project to fail. Minimum acceptable requirements will not be met.
A19: High | B19: The issue will cause the program/project to encounter major cost/schedule increases. Minimum acceptable requirements will be met. Secondary requirements may not be met.
A20: Moderate | B20: The issue will cause the program/project to encounter moderate cost/schedule increases. Minimum acceptable requirements will be met; some secondary requirements may not be met.
A21: Minor | B21: The issue will cause the program/project to encounter small cost/schedule increases. Minimum acceptable requirements will be met. Most secondary requirements will be met.
A22: Negligible | B22: The issue will have no effect on the program/project. All requirements will be met.
A25: Probability
A26: 05. Certain | B26: 91-100%: very likely the risk will occur
A27: 04. Probable | B27: 61-90%: likely the risk will occur
A28: 03. Possible | B28: 41-60%: even likelihood the risk will occur
A29: 02. Doubtful | B29: 11-40%: unlikely the risk will occur
A30: 01. Slight | B30: 0-10%: very unlikely the risk will occur
A31: 00. Unsure | B31: Investigation required
A33: Proximity
A34: 01. Impact less than 4 weeks
A35: 02. Impact greater than 4 weeks
A36: 03. Impact greater than 3 months

Sheet Risk Log
A1: # | B1: Date Captured | C1: Identified by | D1: Status | E1: Cause As a result of (cause) | F1: Risk (uncertain event) may occur | G1: Effect which could/would/may lead to (effect / impact) | H1: Program / Workstream | I1: Project / Workstream | J1: Risk Owner | K1: Assigned to | L1: Priority | M1: Proximity | N1: Risk probability | O1: Impact: Scope | P1: Impact: Quality | Q1: Impact: Schedule | R1: Impact: Cost | S1: Risk Trigger | T1: Risk response | U1: Contingency Plan | V1: Mitigation plan | W1: Update Log (Progress) | X1: Next Review Date | Y1: Escalation level | Z1: Risk resolution | AA1: Required Risk Resolution Date | AB1: Actual Risk Resolution Date | AC1: Input/Output Refernce | AE1: =TODAY() -> 40990 | AF1: Status | AG1: Today > Res. Date | AH1: 30-90 days | AI1: 91-180 days | AJ1: 180+ days | AK1: Critical or High | AL1: Days until Due | AM1: Due in the next week | AN1: Critical, High or Moderate
A2: R102A | B2: 40947 | C2: Neil Sahdev | D2: 07. Risk has become an Issue | E2: Delays confirming future state of each application - in-turn this will delay the A&DM Program Archiving, Decommmisioning and Replatforming applications. | F2: IT Service Delivery Leads are flagging that their teams do not have both the bandwidth and a charge code to review / validate the Rediscovery reports | G2: No response received from IT Service Delivery leads | H2: App and Data Migration | J2: Neil Sahdev | K2: TBC | L2: Critical | M2: 01. Impact < 4 weeks | N2: 04. Probable | O2: 01. Low | P2: 01. Low | Q2: 04. Critical | R2: 03. High | S2: No responses received from IT Service Delivery Leads | T2: Mitigation | U2: None - the decision on the future state of each application needs to be confirmed by the IT Service Delivery Leads on behalf of the business | V2: Host briefing sessions to provide support to the IT Service Delivery teams - in progress | W2: 07-Mar: Risk now closed as item has been raised as an issue (#140) 22-Feb: inc. in man. Pack again; waiting on Operating Model decision. 15-Feb: include in management pack. 8-Feb: Risk raised; Neil reqd this item go into the mng pack. Will impact when the team can do the work and thus has financial implications, as well. | X2: 40968 | Y2: Program Director | AA2: 40970 | AF2: =IFERROR(OR(Table4[[#This Row],[Status]]="02. Open & Assigned",Table4[[#This Row],[Status]]="01. Open",Table4[[#This Row],[Status]]="03. Action/Mitigation Plan Defined",Table4[[#This Row],[Status]]="04. Action Plan Completed",Table4[[#This Row],[Status]]="08. Blank"),"") -> FALSE | AG2: =IF(Table4[[#This Row],[Required Risk Resolution Date]]="","FALSE",IF($AE$1>Table4[[#This Row],[Required Risk Resolution Date]],TRUE,FALSE)) -> TRUE
A3: R106A | B3: 40967 | C3: Neil Sahdev | D3: 02. Open & Assigned | E3: If RFP lead time > 4 months | F3: Based on the time is has taken to finalise other M&C RFPs the lead time to procure vendor(s) required for the A&DM Portfolio Teams may not be sufficient for work commence 1st Jul'12. If this was the case then the delivery date of the target application would be impacted. | G3: The deployment of the first application replatforms from the portfolio teams would be delayed | H3: App and Data Migration | J3: Neil Sahdev | K3: Neil Sahdev | L3: High | M3: 02. Impact > 4 Weeks < 3 Months | N3: 04. Probable | O3: 01. Low | P3: 01. Low | Q3: 03. High | R3: 03. High | S3: If RFP lead time > 4 months | T3: Mitigation | U3: Defer start-dates of the Portfolio teams however this will defer the business benefits (i.e. decommissioning legacy apps) | V3: Gain agreement to the A&DM Operating Model (Issue 141) then work with Procurement to initiate the RFP process | W3: 16-Mar: Neil said there are a few actions remaining before closure (from his call with Alan). 06 Mar: The preferred approach to mitigating the risk is initiate the RFP process now however this is dependant on agreeing both the Operating Model and Resourcing Strategy for A&DM (issue 141) | X3: 40991 | Y3: Program Director | AA3: 40998 | AF3: =IFERROR(OR(Table4[[#This Row],[Status]]="02. Open & Assigned",Table4[[#This Row],[Status]]="01. Open",Table4[[#This Row],[Status]]="03. Action/Mitigation Plan Defined",Table4[[#This Row],[Status]]="04. Action Plan Completed",Table4[[#This Row],[Status]]="08. Blank"),"") -> TRUE | AG3: =IF(Table4[[#This Row],[Required Risk Resolution Date]]="","FALSE",IF($AE$1>Table4[[#This Row],[Required Risk Resolution Date]],TRUE,FALSE)) -> FALSE | AH3: =IF(AE3<30,FALSE,IF(AE3>90,FALSE,TRUE)) -> FALSE | AI3: =IF(AE3<91,FALSE,IF(AE3>180,FALSE,TRUE)) -> FALSE | AJ3: =IF(AE3>180,TRUE,FALSE) -> FALSE | AK3: =OR(Table4[[#This Row],[Priority]]="Critical",Table4[[#This Row],[Priority]]="High") -> TRUE | AL3: =Table4[[#This Row],[Required Risk Resolution Date]]-$AE$1 -> 8 | AM3: =IF(AL3<1,FALSE,IF(AL3>7,FALSE,TRUE)) -> FALSE | AN3: =OR(Table4[[#This Row],[Priority]]="Critical",Table4[[#This Row],[Priority]]="High",Table4[[#This Row],[Priority]]="Moderate") -> TRUE
A4: R23 | B4: 40674 | D4: 05. Risk Closed | F4: Relative scope of Application Migration (AM) and Solution Portfolio Asset Rationalisation (SPAR) unclear | H4: App and Data Migration | J4: Neil Sahdev | N4: 03. Possible | O4: 02. Medium | W4: 30/08- SPAR program now disbanded. Close. | X4: 40772 | Z4: Discussing emerging scope with SPAR program team. Updating AM charter accordingly. Will seek approval of same from SPAR. | AB4: 40785 | AE4: =$AE$1-Table4[[#This Row],[Date Captured]] -> 316 | AF4: =IFERROR(OR(Table4[[#This Row],[Status]]="02. Open & Assigned",Table4[[#This Row],[Status]]="01. Open",Table4[[#This Row],[Status]]="03. Action/Mitigation Plan Defined",Table4[[#This Row],[Status]]="04. Action Plan Completed",Table4[[#This Row],[Status]]="08. Blank"),"") -> FALSE | AG4: =IF(Table4[[#This Row],[Required Risk Resolution Date]]="","FALSE",IF($AE$1>Table4[[#This Row],[Required Risk Resolution Date]],TRUE,FALSE)) -> FALSE | AH4: =IF(AE4<30,FALSE,IF(AE4>90,FALSE,TRUE)) -> FALSE | AI4: =IF(AE4<91,FALSE,IF(AE4>180,FALSE,TRUE)) -> FALSE | AJ4: =IF(AE4>180,TRUE,FALSE) -> TRUE | AK4: =OR(Table4[[#This Row],[Priority]]="Critical",Table4[[#This Row],[Priority]]="High") -> FALSE | AL4: =Table4[[#This Row],[Required Risk Resolution Date]]-$AE$1 -> -40990 | AM4: =IF(AL4<1,FALSE,IF(AL4>7,FALSE,TRUE)) -> FALSE | AN4: =OR(Table4[[#This Row],[Priority]]="Critical",Table4[[#This Row],[Priority]]="High",Table4[[#This Row],[Priority]]="Moderate") -> FALSE
A5: R24 | B5: 40674 | D5: 05. Risk Closed | F5: Process of identifying "as is" applications, business and technical classification, and decision making not well defined. | H5: App and Data Migration | J5: Neil Sahdev | N5: 03. Possible | O5: 02. Medium | W5: 12/10 - Manually reaching out to the business on these applications. | X5: 40821 | Z5: Define processes as part of AM program. Seek approval from SPAR, DCC, and other programs with common interest. | AB5: ? | AE5: =$AE$1-Table4[[#This Row],[Date Captured]] -> 316 | AF5: =IFERROR(OR(Table4[[#This Row],[Status]]="02. Open & Assigned",Table4[[#This Row],[Status]]="01. Open",Table4[[#This Row],[Status]]="03. Action/Mitigation Plan Defined",Table4[[#This Row],[Status]]="04. Action Plan Completed",Table4[[#This Row],[Status]]="08. Blank"),"") -> FALSE | AG5: =IF(Table4[[#This Row],[Required Risk Resolution Date]]="","FALSE",IF($AE$1>Table4[[#This Row],[Required Risk Resolution Date]],TRUE,FALSE)) -> FALSE | AH5: =IF(AE5<30,FALSE,IF(AE5>90,FALSE,TRUE)) -> FALSE | AI5: =IF(AE5<91,FALSE,IF(AE5>180,FALSE,TRUE)) -> FALSE | AJ5: =IF(AE5>180,TRUE,FALSE) -> TRUE | AK5: =OR(Table4[[#This Row],[Priority]]="Critical",Table4[[#This Row],[Priority]]="High") -> FALSE | AL5: =Table4[[#This Row],[Required Risk Resolution Date]]-$AE$1 -> -40990 | AM5: =IF(AL5<1,FALSE,IF(AL5>7,FALSE,TRUE)) -> FALSE | AN5: =OR(Table4[[#This Row],[Priority]]="Critical",Table4[[#This Row],[Priority]]="High",Table4[[#This Row],[Priority]]="Moderate") -> FALSE
A6: R25 | B6: 40674 | C6: unknown | D6: 07. Risk has become an Issue | E6: timeline provided by Msft | F6: Timeline for conversion of 15 applications by Microsoft shows 20+ week schedule which if extrapolated for remainder of the applications would indicate Program would not complete by mid-2013. | G6: wouldn't complete by mid-2013, would still have aplpications running when the licensing expires | H6: App and Data Migration | J6: Neil Sahdev | K6: Neil Sahdev | L6: Moderate | M6: 01. Impact < 4 weeks | N6: 05. Certain | O6: 01. Low | P6: 01. Low | Q6: 04. Critical | R6: 03. High | W6: 10-Jan: Neil confirmed that this is really an issue. Made I91. 12/10 - 'Top Down' Program plan based on current known data; Neil and Martin to rebaseline plan in Q1'12 once data has been enriched through the Rediscovery project | X6: 40933 | Y6: Program Director | Z6: Became issue 10-Jan-2012 | AA6: 40939 | AB6: 10-Jan-2012 (became an issue) | AC6: I91 | AE6: =$AE$1-Table4[[#This Row],[Date Captured]] -> 316 | AF6: =IFERROR(OR(Table4[[#This Row],[Status]]="02. Open & Assigned",Table4[[#This Row],[Status]]="01. Open",Table4[[#This Row],[Status]]="03. Action/Mitigation Plan Defined",Table4[[#This Row],[Status]]="04. Action Plan Completed",Table4[[#This Row],[Status]]="08. Blank"),"") -> FALSE | AG6: =IF(Table4[[#This Row],[Required Risk Resolution Date]]="","FALSE",IF($AE$1>Table4[[#This Row],[Required Risk Resolution Date]],TRUE,FALSE)) -> TRUE | AH6: =IF(AE6<30,FALSE,IF(AE6>90,FALSE,TRUE)) -> FALSE | AI6: =IF(AE6<91,FALSE,IF(AE6>180,FALSE,TRUE)) -> FALSE | AJ6: =IF(AE6>180,TRUE,FALSE) -> TRUE | AK6: =OR(Table4[[#This Row],[Priority]]="Critical",Table4[[#This Row],[Priority]]="High") -> FALSE | AL6: =Table4[[#This Row],[Required Risk Resolution Date]]-$AE$1 -> -51 | AM6: =IF(AL6<1,FALSE,IF(AL6>7,FALSE,TRUE)) -> FALSE | AN6: =OR(Table4[[#This Row],[Priority]]="Critical",Table4[[#This Row],[Priority]]="High",Table4[[#This Row],[Priority]]="Moderate") -> TRUE
A7: R26 | B7: 40674 | C7: unknown | D7: 05. Risk Closed | E7: Lack of business SME availability | F7: Phase 1 plan completion data is dependant on availability of business users and IT service delivery resources to support required activities, i.e. acceptance testing, requirements workshops, etc. | G7: If can't meet the date, will delay completion of Phase 1. | H7: App and Data Migration | J7: Neil Sahdev | K7: Nicola Cooper | L7: Critical | M7: 01. Impact < 4 weeks | N7: 04. Probable | O7: 01. Low | P7: 01. Low | Q7: 03. High | R7: 03. High | S7: If the business and/or IT service delivery resources cannot confirm that they can support required activities, then will occur. | T7: Mitigation | U7: None - Business and IT Service Delivery resources are needed for Phase 1 | V7: Send to the business and IT services resources a list of activities they are expected to support to gain their commitment - in progress | W7: 06-Mar: Risk closed as scope of Phase 1 has been restructured to take into account the availability of the business SMEs 29/Feb :action pending planning meeting shed for Monday 5th March. 22/Feb: inc. in man. pack; still waiting to hear back on Operating Model. 15-Feb: Neil reqd we include in man. pack again. 08-Feb: Neil reqd we include this in the management pack. 07-Feb: The A&DM Operating Model needs to be agreed by the CLT to determine exactly which activities will be performed by the A&DM and IT SD teams 10-Jan: updated with new column data; added a required risk res date (prev blank) of 31-Jan. 02/11 - Candidate applications for Phase 1 being received from the Assurance organisation; currently being reviewed against entry criteria 18/05 - Deferred. Lower priority. 11/05 - No applications identified yet, thus no users. Leave as is until identify the 15 apps (SOW was updated to specify the identification of 15 apps that already have requirements). 22/11 - Phase 1 project team are defining a 'calendar of events' to be sent to the business which will outline the support required over the coming months (incl. UAT) 14/12 - 1st draft 'calendar of events' sent to business reps for first few applications - awaiting confirmation to understand if they can meet the demands | X7: 40968 | Y7: Program Director | AA7: 40947 | AE7: =$AE$1-Table4[[#This Row],[Date Captured]] -> 316 | AF7: =IFERROR(OR(Table4[[#This Row],[Status]]="02. Open & Assigned",Table4[[#This Row],[Status]]="01. Open",Table4[[#This Row],[Status]]="03. Action/Mitigation Plan Defined",Table4[[#This Row],[Status]]="04. Action Plan Completed",Table4[[#This Row],[Status]]="08. Blank"),"") -> FALSE | AG7: =IF(Table4[[#This Row],[Required Risk Resolution Date]]="","FALSE",IF($AE$1>Table4[[#This Row],[Required Risk Resolution Date]],TRUE,FALSE)) -> TRUE | AH7: =IF(AE7<30,FALSE,IF(AE7>90,FALSE,TRUE)) -> FALSE | AI7: =IF(AE7<91,FALSE,IF(AE7>180,FALSE,TRUE)) -> FALSE | AJ7: =IF(AE7>180,TRUE,FALSE) -> TRUE | AK7: =OR(Table4[[#This Row],[Priority]]="Critical",Table4[[#This Row],[Priority]]="High") -> TRUE | AL7: =Table4[[#This Row],[Required Risk Resolution Date]]-$AE$1 -> -43 | AM7: =IF(AL7<1,FALSE,IF(AL7>7,FALSE,TRUE)) -> FALSE | AN7: =OR(Table4[[#This Row],[Priority]]="Critical",Table4[[#This Row],[Priority]]="High",Table4[[#This Row],[Priority]]="Moderate") -> TRUE
A8: R27 | B8: 40674 | C8: unknown | D8: 05. Risk Closed | E8: Msft delivery approach unclear to EY. In addition, SOW has insufficient detail. | F8: Microsoft development effort estimating method unclear, and estimates appear to be nominal. | G8: The timelines within the project plans for Phase 1 may be invalid. | H8: App and Data Migration | J8: Neil Sahdev | K8: Nicola Cooper | L8: Moderate | M8: 01. Impact < 4 weeks | N8: 04. Probable | O8: 02. Medium | P8: 02. Medium | Q8: 02. Medium | R8: 02. Medium | S8: When Msft starts delivering, if they are unable to meet required timelines and quality standards, this will occur. | T8: Mitigation | U8: None - To avoid numerous issues during delivery it is critical that we have a clear and unambiguous SoW between MS and EY | V8: Update the SOW to clarify the points needing clarification | W8: 14-Feb: Decision made to stand-down MSFT development team until key inbound dependancy dates are known (i.e. design of sharepoint components). Risk can be closed. 07-Feb: EY Phase 1 PM has documented all areas that need updating in the SoW (namely testing approach, environment provisioning, timelines, location of resources and roles and responsibililities) 18-Jan: Agreement reached with MS to document areas in the contract that need clarifying which will be discussed later in Jan'12 10-Jan: updated, filling in new columns. Added a req res date of 31-Jan. 30/08 - Engaged with MS to better understand their approach/timelines, etc. 18/05 - Deferred. Lower priority. 11/05 - Will clear this up one MS gets in and can answer our questions. 22/05 - Following a series of calls the MS delivery method for App Transformation and Data Migration is now known and understood. | X8: 40954 | Y8: Program Director | Z8: MSFT team stood down | AA8: 40941 | AB8: 40954 | AE8: =$AE$1-Table4[[#This Row],[Date Captured]] -> 316 | AF8: =IFERROR(OR(Table4[[#This Row],[Status]]="02. Open & Assigned",Table4[[#This Row],[Status]]="01. Open",Table4[[#This Row],[Status]]="03. Action/Mitigation Plan Defined",Table4[[#This Row],[Status]]="04. Action Plan Completed",Table4[[#This Row],[Status]]="08. Blank"),"") -> FALSE | AG8: =IF(Table4[[#This Row],[Required Risk Resolution Date]]="","FALSE",IF($AE$1>Table4[[#This Row],[Required Risk Resolution Date]],TRUE,FALSE)) -> TRUE | AH8: =IF(AE8<30,FALSE,IF(AE8>90,FALSE,TRUE)) -> FALSE | AI8: =IF(AE8<91,FALSE,IF(AE8>180,FALSE,TRUE)) -> FALSE | AJ8: =IF(AE8>180,TRUE,FALSE) -> TRUE | AK8: =OR(Table4[[#This Row],[Priority]]="Critical",Table4[[#This Row],[Priority]]="High") -> FALSE | AL8: =Table4[[#This Row],[Required Risk Resolution Date]]-$AE$1 -> -49 | AM8: =IF(AL8<1,FALSE,IF(AL8>7,FALSE,TRUE)) -> FALSE | AN8: =OR(Table4[[#This Row],[Priority]]="Critical",Table4[[#This Row],[Priority]]="High",Table4[[#This Row],[Priority]]="Moderate") -> TRUE
A9: R50A | B9: 40731 | D9: 05. Risk Closed | F9: Impact of 'Discovery & Assessment' program unknown. If treated as a prerequisite, will impact schedule significantly. | H9: App and Data Migration | J9: Neil Sahdev | N9: 04. Probable | O9: 03. High | W9: 05/10 - Close. 07/09 - Neil: have Discovery and Assessment team identifying apps among Lotus and Lotus Notes. Working to make sure we don't duplicate effort. Neil has long list of actions taking in next couple weeks to mitigate. Follow-up in 2 weeks. | X9: 40821 | Z9: Align approaches between A&DM and D&A Programs. | AB9: 40821 | AE9: =$AE$1-Table4[[#This Row],[Date Captured]] -> 259 | AF9: =IFERROR(OR(Table4[[#This Row],[Status]]="02. Open & Assigned",Table4[[#This Row],[Status]]="01. Open",Table4[[#This Row],[Status]]="03. Action/Mitigation Plan Defined",Table4[[#This Row],[Status]]="04. Action Plan Completed",Table4[[#This Row],[Status]]="08. Blank"),"") -> FALSE | AG9: =IF(Table4[[#This Row],[Required Risk Resolution Date]]="","FALSE",IF($AE$1>Table4[[#This Row],[Required Risk Resolution Date]],TRUE,FALSE)) -> FALSE | AH9: =IF(AE9<30,FALSE,IF(AE9>90,FALSE,TRUE)) -> FALSE | AI9: =IF(AE9<91,FALSE,IF(AE9>180,FALSE,TRUE)) -> FALSE | AJ9: =IF(AE9>180,TRUE,FALSE) -> TRUE | AK9: =OR(Table4[[#This Row],[Priority]]="Critical",Table4[[#This Row],[Priority]]="High") -> FALSE | AL9: =Table4[[#This Row],[Required Risk Resolution Date]]-$AE$1 -> -40990 | AM9: =IF(AL9<1,FALSE,IF(AL9>7,FALSE,TRUE)) -> FALSE | AN9: =OR(Table4[[#This Row],[Priority]]="Critical",Table4[[#This Row],[Priority]]="High",Table4[[#This Row],[Priority]]="Moderate") -> FALSE
A10: R51A | B10: 40731 | D10: 05. Risk Closed | F10: Impact of Data Centre Consolidation Program and associated "Application Remediation" activity is unknown. | H10: App and Data Migration | J10: Neil Sahdev | N10: 04. Probable | O10: 03. High | W10: 05/10 - Close. | X10: 40821 | Z10: Align approaches between A&DM and DCC Programs. | AB10: 40821 | AE10: =$AE$1-Table4[[#This Row],[Date Captured]] -> 259 | AF10: =IFERROR(OR(Table4[[#This Row],[Status]]="02. Open & Assigned",Table4[[#This Row],[Status]]="01. Open",Table4[[#This Row],[Status]]="03. Action/Mitigation Plan Defined",Table4[[#This Row],[Status]]="04. Action Plan Completed",Table4[[#This Row],[Status]]="08. Blank"),"") -> FALSE | AG10: =IF(Table4[[#This Row],[Required Risk Resolution Date]]="","FALSE",IF($AE$1>Table4[[#This Row],[Required Risk Resolution Date]],TRUE,FALSE)) -> FALSE | AH10: =IF(AE10<30,FALSE,IF(AE10>90,FALSE,TRUE)) -> FALSE | AI10: =IF(AE10<91,FALSE,IF(AE10>180,FALSE,TRUE)) -> FALSE | AJ10: =IF(AE10>180,TRUE,FALSE) -> TRUE | AK10: =OR(Table4[[#This Row],[Priority]]="Critical",Table4[[#This Row],[Priority]]="High") -> FALSE | AL10: =Table4[[#This Row],[Required Risk Resolution Date]]-$AE$1 -> -40990 | AM10: =IF(AL10<1,FALSE,IF(AL10>7,FALSE,TRUE)) -> FALSE | AN10: =OR(Table4[[#This Row],[Priority]]="Critical",Table4[[#This Row],[Priority]]="High",Table4[[#This Row],[Priority]]="Moderate") -> FALSE
A11: R52A | B11: 40731 | C11: unknown | D11: 05. Risk Closed | F11: Program is continuing without stakeholder engagement and consequently no agreed charter. | H11: App and Data Migration | J11: Neil Sahdev | L11: Moderate | N11: 03. Possible | O11: 02. Medium | W11: 10-Jan: This is included in R26. Updated wording in R26 to be clearly inclusive and closed this item (Neil and Laura). 02/11 - Program has varying level of engagement from >80% of Service Lines / CBS functions - plans in place to fully engage with remaining areas 05/10 - Monitor this item; push out date one month to November. 22/11 - Engagement with Service Lines / CBS functions continues to mature; team are now working on specific comms to be published to the teams outlining the support required from them over the coming months | X11: 40919 | Z11: Included in R26 (10-Jan) | AB11: 40918 | AC11: R26 | AE11: =$AE$1-Table4[[#This Row],[Date Captured]] -> 259 | AF11: =IFERROR(OR(Table4[[#This Row],[Status]]="02. Open & Assigned",Table4[[#This Row],[Status]]="01. Open",Table4[[#This Row],[Status]]="03. Action/Mitigation Plan Defined",Table4[[#This Row],[Status]]="04. Action Plan Completed",Table4[[#This Row],[Status]]="08. Blank"),"") -> FALSE | AG11: =IF(Table4[[#This Row],[Required Risk Resolution Date]]="","FALSE",IF($AE$1>Table4[[#This Row],[Required Risk Resolution Date]],TRUE,FALSE)) -> FALSE | AH11: =IF(AE11<30,FALSE,IF(AE11>90,FALSE,TRUE)) -> FALSE | AI11: =IF(AE11<91,FALSE,IF(AE11>180,FALSE,TRUE)) -> FALSE | AJ11: =IF(AE11>180,TRUE,FALSE) -> TRUE | AK11: =OR(Table4[[#This Row],[Priority]]="Critical",Table4[[#This Row],[Priority]]="High") -> FALSE | AL11: =Table4[[#This Row],[Required Risk Resolution Date]]-$AE$1 -> -40990 | AM11: =IF(AL11<1,FALSE,IF(AL11>7,FALSE,TRUE)) -> FALSE | AN11: =OR(Table4[[#This Row],[Priority]]="Critical",Table4[[#This Row],[Priority]]="High",Table4[[#This Row],[Priority]]="Moderate") -> TRUE
A12: R53 | B12: 40731 | D12: 05. Risk Closed | F12: Program is being treated as a technical migration program, with no reference back to business process and/or EY's strategic objectives. | H12: App and Data Migration | J12: Neil Sahdev | N12: 04. Probable | O12: 03. High | W12: 05/10 - Neil confirmed this has been resolved. Close. | X12: 40821 | Z12: Build approach to include business interlock, the BCFs and Solution Roadmaps. | AB12: 40821 | AE12: =$AE$1-Table4[[#This Row],[Date Captured]] -> 259 | AF12: =IFERROR(OR(Table4[[#This Row],[Status]]="02. Open & Assigned",Table4[[#This Row],[Status]]="01. Open",Table4[[#This Row],[Status]]="03. Action/Mitigation Plan Defined",Table4[[#This Row],[Status]]="04. Action Plan Completed",Table4[[#This Row],[Status]]="08. Blank"),"") -> FALSE | AG12: =IF(Table4[[#This Row],[Required Risk Resolution Date]]="","FALSE",IF($AE$1>Table4[[#This Row],[Required Risk Resolution Date]],TRUE,FALSE)) -> FALSE | AH12: =IF(AE12<30,FALSE,IF(AE12>90,FALSE,TRUE)) -> FALSE | AI12: =IF(AE12<91,FALSE,IF(AE12>180,FALSE,TRUE)) -> FALSE | AJ12: =IF(AE12>180,TRUE,FALSE) -> TRUE | AK12: =OR(Table4[[#This Row],[Priority]]="Critical",Table4[[#This Row],[Priority]]="High") -> FALSE | AL12: =Table4[[#This Row],[Required Risk Resolution Date]]-$AE$1 -> -40990 | AM12: =IF(AL12<1,FALSE,IF(AL12>7,FALSE,TRUE)) -> FALSE | AN12: =OR(Table4[[#This Row],[Priority]]="Critical",Table4[[#This Row],[Priority]]="High",Table4[[#This Row],[Priority]]="Moderate") -> FALSE
A13: R54 | B13: 40785 | D13: 05. Risk Closed | F13: Most applications do not have existing documentation (technical, business, testing, etc.) so A&DM program will need to factor into future plans. | H13: App and Data Migration | J13: Neil Sahdev | N13: 04. Probable | O13: 02. Medium | W13: 12/10 - Risk closed, documentation is know to be poor or non-existent. Planning assumption. | X13: 40821 | Z13: Make allowances in the detailed plans progressing through Sept '11. | AB13: 40828 | AE13: =$AE$1-Table4[[#This Row],[Date Captured]] -> 205 | AF13: =IFERROR(OR(Table4[[#This Row],[Status]]="02. Open & Assigned",Table4[[#This Row],[Status]]="01. Open",Table4[[#This Row],[Status]]="03. Action/Mitigation Plan Defined",Table4[[#This Row],[Status]]="04. Action Plan Completed",Table4[[#This Row],[Status]]="08. Blank"),"") -> FALSE | AG13: =IF(Table4[[#This Row],[Required Risk Resolution Date]]="","FALSE",IF($AE$1>Table4[[#This Row],[Required Risk Resolution Date]],TRUE,FALSE)) -> FALSE | AH13: =IF(AE13<30,FALSE,IF(AE13>90,FALSE,TRUE)) -> FALSE | AI13: =IF(AE13<91,FALSE,IF(AE13>180,FALSE,TRUE)) -> FALSE | AJ13: =IF(AE13>180,TRUE,FALSE) -> TRUE | AK13: =OR(Table4[[#This Row],[Priority]]="Critical",Table4[[#This Row],[Priority]]="High") -> FALSE | AL13: =Table4[[#This Row],[Required Risk Resolution Date]]-$AE$1 -> -40990 | AM13: =IF(AL13<1,FALSE,IF(AL13>7,FALSE,TRUE)) -> FALSE | AN13: =OR(Table4[[#This Row],[Priority]]="Critical",Table4[[#This Row],[Priority]]="High",Table4[[#This Row],[Priority]]="Moderate") -> FALSE
A14: R55 | B14: 40785 | D14: 05. Risk Closed | F14: Most applications have not undergone a security review so this will need to be factored in future plans (est. 10->20 days / application) | H14: App and Data Migration | J14: Neil Sahdev | N14: 04. Probable | O14: 02. Medium | W14: 12/10 - Risk closed, captured as an activity. | X14: 40821 | Z14: Make allowances in the detailed plans progressing through Sept '11. | AB14: 40828 | AE14: =$AE$1-Table4[[#This Row],[Date Captured]] -> 205 | AF14: =IFERROR(OR(Table4[[#This Row],[Status]]="02. Open & Assigned",Table4[[#This Row],[Status]]="01. Open",Table4[[#This Row],[Status]]="03. Action/Mitigation Plan Defined",Table4[[#This Row],[Status]]="04. Action Plan Completed",Table4[[#This Row],[Status]]="08. Blank"),"") -> FALSE | AG14: =IF(Table4[[#This Row],[Required Risk Resolution Date]]="","FALSE",IF($AE$1>Table4[[#This Row],[Required Risk Resolution Date]],TRUE,FALSE)) -> FALSE | AH14: =IF(AE14<30,FALSE,IF(AE14>90,FALSE,TRUE)) -> FALSE | AI14: =IF(AE14<91,FALSE,IF(AE14>180,FALSE,TRUE)) -> FALSE | AJ14: =IF(AE14>180,TRUE,FALSE) -> TRUE | AK14: =OR(Table4[[#This Row],[Priority]]="Critical",Table4[[#This Row],[Priority]]="High") -> FALSE | AL14: =Table4[[#This Row],[Required Risk Resolution Date]]-$AE$1 -> -40990 | AM14: =IF(AL14<1,FALSE,IF(AL14>7,FALSE,TRUE)) -> FALSE | AN14: =OR(Table4[[#This Row],[Priority]]="Critical",Table4[[#This Row],[Priority]]="High",Table4[[#This Row],[Priority]]="Moderate") -> FALSE
A15: R66 | B15: 40842 | D15: 07. Risk has become an Issue | F15: Lack of space in the Becket House, London office is preventing team from working in a co-located environment. | G15: 40844 | H15: App and Data Migration | J15: TBC | N15: 03. Possible | O15: 02. Medium | T15: Mitigation | V15: Seek necessary approvals to procure space for the team | W15: 22/11/11 - Escalated to an Issue (# I64) | X15: 40842 | AB15: 40869 | AC15: I64 | AE15: =$AE$1-Table4[[#This Row],[Date Captured]] -> 148 | AF15: =IFERROR(OR(Table4[[#This Row],[Status]]="02. Open & Assigned",Table4[[#This Row],[Status]]="01. Open",Table4[[#This Row],[Status]]="03. Action/Mitigation Plan Defined",Table4[[#This Row],[Status]]="04. Action Plan Completed",Table4[[#This Row],[Status]]="08. Blank"),"") -> FALSE | AG15: =IF(Table4[[#This Row],[Required Risk Resolution Date]]="","FALSE",IF($AE$1>Table4[[#This Row],[Required Risk Resolution Date]],TRUE,FALSE)) -> FALSE | AH15: =IF(AE15<30,FALSE,IF(AE15>90,FALSE,TRUE)) -> FALSE | AI15: =IF(AE15<91,FALSE,IF(AE15>180,FALSE,TRUE)) -> TRUE | AJ15: =IF(AE15>180,TRUE,FALSE) -> FALSE | AK15: =OR(Table4[[#This Row],[Priority]]="Critical",Table4[[#This Row],[Priority]]="High") -> FALSE | AL15: =Table4[[#This Row],[Required Risk Resolution Date]]-$AE$1 -> -40990 | AM15: =IF(AL15<1,FALSE,IF(AL15>7,FALSE,TRUE)) -> FALSE | AN15: =OR(Table4[[#This Row],[Priority]]="Critical",Table4[[#This Row],[Priority]]="High",Table4[[#This Row],[Priority]]="Moderate") -> FALSE
A16: R67 | B16: 40842 | C16: unknown | D16: 05. Risk Closed | E16: Significant number of resources required to deliver program. | F16: Approval is required to onboard required resources (as per the resource forecast) to prevent delays to delivery. In addition agreement is needed on the resourcing strategy (i.e. blend of ITS, contractors and CBS / Markets resources) | G16: Delays in gaining approval to onboard project resources will impact project timelines. | H16: App and Data Migration | J16: Neil Sahdev / Martin Stutchbury | K16: Neil Sahdev | L16: Critical | M16: 01. Impact < 4 weeks | N16: 04. Probable | O16: 01. Low | P16: 01. Low | Q16: 04. Critical | R16: 02. Medium | S16: Not getting necessary approvals in time to procure resources. | T16: Mitigation | U16: None - Agreement needs to be reached between the IT SD teams and Cross-Org on where the resources required for the A&DM Program will be sourced from | V16: 1) Ensure all resource requests are in the Resource Request DB and align to project plans - complete 2) Meeting to be scheduled with Margaret Walsh and Christopher Hall to determine percentage of permanent employees to recruit and utilise in the Program - in progress; meetings held, agreement yet to be reached. 3) Agree resourcing strategy / mix with Markets and CBS - in progress (meetings set-up with People and Assurance IT Service Delivery Leaders) 4) Agree Operating Model between x-org and IT SD teams - in progress (proposed A&DM operating model sent to Chris, Margaret and Alan for review / discussion at next CLT meeting scheduled 24/01/12) | W16: 06-Mar: Risk closed as decision (D75B) raised to track agreement to both the A&DM Operating Model and Resourcing Strategy 22-Feb: inc. in man. pack; still waiting to hear on Operating Model. 15-Feb: Neil reqd we include in man. pack again; need decision. 08-Feb: This corresponds with above (R26); need agreement on operating model. Neil would like this raised in mng. pack as well. 07-Feb: Awaiting decision 25-Jan: Awaiting decision from CLT ref preferred resourcing strategy for the Program. Neil sent Mike Laci latest deck (Mike involved on Operating Model team). Neil requested this go to the weekly Management Pack for Guy/Alan. 18-Jan: Portfolio 1 and 2 start dates 1-July; plan has been updated accordingly. Alan working with Mo to determine where the resolution will come from. Review next week. 10-Jan: updated all columns, added risk res date of 31-Jan. | X16: 40968 | Y16: Managing Sponsor | AA16: 40954 | AE16: =$AE$1-Table4[[#This Row],[Date Captured]] -> 148 | AF16: =IFERROR(OR(Table4[[#This Row],[Status]]="02. Open & Assigned",Table4[[#This Row],[Status]]="01. Open",Table4[[#This Row],[Status]]="03. Action/Mitigation Plan Defined",Table4[[#This Row],[Status]]="04. Action Plan Completed",Table4[[#This Row],[Status]]="08. Blank"),"") -> FALSE | AG16: =IF(Table4[[#This Row],[Required Risk Resolution Date]]="","FALSE",IF($AE$1>Table4[[#This Row],[Required Risk Resolution Date]],TRUE,FALSE)) -> TRUE | AH16: =IF(AE16<30,FALSE,IF(AE16>90,FALSE,TRUE)) -> FALSE | AI16: =IF(AE16<91,FALSE,IF(AE16>180,FALSE,TRUE)) -> TRUE | AJ16: =IF(AE16>180,TRUE,FALSE) -> FALSE | AK16: =OR(Table4[[#This Row],[Priority]]="Critical",Table4[[#This Row],[Priority]]="High") -> TRUE | AL16: =Table4[[#This Row],[Required Risk Resolution Date]]-$AE$1 -> -36 | AM16: =IF(AL16<1,FALSE,IF(AL16>7,FALSE,TRUE)) -> FALSE | AN16: =OR(Table4[[#This Row],[Priority]]="Critical",Table4[[#This Row],[Priority]]="High",Table4[[#This Row],[Priority]]="Moderate") -> TRUE
A17: R74 | B17: 40848 | C17: unknown | D17: 05. Risk Closed | F17: To maintain the Program schedule it is important that the Business and IT Service Delivery teams nominate empowered decision makers for each Service Line / CBS function who can readily review / approve Program deliverables and work products. This includes having one decision maker in cases where there are multiple stakeholders (i.e. where an application is owned by one organisation yet consumed by multiple organisations). | H17: App and Data Migration | J17: Neil Sahdev | L17: High | N17: 03. Possible | O17: 03. High | T17: Mitigation | V17: 7/21/11 - Meetings held with Assurance, People, Knowledge, Markets, Comms & Marketing. Scheduled time with Margaret Walsh for 7/12/11 to outline resource requirement and sourcing strategy. Provide the business (Assurance initially for Phase 1) with a clear calendar of events outlining what support is needed (i.e. workshop participation, document reviews, decisions required....) from them over the coming months. | W17: 10-Jan: Closed this risk; this is included in R26. 14/12 - Meetings held with Margaret and Chris to agree A&DM Operating Model - agreement reached for Decomm, Archive and Data Migration; operating model for App Transformation to be finalised 07/12 - Meeting with Margaret today; review next week. 30/11 - Neil and Martin have conversation planned with Assurance for Monday. Thereafter Neil will update this item accordingly. 09/11 - date out end of month. 02/11 - Neil will pick up offline with Michelle for update here. | X17: 40898 | Z17: Included in R26 (10-Jan) | AB17: 40918 | AC17: R26 | AE17: =$AE$1-Table4[[#This Row],[Date Captured]] -> 142 | AF17: =IFERROR(OR(Table4[[#This Row],[Status]]="02. Open & Assigned",Table4[[#This Row],[Status]]="01. Open",Table4[[#This Row],[Status]]="03. Action/Mitigation Plan Defined",Table4[[#This Row],[Status]]="04. Action Plan Completed",Table4[[#This Row],[Status]]="08. Blank"),"") -> FALSE | AG17: =IF(Table4[[#This Row],[Required Risk Resolution Date]]="","FALSE",IF($AE$1>Table4[[#This Row],[Required Risk Resolution Date]],TRUE,FALSE)) -> FALSE | AH17: =IF(AE17<30,FALSE,IF(AE17>90,FALSE,TRUE)) -> FALSE | AI17: =IF(AE17<91,FALSE,IF(AE17>180,FALSE,TRUE)) -> TRUE | AJ17: =IF(AE17>180,TRUE,FALSE) -> FALSE | AK17: =OR(Table4[[#This Row],[Priority]]="Critical",Table4[[#This Row],[Priority]]="High") -> TRUE | AL17: =Table4[[#This Row],[Required Risk Resolution Date]]-$AE$1 -> -40990 | AM17: =IF(AL17<1,FALSE,IF(AL17>7,FALSE,TRUE)) -> FALSE | AN17: =OR(Table4[[#This Row],[Priority]]="Critical",Table4[[#This Row],[Priority]]="High",Table4[[#This Row],[Priority]]="Moderate") -> TRUE
A18: R78A | B18: 40869 | C18: unknown | D18: 05. Risk Closed | E18: Large number of applications needed to be assessed for Phase 1. | F18: To-date the Phase 1 BA team have had to analyse nearly 40 applications to identify 5 which can be progressed. Based on this the team would need to analyse another 80 applications to identify the remaining 10 applications required for Phase 1. | G18: Analysing such large quantities of applications was never planned for and as a result the Phase 1 project plan has been updated to reflect this for the remaining applications that need to be identified. If this ratio of 8 canditates : 1 identied application increases then the project plans will need to be further updated. | H18: App and Data Migration | J18: Neil Sahdev | K18: Nicola Cooper | L18: Moderate | M18: 01. Impact < 4 weeks | N18: 03. Possible | O18: 02. Medium | P18: 01. Low | Q18: 02. Medium | R18: 02. Medium | S18: If Phase 1 BA team is unable to identify and baseline 15 required applications for Phase 1, will occur. | T18: Mitigation | U18: None - Need to ensure sufficient analysis time is allowed for in the plans | V18: 1, Update Phase 1 project plans to take analysis effort into account - complete 2. Monitor the effort expended vs. Planned for the remaining 10 applications - in progress (team are heavily dependant on knowing exactly what the Sharepoint Program will deliver and when) | W18: 07/03 - Risk closed as replanning being managed as a BAU activity 29/02 - Replanning underway following decision to offboard 2 Phase 1 BA resources 22/02 - Since two members of the Phase 1 BA team are being offboarded due to budget reasons the delivery dates are being impacted. It is therefore likely that candidate applications will be descoped from Phase 1 as they can no longer be delivered within the timelines requested by the business. 14/02 - Same status as 07/02/12 07/02 - Phase 1 BA team are heavily dependant on knowing exactly what the Sharepoint Program will deliver and when to baseline the 15 applications 23/11 - Push out 1 month for next review. | X18: 40975 | Y18: Program Director | AA18: 40954 | AE18: =$AE$1-Table4[[#This Row],[Date Captured]] -> 121 | AF18: =IFERROR(OR(Table4[[#This Row],[Status]]="02. Open & Assigned",Table4[[#This Row],[Status]]="01. Open",Table4[[#This Row],[Status]]="03. Action/Mitigation Plan Defined",Table4[[#This Row],[Status]]="04. Action Plan Completed",Table4[[#This Row],[Status]]="08. Blank"),"") -> FALSE | AG18: =IF(Table4[[#This Row],[Required Risk Resolution Date]]="","FALSE",IF($AE$1>Table4[[#This Row],[Required Risk Resolution Date]],TRUE,FALSE)) -> TRUE | AH18: =IF(AE18<30,FALSE,IF(AE18>90,FALSE,TRUE)) -> FALSE | AI18: =IF(AE18<91,FALSE,IF(AE18>180,FALSE,TRUE)) -> TRUE | AJ18: =IF(AE18>180,TRUE,FALSE) -> FALSE | AK18: =OR(Table4[[#This Row],[Priority]]="Critical",Table4[[#This Row],[Priority]]="High") -> FALSE | AL18: =Table4[[#This Row],[Required Risk Resolution Date]]-$AE$1 -> -36 | AM18: =IF(AL18<1,FALSE,IF(AL18>7,FALSE,TRUE)) -> FALSE | AN18: =OR(Table4[[#This Row],[Priority]]="Critical",Table4[[#This Row],[Priority]]="High",Table4[[#This Row],[Priority]]="Moderate") -> TRUE
A19: R87 | B19: 40918 | C19: Neil Sahdev | D19: 07. Risk has become an Issue | E19: Currently discovery team largely staffed with IT advisory resources for a finite period of time. | F19: As the Rediscovery project is now expected to complete June 2012, there is a need to extend the resources of the team. If the resources can't be extended, we will lose them. | G19: We will have to identify and onboard new resources, therefore affecting the timelines. | H19: App and Data Migration | J19: Neil Sahdev | K19: Akos Rabi | L19: High | M19: 01. Impact < 4 weeks | N19: 05. Certain | O19: 01. Low | P19: 01. Low | Q19: 03. High | R19: 03. High | S19: Team can't be extended. | T19: Mitigation | V19: Extend resources | W19: 25-Jan: 3 x ITA resources expected to leave end-Jan'12/early-Feb'12. 2 x resources (1 PM and 1 data analyst) required to backfill however no suitable candidates identified so far. 18-Jan: Approval received from Alan to extend team; Martin now engaging with ITA to agree revised end-dates for each of the resources (which is dependant on start date of their next engagement) 11-Jan: Neil is meeting with Lindsey tomorrow on this topic; should have more information for next week's call. 10-Jan - opened by Neil. | X19: 40933 | Y19: Program Director | Z19: This is no longer a risk, but an issue. 25-Jan made issue #I104. | AA19: 40939 | AB19: 40933 | AC19: I104 | AE19: =$AE$1-Table4[[#This Row],[Date Captured]] -> 72 | AF19: =IFERROR(OR(Table4[[#This Row],[Status]]="02. Open & Assigned",Table4[[#This Row],[Status]]="01. Open",Table4[[#This Row],[Status]]="03. Action/Mitigation Plan Defined",Table4[[#This Row],[Status]]="04. Action Plan Completed",Table4[[#This Row],[Status]]="08. Blank"),"") -> FALSE | AG19: =IF(Table4[[#This Row],[Required Risk Resolution Date]]="","FALSE",IF($AE$1>Table4[[#This Row],[Required Risk Resolution Date]],TRUE,FALSE)) -> TRUE | AH19: =IF(AE19<30,FALSE,IF(AE19>90,FALSE,TRUE)) -> TRUE | AI19: =IF(AE19<91,FALSE,IF(AE19>180,FALSE,TRUE)) -> FALSE | AJ19: =IF(AE19>180,TRUE,FALSE) -> FALSE | AK19: =OR(Table4[[#This Row],[Priority]]="Critical",Table4[[#This Row],[Priority]]="High") -> TRUE | AL19: =Table4[[#This Row],[Required Risk Resolution Date]]-$AE$1 -> -51 | AM19: =IF(AL19<1,FALSE,IF(AL19>7,FALSE,TRUE)) -> FALSE | AN19: =OR(Table4[[#This Row],[Priority]]="Critical",Table4[[#This Row],[Priority]]="High",Table4[[#This Row],[Priority]]="Moderate") -> TRUE
A20: R88 | B20: 40918 | C20: Neil Sahdev | D20: 02. Open & Assigned | E20: The Rediscovery project team need access to Lotus applications to perform analysis | F20: The Rediscovery team does not have the required level of access and therefore can't perform analysis. | G20: Team cannot complete analysis. | H20: App and Data Migration | J20: Neil Sahdev | K20: Christian Driver | L20: Moderate | M20: 01. Impact < 4 weeks | N20: 05. Certain | O20: 01. Low | P20: 01. Low | Q20: 03. High | R20: 01. Low | S20: Team can't get necessary access | T20: Mitigation | U20: None - Team require access to perform analysis | V20: Gain necessary approval from Q&RM and security and operations to grant team required access | W20: 06-Mar: Recently onboarded Rediscovery PM now working with Operations and Q&RM to agree accesses required to these applications 22-Feb: Confirmation received from Q&RM ref gaining access to applications without sensitive data or not in the 'red box' countries; process to be defined for accessing these types of applications 15-Feb: Steve - Susan was documenting her statement around what will be in and out of scope for access. Neil will update further. 18-Jan: This was due to be addressed at the Q&RM Steering Group scheduled 26th Jan'12 however it has now been cancelled. Steve provided update that he spoke with Susan yesterday and this is being moved forward outside of the Steering Group. Should gain clarity by the end of the week. 11-Jan: Operations agreed which data they need in order to get the access. Review in two weeks (for probable ability to close). 10-Jan - opened by Neil. 30 Jan - QRM meeting to make decision cancelled, chasing up outside of normal channels but no decision made yet. | X20: 40991 | Y20: Program Director | AA20: 40998 | AE20: =$AE$1-Table4[[#This Row],[Date Captured]] -> 72 | AF20: =IFERROR(OR(Table4[[#This Row],[Status]]="02. Open & Assigned",Table4[[#This Row],[Status]]="01. Open",Table4[[#This Row],[Status]]="03. Action/Mitigation Plan Defined",Table4[[#This Row],[Status]]="04. Action Plan Completed",Table4[[#This Row],[Status]]="08. Blank"),"") -> TRUE | AG20: =IF(Table4[[#This Row],[Required Risk Resolution Date]]="","FALSE",IF($AE$1>Table4[[#This Row],[Required Risk Resolution Date]],TRUE,FALSE)) -> FALSE | AH20: =IF(AE20<30,FALSE,IF(AE20>90,FALSE,TRUE)) -> TRUE | AI20: =IF(AE20<91,FALSE,IF(AE20>180,FALSE,TRUE)) -> FALSE | AJ20: =IF(AE20>180,TRUE,FALSE) -> FALSE | AK20: =OR(Table4[[#This Row],[Priority]]="Critical",Table4[[#This Row],[Priority]]="High") -> FALSE | AL20: =Table4[[#This Row],[Required Risk Resolution Date]]-$AE$1 -> 8 | AM20: =IF(AL20<1,FALSE,IF(AL20>7,FALSE,TRUE)) -> FALSE | AN20: =OR(Table4[[#This Row],[Priority]]="Critical",Table4[[#This Row],[Priority]]="High",Table4[[#This Row],[Priority]]="Moderate") -> TRUE
A21: R99 | B21: 40940 | C21: Neil Sahdev | D21: 05. Risk Closed | E21: Testing environments may not be available on time | F21: Turn around time for environment provisioning is currently 90 days. To intiate the process requires significant detailed design about the application so that the appropriate environment can be provisioned. This information is not available until the SDD/SAD and TDD have been completed. The development timeframe is short for MSFT, so the codeset will be provided back to us with no environment to put it into. | G21: Testing cannot start of the MSFT deliverables | H21: App and Data Migration | J21: Martin Stutchbury | K21: Nicola Cooper | L21: Moderate | M21: 01. Impact < 4 weeks | N21: 04. Probable | O21: 01. Low | P21: 01. Low | Q21: 03. High | R21: 02. Medium | S21: Unclear process for initial environment provisioning | T21: Mitigation | U21: None - Without environements the delivery schedule will be impacted | V21: Escalate within the Soln architects for Phase 1, and prioritise effort to complete (as best as known) environment requirements | W21: 06/03 - Risk closed as replanning is being managed as a BAU activity 29/02 - Replanning underway since understanding many inbound depenencies will not be delivered many months later than planned 22/02: The dates which the environments are needed by may change depending on the current Phase 1 replan 07-Feb: Phase 1 solution and infrastructure architect teams are working with TF to better understand what information they need to provision environments | X21: 40975 | Y21: Program Director | AA21: 40956 | AE21: =$AE$1-Table4[[#This Row],[Date Captured]] -> 50 | AF21: =IFERROR(OR(Table4[[#This Row],[Status]]="02. Open & Assigned",Table4[[#This Row],[Status]]="01. Open",Table4[[#This Row],[Status]]="03. Action/Mitigation Plan Defined",Table4[[#This Row],[Status]]="04. Action Plan Completed",Table4[[#This Row],[Status]]="08. Blank"),"") -> FALSE | AG21: =IF(Table4[[#This Row],[Required Risk Resolution Date]]="","FALSE",IF($AE$1>Table4[[#This Row],[Required Risk Resolution Date]],TRUE,FALSE)) -> TRUE | AH21: =IF(AE21<30,FALSE,IF(AE21>90,FALSE,TRUE)) -> TRUE | AI21: =IF(AE21<91,FALSE,IF(AE21>180,FALSE,TRUE)) -> FALSE | AJ21: =IF(AE21>180,TRUE,FALSE) -> FALSE | AK21: =OR(Table4[[#This Row],[Priority]]="Critical",Table4[[#This Row],[Priority]]="High") -> FALSE | AL21: =Table4[[#This Row],[Required Risk Resolution Date]]-$AE$1 -> -34 | AM21: =IF(AL21<1,FALSE,IF(AL21>7,FALSE,TRUE)) -> FALSE | AN21: =OR(Table4[[#This Row],[Priority]]="Critical",Table4[[#This Row],[Priority]]="High",Table4[[#This Row],[Priority]]="Moderate") -> TRUE
A22: R58 | B22: 40743 | D22: 05. Risk Closed | F22: The engagement of all key stakeholders across the business will prevent progress being made but there is an expectation that this must be done. | H22: Change Management | J22: Sophie Boiron | N22: 04. Probable | O22: 03. High | T22: Mitigation | V22: Identify key stakeholders with managing Sponsors Agree plan of engagement through Managing Sponsors Suugest we close that issue now Claire is on board and developing a plan moving forward | W22: 04-Jan: Jackie reqd we review this next week. 19/10 - Jackie had added this, but it is to be removed since it is being managed from a project RAID level. | X22: 40919 | AB22: 40835 | AE22: =$AE$1-Table4[[#This Row],[Date Captured]] -> 247 | AF22: =IFERROR(OR(Table4[[#This Row],[Status]]="02. Open & Assigned",Table4[[#This Row],[Status]]="01. Open",Table4[[#This Row],[Status]]="03. Action/Mitigation Plan Defined",Table4[[#This Row],[Status]]="04. Action Plan Completed",Table4[[#This Row],[Status]]="08. Blank"),"") -> FALSE | AG22: =IF(Table4[[#This Row],[Required Risk Resolution Date]]="","FALSE",IF($AE$1>Table4[[#This Row],[Required Risk Resolution Date]],TRUE,FALSE)) -> FALSE | AH22: =IF(AE22<30,FALSE,IF(AE22>90,FALSE,TRUE)) -> FALSE | AI22: =IF(AE22<91,FALSE,IF(AE22>180,FALSE,TRUE)) -> FALSE | AJ22: =IF(AE22>180,TRUE,FALSE) -> TRUE | AK22: =OR(Table4[[#This Row],[Priority]]="Critical",Table4[[#This Row],[Priority]]="High") -> FALSE | AL22: =Table4[[#This Row],[Required Risk Resolution Date]]-$AE$1 -> -40990 | AM22: =IF(AL22<1,FALSE,IF(AL22>7,FALSE,TRUE)) -> FALSE | AN22: =OR(Table4[[#This Row],[Priority]]="Critical",Table4[[#This Row],[Priority]]="High",Table4[[#This Row],[Priority]]="Moderate") -> FALSE
A23: R59 | B23: 40786 | C23: unknown | D23: 05. Risk Closed | E23: Insufficient engagement with senior executives on M&C | F23: There will be insufficient leadership focus from senior executives to drive this major transformation in EY | G23: Realization benefits will be slower than required. | H23: Change Management | J23: Bob Reiner | K23: Bob Reiner | L23: Moderate | M23: 01. Impact < 4 weeks | N23: 03. Possible | O23: 01. Low | P23: 03. High | Q23: 03. High | R23: 02. Medium | S23: not a specific event, see Cause | T23: Avoidance | U23: Roll-out as a technology replacement | V23: Identify the role of the leadership team and the expectations of them - discuss and engage with them. Formalise the briefing mechanism through key sytakeholder engagement Develop a story for Lync and Outlook with a story to engage with the business Engagement by Bob Reiner with John Murphy - also confirmed as Exec Sponsor | W23: 07-Feb: Closed due to mitigating actions including comms manager taking responsibility for SAS deck. 10-Jan: Comms manager is taking over responsibility for developing the final version of the SAS deck. First draft due this week. 19/12 - Final version of SAS deck has gone out to Alan and Bob. Engagement has begun with Amerca's CFO, Asia Pac operations committee and ITS relations managers. Means of engaging with EMEIA still to be identified. Engagement with service lines will make use of the blue print. 9/11 SAS initial draft of M&C story will be presented at FSG for feedback. Jeremy establishing what else needs to be done to develop the story - by service line etc. Jackie Knight is working with Jeremy to establish a plan for engagement with Senior Area leadership. 3/11 - Discussion with leadership is dependent upon the SAS storry and agreement on the messages going forward. Awaiting SAS material. 19/10 - Reduce priority to Moderate. | X23: 40940 | Y23: Executive Sponsor | Z23: 75% towards resolution | AA23: 40908 | AE23: =$AE$1-Table4[[#This Row],[Date Captured]] -> 204 | AF23: =IFERROR(OR(Table4[[#This Row],[Status]]="02. Open & Assigned",Table4[[#This Row],[Status]]="01. Open",Table4[[#This Row],[Status]]="03. Action/Mitigation Plan Defined",Table4[[#This Row],[Status]]="04. Action Plan Completed",Table4[[#This Row],[Status]]="08. Blank"),"") -> FALSE | AG23: =IF(Table4[[#This Row],[Required Risk Resolution Date]]="","FALSE",IF($AE$1>Table4[[#This Row],[Required Risk Resolution Date]],TRUE,FALSE)) -> TRUE | AH23: =IF(AE23<30,FALSE,IF(AE23>90,FALSE,TRUE)) -> FALSE | AI23: =IF(AE23<91,FALSE,IF(AE23>180,FALSE,TRUE)) -> FALSE | AJ23: =IF(AE23>180,TRUE,FALSE) -> TRUE | AK23: =OR(Table4[[#This Row],[Priority]]="Critical",Table4[[#This Row],[Priority]]="High") -> FALSE | AL23: =Table4[[#This Row],[Required Risk Resolution Date]]-$AE$1 -> -82 | AM23: =IF(AL23<1,FALSE,IF(AL23>7,FALSE,TRUE)) -> FALSE | AN23: =OR(Table4[[#This Row],[Priority]]="Critical",Table4[[#This Row],[Priority]]="High",Table4[[#This Row],[Priority]]="Moderate") -> TRUE
A24: R60 | B24: 40743 | D24: 05. Risk Closed | F24: There will be insufficient Business Change Management resource (at central team and 'local' level ie Change network) for a change of this magnitude in EY to meet current expectations of key stakeholder | H24: Change Management | J24: Sophie Boiron | N24: 04. Probable | O24: 03. High | T24: Mitigation | V24: Identify the Change approach and socialise 25/10 Resource plan agreed. Now required to resource to that plan Identify costs and resource requirements including Change network Identify potential sources of resource or where responsibilities will lie - working with Transition Identify where budget will come from work with relationship managers (areas) to evaluate change support and engage on next steps | W24: 02/11 - have confirmation that this can be closed (per Jackie). 24/10 Immediate Resource plan agreed now seeking to resource 19/10 - Opened in Program RAID. Set review date out two weeks. | X24: 40849 | AB24: 40849 | AE24: =$AE$1-Table4[[#This Row],[Date Captured]] -> 247 | AF24: =IFERROR(OR(Table4[[#This Row],[Status]]="02. Open & Assigned",Table4[[#This Row],[Status]]="01. Open",Table4[[#This Row],[Status]]="03. Action/Mitigation Plan Defined",Table4[[#This Row],[Status]]="04. Action Plan Completed",Table4[[#This Row],[Status]]="08. Blank"),"") -> FALSE | AG24: =IF(Table4[[#This Row],[Required Risk Resolution Date]]="","FALSE",IF($AE$1>Table4[[#This Row],[Required Risk Resolution Date]],TRUE,FALSE)) -> FALSE | AH24: =IF(AE24<30,FALSE,IF(AE24>90,FALSE,TRUE)) -> FALSE | AI24: =IF(AE24<91,FALSE,IF(AE24>180,FALSE,TRUE)) -> FALSE | AJ24: =IF(AE24>180,TRUE,FALSE) -> TRUE | AK24: =OR(Table4[[#This Row],[Priority]]="Critical",Table4[[#This Row],[Priority]]="High") -> FALSE | AL24: =Table4[[#This Row],[Required Risk Resolution Date]]-$AE$1 -> -40990 | AM24: =IF(AL24<1,FALSE,IF(AL24>7,FALSE,TRUE)) -> FALSE | AN24: =OR(Table4[[#This Row],[Priority]]="Critical",Table4[[#This Row],[Priority]]="High",Table4[[#This Row],[Priority]]="Moderate") -> FALSE
A25: R61 | B25: 40743 | D25: 05. Risk Closed | F25: We will replace tools without making a step change in collaboration and realising one of the envisaged benefits of M&C | H25: Change Management | J25: Jeremy Brown / Sophie Boiron | N25: 04. Probable | O25: 03. High | T25: Mitigation | U25: Roll out as technology replacemnet and do not reap the full benefits. | V25: Confirm a step change is required Development of the story on what we want to achieve - and benefits behind. To establish the degree og step change required. Assess of behavioural change required Ensure Training and Communications strategy and plans reflect step change requirement. Business Impact assessment must address step change Review behavioural changes that need to occur to address step change. | W25: 29/11 - Now have clarity that we will be making a step change 08/11 - Will be confirmed with validation of the SAS story for M&C. Will be able to descibe the step change and behavioural change. 01/11 - benefits case will identify if step changed required. Story to John Murphy and senior team will help identify what step change they are looking for (if any) 19/10 - Opened in Program RAID. Review next week when Jeremy is present on call. | X25: 40854 | AB25: 40854 | AE25: =$AE$1-Table4[[#This Row],[Date Captured]] -> 247 | AF25: =IFERROR(OR(Table4[[#This Row],[Status]]="02. Open & Assigned",Table4[[#This Row],[Status]]="01. Open",Table4[[#This Row],[Status]]="03. Action/Mitigation Plan Defined",Table4[[#This Row],[Status]]="04. Action Plan Completed",Table4[[#This Row],[Status]]="08. Blank"),"") -> FALSE | AG25: =IF(Table4[[#This Row],[Required Risk Resolution Date]]="","FALSE",IF($AE$1>Table4[[#This Row],[Required Risk Resolution Date]],TRUE,FALSE)) -> FALSE | AH25: =IF(AE25<30,FALSE,IF(AE25>90,FALSE,TRUE)) -> FALSE | AI25: =IF(AE25<91,FALSE,IF(AE25>180,FALSE,TRUE)) -> FALSE | AJ25: =IF(AE25>180,TRUE,FALSE) -> TRUE | AK25: =OR(Table4[[#This Row],[Priority]]="Critical",Table4[[#This Row],[Priority]]="High") -> FALSE | AL25: =Table4[[#This Row],[Required Risk Resolution Date]]-$AE$1 -> -40990 | AM25: =IF(AL25<1,FALSE,IF(AL25>7,FALSE,TRUE)) -> FALSE | AN25: =OR(Table4[[#This Row],[Priority]]="Critical",Table4[[#This Row],[Priority]]="High",Table4[[#This Row],[Priority]]="Moderate") -> FALSE
A26: R62 | B26: 40786 | D26: 05. Risk Closed | F26: There is misalignment across the program, both at senior level and lower down, of the potential benefits and key messages for M&C causing confusion amongst the business/users, mixed managed expectation causing reputational issues, delaying communications. | H26: Change Management | J26: Jeremy Brown | N26: 04. Probable | O26: 03. High | T26: Mitigation | V26: Agreement of high level key messages of managing Sponsor group and Exec. M&C story being developed to clarifyvision and objectives of the program Clear communicated business case - the case for change | W26: 02/11 - Working to get SAS story corrent and to John Murphy for approval. Benefits person; sits with Jeremy. Review beginning December. 24/10 SAS brought on to develop a story for M&C. This will be used to engage with senior executives | X26: 40884 | Z26: Combined with R61 | AB26: 40850 | AE26: =$AE$1-Table4[[#This Row],[Date Captured]] -> 204 | AF26: =IFERROR(OR(Table4[[#This Row],[Status]]="02. Open & Assigned",Table4[[#This Row],[Status]]="01. Open",Table4[[#This Row],[Status]]="03. Action/Mitigation Plan Defined",Table4[[#This Row],[Status]]="04. Action Plan Completed",Table4[[#This Row],[Status]]="08. Blank"),"") -> FALSE | AG26: =IF(Table4[[#This Row],[Required Risk Resolution Date]]="","FALSE",IF($AE$1>Table4[[#This Row],[Required Risk Resolution Date]],TRUE,FALSE)) -> FALSE | AH26: =IF(AE26<30,FALSE,IF(AE26>90,FALSE,TRUE)) -> FALSE | AI26: =IF(AE26<91,FALSE,IF(AE26>180,FALSE,TRUE)) -> FALSE | AJ26: =IF(AE26>180,TRUE,FALSE) -> TRUE | AK26: =OR(Table4[[#This Row],[Priority]]="Critical",Table4[[#This Row],[Priority]]="High") -> FALSE | AL26: =Table4[[#This Row],[Required Risk Resolution Date]]-$AE$1 -> -40990 | AM26: =IF(AL26<1,FALSE,IF(AL26>7,FALSE,TRUE)) -> FALSE | AN26: =OR(Table4[[#This Row],[Priority]]="Critical",Table4[[#This Row],[Priority]]="High",Table4[[#This Row],[Priority]]="Moderate") -> FALSE
A27: R63A | B27: 40743 | D27: 05. Risk Closed | F27: We will offer training to non-EY employees which will compromise the legal position with respect to our contract with them | H27: Change Management | J27: Catherine Graham | N27: 03. Possible | O27: 02. Medium | T27: Acceptance | V27: Global Legal Counsel (Gillian Haselden) has confirmed that non-EY employees may be trained to support EY's transition to M&C | AB27: 40749 | AE27: =$AE$1-Table4[[#This Row],[Date Captured]] -> 247 | AF27: =IFERROR(OR(Table4[[#This Row],[Status]]="02. Open & Assigned",Table4[[#This Row],[Status]]="01. Open",Table4[[#This Row],[Status]]="03. Action/Mitigation Plan Defined",Table4[[#This Row],[Status]]="04. Action Plan Completed",Table4[[#This Row],[Status]]="08. Blank"),"") -> FALSE | AG27: =IF(Table4[[#This Row],[Required Risk Resolution Date]]="","FALSE",IF($AE$1>Table4[[#This Row],[Required Risk Resolution Date]],TRUE,FALSE)) -> FALSE | AH27: =IF(AE27<30,FALSE,IF(AE27>90,FALSE,TRUE)) -> FALSE | AI27: =IF(AE27<91,FALSE,IF(AE27>180,FALSE,TRUE)) -> FALSE | AJ27: =IF(AE27>180,TRUE,FALSE) -> TRUE | AK27: =OR(Table4[[#This Row],[Priority]]="Critical",Table4[[#This Row],[Priority]]="High") -> FALSE | AL27: =Table4[[#This Row],[Required Risk Resolution Date]]-$AE$1 -> -40990 | AM27: =IF(AL27<1,FALSE,IF(AL27>7,FALSE,TRUE)) -> FALSE | AN27: =OR(Table4[[#This Row],[Priority]]="Critical",Table4[[#This Row],[Priority]]="High",Table4[[#This Row],[Priority]]="Moderate") -> FALSE
A28: R63B | B28: 40827 | D28: 07. Risk has become an Issue | F28: The Lync & Outlook Change network will not be in place soon enough to accommodate the roll-out schedule. | H28: Change Management | J28: Jackie Knight | N28: 04. Probable | O28: 03. High | T28: Mitigation | V28: Raise with Business sponsors the necessity for Area representation Work with Lync & Outlook PM re. Seeking alternative area reps | W28: 3/11 - Closed as now an issue 02/11 - Jackie will update; this is same as some others. | X28: 40856 | Z28: Not resolved. Now an issue | AB28: 40850 | AC28: Issue I49 | AE28: =$AE$1-Table4[[#This Row],[Date Captured]] -> 163 | AF28: =IFERROR(OR(Table4[[#This Row],[Status]]="02. Open & Assigned",Table4[[#This Row],[Status]]="01. Open",Table4[[#This Row],[Status]]="03. Action/Mitigation Plan Defined",Table4[[#This Row],[Status]]="04. Action Plan Completed",Table4[[#This Row],[Status]]="08. Blank"),"") -> FALSE | AG28: =IF(Table4[[#This Row],[Required Risk Resolution Date]]="","FALSE",IF($AE$1>Table4[[#This Row],[Required Risk Resolution Date]],TRUE,FALSE)) -> FALSE | AH28: =IF(AE28<30,FALSE,IF(AE28>90,FALSE,TRUE)) -> FALSE | AI28: =IF(AE28<91,FALSE,IF(AE28>180,FALSE,TRUE)) -> TRUE | AJ28: =IF(AE28>180,TRUE,FALSE) -> FALSE | AK28: =OR(Table4[[#This Row],[Priority]]="Critical",Table4[[#This Row],[Priority]]="High") -> FALSE | AL28: =Table4[[#This Row],[Required Risk Resolution Date]]-$AE$1 -> -40990 | AM28: =IF(AL28<1,FALSE,IF(AL28>7,FALSE,TRUE)) -> FALSE | AN28: =OR(Table4[[#This Row],[Priority]]="Critical",Table4[[#This Row],[Priority]]="High",Table4[[#This Row],[Priority]]="Moderate") -> FALSE
A29: R64A | B29: 40743 | D29: 05. Risk Closed | F29: The changing staffing model may lead to wide variances with respect to Training requirements and we sign a contract that is too big for our needs | H29: Change Management | J29: Scott Greengold | N29: 04. Probable | O29: 02. Medium | T29: Mitigation | V29: RFP designed to reflect changing scale | AE29: =$AE$1-Table4[[#This Row],[Date Captured]] -> 247 | AF29: =IFERROR(OR(Table4[[#This Row],[Status]]="02. Open & Assigned",Table4[[#This Row],[Status]]="01. Open",Table4[[#This Row],[Status]]="03. Action/Mitigation Plan Defined",Table4[[#This Row],[Status]]="04. Action Plan Completed",Table4[[#This Row],[Status]]="08. Blank"),"") -> FALSE | AG29: =IF(Table4[[#This Row],[Required Risk Resolution Date]]="","FALSE",IF($AE$1>Table4[[#This Row],[Required Risk Resolution Date]],TRUE,FALSE)) -> FALSE | AH29: =IF(AE29<30,FALSE,IF(AE29>90,FALSE,TRUE)) -> FALSE | AI29: =IF(AE29<91,FALSE,IF(AE29>180,FALSE,TRUE)) -> FALSE | AJ29: =IF(AE29>180,TRUE,FALSE) -> TRUE | AK29: =OR(Table4[[#This Row],[Priority]]="Critical",Table4[[#This Row],[Priority]]="High") -> FALSE | AL29: =Table4[[#This Row],[Required Risk Resolution Date]]-$AE$1 -> -40990 | AM29: =IF(AL29<1,FALSE,IF(AL29>7,FALSE,TRUE)) -> FALSE | AN29: =OR(Table4[[#This Row],[Priority]]="Critical",Table4[[#This Row],[Priority]]="High",Table4[[#This Row],[Priority]]="Moderate") -> FALSE
A30: R64B | B30: 40743 | C30: Sophie Boiron | D30: 03. Action/Mitigation Plan Defined | E30: History of EY portfolio management and business and IT engagement | F30: The individual programs will forge ahead without consideration in the wider sense of the end user community's capacity for change. | G30: Users unable to take on board change in the time scales anticipated | H30: Change Management | J30: Sophie Boiron / Alan Guthrie | K30: Sophie Boiron / Alan Guthrie | L30: Moderate | M30: 03. Impact > 3 Months | N30: 04. Probable | O30: 02. Medium | P30: 02. Medium | Q30: 03. High | R30: 02. Medium | S30: Could be major implementation/change in another area of the business at the same time as that in M&C. | T30: Undecided | U30: NA | V30: Understand of change picture and revise change plan accordingly Use Change networks to asessess change volumes in their area and highlight where too much change is occuring and respond as and when | W30: 13/03/12: RB: Interim approach to communicate to business owners via ITSDLs under discussion with M Walsh. This will only address communication with application owners via IT, however, and not overall end-user impact of multiple changes being deployed. This still needs to be worked through by Business Change once re-baselined plan is delivered at the end of March. Date moved out to mid-April 8/3: Downgraded as a business/IT model is now in place for the program. To be updated based on outcome of I139 29/Feb :action pending planning meeting shed for Monday 5th March. 22-Feb: Sophie has a meeting today on how the programs will work together; Alan to work out how IT and the business with coordinate at cross-program level. Review in 1 month. 15-Feb: Sophie talking to business to build a picture. Sophie will follow-up. 19-Dec: The change deployment team will engage with the business and build a picture of current and future change at area level. 07-Dec: changed from Sophie to Ian since global PMO is looking at this. Review next week. 24/11 Business Deployment manager will be in place in Q1 2012 (calendar) and working closely with change management (sophie) on overall approach for business deployment (overall M&C deployment) There is a plan to build a enterprise view of the change across EY. Work to start in Dec. 09/11 There will be a workshop to identify programme of change for End Users as a whole. Will take place before end of December. Sophie organising. 03/11 Blaine Pardoe and John Pritchett are raising this issue from a capacity of IT to deliver the volume of Chnage itself. 02/11 - Sophie will provide update next week. 26/10 - This is around capacity of end user change. Looking at workshop for end user perspective. Previously the aim has been to coordinate M&C Change plan and integrate and work closely with Enterprise plan however there is no Change Management happening on the other programs to coordinate with. | X30: 40991 | Y30: Executive Sponsor | AA30: 41012 | AE30: =$AE$1-Table4[[#This Row],[Date Captured]] -> 247 | AF30: =IFERROR(OR(Table4[[#This Row],[Status]]="02. Open & Assigned",Table4[[#This Row],[Status]]="01. Open",Table4[[#This Row],[Status]]="03. Action/Mitigation Plan Defined",Table4[[#This Row],[Status]]="04. Action Plan Completed",Table4[[#This Row],[Status]]="08. Blank"),"") -> TRUE | AG30: =IF(Table4[[#This Row],[Required Risk Resolution Date]]="","FALSE",IF($AE$1>Table4[[#This Row],[Required Risk Resolution Date]],TRUE,FALSE)) -> FALSE | AH30: =IF(AE30<30,FALSE,IF(AE30>90,FALSE,TRUE)) -> FALSE | AI30: =IF(AE30<91,FALSE,IF(AE30>180,FALSE,TRUE)) -> FALSE | AJ30: =IF(AE30>180,TRUE,FALSE) -> TRUE | AK30: =OR(Table4[[#This Row],[Priority]]="Critical",Table4[[#This Row],[Priority]]="High") -> FALSE | AL30: =Table4[[#This Row],[Required Risk Resolution Date]]-$AE$1 -> 22 | AM30: =IF(AL30<1,FALSE,IF(AL30>7,FALSE,TRUE)) -> FALSE | AN30: =OR(Table4[[#This Row],[Priority]]="Critical",Table4[[#This Row],[Priority]]="High",Table4[[#This Row],[Priority]]="Moderate") -> TRUE
A31: R65A | B31: 40743 | D31: 05. Risk Closed | F31: All the other IT changes happening outside M&C will impact end users & IT and Knowledge professionals as well and may limit their capacity to take on the changes M&C wish to deliver. New IT Service Management tool (ServiceNow) planned implementation for December 2011. | H31: Change Management | J31: Alan G / Sophie Boiron | N31: 04. Probable | O31: 03. High | T31: Mitigation | V31: Work through EPO to establish timing and impact of M&C changes against overall Change plans. Service Delivery Leaders to understand change in their area of the organisation and reflect back to the M&C program. | W31: 19/10 - Opened in Program RAID, but this is being managed at Project Level. Close here. | X31: 40835 | AB31: 40835 | AE31: =$AE$1-Table4[[#This Row],[Date Captured]] -> 247 | AF31: =IFERROR(OR(Table4[[#This Row],[Status]]="02. Open & Assigned",Table4[[#This Row],[Status]]="01. Open",Table4[[#This Row],[Status]]="03. Action/Mitigation Plan Defined",Table4[[#This Row],[Status]]="04. Action Plan Completed",Table4[[#This Row],[Status]]="08. Blank"),"") -> FALSE | AG31: =IF(Table4[[#This Row],[Required Risk Resolution Date]]="","FALSE",IF($AE$1>Table4[[#This Row],[Required Risk Resolution Date]],TRUE,FALSE)) -> FALSE | AH31: =IF(AE31<30,FALSE,IF(AE31>90,FALSE,TRUE)) -> FALSE | AI31: =IF(AE31<91,FALSE,IF(AE31>180,FALSE,TRUE)) -> FALSE | AJ31: =IF(AE31>180,TRUE,FALSE) -> TRUE | AK31: =OR(Table4[[#This Row],[Priority]]="Critical",Table4[[#This Row],[Priority]]="High") -> FALSE | AL31: =Table4[[#This Row],[Required Risk Resolution Date]]-$AE$1 -> -40990 | AM31: =IF(AL31<1,FALSE,IF(AL31>7,FALSE,TRUE)) -> FALSE | AN31: =OR(Table4[[#This Row],[Priority]]="Critical",Table4[[#This Row],[Priority]]="High",Table4[[#This Row],[Priority]]="Moderate") -> FALSE
A32: R68 | B32: 40758 | D32: 05. Risk Closed | F32: The risk is that the current Silverlight distribution time frame will not result in Silverlight being installed on all IT Services machines in time for use on Outlook, Exchange, Lync and SharePoint e-Learning. | H32: Change Management | J32: Scott Greengold | N32: 03. Possible | O32: 02. Medium | V32: the Training requirement will be 1. For IT training - potentially this can be managed by the IT person going through Service desk to install Silverlight(?) if it gets highlighted in Training material that they need to do this? (your call if appropriate) SCOTT G response: I agree that adding text stating Silverlight may need to be installed is acceptable. Silverlight will ask a user to download and install itself automatically through Microsoft if the need is encountered (i.e. a WBL requiring Silverlight is launched and Silverlight is not present). No one will require Helpdesk / Service Desk assistance to install Silverlight - it's a standard plug-in type of install. However, a machine accepting the install from Microsoft will result in a non-Firm standard version of Silverlight being present on that machine. That is where the risk potential exists. 2.Training development and test - can this be done by requested download or automated? SCOTT G response:We are probably fine to use the automated download as needed on a case-by-case basis if necessary. 3.For End User. That would be for training for any pilot and then for roll-out. SCOTT G response:It seems Lync is scheduled to be the first rollout of all the M&C topics. As long as Silverlight is deployed to the user population targeted by each Lync deployment two to four weeks prior to each rollout date we should be fine. (i.e. Silverlight should go out 2-Jan-2012 to meet the Lync pilot time frame (Feb 2012) learning need. Silverlight should be distributed mid-February to everyone on the Full Rollout list scheduled for March 2012 etc..) Daren Wilks provided dates for Silverlight 'silent roll-out' which will be in time for bluk of learning. Individuals in IT can download silverlight as required before silent roll-out. | AE32: =$AE$1-Table4[[#This Row],[Date Captured]] -> 232 | AF32: =IFERROR(OR(Table4[[#This Row],[Status]]="02. Open & Assigned",Table4[[#This Row],[Status]]="01. Open",Table4[[#This Row],[Status]]="03. Action/Mitigation Plan Defined",Table4[[#This Row],[Status]]="04. Action Plan Completed",Table4[[#This Row],[Status]]="08. Blank"),"") -> FALSE | AG32: =IF(Table4[[#This Row],[Required Risk Resolution Date]]="","FALSE",IF($AE$1>Table4[[#This Row],[Required Risk Resolution Date]],TRUE,FALSE)) -> FALSE | AH32: =IF(AE32<30,FALSE,IF(AE32>90,FALSE,TRUE)) -> FALSE | AI32: =IF(AE32<91,FALSE,IF(AE32>180,FALSE,TRUE)) -> FALSE | AJ32: =IF(AE32>180,TRUE,FALSE) -> TRUE | AK32: =OR(Table4[[#This Row],[Priority]]="Critical",Table4[[#This Row],[Priority]]="High") -> FALSE | AL32: =Table4[[#This Row],[Required Risk Resolution Date]]-$AE$1 -> -40990 | AM32: =IF(AL32<1,FALSE,IF(AL32>7,FALSE,TRUE)) -> FALSE | AN32: =OR(Table4[[#This Row],[Priority]]="Critical",Table4[[#This Row],[Priority]]="High",Table4[[#This Row],[Priority]]="Moderate") -> FALSE
A33: R75 | B33: 40855 | C33: unknown | D33: 05. Risk Closed | E33: The technical team not able to identify all the plug-ins for Outlook and Lync. | F33: Learning resource is not realistic as we do not know the numbers of 'plug-ins' for Outlook/Lync and the current resource is based on predominant use of Microsoft learning material and limited EY specific learning material. | G33: We cannot size accurately the effort required for learning content development , together with the timescales for delivery. Any late changes to the Learning resource model could significantly affect overall roll-out schedule or quality of Learning material/delivery. | H33: Change Management | J33: Jackie Knight | K33: Brigitte Ireland | L33: Moderate | M33: 01. Impact < 4 weeks | N33: 03. Possible | O33: 01. Low | P33: 03. High | Q33: 01. Low | R33: 02. Medium | S33: not specific event, see cause | T33: Mitigation | U33: Additional Learning content developers | V33: Ensure full business representation on requirements from all areas before end of December | W33: 11-Jan: Investigations have identified as many areas as possible and we are working with the technical team on any bchanges that may occur due to office 365 where additional plug ins are going to be unlikely. Therefore the focus continues to be on the implications to Lotus Notes applications of moveing to Lync and Outlpook. The intention is to share this information with the countries as we engage with them to ensure preparation. We will be fully engaged with the business when we speak directly with sub-areas to identify any particular needs but in the mean time we will engage directly wth the key areas. e.g knowledge, HR, comms and Finance. 24/11 - benefits realisation candidate identified. Progress being made with SAS story to finalise benefits 9/11 - Requires SAS M&C story agreed to engage with Area reps to identify requirements lead. | X33: 40919 | Y33: Program Director | Z33: 50% towards resolution | AA33: 40939 | AB33: 40919 | AE33: =$AE$1-Table4[[#This Row],[Date Captured]] -> 135 | AF33: =IFERROR(OR(Table4[[#This Row],[Status]]="02. Open & Assigned",Table4[[#This Row],[Status]]="01. Open",Table4[[#This Row],[Status]]="03. Action/Mitigation Plan Defined",Table4[[#This Row],[Status]]="04. Action Plan Completed",Table4[[#This Row],[Status]]="08. Blank"),"") -> FALSE | AG33: =IF(Table4[[#This Row],[Required Risk Resolution Date]]="","FALSE",IF($AE$1>Table4[[#This Row],[Required Risk Resolution Date]],TRUE,FALSE)) -> TRUE | AH33: =IF(AE33<30,FALSE,IF(AE33>90,FALSE,TRUE)) -> FALSE | AI33: =IF(AE33<91,FALSE,IF(AE33>180,FALSE,TRUE)) -> TRUE | AJ33: =IF(AE33>180,TRUE,FALSE) -> FALSE | AK33: =OR(Table4[[#This Row],[Priority]]="Critical",Table4[[#This Row],[Priority]]="High") -> FALSE | AL33: =Table4[[#This Row],[Required Risk Resolution Date]]-$AE$1 -> -51 | AM33: =IF(AL33<1,FALSE,IF(AL33>7,FALSE,TRUE)) -> FALSE | AN33: =OR(Table4[[#This Row],[Priority]]="Critical",Table4[[#This Row],[Priority]]="High",Table4[[#This Row],[Priority]]="Moderate") -> TRUE
A34: R103 | B34: 40960 | C34: IAM (Sirisha) | D34: 02. Open & Assigned | E34: There is currently NO Environment Manager managing the Coordination of Activities within EYDEV, EYQA, EYUA. | F34: Testing environments inc the coordination activities are yet to be agreed/defined. This may impact our ability to get from EYDEV to EYQA | G34: Multiple streams could be attempting to Test during the same time. | H34: IAM | I34: TF - Messaging | J34: Ted Balfour | K34: Adrian Mickleson | L34: High | M34: 01. Impact < 4 weeks | N34: 03. Possible | O34: 01. Low | P34: 01. Low | Q34: 02. Medium | R34: 02. Medium | S34: Feedback from M&C that additional changes are required. | T34: Mitigation | U34: none | V34: Although we will work with both M&C and the Vendor, there are no known mitigations plans for what we currently to not know. Therefore we need to accept the risk. | W34: 15-Mar: on daily stand up, suggested due date of end of month, moved date out one week to match that. 14-Mar: M&C are working with QA to provide an environment Manager. Start Date is currently unknown. 13-Mar: Environments conversation scheduled for today. 28-Feb: Daren will reach out to M&C for updates. Call is set up for 29-Feb. 22-Feb: Awaiting feedback from M&C (Al/Adrian). 21-Feb: Opened per Sirsha; Reqd and awaiting further detail. 08-March: Environments manager to start by April 1 | X34: 40982 | Y34: Program Manager | Z34: M&C to provide an Environment Manager | AA34: 40998 | AE34: =$AE$1-Table4[[#This Row],[Date Captured]] -> 30 | AF34: =IFERROR(OR(Table4[[#This Row],[Status]]="02. Open & Assigned",Table4[[#This Row],[Status]]="01. Open",Table4[[#This Row],[Status]]="03. Action/Mitigation Plan Defined",Table4[[#This Row],[Status]]="04. Action Plan Completed",Table4[[#This Row],[Status]]="08. Blank"),"") -> TRUE | AG34: =IF(Table4[[#This Row],[Required Risk Resolution Date]]="","FALSE",IF($AE$1>Table4[[#This Row],[Required Risk Resolution Date]],TRUE,FALSE)) -> FALSE | AH34: =IF(AE34<30,FALSE,IF(AE34>90,FALSE,TRUE)) -> TRUE | AI34: =IF(AE34<91,FALSE,IF(AE34>180,FALSE,TRUE)) -> FALSE | AJ34: =IF(AE34>180,TRUE,FALSE) -> FALSE | AK34: =OR(Table4[[#This Row],[Priority]]="Critical",Table4[[#This Row],[Priority]]="High") -> TRUE | AL34: =Table4[[#This Row],[Required Risk Resolution Date]]-$AE$1 -> 8 | AM34: =IF(AL34<1,FALSE,IF(AL34>7,FALSE,TRUE)) -> FALSE | AN34: =OR(Table4[[#This Row],[Priority]]="Critical",Table4[[#This Row],[Priority]]="High",Table4[[#This Row],[Priority]]="Moderate") -> TRUE
A35: R104 | B35: 40960 | C35: IAM (Sirisha) | D35: 05. Risk Closed | E35: No Off Prem Test Environment, this ID Sync cannot test (currently) the Off Prem Solution prior to going live. | F35: ID Sync – Off Prem Lync and New Exchange Mail accounts cannot be tested in the EY environments, and thus the risk is we need M&C to provide a strategy to test this capability prior to going live (with the Off Prem capability). | G35: May not be able to Mail Enable New Exchange Accounts of New Lync Accounts | H35: IAM | I35: TF - Messaging | J35: Ted Balfour | K35: Adrian Mickleson | L35: Critical | M35: 02. Impact > 4 Weeks < 3 Months | N35: 03. Possible | O35: 04. Critical | P35: 04. Critical | Q35: 03. High | R35: 03. High | S35: Confirm ation that this solution cannot be Tested Off Prem, prior to Production rollout. | T35: Undecided | U35: None | V35: Raise risk with M&C M&C to provide Off Prem Testing capabilities | W35: 15-Mar: On daily call confirmed can be closed. Howard sent the resolution statement. Closed. 14-Mar: M&C are exploring potential opportunities to provide either Hosted Off Prem Test environments, or links into EYs existing environments. Awaiting update from M&C. Msft has action from M&C daily call to update with anticipated approval date for CR addressing this. 28-Feb: Daren will reach out to M&C for updates; call set for 29-Feb. 22-Feb: Awaiting feedback from M&C (Al/Adrian). 21-Feb: Opened per Sirsha; Reqd and awaiting further detail. | X35: 40982 | Y35: Program Manager | Z35: 15-Mar Howard: We are closing out the risk by creating a new Change Request for the Exchange Planning workstream to provide a “cloud simulation” environment for EY’s testing purposes prior to O365 “Service Ready”. The CR will be delivered next week. Expecting delivery to EY on Thursday. | AA35: 41001 | AB35: 40983 | AE35: =$AE$1-Table4[[#This Row],[Date Captured]] -> 30 | AF35: =IFERROR(OR(Table4[[#This Row],[Status]]="02. Open & Assigned",Table4[[#This Row],[Status]]="01. Open",Table4[[#This Row],[Status]]="03. Action/Mitigation Plan Defined",Table4[[#This Row],[Status]]="04. Action Plan Completed",Table4[[#This Row],[Status]]="08. Blank"),"") -> FALSE | AG35: =IF(Table4[[#This Row],[Required Risk Resolution Date]]="","FALSE",IF($AE$1>Table4[[#This Row],[Required Risk Resolution Date]],TRUE,FALSE)) -> FALSE | AH35: =IF(AE35<30,FALSE,IF(AE35>90,FALSE,TRUE)) -> TRUE | AI35: =IF(AE35<91,FALSE,IF(AE35>180,FALSE,TRUE)) -> FALSE | AJ35: =IF(AE35>180,TRUE,FALSE) -> FALSE | AK35: =OR(Table4[[#This Row],[Priority]]="Critical",Table4[[#This Row],[Priority]]="High") -> TRUE | AL35: =Table4[[#This Row],[Required Risk Resolution Date]]-$AE$1 -> 11 | AM35: =IF(AL35<1,FALSE,IF(AL35>7,FALSE,TRUE)) -> FALSE | AN35: =OR(Table4[[#This Row],[Priority]]="Critical",Table4[[#This Row],[Priority]]="High",Table4[[#This Row],[Priority]]="Moderate") -> TRUE
A36: R98 | B36: 40960 | C36: IAM (Sirisha) | D36: 05. Risk Closed | E36: The M&C requirement to go O365 means the solution for ID Sync has to change | F36: Allows for scope creep until these docs are agreed, which in turn delays the project. | G36: Needs additional requirements to be defined. Additional functionality is needed Both of the above requires an update to both the Vision & Scope and Functional Specs, which also require re-sign-off delaying the project, and impacts the costs both internally and externally. Also delays the project | H36: IAM | I36: TF - Messaging | J36: Ted Balfour | K36: Al Grljevic | L36: Moderate | M36: 01. Impact < 4 weeks | N36: 01. Slight | O36: 02. Medium | P36: 00. Undecided | Q36: 03. High | R36: 03. High | S36: new req for O365 | T36: Mitigation | U36: none | V36: Updated vision and scope req to facilitate new req. | W36: 14-Mar: The item that I had due for today, R98, can be closed as we are obtaining sign-off and will raise a CR when the O365 changes are needed. This will now be managed through CR process; Ted confirmed can be closed in log. 14 Mar: Scope Lock discussions are due on the 26th-28 March in order to lock down the O365 scope. However, ID Sync is already building the Use and Test Cases for the known baseline requirements, inc O365 requirements from the previous workshop. Any change to this, could potentially delay the testing (and all that this entails) for ID Sync. 7-Mar: per Bharat, Daren has received 95% of his sign-off on the functional spec. Downgraded to moderate. 28-Feb: updates will be provided next week 21-Feb: Opened per Sirsha; Reqd and awaiting further detail. | X36: 40982 | Y36: IAM Program Manager | Z36: Obtaining sign-off and will raise a CR when O365 changes are needed. Will be managed from here through CR process. | AA36: 40982 | AB36: 40982 | AE36: =$AE$1-Table4[[#This Row],[Date Captured]] -> 30 | AF36: =IFERROR(OR(Table4[[#This Row],[Status]]="02. Open & Assigned",Table4[[#This Row],[Status]]="01. Open",Table4[[#This Row],[Status]]="03. Action/Mitigation Plan Defined",Table4[[#This Row],[Status]]="04. Action Plan Completed",Table4[[#This Row],[Status]]="08. Blank"),"") -> FALSE | AG36: =IF(Table4[[#This Row],[Required Risk Resolution Date]]="","FALSE",IF($AE$1>Table4[[#This Row],[Required Risk Resolution Date]],TRUE,FALSE)) -> TRUE | AH36: =IF(AE36<30,FALSE,IF(AE36>90,FALSE,TRUE)) -> TRUE | AI36: =IF(AE36<91,FALSE,IF(AE36>180,FALSE,TRUE)) -> FALSE | AJ36: =IF(AE36>180,TRUE,FALSE) -> FALSE | AK36: =OR(Table4[[#This Row],[Priority]]="Critical",Table4[[#This Row],[Priority]]="High") -> FALSE | AL36: =Table4[[#This Row],[Required Risk Resolution Date]]-$AE$1 -> -8 | AM36: =IF(AL36<1,FALSE,IF(AL36>7,FALSE,TRUE)) -> FALSE | AN36: =OR(Table4[[#This Row],[Priority]]="Critical",Table4[[#This Row],[Priority]]="High",Table4[[#This Row],[Priority]]="Moderate") -> TRUE
A37: R1 | B37: 40589 | C37: unknown | D37: 07. Risk has become an Issue | E37: Due to the recent activities around the Msft cloud decision, we require additional team members (BAs, PMs, engineering, etc.) to face off against the various streams. | F37: Availability of necessary resources within EY across all projects - long lead times in securing the required resources, PMs, BA's and other resources for the various projects | G37: Impact of delivery of Lync and Outlook | H37: M&C Program | J37: Al Grljevic | K37: Al Grljevic | L37: Moderate | N37: 04. Probable | O37: 03. High | P37: 03. High | Q37: 03. High | R37: 02. Medium | T37: Mitigation | U37: Investigate 3rd party systems integrators (IBM) for resourcing needs | V37: Work with resource planning team to Secure resources externally | W37: 11-Jan: Al confirmed that this is an issue. Opened as I95. 5/12 - Location strategy is delaying work completed to date on resources 12/10 - Guy sending an updated resource request to Mo this week. 06/07 - Michelle will follow up with Al. 15/06 - Have made significant progress. Alex Hall would like to talk with Al / Brian on Fusion resourcing. 01/06 - Critical path: need BA's by 6/20 which is the start of req sessions. Need status from Al concerning IBM. 25/05 - Still working; a step closer to securing change manager. Should be joining in next 2 wks. 18/05 - Still working to secure resources, in progress. 11/05 - Lining up PMs and BAs. Defined end of June as deadline. Concern expressed over lumping all resources into one risk as other teams still lacking resources (e.g., Infrastructure Engineering). 27/04 - Much progress has been made, looking to validate staffing have/need. Have 7 outstanding lead developers and architect team. Need by beginning of July, so still ok time-wise. Continuing to work on securing resources. | X37: 40835 | Z37: Complete all interviews and make job offers to selected PM's BA and program support. 11-Jan: became I95 | AB37: 11-Jan-2012 (became an issue) | AC37: I95 | AE37: =$AE$1-Table4[[#This Row],[Date Captured]] -> 401 | AF37: =IFERROR(OR(Table4[[#This Row],[Status]]="02. Open & Assigned",Table4[[#This Row],[Status]]="01. Open",Table4[[#This Row],[Status]]="03. Action/Mitigation Plan Defined",Table4[[#This Row],[Status]]="04. Action Plan Completed",Table4[[#This Row],[Status]]="08. Blank"),"") -> FALSE | AG37: =IF(Table4[[#This Row],[Required Risk Resolution Date]]="","FALSE",IF($AE$1>Table4[[#This Row],[Required Risk Resolution Date]],TRUE,FALSE)) -> FALSE | AH37: =IF(AE37<30,FALSE,IF(AE37>90,FALSE,TRUE)) -> FALSE | AI37: =IF(AE37<91,FALSE,IF(AE37>180,FALSE,TRUE)) -> FALSE | AJ37: =IF(AE37>180,TRUE,FALSE) -> TRUE | AK37: =OR(Table4[[#This Row],[Priority]]="Critical",Table4[[#This Row],[Priority]]="High") -> FALSE | AL37: =Table4[[#This Row],[Required Risk Resolution Date]]-$AE$1 -> -40990 | AM37: =IF(AL37<1,FALSE,IF(AL37>7,FALSE,TRUE)) -> FALSE | AN37: =OR(Table4[[#This Row],[Priority]]="Critical",Table4[[#This Row],[Priority]]="High",Table4[[#This Row],[Priority]]="Moderate") -> TRUE
A38: R86 | B38: 40911 | C38: Bob Cooney | D38: 02. Open & Assigned | E38: M&C still planning; until this is completed, M&C can't provide what IAM needs in order to provide information in return. | F38: If M&C requirements for (IAM) active directory activities (schema extensions (have 15-Feb), domain controller hardware requirements (have 15-Feb) and locations testing) are not delivered to the IAM program with appropriate lead time for evaluation, planning and deployment the M&C program will be delayed. | G38: Program schedule will be impacted | H38: IAM | I38: TF - Messaging | J38: Ted Balfour | K38: Ted Balfour | L38: Critical | M38: 02. Impact > 4 Weeks < 3 Months | N38: 03. Possible | O38: 02. Medium | P38: 01. Low | Q38: 03. High | R38: 02. Medium | S38: If IAM does not get the needed information from M&C, will trigger. | T38: Undecided | W38: 16-Mar: We will have an environment ready for the start of April, what we still don't have is a set off acceptance criteria for IAM so can only hope the 2 pm's understood each other on whats needed. 15-Feb: About 75% there; have schema info, domain controller hardware reqs. The locations are the missing pc.; will come after O365 decisions are made. Review next week. 8-Feb: Ted needs info from M&C; he will follow-up with Ant. Paul Neave is the M&C contact; review next week. 25-Jan: Changed owner to Ted (from Bob). 18-Jan: Ken - no further detail; the team is working to ensure they have full understanding today or tomorrow. Review next week. 11-Jan: Ken - this is further complicated by the O365 decision. Additional planning to come in the next couple weeks. For on-premise, the open item is they are waiting for a CR (Bob or Dean) to say going from SP1 to SP2. (Teams are continuing under assumption of on-prem) 06-Jan: Bob scheduled a call with TF for Monday; from this meeting will determine risk response, mitigation/contingency plan and required risk resolution date. Still review Wednesday. 04-Jan: Bob has been working with Steve Jelf on this; the decision for the schema will be needed within a few weeks. Al will follow-up with Paul and Adrian, review next week. 03/01 - Bob sent the appropriate wording for the risk, opened from A19. | X38: 41003 | Y38: Program Manager | AA38: 41003 | AC38: input: A19 | AE38: =$AE$1-Table4[[#This Row],[Date Captured]] -> 79 | AF38: =IFERROR(OR(Table4[[#This Row],[Status]]="02. Open & Assigned",Table4[[#This Row],[Status]]="01. Open",Table4[[#This Row],[Status]]="03. Action/Mitigation Plan Defined",Table4[[#This Row],[Status]]="04. Action Plan Completed",Table4[[#This Row],[Status]]="08. Blank"),"") -> TRUE | AG38: =IF(Table4[[#This Row],[Required Risk Resolution Date]]="","FALSE",IF($AE$1>Table4[[#This Row],[Required Risk Resolution Date]],TRUE,FALSE)) -> FALSE | AH38: =IF(AE38<30,FALSE,IF(AE38>90,FALSE,TRUE)) -> TRUE | AI38: =IF(AE38<91,FALSE,IF(AE38>180,FALSE,TRUE)) -> FALSE | AJ38: =IF(AE38>180,TRUE,FALSE) -> FALSE | AK38: =OR(Table4[[#This Row],[Priority]]="Critical",Table4[[#This Row],[Priority]]="High") -> TRUE | AL38: =Table4[[#This Row],[Required Risk Resolution Date]]-$AE$1 -> 13 | AM38: =IF(AL38<1,FALSE,IF(AL38>7,FALSE,TRUE)) -> FALSE | AN38: =OR(Table4[[#This Row],[Priority]]="Critical",Table4[[#This Row],[Priority]]="High",Table4[[#This Row],[Priority]]="Moderate") -> TRUE
A39: R107 | B39: 40955 | C39: Nick Coburn | D39: 05. Risk Closed | E39: Complex deployment | F39: The complex deployment process for all aspects of the program may impact the design and adoption of the TOM. We will need to maintain Notes support not only for LN DBs but also for mail given the nature of the deployment and the cutover approach. | H39: M&C Program | K39: Nick Coburn | L39: High | M39: 02. Impact > 4 Weeks < 3 Months | N39: 03. Possible | O39: 02. Medium | P39: 03. High | Q39: 02. Medium | R39: 00. Undecided | S39: Unknown | T39: Mitigation | U39: Unknown | W39: 7-Mar: Nick emailed that this item can be closed as it has been superceded by R108. 24/02: ACTION - Nick to re-word the risk | X39: 40975 | Z39: superceded by R108; track there (per Nick Coburn) | AB39: 40975 | AC39: R108 | AE39: =$AE$1-Table4[[#This Row],[Date Captured]] -> 35 | AF39: =IFERROR(OR(Table4[[#This Row],[Status]]="02. Open & Assigned",Table4[[#This Row],[Status]]="01. Open",Table4[[#This Row],[Status]]="03. Action/Mitigation Plan Defined",Table4[[#This Row],[Status]]="04. Action Plan Completed",Table4[[#This Row],[Status]]="08. Blank"),"") -> FALSE | AG39: =IF(Table4[[#This Row],[Required Risk Resolution Date]]="","FALSE",IF($AE$1>Table4[[#This Row],[Required Risk Resolution Date]],TRUE,FALSE)) -> FALSE | AH39: =IF(AE39<30,FALSE,IF(AE39>90,FALSE,TRUE)) -> TRUE | AI39: =IF(AE39<91,FALSE,IF(AE39>180,FALSE,TRUE)) -> FALSE | AJ39: =IF(AE39>180,TRUE,FALSE) -> FALSE | AK39: =OR(Table4[[#This Row],[Priority]]="Critical",Table4[[#This Row],[Priority]]="High") -> TRUE | AL39: =Table4[[#This Row],[Required Risk Resolution Date]]-$AE$1 -> -40990 | AM39: =IF(AL39<1,FALSE,IF(AL39>7,FALSE,TRUE)) -> FALSE | AN39: =OR(Table4[[#This Row],[Priority]]="Critical",Table4[[#This Row],[Priority]]="High",Table4[[#This Row],[Priority]]="Moderate") -> TRUE
A40: R124 | B40: 40982 | C40: Daren Wicks | D40: 02. Open & Assigned | E40: Lync and Exchange will not be available to the FIM project until the 2nd April in EYDEV for the testing the Enablement of New Lync Accounts, and enablement of New Exchange mail boxes | F40: Need Lync/Exchange fully built and available to the IAM ID Sync Project to start the E2E testing. | G40: Delaying the ID Sync Project | H40: IAM | I40: TF - Messaging | J40: Ted Balfour | K40: Paul Neave/James Harrup-Brooke | L40: High | M40: 01. Impact < 4 weeks | N40: 05. Certain | O40: 01. Low | P40: 01. Low | Q40: 02. Medium | R40: 02. Medium | S40: M&C not providing Lync/Exchange by the 2nd April | T40: Mitigation | U40: IAM to review what additional testing may be available whilst waiting on M&C | V40: M&C to ensure these capabilities are built and available by the 2nd April | W40: 14 Mar : Confirmation received as of the 13th March, from James HB that both capabilities are on track to be delivered into EYDEV by the 2nd April. Added to M&C log. 28-Feb: Daren will reach out to M&C for updates; call set for 29-Feb. 22-Feb: Await | X40: 40982 | Y40: Program Manager | Z40: M&C (Tech F) to provide completed infrastructure inc Application "Readiness Testing", not just to OS layer, so ID Sync can Test the Enablement of New Lync and Mail Enable New Exchange Accounts | AA40: 41001 | AE40: =$AE$1-Table4[[#This Row],[Date Captured]] -> 8 | AF40: =IFERROR(OR(Table4[[#This Row],[Status]]="02. Open & Assigned",Table4[[#This Row],[Status]]="01. Open",Table4[[#This Row],[Status]]="03. Action/Mitigation Plan Defined",Table4[[#This Row],[Status]]="04. Action Plan Completed",Table4[[#This Row],[Status]]="08. Blank"),"") -> TRUE | AG40: =IF(Table4[[#This Row],[Required Risk Resolution Date]]="","FALSE",IF($AE$1>Table4[[#This Row],[Required Risk Resolution Date]],TRUE,FALSE)) -> FALSE | AH40: =IF(AE40<30,FALSE,IF(AE40>90,FALSE,TRUE)) -> FALSE | AI40: =IF(AE40<91,FALSE,IF(AE40>180,FALSE,TRUE)) -> FALSE | AJ40: =IF(AE40>180,TRUE,FALSE) -> FALSE | AK40: =OR(Table4[[#This Row],[Priority]]="Critical",Table4[[#This Row],[Priority]]="High") -> TRUE | AL40: =Table4[[#This Row],[Required Risk Resolution Date]]-$AE$1 -> 11 | AM40: =IF(AL40<1,FALSE,IF(AL40>7,FALSE,TRUE)) -> FALSE | AN40: =OR(Table4[[#This Row],[Priority]]="Critical",Table4[[#This Row],[Priority]]="High",Table4[[#This Row],[Priority]]="Moderate") -> TRUE
A41: R125 | B41: 40982 | C41: Daren Wicks | D41: 02. Open & Assigned | E41: The Lync Strategy may very well be chaning to: Off Prem or On and off Prem | F41: This will impact the design that has currently been put in place, and the Vision and Scope, and Functional Spec, inc Use Cases and Test Cases that will have been agreed/built and potentially tested by the time this decision, and known impacts are agreed | G41: Delaying the ID Sync Project creating a re-design for both the On Prem/Off Prem solution. Will require a further CR from Microsoft, as this will require additional coding Will require amendments to: Vision & Scope Functional Spec Operational Guide Config Doc Traceability Matrix Use Cases Test Cases Business Impact Re-asessment, which may may affect our DR solution Require re-testing of ALL Lync Test Cases | H41: IAM | I41: TF - Messaging | J41: Ted Balfour | K41: James Harrup-Brooke | L41: Critical | M41: 01. Impact < 4 weeks | N41: 04. Probable | O41: 03. High | P41: 01. Low | Q41: 03. High | R41: 03. High | S41: M&C concluding the Lync solution will be either completely Off Prem, or partially On Prem, Partially Off Prem. | T41: Acceptance | U41: None | V41: M&C to conclude as quickly as possible the Lync Strategy, and accept that the solution may not meet the current M&C timescales | W41: 14 Mar : M&C to formally confirm proposed Lync Strategy; added to M&C log. | X41: 40982 | Y41: Program Manager | Z41: M&C to confirm | AA41: 40998 | AE41: =$AE$1-Table4[[#This Row],[Date Captured]] -> 8 | AF41: =IFERROR(OR(Table4[[#This Row],[Status]]="02. Open & Assigned",Table4[[#This Row],[Status]]="01. Open",Table4[[#This Row],[Status]]="03. Action/Mitigation Plan Defined",Table4[[#This Row],[Status]]="04. Action Plan Completed",Table4[[#This Row],[Status]]="08. Blank"),"") -> TRUE | AG41: =IF(Table4[[#This Row],[Required Risk Resolution Date]]="","FALSE",IF($AE$1>Table4[[#This Row],[Required Risk Resolution Date]],TRUE,FALSE)) -> FALSE | AH41: =IF(AE41<30,FALSE,IF(AE41>90,FALSE,TRUE)) -> FALSE | AI41: =IF(AE41<91,FALSE,IF(AE41>180,FALSE,TRUE)) -> FALSE | AJ41: =IF(AE41>180,TRUE,FALSE) -> FALSE | AK41: =OR(Table4[[#This Row],[Priority]]="Critical",Table4[[#This Row],[Priority]]="High") -> TRUE | AL41: =Table4[[#This Row],[Required Risk Resolution Date]]-$AE$1 -> 8 | AM41: =IF(AL41<1,FALSE,IF(AL41>7,FALSE,TRUE)) -> FALSE | AN41: =OR(Table4[[#This Row],[Priority]]="Critical",Table4[[#This Row],[Priority]]="High",Table4[[#This Row],[Priority]]="Moderate") -> TRUE
A42: R11 | B42: 40655 | D42: 05. Risk Closed | F42: Need to make sure that the focus continues to be about the future and not just today. Risk is that the team could re-create some of the issues that exist today. | H42: M&C Program | J42: Al Grljevic | K42: Al Grljevic | N42: 04. Probable | O42: 03. High | T42: Mitigation | U42: NA | V42: Make sure the team documents requirements (What we need not how we do it) Challenge what is needed to verify that it is not a patch put in place to deal with an existing deficiency | W42: 27/04 - Not a risk. Close. | Z42: Add to workplan. | AB42: 40660 | AE42: =$AE$1-Table4[[#This Row],[Date Captured]] -> 335 | AF42: =IFERROR(OR(Table4[[#This Row],[Status]]="02. Open & Assigned",Table4[[#This Row],[Status]]="01. Open",Table4[[#This Row],[Status]]="03. Action/Mitigation Plan Defined",Table4[[#This Row],[Status]]="04. Action Plan Completed",Table4[[#This Row],[Status]]="08. Blank"),"") -> FALSE | AG42: =IF(Table4[[#This Row],[Required Risk Resolution Date]]="","FALSE",IF($AE$1>Table4[[#This Row],[Required Risk Resolution Date]],TRUE,FALSE)) -> FALSE | AH42: =IF(AE42<30,FALSE,IF(AE42>90,FALSE,TRUE)) -> FALSE | AI42: =IF(AE42<91,FALSE,IF(AE42>180,FALSE,TRUE)) -> FALSE | AJ42: =IF(AE42>180,TRUE,FALSE) -> TRUE | AK42: =OR(Table4[[#This Row],[Priority]]="Critical",Table4[[#This Row],[Priority]]="High") -> FALSE | AL42: =Table4[[#This Row],[Required Risk Resolution Date]]-$AE$1 -> -40990 | AM42: =IF(AL42<1,FALSE,IF(AL42>7,FALSE,TRUE)) -> FALSE | AN42: =OR(Table4[[#This Row],[Priority]]="Critical",Table4[[#This Row],[Priority]]="High",Table4[[#This Row],[Priority]]="Moderate") -> FALSE
A43: R110 | B43: 40960 | C43: Blaine Pardoe | D43: 05. Risk Closed | E43: IT Services budgets have been exceeded for the fiscal year | F43: Impacts to the budget may negatively impact our work on TOM and other change activities. | G43: Unknown at this time | H43: M&C Program | J43: Alan Guthrie | K43: Blaine Pardoe | L43: High | M43: 02. Impact > 4 Weeks < 3 Months | N43: 03. Possible | O43: 02. Medium | P43: 03. High | Q43: 02. Medium | R43: 00. Undecided | S43: Unknown | T43: Mitigation | U43: Unknown | V43: Dependent on the budget process | W43: 13-Mar: on daily call, update that this is being managed outside of the RAID log; it is a regular budget activity/process. Close as it is not really a risk, an issue that is being dealt with. | X43: 40975 | Y43: Executive Sponsor | Z43: On daily call, Alan and Ian agreed this is not a risk. It's an issue we are dealing with as part of regular activities. | AB43: 40981 | AE43: =$AE$1-Table4[[#This Row],[Date Captured]] -> 30 | AF43: =IFERROR(OR(Table4[[#This Row],[Status]]="02. Open & Assigned",Table4[[#This Row],[Status]]="01. Open",Table4[[#This Row],[Status]]="03. Action/Mitigation Plan Defined",Table4[[#This Row],[Status]]="04. Action Plan Completed",Table4[[#This Row],[Status]]="08. Blank"),"") -> FALSE | AG43: =IF(Table4[[#This Row],[Required Risk Resolution Date]]="","FALSE",IF($AE$1>Table4[[#This Row],[Required Risk Resolution Date]],TRUE,FALSE)) -> FALSE | AH43: =IF(AE43<30,FALSE,IF(AE43>90,FALSE,TRUE)) -> TRUE | AI43: =IF(AE43<91,FALSE,IF(AE43>180,FALSE,TRUE)) -> FALSE | AJ43: =IF(AE43>180,TRUE,FALSE) -> FALSE | AK43: =OR(Table4[[#This Row],[Priority]]="Critical",Table4[[#This Row],[Priority]]="High") -> TRUE | AL43: =Table4[[#This Row],[Required Risk Resolution Date]]-$AE$1 -> -40990 | AM43: =IF(AL43<1,FALSE,IF(AL43>7,FALSE,TRUE)) -> FALSE | AN43: =OR(Table4[[#This Row],[Priority]]="Critical",Table4[[#This Row],[Priority]]="High",Table4[[#This Row],[Priority]]="Moderate") -> TRUE
A44: R17 | B44: 40655 | D44: 05. Risk Closed | F44: Data schemas vary dramatically among tools on different platforms and even within tools on common platforms (e.g., Lotus Notes). Further, there may be outdated content, duplicate content, and "bad" content or tagging. Quantity of content is vast. | H44: M&C Program | J44: Phil Stubbington | N44: 04. Probable | O44: 03. High | T44: Mitigation | U44: NA | V44: Application and Content Migration workstream is identifying today’s knowledge applications. These will be reviewed and a migration strategy for each will be developed | W44: 27/04 - Not a risk, but a task. Verification to occur prior to SOW. Close. | Z44: Add to workplan. | AB44: 40660 | AE44: =$AE$1-Table4[[#This Row],[Date Captured]] -> 335 | AF44: =IFERROR(OR(Table4[[#This Row],[Status]]="02. Open & Assigned",Table4[[#This Row],[Status]]="01. Open",Table4[[#This Row],[Status]]="03. Action/Mitigation Plan Defined",Table4[[#This Row],[Status]]="04. Action Plan Completed",Table4[[#This Row],[Status]]="08. Blank"),"") -> FALSE | AG44: =IF(Table4[[#This Row],[Required Risk Resolution Date]]="","FALSE",IF($AE$1>Table4[[#This Row],[Required Risk Resolution Date]],TRUE,FALSE)) -> FALSE | AH44: =IF(AE44<30,FALSE,IF(AE44>90,FALSE,TRUE)) -> FALSE | AI44: =IF(AE44<91,FALSE,IF(AE44>180,FALSE,TRUE)) -> FALSE | AJ44: =IF(AE44>180,TRUE,FALSE) -> TRUE | AK44: =OR(Table4[[#This Row],[Priority]]="Critical",Table4[[#This Row],[Priority]]="High") -> FALSE | AL44: =Table4[[#This Row],[Required Risk Resolution Date]]-$AE$1 -> -40990 | AM44: =IF(AL44<1,FALSE,IF(AL44>7,FALSE,TRUE)) -> FALSE | AN44: =OR(Table4[[#This Row],[Priority]]="Critical",Table4[[#This Row],[Priority]]="High",Table4[[#This Row],[Priority]]="Moderate") -> FALSE
A45: R21 | B45: 40673 | D45: 05. Risk Closed | F45: In June there are planned to be a number of elaboration sessions for Lync, Exchange, SP Foundation and a Desing 0 Session. Currently the exact dates and locations of these sesssions cannot be confirmed. The cost of travel will continue to increase as the date come closer and key resources may not be available. Need to schedule sessions ASAP | H45: M&C Program | J45: Al Grljevic | N45: 04. Probable | O45: 03. High | T45: Mitigation | U45: NA | W45: 11/04 - Close here and make it a Critical Issue. | AB45: 40674 | AE45: =$AE$1-Table4[[#This Row],[Date Captured]] -> 317 | AF45: =IFERROR(OR(Table4[[#This Row],[Status]]="02. Open & Assigned",Table4[[#This Row],[Status]]="01. Open",Table4[[#This Row],[Status]]="03. Action/Mitigation Plan Defined",Table4[[#This Row],[Status]]="04. Action Plan Completed",Table4[[#This Row],[Status]]="08. Blank"),"") -> FALSE | AG45: =IF(Table4[[#This Row],[Required Risk Resolution Date]]="","FALSE",IF($AE$1>Table4[[#This Row],[Required Risk Resolution Date]],TRUE,FALSE)) -> FALSE | AH45: =IF(AE45<30,FALSE,IF(AE45>90,FALSE,TRUE)) -> FALSE | AI45: =IF(AE45<91,FALSE,IF(AE45>180,FALSE,TRUE)) -> FALSE | AJ45: =IF(AE45>180,TRUE,FALSE) -> TRUE | AK45: =OR(Table4[[#This Row],[Priority]]="Critical",Table4[[#This Row],[Priority]]="High") -> FALSE | AL45: =Table4[[#This Row],[Required Risk Resolution Date]]-$AE$1 -> -40990 | AM45: =IF(AL45<1,FALSE,IF(AL45>7,FALSE,TRUE)) -> FALSE | AN45: =OR(Table4[[#This Row],[Priority]]="Critical",Table4[[#This Row],[Priority]]="High",Table4[[#This Row],[Priority]]="Moderate") -> FALSE
A46: R22 | B46: 40673 | D46: 05. Risk Closed | F46: The MS hourly rates received from procurement are higher than the original plan. Working to determine the impact to the overall cost. | H46: M&C Program | J46: Michelle Edmonds | N46: 04. Probable | O46: 03. High | T46: Acceptance | U46: NA | W46: 29/06 - SOW's signed - close. 08/06 - SOW have not been confirmed so it is still a risk. $'s are material and will have a cost impact. Support and guidance roles are affected - continue to work through details / SOWs. 25/05 - Michelle: No detail received yet; will talk with Rita. 18/05 - Haven't yet received final hourly rates. 11/05 - Unsure of impact as of now; wait for procurement to see where rates are. | X46: 40723 | AB46: 40723 | AE46: =$AE$1-Table4[[#This Row],[Date Captured]] -> 317 | AF46: =IFERROR(OR(Table4[[#This Row],[Status]]="02. Open & Assigned",Table4[[#This Row],[Status]]="01. Open",Table4[[#This Row],[Status]]="03. Action/Mitigation Plan Defined",Table4[[#This Row],[Status]]="04. Action Plan Completed",Table4[[#This Row],[Status]]="08. Blank"),"") -> FALSE | AG46: =IF(Table4[[#This Row],[Required Risk Resolution Date]]="","FALSE",IF($AE$1>Table4[[#This Row],[Required Risk Resolution Date]],TRUE,FALSE)) -> FALSE | AH46: =IF(AE46<30,FALSE,IF(AE46>90,FALSE,TRUE)) -> FALSE | AI46: =IF(AE46<91,FALSE,IF(AE46>180,FALSE,TRUE)) -> FALSE | AJ46: =IF(AE46>180,TRUE,FALSE) -> TRUE | AK46: =OR(Table4[[#This Row],[Priority]]="Critical",Table4[[#This Row],[Priority]]="High") -> FALSE | AL46: =Table4[[#This Row],[Required Risk Resolution Date]]-$AE$1 -> -40990 | AM46: =IF(AL46<1,FALSE,IF(AL46>7,FALSE,TRUE)) -> FALSE | AN46: =OR(Table4[[#This Row],[Priority]]="Critical",Table4[[#This Row],[Priority]]="High",Table4[[#This Row],[Priority]]="Moderate") -> FALSE
A47: R28 | B47: 40674 | D47: 05. Risk Closed | F47: Delay in agreeing and signing off the Microsoft MOU, EA and Master Work Order. | H47: M&C Program | J47: Al Grljevic | N47: 04. Probable | O47: 03. High | T47: Acceptance | W47: 11/05 - Opened as risk and closed as Issue 3; waiting on legal sign-off. 18/05 - Still seem to be on track. Conversation with MS legal to push them harder. 25/05 - Still planning sign-off by 1-June; call scheduled this afternoon to determine how realistic this is and how to mitigate if it's not. Planning for all to be signed-off same day. 08/06 - Accept and Close. June 28th is the date for signing the MOU, EA, and Mater work order. | X47: 40709 | AB47: 40702 | AE47: =$AE$1-Table4[[#This Row],[Date Captured]] -> 316 | AF47: =IFERROR(OR(Table4[[#This Row],[Status]]="02. Open & Assigned",Table4[[#This Row],[Status]]="01. Open",Table4[[#This Row],[Status]]="03. Action/Mitigation Plan Defined",Table4[[#This Row],[Status]]="04. Action Plan Completed",Table4[[#This Row],[Status]]="08. Blank"),"") -> FALSE | AG47: =IF(Table4[[#This Row],[Required Risk Resolution Date]]="","FALSE",IF($AE$1>Table4[[#This Row],[Required Risk Resolution Date]],TRUE,FALSE)) -> FALSE | AH47: =IF(AE47<30,FALSE,IF(AE47>90,FALSE,TRUE)) -> FALSE | AI47: =IF(AE47<91,FALSE,IF(AE47>180,FALSE,TRUE)) -> FALSE | AJ47: =IF(AE47>180,TRUE,FALSE) -> TRUE | AK47: =OR(Table4[[#This Row],[Priority]]="Critical",Table4[[#This Row],[Priority]]="High") -> FALSE | AL47: =Table4[[#This Row],[Required Risk Resolution Date]]-$AE$1 -> -40990 | AM47: =IF(AL47<1,FALSE,IF(AL47>7,FALSE,TRUE)) -> FALSE | AN47: =OR(Table4[[#This Row],[Priority]]="Critical",Table4[[#This Row],[Priority]]="High",Table4[[#This Row],[Priority]]="Moderate") -> FALSE
A48: R30 | B48: 40702 | D48: 05. Risk Closed | F48: 5 Managing Sponsors still need to be identified (Finance and 4 Area Sponsors) | H48: M&C Program | J48: Al Grljevic | N48: 04. Probable | O48: 03. High | T48: Acceptance | W48: 08/06 - accept the risk and close. 25/05 - Michelle and Al have communicated this to John; remains open. 01/06 - Discuss at Friday's IT Steering Committee meeting (and at Ken's meeting). 08/06 - John is aware of the need for the managing sponsors. Accept this as a risk and close. | X48: 40702 | Z48: Michelle and Al have communicated this to John and he is aware of the need for the managing sponsors. Accept this as a risk and close. | AE48: =$AE$1-Table4[[#This Row],[Date Captured]] -> 288 | AF48: =IFERROR(OR(Table4[[#This Row],[Status]]="02. Open & Assigned",Table4[[#This Row],[Status]]="01. Open",Table4[[#This Row],[Status]]="03. Action/Mitigation Plan Defined",Table4[[#This Row],[Status]]="04. Action Plan Completed",Table4[[#This Row],[Status]]="08. Blank"),"") -> FALSE | AG48: =IF(Table4[[#This Row],[Required Risk Resolution Date]]="","FALSE",IF($AE$1>Table4[[#This Row],[Required Risk Resolution Date]],TRUE,FALSE)) -> FALSE | AH48: =IF(AE48<30,FALSE,IF(AE48>90,FALSE,TRUE)) -> FALSE | AI48: =IF(AE48<91,FALSE,IF(AE48>180,FALSE,TRUE)) -> FALSE | AJ48: =IF(AE48>180,TRUE,FALSE) -> TRUE | AK48: =OR(Table4[[#This Row],[Priority]]="Critical",Table4[[#This Row],[Priority]]="High") -> FALSE | AL48: =Table4[[#This Row],[Required Risk Resolution Date]]-$AE$1 -> -40990 | AM48: =IF(AL48<1,FALSE,IF(AL48>7,FALSE,TRUE)) -> FALSE | AN48: =OR(Table4[[#This Row],[Priority]]="Critical",Table4[[#This Row],[Priority]]="High",Table4[[#This Row],[Priority]]="Moderate") -> FALSE
A49: R31 | B49: 40702 | D49: 05. Risk Closed | F49: Identify MS Resources for the Envisioning Workshops in July. | H49: M&C Program | J49: Al Grljevic | N49: 04. Probable | O49: 03. High | T49: Mitigation | V49: Work with Rita to assign roles / receive CV's for EY review. Provide Rita the July envisioning schedule so she can start assigning MS Resources. | W49: 06/07 - 14 resources identified by Rita for Secaucus. Scott is working with Sourcing to on-board - close 29/06 - Need to touch base with Rita for MS Resources. 15/06 - CV's are due back shortly from MS. 08/06 - Adrian said since delay, MS has disbanded their team / clean sheet going forward. Need to review CV's / roles so we get MS resources assigned for July workshops. | X49: 40730 | AB49: 40730 | AE49: =$AE$1-Table4[[#This Row],[Date Captured]] -> 288 | AF49: =IFERROR(OR(Table4[[#This Row],[Status]]="02. Open & Assigned",Table4[[#This Row],[Status]]="01. Open",Table4[[#This Row],[Status]]="03. Action/Mitigation Plan Defined",Table4[[#This Row],[Status]]="04. Action Plan Completed",Table4[[#This Row],[Status]]="08. Blank"),"") -> FALSE | AG49: =IF(Table4[[#This Row],[Required Risk Resolution Date]]="","FALSE",IF($AE$1>Table4[[#This Row],[Required Risk Resolution Date]],TRUE,FALSE)) -> FALSE | AH49: =IF(AE49<30,FALSE,IF(AE49>90,FALSE,TRUE)) -> FALSE | AI49: =IF(AE49<91,FALSE,IF(AE49>180,FALSE,TRUE)) -> FALSE | AJ49: =IF(AE49>180,TRUE,FALSE) -> TRUE | AK49: =OR(Table4[[#This Row],[Priority]]="Critical",Table4[[#This Row],[Priority]]="High") -> FALSE | AL49: =Table4[[#This Row],[Required Risk Resolution Date]]-$AE$1 -> -40990 | AM49: =IF(AL49<1,FALSE,IF(AL49>7,FALSE,TRUE)) -> FALSE | AN49: =OR(Table4[[#This Row],[Priority]]="Critical",Table4[[#This Row],[Priority]]="High",Table4[[#This Row],[Priority]]="Moderate") -> FALSE
A50: R38 | B50: 40730 | C50: unknown | D50: 07. Risk has become an Issue | E50: As a result of strategy decisions, order hardware placements have been put on hold. | F50: A managed services RFP is being run to select vendor for services for Lync, Exchange and SharePoint. There is a risk that we may impact hardware order dates. Decision had been taken to do prerequisite vendor workshops with 8 vendors to finalize RFP future state requirements. Workshops completing 28-October. | G50: This would have an impact on the timeline. | H50: M&C Program | J50: Adrian Mickleson | K50: Adrian Mickleson | L50: High | N50: 03. Possible | O50: 03. High | T50: Mitigation | V50: Begin analysis / research of competing solutions. | W50: 18-Jan: Adrian provided update - we are halfway through the RFP presentation week now; targetting Friday for completion. Review in two weeks. 04-Jan- expect feedback for SP and Exchange in the next two weeks, for Lync at end of month. Review in two weeks. 14/12 - Response due back from vendors in January. 07/12 - This risk ongoing until decision is made. Negotiations are underway this week. Leave as risk to be reviewed next week; if do not have an answer then, will become an issue. Brett suggested at some point splitting this item into the different RFP streams. 30/11 - Adrian said there are two actions occurring here: 1. prepping impact assessment (high level view of what will happen with RFP) for Guy and Alan for Friday, and 2. 2 vendors got RFP on Friday and it's due back just before Christmas. Al took an action to have Karen set up a meeting between Alan, Al and Adrian for Monday at the latest. Need to determine impact and what to do with CRs and resources. Laura took action to work with Adrian to open this as an issue and close as a risk. 23/11 - Adrian said the RFP decision should come Friday.Review next week. 02/11 - Al rec change review dates to 2 wks out. 12/10 - Determine risk after we have workshops. 05/10 - Decision had been taken to do prerequisite vendor workshops with 8 vendors to finalize RFP future state requirements. Workshops completing 28-October. 22/09 - Assign back to Adrian. Needs to be restated-- cloud is one scenario in RFP. 07/09 - We're about 2 weeks behind on the RFP; meeting with Forrester tomorrow to review. Very close to issuing to short list. Concern that we owe our consolidated plans to the Managing Sponsors in 2 weeks. Check with Adrian on rewording so risk is clear. 31/08 - 3 options still included In RFP. 24/08 - No update, but this is definitely still an option within RFP as currently stands. 17/08 - No update. 10/08 - No update, is this still in scope and budget? 27/07 - new issue, review next week. | X50: 40940 | Z50: 8-Feb: per call with Paul and James, determined that 1. this item is an issue, and 2. it should be split out into the different streams since they are in different places, with different impacts, etc. Opened as I111 and I112 for Lync and Exchange and followed up with SP to see whether they have an issue around this or not. | AB50: 40947 | AC50: I111, I112 | AE50: =$AE$1-Table4[[#This Row],[Date Captured]] -> 260 | AF50: =IFERROR(OR(Table4[[#This Row],[Status]]="02. Open & Assigned",Table4[[#This Row],[Status]]="01. Open",Table4[[#This Row],[Status]]="03. Action/Mitigation Plan Defined",Table4[[#This Row],[Status]]="04. Action Plan Completed",Table4[[#This Row],[Status]]="08. Blank"),"") -> FALSE | AG50: =IF(Table4[[#This Row],[Required Risk Resolution Date]]="","FALSE",IF($AE$1>Table4[[#This Row],[Required Risk Resolution Date]],TRUE,FALSE)) -> FALSE | AH50: =IF(AE50<30,FALSE,IF(AE50>90,FALSE,TRUE)) -> FALSE | AI50: =IF(AE50<91,FALSE,IF(AE50>180,FALSE,TRUE)) -> FALSE | AJ50: =IF(AE50>180,TRUE,FALSE) -> TRUE | AK50: =OR(Table4[[#This Row],[Priority]]="Critical",Table4[[#This Row],[Priority]]="High") -> TRUE | AL50: =Table4[[#This Row],[Required Risk Resolution Date]]-$AE$1 -> -40990 | AM50: =IF(AL50<1,FALSE,IF(AL50>7,FALSE,TRUE)) -> FALSE | AN50: =OR(Table4[[#This Row],[Priority]]="Critical",Table4[[#This Row],[Priority]]="High",Table4[[#This Row],[Priority]]="Moderate") -> TRUE
A51: R39 | B51: 40751 | D51: 05. Risk Closed | F51: Inter-program dependencies around sharing resources (i.e. IAM resources) | H51: M&C Program | J51: Al Grljevic | N51: 03. Possible | O51: 03. High | T51: Mitigation | V51: Invite Steve and Ken to RAID call. | W51: 10/08 - Bob and Ken have joined the M&C weekly RAID call. Daren Wicks identified to represent M&C Program for Inter-program dependencies. Close risk. 27/07 - Steve Betts will send list to Lauren so they can be included in the call. | X51: 40765 | AB51: 40765 | AE51: =$AE$1-Table4[[#This Row],[Date Captured]] -> 239 | AF51: =IFERROR(OR(Table4[[#This Row],[Status]]="02. Open & Assigned",Table4[[#This Row],[Status]]="01. Open",Table4[[#This Row],[Status]]="03. Action/Mitigation Plan Defined",Table4[[#This Row],[Status]]="04. Action Plan Completed",Table4[[#This Row],[Status]]="08. Blank"),"") -> FALSE | AG51: =IF(Table4[[#This Row],[Required Risk Resolution Date]]="","FALSE",IF($AE$1>Table4[[#This Row],[Required Risk Resolution Date]],TRUE,FALSE)) -> FALSE | AH51: =IF(AE51<30,FALSE,IF(AE51>90,FALSE,TRUE)) -> FALSE | AI51: =IF(AE51<91,FALSE,IF(AE51>180,FALSE,TRUE)) -> FALSE | AJ51: =IF(AE51>180,TRUE,FALSE) -> TRUE | AK51: =OR(Table4[[#This Row],[Priority]]="Critical",Table4[[#This Row],[Priority]]="High") -> FALSE | AL51: =Table4[[#This Row],[Required Risk Resolution Date]]-$AE$1 -> -40990 | AM51: =IF(AL51<1,FALSE,IF(AL51>7,FALSE,TRUE)) -> FALSE | AN51: =OR(Table4[[#This Row],[Priority]]="Critical",Table4[[#This Row],[Priority]]="High",Table4[[#This Row],[Priority]]="Moderate") -> FALSE
A52: R50B | B52: 40826 | D52: 05. Risk Closed | F52: Need to validate we have the appropriate oversight for contractors / third parties with regards to work products, timesheets, invoices, expenses | H52: M&C Program | J52: Alan Guthrie | N52: 03. Possible | O52: 03. High | T52: Mitigation | V52: Assessment under way and analyzing risk to effort | W52: 19/10 - Al said to close. | X52: 40835 | AB52: 40835 | AE52: =$AE$1-Table4[[#This Row],[Date Captured]] -> 164 | AF52: =IFERROR(OR(Table4[[#This Row],[Status]]="02. Open & Assigned",Table4[[#This Row],[Status]]="01. Open",Table4[[#This Row],[Status]]="03. Action/Mitigation Plan Defined",Table4[[#This Row],[Status]]="04. Action Plan Completed",Table4[[#This Row],[Status]]="08. Blank"),"") -> FALSE | AG52: =IF(Table4[[#This Row],[Required Risk Resolution Date]]="","FALSE",IF($AE$1>Table4[[#This Row],[Required Risk Resolution Date]],TRUE,FALSE)) -> FALSE | AH52: =IF(AE52<30,FALSE,IF(AE52>90,FALSE,TRUE)) -> FALSE | AI52: =IF(AE52<91,FALSE,IF(AE52>180,FALSE,TRUE)) -> TRUE | AJ52: =IF(AE52>180,TRUE,FALSE) -> FALSE | AK52: =OR(Table4[[#This Row],[Priority]]="Critical",Table4[[#This Row],[Priority]]="High") -> FALSE | AL52: =Table4[[#This Row],[Required Risk Resolution Date]]-$AE$1 -> -40990 | AM52: =IF(AL52<1,FALSE,IF(AL52>7,FALSE,TRUE)) -> FALSE | AN52: =OR(Table4[[#This Row],[Priority]]="Critical",Table4[[#This Row],[Priority]]="High",Table4[[#This Row],[Priority]]="Moderate") -> FALSE
A53: R57 | B53: 40820 | D53: 05. Risk Closed | F53: Final locations for in-country build-outs for Exchange, Lync and SharePoint cannot be finalized until a detailed evaulation of the Q&RM DCC due dilligence findings against the type of data for each of these solutions has been undertaken with Q&RM. This means that design & planning cannot be completed without significant assumptions being made. | H53: M&C Program | J53: Michelle / Adrian | O53: 03. High | T53: Mitigation | V53: Use the locations specified by Q&RM | W53: 14/12 - M&C Q&RM report was sent out by Susan. Adrian to sink up with Binu on his slide deck. 07/12 - Michelle said they are working through this; Brett has discussed with Siggi and John. It is a matter of pursuing the Q&RM angle or the in-country infrastructure (very expensive); not enough resources to go at it both ways. Will be ok for SP Phase 1, but will affect Exchange and SP Phase 2. Review next week. 23/11 - Adrian requested we move the review date out 2 wks. 02/11 - Q&RM steering comm reviewed the list and provided guidance. Reviewing note and confirming undertanding. Create business case for countries and confirm understanding. 02/11 - Al said Q&RM steering comm meeting tomorrow; update next week. 19/10 - Michelle - update new Impact column to reflect impact on budget and time. 12/10 - Susan Chakerian scheduling workshops for Q&RM. Focus of the workshops is to determine if we have the right support in the right locations. 04/10 - opened by Michelle. Examples: North America non US client data should be housed in Toronto as a main data center not Secaucus. As a team we need to confirm that operations, network, capacity, etc. are all ready in the Toronto DC to accept the work. Certain types of people data cannot be transferred out of country so how will this impact the People Profiles and the ability to find people globally and the servers needed to support that. | X53: 40898 | AE53: =$AE$1-Table4[[#This Row],[Date Captured]] -> 170 | AF53: =IFERROR(OR(Table4[[#This Row],[Status]]="02. Open & Assigned",Table4[[#This Row],[Status]]="01. Open",Table4[[#This Row],[Status]]="03. Action/Mitigation Plan Defined",Table4[[#This Row],[Status]]="04. Action Plan Completed",Table4[[#This Row],[Status]]="08. Blank"),"") -> FALSE | AG53: =IF(Table4[[#This Row],[Required Risk Resolution Date]]="","FALSE",IF($AE$1>Table4[[#This Row],[Required Risk Resolution Date]],TRUE,FALSE)) -> FALSE | AH53: =IF(AE53<30,FALSE,IF(AE53>90,FALSE,TRUE)) -> FALSE | AI53: =IF(AE53<91,FALSE,IF(AE53>180,FALSE,TRUE)) -> TRUE | AJ53: =IF(AE53>180,TRUE,FALSE) -> FALSE | AK53: =OR(Table4[[#This Row],[Priority]]="Critical",Table4[[#This Row],[Priority]]="High") -> FALSE | AL53: =Table4[[#This Row],[Required Risk Resolution Date]]-$AE$1 -> -40990 | AM53: =IF(AL53<1,FALSE,IF(AL53>7,FALSE,TRUE)) -> FALSE | AN53: =OR(Table4[[#This Row],[Priority]]="Critical",Table4[[#This Row],[Priority]]="High",Table4[[#This Row],[Priority]]="Moderate") -> FALSE
A54: R65B | B54: 40842 | D54: 05. Risk Closed | F54: Lync Dormant Deployment - Currently the SMS deployment Gateway has "Operational Challenges" which is delaying the deployment of out package Currently we have a 1 week delay to the project, which is taking us very close to the moratorium date. Impact could be on Business Change | H54: M&C Program | J54: Adrian Mickleson | N54: 01. Slight | O54: 03. High | T54: Mitigation | V54: 09/11 - Adrian: this is on-going; review 2 wks. 02-11 Lync dormant deployment - Transition 2b - was distributed as per revised plan of 1st Nov. Confirmation being sought as to the current deployment status, as we have another Transition (2c) planned for Tuesday 8th Nov. No impact on Business Change, as they have confirmed there delivery is now based on the 31st Jan, and not as previously stated, the 9th Jan. 26/10 - Daren said can't get this escalated unless is is business or revenue-impacting. Daren to set meeting with Guy, Al, Mario and Martin to discuss. Raise with the package Deployment team for rollout using Level 3 Tier distribution servers | W54: 23/11 - Adrian said this has been resolved and they got the green light to deploy last night. Close. | X54: 40870 | AA54: 40851 | AB54: 40870 | AE54: =$AE$1-Table4[[#This Row],[Date Captured]] -> 148 | AF54: =IFERROR(OR(Table4[[#This Row],[Status]]="02. Open & Assigned",Table4[[#This Row],[Status]]="01. Open",Table4[[#This Row],[Status]]="03. Action/Mitigation Plan Defined",Table4[[#This Row],[Status]]="04. Action Plan Completed",Table4[[#This Row],[Status]]="08. Blank"),"") -> FALSE | AG54: =IF(Table4[[#This Row],[Required Risk Resolution Date]]="","FALSE",IF($AE$1>Table4[[#This Row],[Required Risk Resolution Date]],TRUE,FALSE)) -> TRUE | AH54: =IF(AE54<30,FALSE,IF(AE54>90,FALSE,TRUE)) -> FALSE | AI54: =IF(AE54<91,FALSE,IF(AE54>180,FALSE,TRUE)) -> TRUE | AJ54: =IF(AE54>180,TRUE,FALSE) -> FALSE | AK54: =OR(Table4[[#This Row],[Priority]]="Critical",Table4[[#This Row],[Priority]]="High") -> FALSE | AL54: =Table4[[#This Row],[Required Risk Resolution Date]]-$AE$1 -> -139 | AM54: =IF(AL54<1,FALSE,IF(AL54>7,FALSE,TRUE)) -> FALSE | AN54: =OR(Table4[[#This Row],[Priority]]="Critical",Table4[[#This Row],[Priority]]="High",Table4[[#This Row],[Priority]]="Moderate") -> FALSE
A55: R126 | B55: 40982 | C55: Daren Wicks | D55: 02. Open & Assigned | E55: No policies or procedures have been provided by M&C for Group Management | F55: Policies required to ensure controls and constraints can be applied to the Service in order to maintain the EY environment, and offer the Users a great experience. | G55: IAM will install the Group ID product, with all the capabilities, but Ops will struggle to identify which procedure belongs to which policy when enacting or creating Groups. The same applies to the Self Service Portal, i.e. Identifying what we should or should not allow the Users to do/not do in terms of setting up Groups (as an example) of 150 members. Also means we cant test these out prior to Production, hence delaying the project. | H55: IAM | I55: TF - Messaging | J55: Ted Balfour | K55: Nikolay Krastev | L55: Critical | M55: 02. Impact > 4 Weeks < 3 Months | N55: 03. Possible | O55: 03. High | P55: 03. High | Q55: 03. High | R55: 02. Medium | S55: M&C not providing relevant Group Management policies. | T55: Mitigation | U55: None | V55: M&C to work with the various streams/business users to define Group Policies and procedures | W55: 14 Mar: Risk raised with Nikolay on the 7th Feb. Awaiting feedback | X55: 40989 | Y55: Program Manager | Z55: M&C to provide Group Management Policies and Procedures so they can be tested and signed off. | AA55: 40998 | AE55: =$AE$1-Table4[[#This Row],[Date Captured]] -> 8 | AF55: =IFERROR(OR(Table4[[#This Row],[Status]]="02. Open & Assigned",Table4[[#This Row],[Status]]="01. Open",Table4[[#This Row],[Status]]="03. Action/Mitigation Plan Defined",Table4[[#This Row],[Status]]="04. Action Plan Completed",Table4[[#This Row],[Status]]="08. Blank"),"") -> TRUE | AG55: =IF(Table4[[#This Row],[Required Risk Resolution Date]]="","FALSE",IF($AE$1>Table4[[#This Row],[Required Risk Resolution Date]],TRUE,FALSE)) -> FALSE | AH55: =IF(AE55<30,FALSE,IF(AE55>90,FALSE,TRUE)) -> FALSE | AI55: =IF(AE55<91,FALSE,IF(AE55>180,FALSE,TRUE)) -> FALSE | AJ55: =IF(AE55>180,TRUE,FALSE) -> FALSE | AK55: =OR(Table4[[#This Row],[Priority]]="Critical",Table4[[#This Row],[Priority]]="High") -> TRUE | AL55: =Table4[[#This Row],[Required Risk Resolution Date]]-$AE$1 -> 8 | AM55: =IF(AL55<1,FALSE,IF(AL55>7,FALSE,TRUE)) -> FALSE | AN55: =OR(Table4[[#This Row],[Priority]]="Critical",Table4[[#This Row],[Priority]]="High",Table4[[#This Row],[Priority]]="Moderate") -> TRUE
A56: R8 | B56: 40619 | D56: 05. Risk Closed | F56: There is a risk that the Active Directory requirements for M&C program will not be delivered on time. This is currently a program that is yet to be kicked off. Users Groups Infrastructure | H56: M&C Program | J56: Peter Browne | N56: 04. Probable | O56: 03. High | T56: Mitigation | U56: Consider tactical implementation of the AD needs for M&C program | V56: Work with AD program sponsor to manage the dependencies between the programs 20/04 - Interim SOW working identify AD specific requirements. | W56: 27/04 - 3-day workshop scheduled for next week; will allow for a better idea of the plan for 6 months. Adrian will follow-up with Peter to verify. Pertains to Interim SOW. Close. | Z56: Obtain and monitor time scales for other programs 15/04 - initial indication shows 6 months for completing the AD needs in order to migrate to Exchange. Detailed planning to be obtained once AD program is kicked off | AB56: 5/26/2011; Closed 27/04/2011 | AE56: =$AE$1-Table4[[#This Row],[Date Captured]] -> 371 | AF56: =IFERROR(OR(Table4[[#This Row],[Status]]="02. Open & Assigned",Table4[[#This Row],[Status]]="01. Open",Table4[[#This Row],[Status]]="03. Action/Mitigation Plan Defined",Table4[[#This Row],[Status]]="04. Action Plan Completed",Table4[[#This Row],[Status]]="08. Blank"),"") -> FALSE | AG56: =IF(Table4[[#This Row],[Required Risk Resolution Date]]="","FALSE",IF($AE$1>Table4[[#This Row],[Required Risk Resolution Date]],TRUE,FALSE)) -> FALSE | AH56: =IF(AE56<30,FALSE,IF(AE56>90,FALSE,TRUE)) -> FALSE | AI56: =IF(AE56<91,FALSE,IF(AE56>180,FALSE,TRUE)) -> FALSE | AJ56: =IF(AE56>180,TRUE,FALSE) -> TRUE | AK56: =OR(Table4[[#This Row],[Priority]]="Critical",Table4[[#This Row],[Priority]]="High") -> FALSE | AL56: =Table4[[#This Row],[Required Risk Resolution Date]]-$AE$1 -> -40990 | AM56: =IF(AL56<1,FALSE,IF(AL56>7,FALSE,TRUE)) -> FALSE | AN56: =OR(Table4[[#This Row],[Priority]]="Critical",Table4[[#This Row],[Priority]]="High",Table4[[#This Row],[Priority]]="Moderate") -> FALSE
A57: R81 | B57: 40882 | C57: unknown | D57: 07. Risk has become an Issue | F57: Iteration overrun | G57: Testing containment per iteration would be compromised, resources and overall plans impacted and complexity added to Config Management. | H57: M&C Program | J57: Michelle Edmonds | L57: Moderate | N57: 03. Possible | O57: 02. Medium | T57: Mitigation | U57: Engage PM to escalate to Program Manager | V57: Constant engagement with Project throughout every iteration to monitor possible and mitigate for possible overruns e.g. re-scheduling, re-prioritizing, additional resources, extended hours. | W57: 05/03 - Laura emailed Michelle to determine whether this has been resolved, or if not what the current status/priority is. 05/12 - Risk opened. | X57: 40884 | AE57: =$AE$1-Table4[[#This Row],[Date Captured]] -> 108 | AF57: =IFERROR(OR(Table4[[#This Row],[Status]]="02. Open & Assigned",Table4[[#This Row],[Status]]="01. Open",Table4[[#This Row],[Status]]="03. Action/Mitigation Plan Defined",Table4[[#This Row],[Status]]="04. Action Plan Completed",Table4[[#This Row],[Status]]="08. Blank"),"") -> FALSE | AG57: =IF(Table4[[#This Row],[Required Risk Resolution Date]]="","FALSE",IF($AE$1>Table4[[#This Row],[Required Risk Resolution Date]],TRUE,FALSE)) -> FALSE | AH57: =IF(AE57<30,FALSE,IF(AE57>90,FALSE,TRUE)) -> FALSE | AI57: =IF(AE57<91,FALSE,IF(AE57>180,FALSE,TRUE)) -> TRUE | AJ57: =IF(AE57>180,TRUE,FALSE) -> FALSE | AK57: =OR(Table4[[#This Row],[Priority]]="Critical",Table4[[#This Row],[Priority]]="High") -> FALSE | AL57: =Table4[[#This Row],[Required Risk Resolution Date]]-$AE$1 -> -40990 | AM57: =IF(AL57<1,FALSE,IF(AL57>7,FALSE,TRUE)) -> FALSE | AN57: =OR(Table4[[#This Row],[Priority]]="Critical",Table4[[#This Row],[Priority]]="High",Table4[[#This Row],[Priority]]="Moderate") -> TRUE
A58: R106B | B58: 40955 | C58: Nick Coburn | D58: 02. Open & Assigned | E58: Current M&C replanning at project level | F58: There is a risk that revised project timelines may impact the timeline of TOM design. If we do this too early we may not get buy in and could potentially create rework later in the process. | G58: IT Services may become disengaged and disenfranchised with the change management process. Service Design will need to be reviewed for each time we define the Service Transition Plan. | H58: M&C Program | J58: Nick Coburn | K58: Nick Coburn | L58: High | M58: 02. Impact > 4 Weeks < 3 Months | N58: 03. Possible | O58: 02. Medium | P58: 03. High | Q58: 02. Medium | R58: 00. Undecided | S58: Unknown | T58: Mitigation | U58: Unknown | V58: Will need to revisit once all plans are baselined and following 30 day 'get to green' approach to assess if our current plan timeline remains valid. | W58: 7-Mar: Nick provided additional detail for this item. | X58: 40975 | Y58: Program Manager | AA58: 40999 | AE58: =$AE$1-Table4[[#This Row],[Date Captured]] -> 35 | AF58: =IFERROR(OR(Table4[[#This Row],[Status]]="02. Open & Assigned",Table4[[#This Row],[Status]]="01. Open",Table4[[#This Row],[Status]]="03. Action/Mitigation Plan Defined",Table4[[#This Row],[Status]]="04. Action Plan Completed",Table4[[#This Row],[Status]]="08. Blank"),"") -> TRUE | AG58: =IF(Table4[[#This Row],[Required Risk Resolution Date]]="","FALSE",IF($AE$1>Table4[[#This Row],[Required Risk Resolution Date]],TRUE,FALSE)) -> FALSE | AH58: =IF(AE58<30,FALSE,IF(AE58>90,FALSE,TRUE)) -> TRUE | AI58: =IF(AE58<91,FALSE,IF(AE58>180,FALSE,TRUE)) -> FALSE | AJ58: =IF(AE58>180,TRUE,FALSE) -> FALSE | AK58: =OR(Table4[[#This Row],[Priority]]="Critical",Table4[[#This Row],[Priority]]="High") -> TRUE | AL58: =Table4[[#This Row],[Required Risk Resolution Date]]-$AE$1 -> 9 | AM58: =IF(AL58<1,FALSE,IF(AL58>7,FALSE,TRUE)) -> FALSE | AN58: =OR(Table4[[#This Row],[Priority]]="Critical",Table4[[#This Row],[Priority]]="High",Table4[[#This Row],[Priority]]="Moderate") -> TRUE
A59: R108 | B59: 40955 | C59: Nick Coburn | D59: 02. Open & Assigned | E59: Complex deployment | F59: The deployment approach for Outlook and SharePoint could significantly increased the cost associated with both internal and external support. | G59: We will need to support Lotus Notes for a significant period of time following deployment of Exchange and SharePoint and this will potentially increase support costs for FY13. | H59: M&C Program | J59: Nick Coburn | K59: Nick Coburn | L59: High | M59: 02. Impact > 4 Weeks < 3 Months | N59: 03. Possible | O59: 02. Medium | P59: 03. High | Q59: 02. Medium | R59: 00. Undecided | S59: Unknown | T59: Mitigation | U59: Unknown | V59: Will be validated via Service Design approach and better understanding of external support costs from external vendors for Cloud and On Premise. | W59: 7-Mar: Nick provided additional detail for this item. R107 closed as it is accounted for in this item. | X59: 40975 | Y59: Program Director | AA59: 41061 | AE59: =$AE$1-Table4[[#This Row],[Date Captured]] -> 35 | AF59: =IFERROR(OR(Table4[[#This Row],[Status]]="02. Open & Assigned",Table4[[#This Row],[Status]]="01. Open",Table4[[#This Row],[Status]]="03. Action/Mitigation Plan Defined",Table4[[#This Row],[Status]]="04. Action Plan Completed",Table4[[#This Row],[Status]]="08. Blank"),"") -> TRUE | AG59: =IF(Table4[[#This Row],[Required Risk Resolution Date]]="","FALSE",IF($AE$1>Table4[[#This Row],[Required Risk Resolution Date]],TRUE,FALSE)) -> FALSE | AH59: =IF(AE59<30,FALSE,IF(AE59>90,FALSE,TRUE)) -> TRUE | AI59: =IF(AE59<91,FALSE,IF(AE59>180,FALSE,TRUE)) -> FALSE | AJ59: =IF(AE59>180,TRUE,FALSE) -> FALSE | AK59: =OR(Table4[[#This Row],[Priority]]="Critical",Table4[[#This Row],[Priority]]="High") -> TRUE | AL59: =Table4[[#This Row],[Required Risk Resolution Date]]-$AE$1 -> 71 | AM59: =IF(AL59<1,FALSE,IF(AL59>7,FALSE,TRUE)) -> FALSE | AN59: =OR(Table4[[#This Row],[Priority]]="Critical",Table4[[#This Row],[Priority]]="High",Table4[[#This Row],[Priority]]="Moderate") -> TRUE
A60: R109 | B60: 40960 | C60: Blaine Pardoe | D60: 01. Open | E60: This program is the most technically complex we have undertaken. It requires leaders to understand this technology and to be able to articulate it to their customers. This is far beyond just support people. | F60: The knowledge proliferation efforts required by M&C are larger and more complex than for any previous technology initiative. It requires us to do things differently to ensure people are fully prepared for the transition. | G60: We will need Proliferation plans in place beyond just support. | H60: M&C Program | J60: Blaine Pardoe | K60: Blaine Pardoe | L60: High | M60: 02. Impact > 4 Weeks < 3 Months | N60: 03. Possible | O60: 02. Medium | P60: 03. High | Q60: 02. Medium | R60: 00. Undecided | S60: Unknown | T60: Mitigation | U60: Unknown | V60: We will devise a knowledge proliferation plan. | W60: 24/02: ACTION - On next call review with B. Pardoe & clarify / re-word the risk | X60: 40975 | Y60: Other | AA60: 41040 | AE60: =$AE$1-Table4[[#This Row],[Date Captured]] -> 30 | AF60: =IFERROR(OR(Table4[[#This Row],[Status]]="02. Open & Assigned",Table4[[#This Row],[Status]]="01. Open",Table4[[#This Row],[Status]]="03. Action/Mitigation Plan Defined",Table4[[#This Row],[Status]]="04. Action Plan Completed",Table4[[#This Row],[Status]]="08. Blank"),"") -> TRUE | AG60: =IF(Table4[[#This Row],[Required Risk Resolution Date]]="","FALSE",IF($AE$1>Table4[[#This Row],[Required Risk Resolution Date]],TRUE,FALSE)) -> FALSE | AH60: =IF(AE60<30,FALSE,IF(AE60>90,FALSE,TRUE)) -> TRUE | AI60: =IF(AE60<91,FALSE,IF(AE60>180,FALSE,TRUE)) -> FALSE | AJ60: =IF(AE60>180,TRUE,FALSE) -> FALSE | AK60: =OR(Table4[[#This Row],[Priority]]="Critical",Table4[[#This Row],[Priority]]="High") -> TRUE | AL60: =Table4[[#This Row],[Required Risk Resolution Date]]-$AE$1 -> 50 | AM60: =IF(AL60<1,FALSE,IF(AL60>7,FALSE,TRUE)) -> FALSE | AN60: =OR(Table4[[#This Row],[Priority]]="Critical",Table4[[#This Row],[Priority]]="High",Table4[[#This Row],[Priority]]="Moderate") -> TRUE
A61: R115 | B61: 40973 | C61: Michelle Edmonds | D61: 05. Risk Closed | E61: FAST does not have the same interface as Autonomy. | F61: FAST does not have the same tools for search management as Autonomy. Need to determine how FAST will be managed. | G61: Requirements for a customized FAST management interface. | H61: SharePoint | J61: Stevens Sebastian | K61: Andy Walsh | L61: Moderate | M61: 02. Impact > 4 Weeks < 3 Months | N61: 00. Unsure | O61: 02. Medium | P61: 02. Medium | Q61: 02. Medium | R61: 02. Medium | S61: Search Admin Reqs are defined for FAST mgmt. | T61: Mitigation | U61: TBD | V61: TBD | W61: 7 Feb: working with the WSL to confirm if this is a RISK. 13 March - Closed will be planned for in serach work | X61: 40982 | Y61: Managing Sponsor | Z61: Closed; will be planned for in Search work. | AA61: 40998 | AB61: 40981 | AE61: =$AE$1-Table4[[#This Row],[Date Captured]] -> 17 | AF61: =IFERROR(OR(Table4[[#This Row],[Status]]="02. Open & Assigned",Table4[[#This Row],[Status]]="01. Open",Table4[[#This Row],[Status]]="03. Action/Mitigation Plan Defined",Table4[[#This Row],[Status]]="04. Action Plan Completed",Table4[[#This Row],[Status]]="08. Blank"),"") -> FALSE | AG61: =IF(Table4[[#This Row],[Required Risk Resolution Date]]="","FALSE",IF($AE$1>Table4[[#This Row],[Required Risk Resolution Date]],TRUE,FALSE)) -> FALSE | AH61: =IF(AE61<30,FALSE,IF(AE61>90,FALSE,TRUE)) -> FALSE | AI61: =IF(AE61<91,FALSE,IF(AE61>180,FALSE,TRUE)) -> FALSE | AJ61: =IF(AE61>180,TRUE,FALSE) -> FALSE | AK61: =OR(Table4[[#This Row],[Priority]]="Critical",Table4[[#This Row],[Priority]]="High") -> FALSE | AL61: =Table4[[#This Row],[Required Risk Resolution Date]]-$AE$1 -> 8 | AM61: =IF(AL61<1,FALSE,IF(AL61>7,FALSE,TRUE)) -> FALSE | AN61: =OR(Table4[[#This Row],[Priority]]="Critical",Table4[[#This Row],[Priority]]="High",Table4[[#This Row],[Priority]]="Moderate") -> TRUE
A62: R116 | B62: 40973 | C62: Michelle Edmonds | D62: 05. Risk Closed | E62: Best Bets may not be approved for the Cloud | F62: Management of 'best bets' on the cloud | G62: Impact to the expected User Experience | H62: SharePoint | J62: Stevens Sebastian | K62: Cem Aykan | L62: Moderate | M62: 02. Impact > 4 Weeks < 3 Months | N62: 03. Possible | O62: 02. Medium | P62: 02. Medium | Q62: 02. Medium | R62: 02. Medium | S62: HDL process does not allow for Best Hits in the cloud | T62: Undecided | U62: TBD | V62: TBD | W62: 7 Feb: Added and updated Risk. | X62: 40975 | Y62: Project Manager | AA62: 40998 | AE62: =$AE$1-Table4[[#This Row],[Date Captured]] -> 17 | AF62: =IFERROR(OR(Table4[[#This Row],[Status]]="02. Open & Assigned",Table4[[#This Row],[Status]]="01. Open",Table4[[#This Row],[Status]]="03. Action/Mitigation Plan Defined",Table4[[#This Row],[Status]]="04. Action Plan Completed",Table4[[#This Row],[Status]]="08. Blank"),"") -> FALSE | AG62: =IF(Table4[[#This Row],[Required Risk Resolution Date]]="","FALSE",IF($AE$1>Table4[[#This Row],[Required Risk Resolution Date]],TRUE,FALSE)) -> FALSE | AH62: =IF(AE62<30,FALSE,IF(AE62>90,FALSE,TRUE)) -> FALSE | AI62: =IF(AE62<91,FALSE,IF(AE62>180,FALSE,TRUE)) -> FALSE | AJ62: =IF(AE62>180,TRUE,FALSE) -> FALSE | AK62: =OR(Table4[[#This Row],[Priority]]="Critical",Table4[[#This Row],[Priority]]="High") -> FALSE | AL62: =Table4[[#This Row],[Required Risk Resolution Date]]-$AE$1 -> 8 | AM62: =IF(AL62<1,FALSE,IF(AL62>7,FALSE,TRUE)) -> FALSE | AN62: =OR(Table4[[#This Row],[Priority]]="Critical",Table4[[#This Row],[Priority]]="High",Table4[[#This Row],[Priority]]="Moderate") -> TRUE
A63: R73 | B63: 40848 | C63: unknown | D63: 02. Open & Assigned | E63: General Lack of DR standards | F63: Lack of Enterprise Standards for Disaster Recovery (DR) may affect quality of design deliverables | G63: Incomplete or insuffiecient documentation being handed over to Operations. Resulting in increased recovery times in the event of a disaster. | H63: M&C Program | J63: Mike Laci | K63: Operations | L63: Minor | M63: 03. Impact > 3 Months | N63: 03. Possible | O63: 01. Low | P63: 02. Medium | Q63: 02. Medium | R63: 02. Medium | S63: Incomplete handover of information to Operations regarding the DR plan. | T63: Undecided | U63: NA | V63: Review current DR strategy wth Ops and define next steps. | W63: 2/1 - Lowered Risk level.1/11 - MCS - Project workstreams are concerned that EY has not communicated a standard as it relates to RPO/RTO and other DR/Business Continuity metrics. Decisions are being made at the project workstream level that may not meet business stakeholder expectations. | X63: 40947 | Y63: Project Manager | AA63: 41090 | AE63: =$AE$1-Table4[[#This Row],[Date Captured]] -> 142 | AF63: =IFERROR(OR(Table4[[#This Row],[Status]]="02. Open & Assigned",Table4[[#This Row],[Status]]="01. Open",Table4[[#This Row],[Status]]="03. Action/Mitigation Plan Defined",Table4[[#This Row],[Status]]="04. Action Plan Completed",Table4[[#This Row],[Status]]="08. Blank"),"") -> TRUE | AG63: =IF(Table4[[#This Row],[Required Risk Resolution Date]]="","FALSE",IF($AE$1>Table4[[#This Row],[Required Risk Resolution Date]],TRUE,FALSE)) -> FALSE | AH63: =IF(AE63<30,FALSE,IF(AE63>90,FALSE,TRUE)) -> FALSE | AI63: =IF(AE63<91,FALSE,IF(AE63>180,FALSE,TRUE)) -> TRUE | AJ63: =IF(AE63>180,TRUE,FALSE) -> FALSE | AK63: =OR(Table4[[#This Row],[Priority]]="Critical",Table4[[#This Row],[Priority]]="High") -> FALSE | AL63: =Table4[[#This Row],[Required Risk Resolution Date]]-$AE$1 -> 100 | AM63: =IF(AL63<1,FALSE,IF(AL63>7,FALSE,TRUE)) -> FALSE | AN63: =OR(Table4[[#This Row],[Priority]]="Critical",Table4[[#This Row],[Priority]]="High",Table4[[#This Row],[Priority]]="Moderate") -> FALSE
A64: R85 | B64: 40892 | C64: unknown | D64: 02. Open & Assigned | E64: Schedule/location for the Olympic games | F64: The Olympics & Paralympic Games are less than a year away (27 July - 12 August and 19 August - 9 September respectively). The majority of London based employees will be asked to work in differnet location or from home which means that the load on the VPN network may prevent items such as upgrades taking place.Need to evaluate what work will be taking place during this period and the possible impact. | G64: Could hamper progress with deployment. Also with regards to staff getting on site | H64: M&C Program | J64: Ian Bourne | K64: Ian Bourne | L64: Moderate | M64: 03. Impact > 3 Months | N64: 04. Probable | O64: 02. Medium | P64: 02. Medium | Q64: 02. Medium | R64: 02. Medium | S64: Olympic Start date | T64: Mitigation | U64: Greater understand work taking place. Plan into plans. | V64: Whilst corporate direction is not solid at present, need to understand possible impact from an M&C perspective. | W64: 16-Mar: Ian suggested next review 18-April. Direction provided by Alan for Cross Org that all to work as normal. | X64: 41017 | Y64: Program Director | AA64: 41030 | AE64: =$AE$1-Table4[[#This Row],[Date Captured]] -> 98 | AF64: =IFERROR(OR(Table4[[#This Row],[Status]]="02. Open & Assigned",Table4[[#This Row],[Status]]="01. Open",Table4[[#This Row],[Status]]="03. Action/Mitigation Plan Defined",Table4[[#This Row],[Status]]="04. Action Plan Completed",Table4[[#This Row],[Status]]="08. Blank"),"") -> TRUE | AG64: =IF(Table4[[#This Row],[Required Risk Resolution Date]]="","FALSE",IF($AE$1>Table4[[#This Row],[Required Risk Resolution Date]],TRUE,FALSE)) -> FALSE | AH64: =IF(AE64<30,FALSE,IF(AE64>90,FALSE,TRUE)) -> FALSE | AI64: =IF(AE64<91,FALSE,IF(AE64>180,FALSE,TRUE)) -> TRUE | AJ64: =IF(AE64>180,TRUE,FALSE) -> FALSE | AK64: =OR(Table4[[#This Row],[Priority]]="Critical",Table4[[#This Row],[Priority]]="High") -> FALSE | AL64: =Table4[[#This Row],[Required Risk Resolution Date]]-$AE$1 -> 40 | AM64: =IF(AL64<1,FALSE,IF(AL64>7,FALSE,TRUE)) -> FALSE | AN64: =OR(Table4[[#This Row],[Priority]]="Critical",Table4[[#This Row],[Priority]]="High",Table4[[#This Row],[Priority]]="Moderate") -> TRUE
A65: R119 | B65: 40973 | C65: Michelle Edmonds | D65: 05. Risk Closed | E65: Integration points across the Program | F65: The amount of time required to complete DTU Phase #1 may be longer than the requested Phase #1 go-live date (soce and resource availability) | G65: Not being able to have DTU included in Release 1. | H65: SharePoint | J65: Michael Cliffel | L65: High | M65: 03. Impact > 3 Months | N65: 05. Certain | O65: 03. High | P65: 03. High | Q65: 03. High | R65: 03. High | S65: TBD | T65: Undecided | V65: TBD | W65: 7 Feb: Added and updated Risk. This will be discussed on 3/7 mtg with the business. | X65: 40982 | Y65: Program Manager | Z65: This item is being addressed as part of Blue print. | AA65: 40998 | AB65: 40975 | AE65: =$AE$1-Table4[[#This Row],[Date Captured]] -> 17 | AF65: =IFERROR(OR(Table4[[#This Row],[Status]]="02. Open & Assigned",Table4[[#This Row],[Status]]="01. Open",Table4[[#This Row],[Status]]="03. Action/Mitigation Plan Defined",Table4[[#This Row],[Status]]="04. Action Plan Completed",Table4[[#This Row],[Status]]="08. Blank"),"") -> FALSE | AG65: =IF(Table4[[#This Row],[Required Risk Resolution Date]]="","FALSE",IF($AE$1>Table4[[#This Row],[Required Risk Resolution Date]],TRUE,FALSE)) -> FALSE | AH65: =IF(AE65<30,FALSE,IF(AE65>90,FALSE,TRUE)) -> FALSE | AI65: =IF(AE65<91,FALSE,IF(AE65>180,FALSE,TRUE)) -> FALSE | AJ65: =IF(AE65>180,TRUE,FALSE) -> FALSE | AK65: =OR(Table4[[#This Row],[Priority]]="Critical",Table4[[#This Row],[Priority]]="High") -> TRUE | AL65: =Table4[[#This Row],[Required Risk Resolution Date]]-$AE$1 -> 8 | AM65: =IF(AL65<1,FALSE,IF(AL65>7,FALSE,TRUE)) -> FALSE | AN65: =OR(Table4[[#This Row],[Priority]]="Critical",Table4[[#This Row],[Priority]]="High",Table4[[#This Row],[Priority]]="Moderate") -> TRUE
A66: R113 | B66: 40973 | C66: Rewa Bouji | D66: 03. Action/Mitigation Plan Defined | E66: Lack of clearly defined expectations between the program and the business sponsors | F66: There is a risk that the business expects the UC stream to deliver the integration of legacy mail-integrated applications as part of the delivery of Outlook. The UC program is working with business application owners to explain that if they require a legacy mail-integrated tool to be compatible with Outlook, they will need to initiate - and pay for - a project to do this. It is not clear from conversations we have had with the business to date that they have budgeted for resource or project spend in FY13 to support this activity. If the application(s) is(are) required for Day 1 and the business will not accept Outlook deployment without it(them) being integrated, there is a risk that the program will need to deliver these and absorb the cost of doing so. This is not currently in scope or budgeted for. | G66: Increase in program cost and resource needs, delays to the go-live date if the applications cannot be delivered for integration in time for the current Live deployment date | H66: M&C Program | J66: Rewa Bouji | K66: Alan Guthrie | L66: Critical | M66: 02. Impact > 4 Weeks < 3 Months | N66: 04. Probable | O66: 04. Critical | P66: 03. High | Q66: 04. Critical | R66: 03. High | S66: Decision by the business to include delivery of Mail-integrated apps into UC's scope | T66: Mitigation | U66: NA | V66: Work with the Business Change and Deployment teams, and business application owners, to clarify UC scope and ensure that if they have an application that requires mail integration, that they have budgeted for this in the FY13 plan. AG to raise via Mo/Gina to ensure FY13 budgets provision for all transformational programs, not just M&C | W66: 13/03/12: RB: Alan Guthrie took action at the stand up to raise via Mo/Gina (Global PMO) the requirement for all IT Services SD budgets to make provision to support all cross-org programs in FY13 . This will take place at the end of March. Workstream changed from UC to M&C Program as impacts all M&C workstreams, not just UC 06/03/12: RB: As agreed in standup meeting, ownership to be moved from Guy Morgan to Martin Kremmer 05/03/12: RB: Risk logged | X66: 40975 | Y66: Executive Sponsor | AA66: 40999 | AE66: =$AE$1-Table4[[#This Row],[Date Captured]] -> 17 | AF66: =IFERROR(OR(Table4[[#This Row],[Status]]="02. Open & Assigned",Table4[[#This Row],[Status]]="01. Open",Table4[[#This Row],[Status]]="03. Action/Mitigation Plan Defined",Table4[[#This Row],[Status]]="04. Action Plan Completed",Table4[[#This Row],[Status]]="08. Blank"),"") -> TRUE | AG66: =IF(Table4[[#This Row],[Required Risk Resolution Date]]="","FALSE",IF($AE$1>Table4[[#This Row],[Required Risk Resolution Date]],TRUE,FALSE)) -> FALSE | AH66: =IF(AE66<30,FALSE,IF(AE66>90,FALSE,TRUE)) -> FALSE | AI66: =IF(AE66<91,FALSE,IF(AE66>180,FALSE,TRUE)) -> FALSE | AJ66: =IF(AE66>180,TRUE,FALSE) -> FALSE | AK66: =OR(Table4[[#This Row],[Priority]]="Critical",Table4[[#This Row],[Priority]]="High") -> TRUE | AL66: =Table4[[#This Row],[Required Risk Resolution Date]]-$AE$1 -> 9 | AM66: =IF(AL66<1,FALSE,IF(AL66>7,FALSE,TRUE)) -> FALSE | AN66: =OR(Table4[[#This Row],[Priority]]="Critical",Table4[[#This Row],[Priority]]="High",Table4[[#This Row],[Priority]]="Moderate") -> TRUE
A67: R127 | B67: 40983 | C67: Nicky Watson | D67: 02. Open & Assigned | E67: Shortage of additional environment domain to host a segregated Performance Testing environment for M&C | F67: If performance testing needs to use either the QA integration or UAT environments, this may mean multiple projects will need to queue for environment use. Alternatively if Performance testing is carried out in an environment whilst other workstreams are performing test cycles, it may slow down testing | G67: May cause schedule delays as the separate workstreams/projects may need to queue for scheduled slots to exclusively use the environment for their testing needs. Planning should factor this in. | H67: M&C Program | J67: Al Grljevic | K67: Al Grljevic | L67: High | M67: 03. Impact > 3 Months | N67: 04. Probable | O67: 02. Medium | P67: 03. High | Q67: 03. High | R67: 02. Medium | S67: Confirmation that no budget is available to build out a separate Performance Testing environment domain | T67: Mitigation | U67: Schedule Test Environment utilisation with enforced adherence to schedule | V67: Use UAT or QA Integration environments for performance testing using controlled environment usage and scheduling | W67: 15/03/2012: NW: Follow up with TF as to whether budget can be applied for to build a PT environment. Also assess needs and contention issues with PM's and Infrastructure Engineering. | X67: 40998 | Y67: Program Director | AA67: 41029 | AE67: =$AE$1-Table4[[#This Row],[Date Captured]] -> 7 | AF67: =IFERROR(OR(Table4[[#This Row],[Status]]="02. Open & Assigned",Table4[[#This Row],[Status]]="01. Open",Table4[[#This Row],[Status]]="03. Action/Mitigation Plan Defined",Table4[[#This Row],[Status]]="04. Action Plan Completed",Table4[[#This Row],[Status]]="08. Blank"),"") -> TRUE | AG67: =IF(Table4[[#This Row],[Required Risk Resolution Date]]="","FALSE",IF($AE$1>Table4[[#This Row],[Required Risk Resolution Date]],TRUE,FALSE)) -> FALSE | AH67: =IF(AE67<30,FALSE,IF(AE67>90,FALSE,TRUE)) -> FALSE | AI67: =IF(AE67<91,FALSE,IF(AE67>180,FALSE,TRUE)) -> FALSE | AJ67: =IF(AE67>180,TRUE,FALSE) -> FALSE | AK67: =OR(Table4[[#This Row],[Priority]]="Critical",Table4[[#This Row],[Priority]]="High") -> TRUE | AL67: =Table4[[#This Row],[Required Risk Resolution Date]]-$AE$1 -> 39 | AM67: =IF(AL67<1,FALSE,IF(AL67>7,FALSE,TRUE)) -> FALSE | AN67: =OR(Table4[[#This Row],[Priority]]="Critical",Table4[[#This Row],[Priority]]="High",Table4[[#This Row],[Priority]]="Moderate") -> TRUE
A68: R122 | B68: 40974 | C68: Michelle Edmonds | D68: 07. Risk has become an Issue | E68: Changed priorities in M&C Program since Frog SOW was signed. | F68: Frog user experience deliverables may not achieve desired goals | G68: Disconnect between Blueprint and Frog current SOW. | H68: SharePoint | J68: Binoy Raj | K68: Eric Wahl / Kevin Smyth | L68: High | M68: 03. Impact > 3 Months | N68: 04. Probable | O68: 04. Critical | P68: 03. High | Q68: 04. Critical | R68: 04. Critical | S68: Scope creep on Frog's engagement | T68: Mitigation | V68: TBD | W68: 7 Feb: Added and updated Risk. | X68: 40989 | Y68: Managing Sponsor | Z68: Risk became issue, opened as I150. | AA68: 40984 | AB68: 40976 | AC68: I150 | AE68: =$AE$1-Table4[[#This Row],[Date Captured]] -> 16 | AF68: =IFERROR(OR(Table4[[#This Row],[Status]]="02. Open & Assigned",Table4[[#This Row],[Status]]="01. Open",Table4[[#This Row],[Status]]="03. Action/Mitigation Plan Defined",Table4[[#This Row],[Status]]="04. Action Plan Completed",Table4[[#This Row],[Status]]="08. Blank"),"") -> FALSE | AG68: =IF(Table4[[#This Row],[Required Risk Resolution Date]]="","FALSE",IF($AE$1>Table4[[#This Row],[Required Risk Resolution Date]],TRUE,FALSE)) -> TRUE | AH68: =IF(AE68<30,FALSE,IF(AE68>90,FALSE,TRUE)) -> FALSE | AI68: =IF(AE68<91,FALSE,IF(AE68>180,FALSE,TRUE)) -> FALSE | AJ68: =IF(AE68>180,TRUE,FALSE) -> FALSE | AK68: =OR(Table4[[#This Row],[Priority]]="Critical",Table4[[#This Row],[Priority]]="High") -> TRUE | AL68: =Table4[[#This Row],[Required Risk Resolution Date]]-$AE$1 -> -6 | AM68: =IF(AL68<1,FALSE,IF(AL68>7,FALSE,TRUE)) -> FALSE | AN68: =OR(Table4[[#This Row],[Priority]]="Critical",Table4[[#This Row],[Priority]]="High",Table4[[#This Row],[Priority]]="Moderate") -> TRUE
A69: R14 | B69: 40655 | D69: 05. Risk Closed | F69: New process of "pair programming" impacts productivity and/or timeline | H69: SharePoint | J69: Michelle Edmonds | N69: 04. Probable | O69: 03. High | T69: Mitigation | U69: NA | V69: Monitor closely, especially early on to limit any adverse impacts | W69: 27/04 - Not a risk, but a task. Close. | Z69: Add to workplan. | AB69: 40660 | AE69: =$AE$1-Table4[[#This Row],[Date Captured]] -> 335 | AF69: =IFERROR(OR(Table4[[#This Row],[Status]]="02. Open & Assigned",Table4[[#This Row],[Status]]="01. Open",Table4[[#This Row],[Status]]="03. Action/Mitigation Plan Defined",Table4[[#This Row],[Status]]="04. Action Plan Completed",Table4[[#This Row],[Status]]="08. Blank"),"") -> FALSE | AG69: =IF(Table4[[#This Row],[Required Risk Resolution Date]]="","FALSE",IF($AE$1>Table4[[#This Row],[Required Risk Resolution Date]],TRUE,FALSE)) -> FALSE | AH69: =IF(AE69<30,FALSE,IF(AE69>90,FALSE,TRUE)) -> FALSE | AI69: =IF(AE69<91,FALSE,IF(AE69>180,FALSE,TRUE)) -> FALSE | AJ69: =IF(AE69>180,TRUE,FALSE) -> TRUE | AK69: =OR(Table4[[#This Row],[Priority]]="Critical",Table4[[#This Row],[Priority]]="High") -> FALSE | AL69: =Table4[[#This Row],[Required Risk Resolution Date]]-$AE$1 -> -40990 | AM69: =IF(AL69<1,FALSE,IF(AL69>7,FALSE,TRUE)) -> FALSE | AN69: =OR(Table4[[#This Row],[Priority]]="Critical",Table4[[#This Row],[Priority]]="High",Table4[[#This Row],[Priority]]="Moderate") -> FALSE
A70: R15 | B70: 40655 | D70: 05. Risk Closed | F70: New process of automated testing impacts productivity and/or timeline | H70: SharePoint | J70: Michelle Edmonds | N70: 04. Probable | O70: 02. Medium | T70: Mitigation | U70: NA | V70: Monitor closely, especially early on to limit any adverse impacts | W70: 06/07 - Michelle will look into this. 27/04 - Nicole noted this is in-progress and she will have an update next week. | X70: 40807 | Z70: Nicole to define 04-May. | AB70: 40667 | AE70: =$AE$1-Table4[[#This Row],[Date Captured]] -> 335 | AF70: =IFERROR(OR(Table4[[#This Row],[Status]]="02. Open & Assigned",Table4[[#This Row],[Status]]="01. Open",Table4[[#This Row],[Status]]="03. Action/Mitigation Plan Defined",Table4[[#This Row],[Status]]="04. Action Plan Completed",Table4[[#This Row],[Status]]="08. Blank"),"") -> FALSE | AG70: =IF(Table4[[#This Row],[Required Risk Resolution Date]]="","FALSE",IF($AE$1>Table4[[#This Row],[Required Risk Resolution Date]],TRUE,FALSE)) -> FALSE | AH70: =IF(AE70<30,FALSE,IF(AE70>90,FALSE,TRUE)) -> FALSE | AI70: =IF(AE70<91,FALSE,IF(AE70>180,FALSE,TRUE)) -> FALSE | AJ70: =IF(AE70>180,TRUE,FALSE) -> TRUE | AK70: =OR(Table4[[#This Row],[Priority]]="Critical",Table4[[#This Row],[Priority]]="High") -> FALSE | AL70: =Table4[[#This Row],[Required Risk Resolution Date]]-$AE$1 -> -40990 | AM70: =IF(AL70<1,FALSE,IF(AL70>7,FALSE,TRUE)) -> FALSE | AN70: =OR(Table4[[#This Row],[Priority]]="Critical",Table4[[#This Row],[Priority]]="High",Table4[[#This Row],[Priority]]="Moderate") -> FALSE
A71: R16 | B71: 40655 | D71: 05. Risk Closed | F71: New process of "continuous build" impacts productivity and/or timeline | H71: SharePoint | J71: Michelle Edmonds | N71: 04. Probable | O71: 03. High | T71: Mitigation | U71: NA | V71: Monitor closely, especially early on to limit any adverse impacts | W71: 27/04 - Risk to plan for at this time. Close. | Z71: Add to workplan. | AB71: 40660 | AE71: =$AE$1-Table4[[#This Row],[Date Captured]] -> 335 | AF71: =IFERROR(OR(Table4[[#This Row],[Status]]="02. Open & Assigned",Table4[[#This Row],[Status]]="01. Open",Table4[[#This Row],[Status]]="03. Action/Mitigation Plan Defined",Table4[[#This Row],[Status]]="04. Action Plan Completed",Table4[[#This Row],[Status]]="08. Blank"),"") -> FALSE | AG71: =IF(Table4[[#This Row],[Required Risk Resolution Date]]="","FALSE",IF($AE$1>Table4[[#This Row],[Required Risk Resolution Date]],TRUE,FALSE)) -> FALSE | AH71: =IF(AE71<30,FALSE,IF(AE71>90,FALSE,TRUE)) -> FALSE | AI71: =IF(AE71<91,FALSE,IF(AE71>180,FALSE,TRUE)) -> FALSE | AJ71: =IF(AE71>180,TRUE,FALSE) -> TRUE | AK71: =OR(Table4[[#This Row],[Priority]]="Critical",Table4[[#This Row],[Priority]]="High") -> FALSE | AL71: =Table4[[#This Row],[Required Risk Resolution Date]]-$AE$1 -> -40990 | AM71: =IF(AL71<1,FALSE,IF(AL71>7,FALSE,TRUE)) -> FALSE | AN71: =OR(Table4[[#This Row],[Priority]]="Critical",Table4[[#This Row],[Priority]]="High",Table4[[#This Row],[Priority]]="Moderate") -> FALSE
A72: R18 | B72: 40655 | C72: unknown | D72: 07. Risk has become an Issue | E72: Lack of a new vision and inability to change. | F72: Recreating the current "siloed" approach to knowledge tools, rather than creating an integrated solution that can be leveraged firm-wide. With GSS and EYD starting SharePoint initiatives, we now have a growing number of separate solutions. | G72: Additional cost of point solutions will may with SP | H72: SharePoint | J72: Michelle Edmonds | K72: Alan Guthrie | L72: High | M72: 02. Impact > 4 Weeks < 3 Months | N72: 03. Possible | O72: 03. High | P72: 03. High | Q72: 03. High | R72: 03. High | S72: Assurance choosing Ovitas | T72: Mitigation | U72: NA | V72: Strong cross-service line/stakeholder governance model Involving stakeholders in early strategy and feasibility sessions to encourage thinking ahead. Working with vendors and researching best practices to understand the art of the possible Starting with defined business requirements to understand WHAT functionality must be included before discussing how | W72: 22-Feb: Brett and Michelle agreed on the call that the growing number of multiple instances is an issue. 5/10 - assessment will continue throughout the program 21/09 - assessment will continue throughout the program. | X72: 40961 | Y72: Executive Project Sponsor | Z72: 22-Feb: Now an issue, I121. | AA72: 40969 | AB72: 40961 | AC72: I121 | AE72: =$AE$1-Table4[[#This Row],[Date Captured]] -> 335 | AF72: =IFERROR(OR(Table4[[#This Row],[Status]]="02. Open & Assigned",Table4[[#This Row],[Status]]="01. Open",Table4[[#This Row],[Status]]="03. Action/Mitigation Plan Defined",Table4[[#This Row],[Status]]="04. Action Plan Completed",Table4[[#This Row],[Status]]="08. Blank"),"") -> FALSE | AG72: =IF(Table4[[#This Row],[Required Risk Resolution Date]]="","FALSE",IF($AE$1>Table4[[#This Row],[Required Risk Resolution Date]],TRUE,FALSE)) -> TRUE | AH72: =IF(AE72<30,FALSE,IF(AE72>90,FALSE,TRUE)) -> FALSE | AI72: =IF(AE72<91,FALSE,IF(AE72>180,FALSE,TRUE)) -> FALSE | AJ72: =IF(AE72>180,TRUE,FALSE) -> TRUE | AK72: =OR(Table4[[#This Row],[Priority]]="Critical",Table4[[#This Row],[Priority]]="High") -> TRUE | AL72: =Table4[[#This Row],[Required Risk Resolution Date]]-$AE$1 -> -21 | AM72: =IF(AL72<1,FALSE,IF(AL72>7,FALSE,TRUE)) -> FALSE | AN72: =OR(Table4[[#This Row],[Priority]]="Critical",Table4[[#This Row],[Priority]]="High",Table4[[#This Row],[Priority]]="Moderate") -> TRUE
A73: R19 | B73: 40655 | D73: 05. Risk Closed | F73: Lack of a voice from every end user may lead to missed requirements; It may be difficult to identify the correct resources from whom to elicit requirements. | H73: SharePoint | J73: Michelle Edmonds | N73: 03. Possible | O73: 02. Medium | T73: Mitigation | U73: NA | V73: Representation from all service lines, EY Knowledge, and some CBS groups in workshops. Used feedback and reporting on external sites to understand some of external user requirements User group validation planned for future phases - design and implementation. Plan to conduct usability testing with “real” practitioners throughout design and implementation phases. An iterative approach will be used for further requirement gathering and build to increase flexibility in response to discovering “missed” or “changing” requirements. The effort will be divided into workstreams and phases to try to manage tackling too much at once. The business will identify primary SMR’s who will be able to reach out to additional contacts as needed. | W73: 10/05 - discuss in the Thursday PM call. 27/04 - Need names of appropriate representatives by 21 May. | X73: 40807 | Z73: See Mitigation Plan. | AB73: 40684 | AE73: =$AE$1-Table4[[#This Row],[Date Captured]] -> 335 | AF73: =IFERROR(OR(Table4[[#This Row],[Status]]="02. Open & Assigned",Table4[[#This Row],[Status]]="01. Open",Table4[[#This Row],[Status]]="03. Action/Mitigation Plan Defined",Table4[[#This Row],[Status]]="04. Action Plan Completed",Table4[[#This Row],[Status]]="08. Blank"),"") -> FALSE | AG73: =IF(Table4[[#This Row],[Required Risk Resolution Date]]="","FALSE",IF($AE$1>Table4[[#This Row],[Required Risk Resolution Date]],TRUE,FALSE)) -> FALSE | AH73: =IF(AE73<30,FALSE,IF(AE73>90,FALSE,TRUE)) -> FALSE | AI73: =IF(AE73<91,FALSE,IF(AE73>180,FALSE,TRUE)) -> FALSE | AJ73: =IF(AE73>180,TRUE,FALSE) -> TRUE | AK73: =OR(Table4[[#This Row],[Priority]]="Critical",Table4[[#This Row],[Priority]]="High") -> FALSE | AL73: =Table4[[#This Row],[Required Risk Resolution Date]]-$AE$1 -> -40990 | AM73: =IF(AL73<1,FALSE,IF(AL73>7,FALSE,TRUE)) -> FALSE | AN73: =OR(Table4[[#This Row],[Priority]]="Critical",Table4[[#This Row],[Priority]]="High",Table4[[#This Row],[Priority]]="Moderate") -> FALSE
A74: R20 | B74: 40655 | D74: 05. Risk Closed | F74: It may be difficult to identify the correct resources from whom to elicit requirements. | H74: SharePoint | J74: Michelle Edmonds | N74: 03. Possible | O74: 03. High | T74: Mitigation | V74: An iterative approach will be used for further requirement gathering and build to increase flexibility in response to discovering “missed” or “changing” requirements. The effort will be divided into workstreams and phases to try to manage tackling too much at once. The business will identify primary SMR’s who will be able to reach out to additional contacts as needed. | W74: 27/04 - Combine with R19. Close. | AB74: 40660 | AC74: R19 | AE74: =$AE$1-Table4[[#This Row],[Date Captured]] -> 335 | AF74: =IFERROR(OR(Table4[[#This Row],[Status]]="02. Open & Assigned",Table4[[#This Row],[Status]]="01. Open",Table4[[#This Row],[Status]]="03. Action/Mitigation Plan Defined",Table4[[#This Row],[Status]]="04. Action Plan Completed",Table4[[#This Row],[Status]]="08. Blank"),"") -> FALSE | AG74: =IF(Table4[[#This Row],[Required Risk Resolution Date]]="","FALSE",IF($AE$1>Table4[[#This Row],[Required Risk Resolution Date]],TRUE,FALSE)) -> FALSE | AH74: =IF(AE74<30,FALSE,IF(AE74>90,FALSE,TRUE)) -> FALSE | AI74: =IF(AE74<91,FALSE,IF(AE74>180,FALSE,TRUE)) -> FALSE | AJ74: =IF(AE74>180,TRUE,FALSE) -> TRUE | AK74: =OR(Table4[[#This Row],[Priority]]="Critical",Table4[[#This Row],[Priority]]="High") -> FALSE | AL74: =Table4[[#This Row],[Required Risk Resolution Date]]-$AE$1 -> -40990 | AM74: =IF(AL74<1,FALSE,IF(AL74>7,FALSE,TRUE)) -> FALSE | AN74: =OR(Table4[[#This Row],[Priority]]="Critical",Table4[[#This Row],[Priority]]="High",Table4[[#This Row],[Priority]]="Moderate") -> FALSE
A75: R36 | B75: 40709 | D75: 05. Risk Closed | F75: SharePoint Developer Environments -- Performance / Sizing | H75: SharePoint | J75: Greg Van Valkenburgh | N75: 03. Possible | O75: 02. Medium | T75: Acceptance | U75: N/A | V75: Waiting for Confirmation from Microsoft on the sizing -- e.g., especially RAM. Will not provide confirmation until signing and MS resources assigned | W75: 15/06 - Microsoft SOW lacking detail. | X75: 40751 | Z75: MS provided confirmation that 8GB is sufficient for baseline workstation. | AB75: ? | AE75: =$AE$1-Table4[[#This Row],[Date Captured]] -> 281 | AF75: =IFERROR(OR(Table4[[#This Row],[Status]]="02. Open & Assigned",Table4[[#This Row],[Status]]="01. Open",Table4[[#This Row],[Status]]="03. Action/Mitigation Plan Defined",Table4[[#This Row],[Status]]="04. Action Plan Completed",Table4[[#This Row],[Status]]="08. Blank"),"") -> FALSE | AG75: =IF(Table4[[#This Row],[Required Risk Resolution Date]]="","FALSE",IF($AE$1>Table4[[#This Row],[Required Risk Resolution Date]],TRUE,FALSE)) -> FALSE | AH75: =IF(AE75<30,FALSE,IF(AE75>90,FALSE,TRUE)) -> FALSE | AI75: =IF(AE75<91,FALSE,IF(AE75>180,FALSE,TRUE)) -> FALSE | AJ75: =IF(AE75>180,TRUE,FALSE) -> TRUE | AK75: =OR(Table4[[#This Row],[Priority]]="Critical",Table4[[#This Row],[Priority]]="High") -> FALSE | AL75: =Table4[[#This Row],[Required Risk Resolution Date]]-$AE$1 -> -40990 | AM75: =IF(AL75<1,FALSE,IF(AL75>7,FALSE,TRUE)) -> FALSE | AN75: =OR(Table4[[#This Row],[Priority]]="Critical",Table4[[#This Row],[Priority]]="High",Table4[[#This Row],[Priority]]="Moderate") -> FALSE
A76: R37 | B76: 40722 | D76: 05. Risk Closed | F76: Development Workstation Buildout - receiving MS requirements / direction so the 35 VM's (workstations) can be built for Fusion development team. | H76: SharePoint | J76: Scott Machovina | N76: 03. Possible | O76: 03. High | T76: Mitigation | V76: Work with MS to receive requirements prior to the start of development. | W76: 27/07 - Nick Wood said to reach out and work with MS on load / config requirements - close risk. 06/07 - MS engaged - meeting to be scheduled to finalize dev workstation build. 29/06 -Microsoft needs to tell us what exactly they need. Brian and Greg to discuss off-line. | X76: 40751 | AB76: 40751 | AE76: =$AE$1-Table4[[#This Row],[Date Captured]] -> 268 | AF76: =IFERROR(OR(Table4[[#This Row],[Status]]="02. Open & Assigned",Table4[[#This Row],[Status]]="01. Open",Table4[[#This Row],[Status]]="03. Action/Mitigation Plan Defined",Table4[[#This Row],[Status]]="04. Action Plan Completed",Table4[[#This Row],[Status]]="08. Blank"),"") -> FALSE | AG76: =IF(Table4[[#This Row],[Required Risk Resolution Date]]="","FALSE",IF($AE$1>Table4[[#This Row],[Required Risk Resolution Date]],TRUE,FALSE)) -> FALSE | AH76: =IF(AE76<30,FALSE,IF(AE76>90,FALSE,TRUE)) -> FALSE | AI76: =IF(AE76<91,FALSE,IF(AE76>180,FALSE,TRUE)) -> FALSE | AJ76: =IF(AE76>180,TRUE,FALSE) -> TRUE | AK76: =OR(Table4[[#This Row],[Priority]]="Critical",Table4[[#This Row],[Priority]]="High") -> FALSE | AL76: =Table4[[#This Row],[Required Risk Resolution Date]]-$AE$1 -> -40990 | AM76: =IF(AL76<1,FALSE,IF(AL76>7,FALSE,TRUE)) -> FALSE | AN76: =OR(Table4[[#This Row],[Priority]]="Critical",Table4[[#This Row],[Priority]]="High",Table4[[#This Row],[Priority]]="Moderate") -> FALSE
A77: R43 | B77: 40760 | C77: unknown | D77: 05. Risk Closed | E77: We took action without knowing the People Strategy. We took requirements and design solutions. | F77: The "People Strategy Refresh" is in process. Decisions/directions could be set that would change or alter approaches and strategy that could affect Fusion. Strategy is to be presented in September, then going through an approval/vetting process, and a "working plan" targeted for November. | G77: Decisions/directions could be set that would change or alter approaches and strategy that could affect Fusion. | H77: SharePoint | J77: Michelle Edmonds | K77: Michelle Edmonds | L77: Minor | M77: 03. Impact > 3 Months | N77: 01. Slight | O77: 01. Low | P77: 01. Low | Q77: 01. Low | R77: 01. Low | S77: If the People Refresh Strategy significantly changes decisions on the People workstream. | T77: Acceptance | U77: Need to wait until strategy is defined | V77: Evaluate impact when strategy is accepted/announced | W77: 5/10 - still need to assess impact when strategy is announced. 21/09 - still need to assess impact when strategy is announced. 08/05 - new risk opened | X77: 40996 | Y77: Project Manager | Z77: Will be addressed by the WSL | AA77: 40997 | AE77: =$AE$1-Table4[[#This Row],[Date Captured]] -> 230 | AF77: =IFERROR(OR(Table4[[#This Row],[Status]]="02. Open & Assigned",Table4[[#This Row],[Status]]="01. Open",Table4[[#This Row],[Status]]="03. Action/Mitigation Plan Defined",Table4[[#This Row],[Status]]="04. Action Plan Completed",Table4[[#This Row],[Status]]="08. Blank"),"") -> FALSE | AG77: =IF(Table4[[#This Row],[Required Risk Resolution Date]]="","FALSE",IF($AE$1>Table4[[#This Row],[Required Risk Resolution Date]],TRUE,FALSE)) -> FALSE | AH77: =IF(AE77<30,FALSE,IF(AE77>90,FALSE,TRUE)) -> FALSE | AI77: =IF(AE77<91,FALSE,IF(AE77>180,FALSE,TRUE)) -> FALSE | AJ77: =IF(AE77>180,TRUE,FALSE) -> TRUE | AK77: =OR(Table4[[#This Row],[Priority]]="Critical",Table4[[#This Row],[Priority]]="High") -> FALSE | AL77: =Table4[[#This Row],[Required Risk Resolution Date]]-$AE$1 -> 7 | AM77: =IF(AL77<1,FALSE,IF(AL77>7,FALSE,TRUE)) -> TRUE | AN77: =OR(Table4[[#This Row],[Priority]]="Critical",Table4[[#This Row],[Priority]]="High",Table4[[#This Row],[Priority]]="Moderate") -> FALSE
A78: R44 | B78: 40764 | C78: unknown | D78: 05. Risk Closed | E78: The RFP time takes longer than initial plan. | F78: Prioritization of all work for Phase 1 will not be possible due to the need to have 3rd party components for items such as Taxonomy Management | G78: The end date of the effort will not be able to be projected | H78: SharePoint | J78: Michelle Edmonds | K78: Michelle Edmonds | L78: Minor | M78: 01. Impact < 4 weeks | N78: 03. Possible | O78: 02. Medium | P78: 01. Low | Q78: 02. Medium | R78: 02. Medium | S78: RFP decision. | T78: Mitigation | V78: Priorizite all work with the information known to date | W78: 31-Jan: Incorporating changes in the re-plan 5/10 - assessment will continue throughout the program 28/09 - in process | X78: 40961 | AA78: 40940 | AE78: =$AE$1-Table4[[#This Row],[Date Captured]] -> 226 | AF78: =IFERROR(OR(Table4[[#This Row],[Status]]="02. Open & Assigned",Table4[[#This Row],[Status]]="01. Open",Table4[[#This Row],[Status]]="03. Action/Mitigation Plan Defined",Table4[[#This Row],[Status]]="04. Action Plan Completed",Table4[[#This Row],[Status]]="08. Blank"),"") -> FALSE | AG78: =IF(Table4[[#This Row],[Required Risk Resolution Date]]="","FALSE",IF($AE$1>Table4[[#This Row],[Required Risk Resolution Date]],TRUE,FALSE)) -> TRUE | AH78: =IF(AE78<30,FALSE,IF(AE78>90,FALSE,TRUE)) -> FALSE | AI78: =IF(AE78<91,FALSE,IF(AE78>180,FALSE,TRUE)) -> FALSE | AJ78: =IF(AE78>180,TRUE,FALSE) -> TRUE | AK78: =OR(Table4[[#This Row],[Priority]]="Critical",Table4[[#This Row],[Priority]]="High") -> FALSE | AL78: =Table4[[#This Row],[Required Risk Resolution Date]]-$AE$1 -> -50 | AM78: =IF(AL78<1,FALSE,IF(AL78>7,FALSE,TRUE)) -> FALSE | AN78: =OR(Table4[[#This Row],[Priority]]="Critical",Table4[[#This Row],[Priority]]="High",Table4[[#This Row],[Priority]]="Moderate") -> FALSE
A79: R45 | B79: 40764 | D79: 05. Risk Closed | F79: If the placeholders used to gauge the work for Phase 1 are significantly less than the detailed estimates, the team size could be off. | G79: Wrong size of the development team, excess capacity or not enough capacity or not enough of the right type | H79: SharePoint | J79: Michelle Edmonds | N79: 03. Possible | O79: 02. Medium | T79: Mitigation | V79: Review work load as new information becomes available. Use best practices from similar efforts to verify estimates. Review weekly with the any new information available | W79: 5/10 - assessment will continue throughout the program 28/09 - in process | X79: 40909 | AE79: =$AE$1-Table4[[#This Row],[Date Captured]] -> 226 | AF79: =IFERROR(OR(Table4[[#This Row],[Status]]="02. Open & Assigned",Table4[[#This Row],[Status]]="01. Open",Table4[[#This Row],[Status]]="03. Action/Mitigation Plan Defined",Table4[[#This Row],[Status]]="04. Action Plan Completed",Table4[[#This Row],[Status]]="08. Blank"),"") -> FALSE | AG79: =IF(Table4[[#This Row],[Required Risk Resolution Date]]="","FALSE",IF($AE$1>Table4[[#This Row],[Required Risk Resolution Date]],TRUE,FALSE)) -> FALSE | AH79: =IF(AE79<30,FALSE,IF(AE79>90,FALSE,TRUE)) -> FALSE | AI79: =IF(AE79<91,FALSE,IF(AE79>180,FALSE,TRUE)) -> FALSE | AJ79: =IF(AE79>180,TRUE,FALSE) -> TRUE | AK79: =OR(Table4[[#This Row],[Priority]]="Critical",Table4[[#This Row],[Priority]]="High") -> FALSE | AL79: =Table4[[#This Row],[Required Risk Resolution Date]]-$AE$1 -> -40990 | AM79: =IF(AL79<1,FALSE,IF(AL79>7,FALSE,TRUE)) -> FALSE | AN79: =OR(Table4[[#This Row],[Priority]]="Critical",Table4[[#This Row],[Priority]]="High",Table4[[#This Row],[Priority]]="Moderate") -> FALSE
A80: R49B | B80: 40826 | C80: unknown | D80: 07. Risk has become an Issue | E80: The go live of SharePoint | F80: Level 4 Support Team for Post Phase 1 Go-Live has not been confirmed (IT Solutions Teams are structured by Portfolio) | G80: Resources not available causng existing resources to be used and less functionality in Phase 2 | H80: SharePoint | J80: Guy Morgan Alan Guthrie | K80: Mike Laci | L80: High | M80: 03. Impact > 3 Months | N80: 03. Possible | O80: 03. High | P80: 03. High | Q80: 03. High | R80: 03. High | S80: Go Live | T80: Mitigation | U80: Current team will do fixes after Go Live | V80: We need to define the Level 4 Support Team | W80: 07/12 - Per Alan, Skip. Review next week. 12/10 - Application Engineer support needed. Guy will follow up with Alan. | X80: 40940 | Y80: Executive Project Sponsor | AE80: =$AE$1-Table4[[#This Row],[Date Captured]] -> 164 | AF80: =IFERROR(OR(Table4[[#This Row],[Status]]="02. Open & Assigned",Table4[[#This Row],[Status]]="01. Open",Table4[[#This Row],[Status]]="03. Action/Mitigation Plan Defined",Table4[[#This Row],[Status]]="04. Action Plan Completed",Table4[[#This Row],[Status]]="08. Blank"),"") -> FALSE | AG80: =IF(Table4[[#This Row],[Required Risk Resolution Date]]="","FALSE",IF($AE$1>Table4[[#This Row],[Required Risk Resolution Date]],TRUE,FALSE)) -> FALSE | AH80: =IF(AE80<30,FALSE,IF(AE80>90,FALSE,TRUE)) -> FALSE | AI80: =IF(AE80<91,FALSE,IF(AE80>180,FALSE,TRUE)) -> TRUE | AJ80: =IF(AE80>180,TRUE,FALSE) -> FALSE | AK80: =OR(Table4[[#This Row],[Priority]]="Critical",Table4[[#This Row],[Priority]]="High") -> TRUE | AL80: =Table4[[#This Row],[Required Risk Resolution Date]]-$AE$1 -> -40990 | AM80: =IF(AL80<1,FALSE,IF(AL80>7,FALSE,TRUE)) -> FALSE | AN80: =OR(Table4[[#This Row],[Priority]]="Critical",Table4[[#This Row],[Priority]]="High",Table4[[#This Row],[Priority]]="Moderate") -> TRUE
A81: R51B | B81: 40826 | C81: unknown | D81: 05. Risk Closed | E81: Unclear responsibilities | F81: EY needs to make sure we do not accidentally take Microsoft responsibilies for Architecture, Design and Development | G81: EY would have paid too much to mitigate a risk that they had taken | H81: SharePoint | J81: Michelle Edmonds | K81: Michelle Edmonds | L81: Minor | M81: 03. Impact > 3 Months | N81: 01. Slight | O81: 03. High | P81: 03. High | Q81: 02. Medium | R81: 03. High | S81: EY decision to deviate from Microsoft recommendation. | T81: Mitigation | U81: Make sure we fully communicate Roles and Responsibilities across the MS / EY Teams. | V81: Make sure we fully communicate Roles and Responsibilities across the MS / EY Teams. | W81: 7 Feb: This Risk will be throughout the project. | X81: 41189 | Y81: Program Manager | Z81: Will be addressed as part of the replan | AA81: 41189 | AE81: =$AE$1-Table4[[#This Row],[Date Captured]] -> 164 | AF81: =IFERROR(OR(Table4[[#This Row],[Status]]="02. Open & Assigned",Table4[[#This Row],[Status]]="01. Open",Table4[[#This Row],[Status]]="03. Action/Mitigation Plan Defined",Table4[[#This Row],[Status]]="04. Action Plan Completed",Table4[[#This Row],[Status]]="08. Blank"),"") -> FALSE | AG81: =IF(Table4[[#This Row],[Required Risk Resolution Date]]="","FALSE",IF($AE$1>Table4[[#This Row],[Required Risk Resolution Date]],TRUE,FALSE)) -> FALSE | AH81: =IF(AE81<30,FALSE,IF(AE81>90,FALSE,TRUE)) -> FALSE | AI81: =IF(AE81<91,FALSE,IF(AE81>180,FALSE,TRUE)) -> TRUE | AJ81: =IF(AE81>180,TRUE,FALSE) -> FALSE | AK81: =OR(Table4[[#This Row],[Priority]]="Critical",Table4[[#This Row],[Priority]]="High") -> FALSE | AL81: =Table4[[#This Row],[Required Risk Resolution Date]]-$AE$1 -> 199 | AM81: =IF(AL81<1,FALSE,IF(AL81>7,FALSE,TRUE)) -> FALSE | AN81: =OR(Table4[[#This Row],[Priority]]="Critical",Table4[[#This Row],[Priority]]="High",Table4[[#This Row],[Priority]]="Moderate") -> FALSE
A82: R52B | B82: 40826 | D82: 07. Risk has become an Issue | F82: We may not have time to complete Phase I delivery for Assurance depending upon the decision at the end of Nov. (Assurance Knowledge Tool). | G82: GAAIT replacement would be delayed | H82: SharePoint | J82: Michelle Edmonds | N82: 03. Possible | O82: 03. High | T82: Mitigation | V82: We will continue to work with the Core Team to confirm plan. We will work with them to look at the deliveries to confirm what is possible for Phase I. | W82: 1/11 - Decision will now be in December working with the Assurance on the Ovitas and the other 3 solutions | X82: 40909 | AA82: 40969 | AE82: =$AE$1-Table4[[#This Row],[Date Captured]] -> 164 | AF82: =IFERROR(OR(Table4[[#This Row],[Status]]="02. Open & Assigned",Table4[[#This Row],[Status]]="01. Open",Table4[[#This Row],[Status]]="03. Action/Mitigation Plan Defined",Table4[[#This Row],[Status]]="04. Action Plan Completed",Table4[[#This Row],[Status]]="08. Blank"),"") -> FALSE | AG82: =IF(Table4[[#This Row],[Required Risk Resolution Date]]="","FALSE",IF($AE$1>Table4[[#This Row],[Required Risk Resolution Date]],TRUE,FALSE)) -> TRUE | AH82: =IF(AE82<30,FALSE,IF(AE82>90,FALSE,TRUE)) -> FALSE | AI82: =IF(AE82<91,FALSE,IF(AE82>180,FALSE,TRUE)) -> TRUE | AJ82: =IF(AE82>180,TRUE,FALSE) -> FALSE | AK82: =OR(Table4[[#This Row],[Priority]]="Critical",Table4[[#This Row],[Priority]]="High") -> FALSE | AL82: =Table4[[#This Row],[Required Risk Resolution Date]]-$AE$1 -> -21 | AM82: =IF(AL82<1,FALSE,IF(AL82>7,FALSE,TRUE)) -> FALSE | AN82: =OR(Table4[[#This Row],[Priority]]="Critical",Table4[[#This Row],[Priority]]="High",Table4[[#This Row],[Priority]]="Moderate") -> FALSE
A83: R56 | B83: 40807 | D83: 07. Risk has become an Issue | F83: Open resource needs for SharePoint workstream (QA Lead, QA, Lead Developers, Release Manager, Solution Arch's, PM's, BA's) | H83: SharePoint | J83: Michelle Edmonds | N83: 03. Possible | O83: 03. High | V83: Continue to assess and work with Resource Planning to fill open positions. | W83: 12/10 - placed as a Critical issue 5/10 - Receiving / reviewing resumes for QA Lead, Release Mgr, PM, and BA open positions. 28/09 - continue to work with Cross Portfolio resource planning team to fill open requests. 21/09 - Submitted all open resource requests with Resource Planning Team. Weekly meetings scheduled to review with resource planning and sourcing. | X83: 40828 | AB83: 40828 | AC83: Issue ? | AE83: =$AE$1-Table4[[#This Row],[Date Captured]] -> 183 | AF83: =IFERROR(OR(Table4[[#This Row],[Status]]="02. Open & Assigned",Table4[[#This Row],[Status]]="01. Open",Table4[[#This Row],[Status]]="03. Action/Mitigation Plan Defined",Table4[[#This Row],[Status]]="04. Action Plan Completed",Table4[[#This Row],[Status]]="08. Blank"),"") -> FALSE | AG83: =IF(Table4[[#This Row],[Required Risk Resolution Date]]="","FALSE",IF($AE$1>Table4[[#This Row],[Required Risk Resolution Date]],TRUE,FALSE)) -> FALSE | AH83: =IF(AE83<30,FALSE,IF(AE83>90,FALSE,TRUE)) -> FALSE | AI83: =IF(AE83<91,FALSE,IF(AE83>180,FALSE,TRUE)) -> FALSE | AJ83: =IF(AE83>180,TRUE,FALSE) -> TRUE | AK83: =OR(Table4[[#This Row],[Priority]]="Critical",Table4[[#This Row],[Priority]]="High") -> FALSE | AL83: =Table4[[#This Row],[Required Risk Resolution Date]]-$AE$1 -> -40990 | AM83: =IF(AL83<1,FALSE,IF(AL83>7,FALSE,TRUE)) -> FALSE | AN83: =OR(Table4[[#This Row],[Priority]]="Critical",Table4[[#This Row],[Priority]]="High",Table4[[#This Row],[Priority]]="Moderate") -> FALSE
A84: R69 | B84: 40848 | D84: 05. Risk Closed | F84: IPM was the forum to have cross workstream communication and awareness. Executive Sponsors concerned about effectveness and expense of meeting. | H84: SharePoint | J84: Michelle Edmonds | N84: 03. Possible | O84: 02. Medium | T84: Mitigation | V84: Changed IPM and implemented a cross group meeting to address this risk | W84: 1/11 - Met with team today to define options. Will continue to monitor. | X84: 40849 | AE84: =$AE$1-Table4[[#This Row],[Date Captured]] -> 142 | AF84: =IFERROR(OR(Table4[[#This Row],[Status]]="02. Open & Assigned",Table4[[#This Row],[Status]]="01. Open",Table4[[#This Row],[Status]]="03. Action/Mitigation Plan Defined",Table4[[#This Row],[Status]]="04. Action Plan Completed",Table4[[#This Row],[Status]]="08. Blank"),"") -> FALSE | AG84: =IF(Table4[[#This Row],[Required Risk Resolution Date]]="","FALSE",IF($AE$1>Table4[[#This Row],[Required Risk Resolution Date]],TRUE,FALSE)) -> FALSE | AH84: =IF(AE84<30,FALSE,IF(AE84>90,FALSE,TRUE)) -> FALSE | AI84: =IF(AE84<91,FALSE,IF(AE84>180,FALSE,TRUE)) -> TRUE | AJ84: =IF(AE84>180,TRUE,FALSE) -> FALSE | AK84: =OR(Table4[[#This Row],[Priority]]="Critical",Table4[[#This Row],[Priority]]="High") -> FALSE | AL84: =Table4[[#This Row],[Required Risk Resolution Date]]-$AE$1 -> -40990 | AM84: =IF(AL84<1,FALSE,IF(AL84>7,FALSE,TRUE)) -> FALSE | AN84: =OR(Table4[[#This Row],[Priority]]="Critical",Table4[[#This Row],[Priority]]="High",Table4[[#This Row],[Priority]]="Moderate") -> FALSE
A85: R7 | B85: 40619 | D85: 05. Risk Closed | F85: Document conversion service for SharePoint Online is not on the current Microsoft offering, but on the roadmap. The timing of the implementation of DCS may not fit in with our time scales. | H85: SharePoint | J85: Adrian Mickleson | N85: 03. Possible | O85: 01. Low | T85: Mitigation | U85: Implement SharePoint Modules that require DCS on premises | V85: This is on the basis that all SharePoint workloads will be implemented in the cloud. | W85: 06/07 - Not going BPOS, don’t know what other managing service position would be on this. 27/04 - The team provided a recommendation to John C. He is reviewing the recommendation. Hold open until hear back from John. | X85: 40772 | Z85: Monitor MS progress for DCS 19/04 - Current recommendation from the IT team is to implement all SharePoint services on premises. | AB85: 40674 | AE85: =$AE$1-Table4[[#This Row],[Date Captured]] -> 371 | AF85: =IFERROR(OR(Table4[[#This Row],[Status]]="02. Open & Assigned",Table4[[#This Row],[Status]]="01. Open",Table4[[#This Row],[Status]]="03. Action/Mitigation Plan Defined",Table4[[#This Row],[Status]]="04. Action Plan Completed",Table4[[#This Row],[Status]]="08. Blank"),"") -> FALSE | AG85: =IF(Table4[[#This Row],[Required Risk Resolution Date]]="","FALSE",IF($AE$1>Table4[[#This Row],[Required Risk Resolution Date]],TRUE,FALSE)) -> FALSE | AH85: =IF(AE85<30,FALSE,IF(AE85>90,FALSE,TRUE)) -> FALSE | AI85: =IF(AE85<91,FALSE,IF(AE85>180,FALSE,TRUE)) -> FALSE | AJ85: =IF(AE85>180,TRUE,FALSE) -> TRUE | AK85: =OR(Table4[[#This Row],[Priority]]="Critical",Table4[[#This Row],[Priority]]="High") -> FALSE | AL85: =Table4[[#This Row],[Required Risk Resolution Date]]-$AE$1 -> -40990 | AM85: =IF(AL85<1,FALSE,IF(AL85>7,FALSE,TRUE)) -> FALSE | AN85: =OR(Table4[[#This Row],[Priority]]="Critical",Table4[[#This Row],[Priority]]="High",Table4[[#This Row],[Priority]]="Moderate") -> FALSE
A86: R70 | B86: 40848 | D86: 05. Risk Closed | F86: Prioritization of work across workstreams. Original plan will not work. | H86: SharePoint | J86: Michelle Edmonds | O86: 01. Low | V86: Duplicate of another risk | AE86: =$AE$1-Table4[[#This Row],[Date Captured]] -> 142 | AF86: =IFERROR(OR(Table4[[#This Row],[Status]]="02. Open & Assigned",Table4[[#This Row],[Status]]="01. Open",Table4[[#This Row],[Status]]="03. Action/Mitigation Plan Defined",Table4[[#This Row],[Status]]="04. Action Plan Completed",Table4[[#This Row],[Status]]="08. Blank"),"") -> FALSE | AG86: =IF(Table4[[#This Row],[Required Risk Resolution Date]]="","FALSE",IF($AE$1>Table4[[#This Row],[Required Risk Resolution Date]],TRUE,FALSE)) -> FALSE | AH86: =IF(AE86<30,FALSE,IF(AE86>90,FALSE,TRUE)) -> FALSE | AI86: =IF(AE86<91,FALSE,IF(AE86>180,FALSE,TRUE)) -> TRUE | AJ86: =IF(AE86>180,TRUE,FALSE) -> FALSE | AK86: =OR(Table4[[#This Row],[Priority]]="Critical",Table4[[#This Row],[Priority]]="High") -> FALSE | AL86: =Table4[[#This Row],[Required Risk Resolution Date]]-$AE$1 -> -40990 | AM86: =IF(AL86<1,FALSE,IF(AL86>7,FALSE,TRUE)) -> FALSE | AN86: =OR(Table4[[#This Row],[Priority]]="Critical",Table4[[#This Row],[Priority]]="High",Table4[[#This Row],[Priority]]="Moderate") -> FALSE
A87: R71 | B87: 40848 | D87: 05. Risk Closed | F87: Limited/reduced EY participation in SharePoint Foundation Planning workshops may affect quality of SharePoint Foundation Planning activities & deliverables | G87: wrong infrastructure would cause delays | H87: SharePoint | O87: 01. Low | T87: Mitigation | V87: Provide resource and let other items not be completed | W87: 1/11 - MCS - Limited/reduced EY participation in Planning Workshops may affect quality of Design/Planning workshops; Dan Mulligan does not appear to be the correct resource to represent Infrastructure; Michelle Edmonds not available for Week 2; Kerri Keller not available to represent her area. | X87: 40909 | AA87: 40848 | AE87: =$AE$1-Table4[[#This Row],[Date Captured]] -> 142 | AF87: =IFERROR(OR(Table4[[#This Row],[Status]]="02. Open & Assigned",Table4[[#This Row],[Status]]="01. Open",Table4[[#This Row],[Status]]="03. Action/Mitigation Plan Defined",Table4[[#This Row],[Status]]="04. Action Plan Completed",Table4[[#This Row],[Status]]="08. Blank"),"") -> FALSE | AG87: =IF(Table4[[#This Row],[Required Risk Resolution Date]]="","FALSE",IF($AE$1>Table4[[#This Row],[Required Risk Resolution Date]],TRUE,FALSE)) -> TRUE | AH87: =IF(AE87<30,FALSE,IF(AE87>90,FALSE,TRUE)) -> FALSE | AI87: =IF(AE87<91,FALSE,IF(AE87>180,FALSE,TRUE)) -> TRUE | AJ87: =IF(AE87>180,TRUE,FALSE) -> FALSE | AK87: =OR(Table4[[#This Row],[Priority]]="Critical",Table4[[#This Row],[Priority]]="High") -> FALSE | AL87: =Table4[[#This Row],[Required Risk Resolution Date]]-$AE$1 -> -142 | AM87: =IF(AL87<1,FALSE,IF(AL87>7,FALSE,TRUE)) -> FALSE | AN87: =OR(Table4[[#This Row],[Priority]]="Critical",Table4[[#This Row],[Priority]]="High",Table4[[#This Row],[Priority]]="Moderate") -> FALSE
A88: R77 | B88: 40869 | D88: 05. Risk Closed | F88: The SharePoint Foundation team used knowledge of current service delivery efforts and has specified an environment for external collaboration. If during requirements ECMA significantly varies from this the infrastructure will have to be redesigned | G88: The infrastructure would have to be rebuilt for those items incorrect and the environments would be delayed or not meet the needs | H88: SharePoint | J88: Michelle Edmonds | N88: 03. Possible | O88: 03. High | W88: 07/12 - Michelle said to push next review to February. | X88: 40940 | AE88: =$AE$1-Table4[[#This Row],[Date Captured]] -> 121 | AF88: =IFERROR(OR(Table4[[#This Row],[Status]]="02. Open & Assigned",Table4[[#This Row],[Status]]="01. Open",Table4[[#This Row],[Status]]="03. Action/Mitigation Plan Defined",Table4[[#This Row],[Status]]="04. Action Plan Completed",Table4[[#This Row],[Status]]="08. Blank"),"") -> FALSE | AG88: =IF(Table4[[#This Row],[Required Risk Resolution Date]]="","FALSE",IF($AE$1>Table4[[#This Row],[Required Risk Resolution Date]],TRUE,FALSE)) -> FALSE | AH88: =IF(AE88<30,FALSE,IF(AE88>90,FALSE,TRUE)) -> FALSE | AI88: =IF(AE88<91,FALSE,IF(AE88>180,FALSE,TRUE)) -> TRUE | AJ88: =IF(AE88>180,TRUE,FALSE) -> FALSE | AK88: =OR(Table4[[#This Row],[Priority]]="Critical",Table4[[#This Row],[Priority]]="High") -> FALSE | AL88: =Table4[[#This Row],[Required Risk Resolution Date]]-$AE$1 -> -40990 | AM88: =IF(AL88<1,FALSE,IF(AL88>7,FALSE,TRUE)) -> FALSE | AN88: =OR(Table4[[#This Row],[Priority]]="Critical",Table4[[#This Row],[Priority]]="High",Table4[[#This Row],[Priority]]="Moderate") -> FALSE
